Workbook

Sheet 01 Industry Model
A1: AI-EXPOSED WAGE POOL | U.S. PRIVATE INDUSTRIES (2025)
A2: Primary: QCEW private industry wages × Wharton task exposure, weighted by OEWS occupation wages. All mapping is formula-driven in DATA OEWS.
A4: NAICS | B4: Industry | C4: Private Wages ($bn) | D4: OEWS Wages ($bn) | E4: Matched Wages ($bn) | F4: Exposure-Weighted Wages ($bn) | G4: Wharton Match Rate | H4: Wharton Task Exposure | I4: GROSS EXPOSED ($bn) | J4: BTOS AI Using Firms | K4: BTOS Firm-Use Proxy ($bn)
A5: 11 | B5: Agriculture, forestry, fishing and hunting | C5: =IFERROR(XLOOKUP(A5,'DATA QCEW'!$A$2:$A$20,'DATA QCEW'!$C$2:$C$20)/1000000000,"") | D5: =SUMIF('DATA OEWS'!$A$2:$A$13458,A5,'DATA OEWS'!$G$2:$G$13458)/1000000000 | E5: =SUMIF('DATA OEWS'!$A$2:$A$13458,A5,'DATA OEWS'!$I$2:$I$13458)/1000000000 | F5: =SUMIF('DATA OEWS'!$A$2:$A$13458,A5,'DATA OEWS'!$J$2:$J$13458)/1000000000 | G5: =IF(D5=0,"",E5/D5) | H5: =IF(E5=0,"",F5/E5) | I5: =C5*H5 | J5: =IFERROR(XLOOKUP(A5,'DATA Census'!$A$2:$A$20,'DATA Census'!$C$2:$C$20),"") | K5: =I5*J5
A6: 21 | B6: Mining, quarrying, and oil and gas extraction | C6: =IFERROR(XLOOKUP(A6,'DATA QCEW'!$A$2:$A$20,'DATA QCEW'!$C$2:$C$20)/1000000000,"") | D6: =SUMIF('DATA OEWS'!$A$2:$A$13458,A6,'DATA OEWS'!$G$2:$G$13458)/1000000000 | E6: =SUMIF('DATA OEWS'!$A$2:$A$13458,A6,'DATA OEWS'!$I$2:$I$13458)/1000000000 | F6: =SUMIF('DATA OEWS'!$A$2:$A$13458,A6,'DATA OEWS'!$J$2:$J$13458)/1000000000 | G6: =IF(D6=0,"",E6/D6) | H6: =IF(E6=0,"",F6/E6) | I6: =C6*H6 | J6: =IFERROR(XLOOKUP(A6,'DATA Census'!$A$2:$A$20,'DATA Census'!$C$2:$C$20),"") | K6: =I6*J6
A7: 22 | B7: Utilities | C7: =IFERROR(XLOOKUP(A7,'DATA QCEW'!$A$2:$A$20,'DATA QCEW'!$C$2:$C$20)/1000000000,"") | D7: =SUMIF('DATA OEWS'!$A$2:$A$13458,A7,'DATA OEWS'!$G$2:$G$13458)/1000000000 | E7: =SUMIF('DATA OEWS'!$A$2:$A$13458,A7,'DATA OEWS'!$I$2:$I$13458)/1000000000 | F7: =SUMIF('DATA OEWS'!$A$2:$A$13458,A7,'DATA OEWS'!$J$2:$J$13458)/1000000000 | G7: =IF(D7=0,"",E7/D7) | H7: =IF(E7=0,"",F7/E7) | I7: =C7*H7 | J7: =IFERROR(XLOOKUP(A7,'DATA Census'!$A$2:$A$20,'DATA Census'!$C$2:$C$20),"") | K7: =I7*J7
A8: 23 | B8: Construction | C8: =IFERROR(XLOOKUP(A8,'DATA QCEW'!$A$2:$A$20,'DATA QCEW'!$C$2:$C$20)/1000000000,"") | D8: =SUMIF('DATA OEWS'!$A$2:$A$13458,A8,'DATA OEWS'!$G$2:$G$13458)/1000000000 | E8: =SUMIF('DATA OEWS'!$A$2:$A$13458,A8,'DATA OEWS'!$I$2:$I$13458)/1000000000 | F8: =SUMIF('DATA OEWS'!$A$2:$A$13458,A8,'DATA OEWS'!$J$2:$J$13458)/1000000000 | G8: =IF(D8=0,"",E8/D8) | H8: =IF(E8=0,"",F8/E8) | I8: =C8*H8 | J8: =IFERROR(XLOOKUP(A8,'DATA Census'!$A$2:$A$20,'DATA Census'!$C$2:$C$20),"") | K8: =I8*J8
A9: 31-33 | B9: Manufacturing | C9: =IFERROR(XLOOKUP(A9,'DATA QCEW'!$A$2:$A$20,'DATA QCEW'!$C$2:$C$20)/1000000000,"") | D9: =SUMIF('DATA OEWS'!$A$2:$A$13458,A9,'DATA OEWS'!$G$2:$G$13458)/1000000000 | E9: =SUMIF('DATA OEWS'!$A$2:$A$13458,A9,'DATA OEWS'!$I$2:$I$13458)/1000000000 | F9: =SUMIF('DATA OEWS'!$A$2:$A$13458,A9,'DATA OEWS'!$J$2:$J$13458)/1000000000 | G9: =IF(D9=0,"",E9/D9) | H9: =IF(E9=0,"",F9/E9) | I9: =C9*H9 | J9: =IFERROR(XLOOKUP(A9,'DATA Census'!$A$2:$A$20,'DATA Census'!$C$2:$C$20),"") | K9: =I9*J9
A10: 42 | B10: Wholesale trade | C10: =IFERROR(XLOOKUP(A10,'DATA QCEW'!$A$2:$A$20,'DATA QCEW'!$C$2:$C$20)/1000000000,"") | D10: =SUMIF('DATA OEWS'!$A$2:$A$13458,A10,'DATA OEWS'!$G$2:$G$13458)/1000000000 | E10: =SUMIF('DATA OEWS'!$A$2:$A$13458,A10,'DATA OEWS'!$I$2:$I$13458)/1000000000 | F10: =SUMIF('DATA OEWS'!$A$2:$A$13458,A10,'DATA OEWS'!$J$2:$J$13458)/1000000000 | G10: =IF(D10=0,"",E10/D10) | H10: =IF(E10=0,"",F10/E10) | I10: =C10*H10 | J10: =IFERROR(XLOOKUP(A10,'DATA Census'!$A$2:$A$20,'DATA Census'!$C$2:$C$20),"") | K10: =I10*J10
A11: 44-45 | B11: Retail trade | C11: =IFERROR(XLOOKUP(A11,'DATA QCEW'!$A$2:$A$20,'DATA QCEW'!$C$2:$C$20)/1000000000,"") | D11: =SUMIF('DATA OEWS'!$A$2:$A$13458,A11,'DATA OEWS'!$G$2:$G$13458)/1000000000 | E11: =SUMIF('DATA OEWS'!$A$2:$A$13458,A11,'DATA OEWS'!$I$2:$I$13458)/1000000000 | F11: =SUMIF('DATA OEWS'!$A$2:$A$13458,A11,'DATA OEWS'!$J$2:$J$13458)/1000000000 | G11: =IF(D11=0,"",E11/D11) | H11: =IF(E11=0,"",F11/E11) | I11: =C11*H11 | J11: =IFERROR(XLOOKUP(A11,'DATA Census'!$A$2:$A$20,'DATA Census'!$C$2:$C$20),"") | K11: =I11*J11
A12: 48-49 | B12: Transportation and warehousing | C12: =IFERROR(XLOOKUP(A12,'DATA QCEW'!$A$2:$A$20,'DATA QCEW'!$C$2:$C$20)/1000000000,"") | D12: =SUMIF('DATA OEWS'!$A$2:$A$13458,A12,'DATA OEWS'!$G$2:$G$13458)/1000000000 | E12: =SUMIF('DATA OEWS'!$A$2:$A$13458,A12,'DATA OEWS'!$I$2:$I$13458)/1000000000 | F12: =SUMIF('DATA OEWS'!$A$2:$A$13458,A12,'DATA OEWS'!$J$2:$J$13458)/1000000000 | G12: =IF(D12=0,"",E12/D12) | H12: =IF(E12=0,"",F12/E12) | I12: =C12*H12 | J12: =IFERROR(XLOOKUP(A12,'DATA Census'!$A$2:$A$20,'DATA Census'!$C$2:$C$20),"") | K12: =I12*J12
A13: 51 | B13: Information | C13: =IFERROR(XLOOKUP(A13,'DATA QCEW'!$A$2:$A$20,'DATA QCEW'!$C$2:$C$20)/1000000000,"") | D13: =SUMIF('DATA OEWS'!$A$2:$A$13458,A13,'DATA OEWS'!$G$2:$G$13458)/1000000000 | E13: =SUMIF('DATA OEWS'!$A$2:$A$13458,A13,'DATA OEWS'!$I$2:$I$13458)/1000000000 | F13: =SUMIF('DATA OEWS'!$A$2:$A$13458,A13,'DATA OEWS'!$J$2:$J$13458)/1000000000 | G13: =IF(D13=0,"",E13/D13) | H13: =IF(E13=0,"",F13/E13) | I13: =C13*H13 | J13: =IFERROR(XLOOKUP(A13,'DATA Census'!$A$2:$A$20,'DATA Census'!$C$2:$C$20),"") | K13: =I13*J13
A14: 52 | B14: Finance and insurance | C14: =IFERROR(XLOOKUP(A14,'DATA QCEW'!$A$2:$A$20,'DATA QCEW'!$C$2:$C$20)/1000000000,"") | D14: =SUMIF('DATA OEWS'!$A$2:$A$13458,A14,'DATA OEWS'!$G$2:$G$13458)/1000000000 | E14: =SUMIF('DATA OEWS'!$A$2:$A$13458,A14,'DATA OEWS'!$I$2:$I$13458)/1000000000 | F14: =SUMIF('DATA OEWS'!$A$2:$A$13458,A14,'DATA OEWS'!$J$2:$J$13458)/1000000000 | G14: =IF(D14=0,"",E14/D14) | H14: =IF(E14=0,"",F14/E14) | I14: =C14*H14 | J14: =IFERROR(XLOOKUP(A14,'DATA Census'!$A$2:$A$20,'DATA Census'!$C$2:$C$20),"") | K14: =I14*J14
A15: 53 | B15: Real estate and rental and leasing | C15: =IFERROR(XLOOKUP(A15,'DATA QCEW'!$A$2:$A$20,'DATA QCEW'!$C$2:$C$20)/1000000000,"") | D15: =SUMIF('DATA OEWS'!$A$2:$A$13458,A15,'DATA OEWS'!$G$2:$G$13458)/1000000000 | E15: =SUMIF('DATA OEWS'!$A$2:$A$13458,A15,'DATA OEWS'!$I$2:$I$13458)/1000000000 | F15: =SUMIF('DATA OEWS'!$A$2:$A$13458,A15,'DATA OEWS'!$J$2:$J$13458)/1000000000 | G15: =IF(D15=0,"",E15/D15) | H15: =IF(E15=0,"",F15/E15) | I15: =C15*H15 | J15: =IFERROR(XLOOKUP(A15,'DATA Census'!$A$2:$A$20,'DATA Census'!$C$2:$C$20),"") | K15: =I15*J15
A16: 54 | B16: Professional, scientific, and technical services | C16: =IFERROR(XLOOKUP(A16,'DATA QCEW'!$A$2:$A$20,'DATA QCEW'!$C$2:$C$20)/1000000000,"") | D16: =SUMIF('DATA OEWS'!$A$2:$A$13458,A16,'DATA OEWS'!$G$2:$G$13458)/1000000000 | E16: =SUMIF('DATA OEWS'!$A$2:$A$13458,A16,'DATA OEWS'!$I$2:$I$13458)/1000000000 | F16: =SUMIF('DATA OEWS'!$A$2:$A$13458,A16,'DATA OEWS'!$J$2:$J$13458)/1000000000 | G16: =IF(D16=0,"",E16/D16) | H16: =IF(E16=0,"",F16/E16) | I16: =C16*H16 | J16: =IFERROR(XLOOKUP(A16,'DATA Census'!$A$2:$A$20,'DATA Census'!$C$2:$C$20),"") | K16: =I16*J16
... A23: 81 | B23: Other services (except public administration) | C23: =IFERROR(XLOOKUP(A23,'DATA QCEW'!$A$2:$A$20,'DATA QCEW'!$C$2:$C$20)/1000000000,"") | D23: =SUMIF('DATA OEWS'!$A$2:$A$13458,A23,'DATA OEWS'!$G$2:$G$13458)/1000000000 | E23: =SUMIF('DATA OEWS'!$A$2:$A$13458,A23,'DATA OEWS'!$I$2:$I$13458)/1000000000 | F23: =SUMIF('DATA OEWS'!$A$2:$A$13458,A23,'DATA OEWS'!$J$2:$J$13458)/1000000000 | G23: =IF(D23=0,"",E23/D23) | H23: =IF(E23=0,"",F23/E23) | I23: =C23*H23 | J23: =IFERROR(XLOOKUP(A23,'DATA Census'!$A$2:$A$20,'DATA Census'!$C$2:$C$20),"") | K23: =I23*J23
A25: TOTAL | B25: 19 private industries (excluding NAICS 99 unclassified) | C25: =SUM(C5:C23) | D25: =SUM(D5:D23) | E25: =SUM(E5:E23) | F25: =SUM(F5:F23) | G25: =IF(D25=0,"",E25/D25) | H25: =IF(E25=0,"",F25/E25) | I25: =SUM(I5:I23) | K25: =SUM(K5:K23)
A27: CHECK | B27: Value ($bn) | C27: Explanation
A28: US QCEW private wages | B28: 10532.191 | C28: All industries including NAICS 99
A29: Unclassified NAICS 99 | B29: 16.545878 | C29: Excluded from the 19-sector exposed wage calculation
A30: Reconciliation (should equal zero) | B30: =B28-C25-B29
A32: IMPORTANT: BTOS firm-use percentage is NOT the share of workers using AI. Column K is a scenario proxy, not measured wage savings.
A33: Ownership caveat: OEWS 48-49, 71 and 72 occupational weights contain mixed ownership. Industry QCEW payroll remains private only.

Sheet Five-Year Projection
A1: FIVE-YEAR PROJECTION | AI-EXPOSED WAGE POOL (2025–2030)
A2: BLS 2025–2035 job growth | projected nominal wages | Wharton exposure | Census 2026 firm-level AI adoption + editable annual growth
A3: Gross exposure is NOT wages saved. Adoption-adjusted exposure is a scenario proxy, NOT realized AI economic benefit.
A5: U.S. PRIVATE SECTORS ($bn unless indicated) | B5: 2025 | C5: 2026 | D5: 2027 | E5: 2028 | F5: 2029 | G5: 2030
A6: Industry wages ($bn) | B6: =SUMIF($C$17:$C$130,B$5,$F$17:$F$130) -> 10515.646 | C6: =SUMIF($C$17:$C$130,C$5,$F$17:$F$130) -> 10877.917 | D6: =SUMIF($C$17:$C$130,D$5,$F$17:$F$130) -> 11252.782 | E6: =SUMIF($C$17:$C$130,E$5,$F$17:$F$130) -> 11640.684 | F6: =SUMIF($C$17:$C$130,F$5,$F$17:$F$130) -> 12042.078 | G6: =SUMIF($C$17:$C$130,G$5,$F$17:$F$130) -> 12457.439
A7: Gross AI-exposed wage pool ($bn) | B7: =SUMIF($C$17:$C$130,B$5,$J$17:$J$130) -> 4435.9142 | C7: =SUMIF($C$17:$C$130,C$5,$J$17:$J$130) -> 4588.4232 | D7: =SUMIF($C$17:$C$130,D$5,$J$17:$J$130) -> 4746.2206 | E7: =SUMIF($C$17:$C$130,E$5,$J$17:$J$130) -> 4909.4915 | F7: =SUMIF($C$17:$C$130,F$5,$J$17:$J$130) -> 5078.4273 | G7: =SUMIF($C$17:$C$130,G$5,$J$17:$J$130) -> 5253.2262
A8: Firm-use-adjusted wage pool ($bn) | B8: =IF(B$5=2025,"",SUMIF($C$17:$C$130,B$5,$L$17:$L$130)) | C8: =IF(C$5=2025,"",SUMIF($C$17:$C$130,C$5,$L$17:$L$130)) -> 1357.2013 | D8: =IF(D$5=2025,"",SUMIF($C$17:$C$130,D$5,$L$17:$L$130)) -> 1641.8751 | E8: =IF(E$5=2025,"",SUMIF($C$17:$C$130,E$5,$L$17:$L$130)) -> 1944.5421 | F8: =IF(F$5=2025,"",SUMIF($C$17:$C$130,F$5,$L$17:$L$130)) -> 2266.1112 | G8: =IF(G$5=2025,"",SUMIF($C$17:$C$130,G$5,$L$17:$L$130)) -> 2607.5329
A9: Firm-use proxy / gross exposure | B9: =IF(B$5=2025,"",B8/B7) | C9: =IF(C$5=2025,"",C8/C7) -> 0.29578817 | D9: =IF(D$5=2025,"",D8/D7) -> 0.34593315 | E9: =IF(E$5=2025,"",E8/E7) -> 0.3960781 | F9: =IF(F$5=2025,"",F8/F7) -> 0.44622303 | G9: =IF(G$5=2025,"",G8/G7) -> 0.49636791
A10: Gross exposed vs. 2025 | B10: =B7/$B$7-1 -> 0 | C10: =C7/$B$7-1 -> 0.034380507 | D10: =D7/$B$7-1 -> 0.069953204 | E10: =E7/$B$7-1 -> 0.10675979 | F10: =F7/$B$7-1 -> 0.14484343 | G10: =G7/$B$7-1 -> 0.18424883
A12: 2025 = measured wage base; 2026–2030 = modeled forward scenario. All nominal dollars; no discounting or AI capture rate.
A13: How to edit: change Projection Assumptions!C5:C7 globally, or per-industry C13:E31; job growth always comes from DATA BLS Projections.
A15: INDUSTRY × YEAR DETAIL | ONE ROW PER YEAR; FORMULAS COPY DOWN
A16: NAICS | B16: Industry | C16: Year | D16: BLS Jobs CAGR | E16: Wage / Worker CAGR | F16: Wage Bill ($bn) | G16: 2025 AI Task Exposure | H16: Annual Exposure Δ (pp) | I16: Projected Task Exposure | J16: Gross Exposed ($bn) | K16: AI-Using Firms | L16: Use-Adjusted Proxy ($bn)
A17: 11 | B17: Agriculture, forestry, fishing and hunting | C17: 2025 | D17: =IFERROR(XLOOKUP(A17,'DATA BLS Projections'!$A$5:$A$23,'DATA BLS Projections'!$E$5:$E$23),"") -> 0.001474046 | E17: =IFERROR(XLOOKUP(A17,'Projection Assumptions'!$A$13:$A$31,'Projection Assumptions'!$C$13:$C$31),"") -> 0.03 | F17: =IFERROR(XLOOKUP(A17,'01 Industry Model'!$A$5:$A$23,'01 Industry Model'!$C$5:$C$23),"") -> 60.088225 | G17: =IFERROR(XLOOKUP(A17,'01 Industry Model'!$A$5:$A$23,'01 Industry Model'!$H$5:$H$23),"") -> 0.18131399 | H17: =IFERROR(XLOOKUP(A17,'Projection Assumptions'!$A$13:$A$31,'Projection Assumptions'!$E$13:$E$31),"") -> 0 | I17: =MIN(1,MAX(0,G17+(C17-2025)*H17)) -> 0.18131399 | J17: =F17*I17 -> 10.894836 | K17: =IF(C17=2025,"",0) | L17: =IF(K17="","",J17*K17)
A18: 11 | B18: Agriculture, forestry, fishing and hunting | C18: 2026 | D18: =IFERROR(XLOOKUP(A18,'DATA BLS Projections'!$A$5:$A$23,'DATA BLS Projections'!$E$5:$E$23),"") -> 0.001474046 | E18: =IFERROR(XLOOKUP(A18,'Projection Assumptions'!$A$13:$A$31,'Projection Assumptions'!$C$13:$C$31),"") -> 0.03 | F18: =F17*(1+D18)*(1+E18) -> 61.982102 | G18: =IFERROR(XLOOKUP(A18,'01 Industry Model'!$A$5:$A$23,'01 Industry Model'!$H$5:$H$23),"") -> 0.18131399 | H18: =IFERROR(XLOOKUP(A18,'Projection Assumptions'!$A$13:$A$31,'Projection Assumptions'!$E$13:$E$31),"") -> 0 | I18: =MIN(1,MAX(0,G18+(C18-2025)*H18)) -> 0.18131399 | J18: =F18*I18 -> 11.238222 | K18: =IFERROR(XLOOKUP(A18,'DATA Census'!$A$2:$A$20,'DATA Census'!$C$2:$C$20),"") -> 0.095 | L18: =IF(K18="","",J18*K18) -> 1.0676311
A19: 11 | B19: Agriculture, forestry, fishing and hunting | C19: 2027 | D19: =IFERROR(XLOOKUP(A19,'DATA BLS Projections'!$A$5:$A$23,'DATA BLS Projections'!$E$5:$E$23),"") -> 0.001474046 | E19: =IFERROR(XLOOKUP(A19,'Projection Assumptions'!$A$13:$A$31,'Projection Assumptions'!$C$13:$C$31),"") -> 0.03 | F19: =F18*(1+D19)*(1+E19) -> 63.93567 | G19: =IFERROR(XLOOKUP(A19,'01 Industry Model'!$A$5:$A$23,'01 Industry Model'!$H$5:$H$23),"") -> 0.18131399 | H19: =IFERROR(XLOOKUP(A19,'Projection Assumptions'!$A$13:$A$31,'Projection Assumptions'!$E$13:$E$31),"") -> 0 | I19: =MIN(1,MAX(0,G19+(C19-2025)*H19)) -> 0.18131399 | J19: =F19*I19 -> 11.592431 | K19: =MIN(1,K18+XLOOKUP(A19,'Projection Assumptions'!$A$13:$A$31,'Projection Assumptions'!$D$13:$D$31)) -> 0.145 | L19: =IF(K19="","",J19*K19) -> 1.6809026
A20: 11 | B20: Agriculture, forestry, fishing and hunting | C20: 2028 | D20: =IFERROR(XLOOKUP(A20,'DATA BLS Projections'!$A$5:$A$23,'DATA BLS Projections'!$E$5:$E$23),"") -> 0.001474046 | E20: =IFERROR(XLOOKUP(A20,'Projection Assumptions'!$A$13:$A$31,'Projection Assumptions'!$C$13:$C$31),"") -> 0.03 | F20: =F19*(1+D20)*(1+E20) -> 65.950812 | G20: =IFERROR(XLOOKUP(A20,'01 Industry Model'!$A$5:$A$23,'01 Industry Model'!$H$5:$H$23),"") -> 0.18131399 | H20: =IFERROR(XLOOKUP(A20,'Projection Assumptions'!$A$13:$A$31,'Projection Assumptions'!$E$13:$E$31),"") -> 0 | I20: =MIN(1,MAX(0,G20+(C20-2025)*H20)) -> 0.18131399 | J20: =F20*I20 -> 11.957805 | K20: =MIN(1,K19+XLOOKUP(A20,'Projection Assumptions'!$A$13:$A$31,'Projection Assumptions'!$D$13:$D$31)) -> 0.195 | L20: =IF(K20="","",J20*K20) -> 2.3317719
A21: 11 | B21: Agriculture, forestry, fishing and hunting | C21: 2029 | D21: =IFERROR(XLOOKUP(A21,'DATA BLS Projections'!$A$5:$A$23,'DATA BLS Projections'!$E$5:$E$23),"") -> 0.001474046 | E21: =IFERROR(XLOOKUP(A21,'Projection Assumptions'!$A$13:$A$31,'Projection Assumptions'!$C$13:$C$31),"") -> 0.03 | F21: =F20*(1+D21)*(1+E21) -> 68.029467 | G21: =IFERROR(XLOOKUP(A21,'01 Industry Model'!$A$5:$A$23,'01 Industry Model'!$H$5:$H$23),"") -> 0.18131399 | H21: =IFERROR(XLOOKUP(A21,'Projection Assumptions'!$A$13:$A$31,'Projection Assumptions'!$E$13:$E$31),"") -> 0 | I21: =MIN(1,MAX(0,G21+(C21-2025)*H21)) -> 0.18131399 | J21: =F21*I21 -> 12.334694 | K21: =MIN(1,K20+XLOOKUP(A21,'Projection Assumptions'!$A$13:$A$31,'Projection Assumptions'!$D$13:$D$31)) -> 0.245 | L21: =IF(K21="","",J21*K21) -> 3.022
A22: 11 | B22: Agriculture, forestry, fishing and hunting | C22: 2030 | D22: =IFERROR(XLOOKUP(A22,'DATA BLS Projections'!$A$5:$A$23,'DATA BLS Projections'!$E$5:$E$23),"") -> 0.001474046 | E22: =IFERROR(XLOOKUP(A22,'Projection Assumptions'!$A$13:$A$31,'Projection Assumptions'!$C$13:$C$31),"") -> 0.03 | F22: =F21*(1+D22)*(1+E22) -> 70.173638 | G22: =IFERROR(XLOOKUP(A22,'01 Industry Model'!$A$5:$A$23,'01 Industry Model'!$H$5:$H$23),"") -> 0.18131399 | H22: =IFERROR(XLOOKUP(A22,'Projection Assumptions'!$A$13:$A$31,'Projection Assumptions'!$E$13:$E$31),"") -> 0 | I22: =MIN(1,MAX(0,G22+(C22-2025)*H22)) -> 0.18131399 | J22: =F22*I22 -> 12.723462 | K22: =MIN(1,K21+XLOOKUP(A22,'Projection Assumptions'!$A$13:$A$31,'Projection Assumptions'!$D$13:$D$31)) -> 0.295 | L22: =IF(K22="","",J22*K22) -> 3.7534214
A23: 21 | B23: Mining, quarrying, and oil and gas extraction | C23: 2025 | D23: =IFERROR(XLOOKUP(A23,'DATA BLS Projections'!$A$5:$A$23,'DATA BLS Projections'!$E$5:$E$23),"") -> 0.00066063067 | E23: =IFERROR(XLOOKUP(A23,'Projection Assumptions'!$A$13:$A$31,'Projection Assumptions'!$C$13:$C$31),"") -> 0.03 | F23: =IFERROR(XLOOKUP(A23,'01 Industry Model'!$A$5:$A$23,'01 Industry Model'!$C$5:$C$23),"") -> 76.216722 | G23: =IFERROR(XLOOKUP(A23,'01 Industry Model'!$A$5:$A$23,'01 Industry Model'!$H$5:$H$23),"") -> 0.29026433 | H23: =IFERROR(XLOOKUP(A23,'Projection Assumptions'!$A$13:$A$31,'Projection Assumptions'!$E$13:$E$31),"") -> 0 | I23: =MIN(1,MAX(0,G23+(C23-2025)*H23)) -> 0.29026433 | J23: =F23*I23 -> 22.122996 | K23: =IF(C23=2025,"",0) | L23: =IF(K23="","",J23*K23)
A24: 21 | B24: Mining, quarrying, and oil and gas extraction | C24: 2026 | D24: =IFERROR(XLOOKUP(A24,'DATA BLS Projections'!$A$5:$A$23,'DATA BLS Projections'!$E$5:$E$23),"") -> 0.00066063067 | E24: =IFERROR(XLOOKUP(A24,'Projection Assumptions'!$A$13:$A$31,'Projection Assumptions'!$C$13:$C$31),"") -> 0.03 | F24: =F23*(1+D24)*(1+E24) -> 78.555085 | G24: =IFERROR(XLOOKUP(A24,'01 Industry Model'!$A$5:$A$23,'01 Industry Model'!$H$5:$H$23),"") -> 0.29026433 | H24: =IFERROR(XLOOKUP(A24,'Projection Assumptions'!$A$13:$A$31,'Projection Assumptions'!$E$13:$E$31),"") -> 0 | I24: =MIN(1,MAX(0,G24+(C24-2025)*H24)) -> 0.29026433 | J24: =F24*I24 -> 22.801739 | K24: =IFERROR(XLOOKUP(A24,'DATA Census'!$A$2:$A$20,'DATA Census'!$C$2:$C$20),"") -> 0.13 | L24: =IF(K24="","",J24*K24) -> 2.9642261
A25: 21 | B25: Mining, quarrying, and oil and gas extraction | C25: 2027 | D25: =IFERROR(XLOOKUP(A25,'DATA BLS Projections'!$A$5:$A$23,'DATA BLS Projections'!$E$5:$E$23),"") -> 0.00066063067 | E25: =IFERROR(XLOOKUP(A25,'Projection Assumptions'!$A$13:$A$31,'Projection Assumptions'!$C$13:$C$31),"") -> 0.03 | F25: =F24*(1+D25)*(1+E25) -> 80.965191 | G25: =IFERROR(XLOOKUP(A25,'01 Industry Model'!$A$5:$A$23,'01 Industry Model'!$H$5:$H$23),"") -> 0.29026433 | H25: =IFERROR(XLOOKUP(A25,'Projection Assumptions'!$A$13:$A$31,'Projection Assumptions'!$E$13:$E$31),"") -> 0 | I25: =MIN(1,MAX(0,G25+(C25-2025)*H25)) -> 0.29026433 | J25: =F25*I25 -> 23.501307 | K25: =MIN(1,K24+XLOOKUP(A25,'Projection Assumptions'!$A$13:$A$31,'Projection Assumptions'!$D$13:$D$31)) -> 0.18 | L25: =IF(K25="","",J25*K25) -> 4.2302352
A26: 21 | B26: Mining, quarrying, and oil and gas extraction | C26: 2028 | D26: =IFERROR(XLOOKUP(A26,'DATA BLS Projections'!$A$5:$A$23,'DATA BLS Projections'!$E$5:$E$23),"") -> 0.00066063067 | E26: =IFERROR(XLOOKUP(A26,'Projection Assumptions'!$A$13:$A$31,'Projection Assumptions'!$C$13:$C$31),"") -> 0.03 | F26: =F25*(1+D26)*(1+E26) -> 83.449239 | G26: =IFERROR(XLOOKUP(A26,'01 Industry Model'!$A$5:$A$23,'01 Industry Model'!$H$5:$H$23),"") -> 0.29026433 | H26: =IFERROR(XLOOKUP(A26,'Projection Assumptions'!$A$13:$A$31,'Projection Assumptions'!$E$13:$E$31),"") -> 0 | I26: =MIN(1,MAX(0,G26+(C26-2025)*H26)) -> 0.29026433 | J26: =F26*I26 -> 24.222338 | K26: =MIN(1,K25+XLOOKUP(A26,'Projection Assumptions'!$A$13:$A$31,'Projection Assumptions'!$D$13:$D$31)) -> 0.23 | L26: =IF(K26="","",J26*K26) -> 5.5711376
A27: 21 | B27: Mining, quarrying, and oil and gas extraction | C27: 2029 | D27: =IFERROR(XLOOKUP(A27,'DATA BLS Projections'!$A$5:$A$23,'DATA BLS Projections'!$E$5:$E$23),"") -> 0.00066063067 | E27: =IFERROR(XLOOKUP(A27,'Projection Assumptions'!$A$13:$A$31,'Projection Assumptions'!$C$13:$C$31),"") -> 0.03 | F27: =F26*(1+D27)*(1+E27) -> 86.009499 | G27: =IFERROR(XLOOKUP(A27,'01 Industry Model'!$A$5:$A$23,'01 Industry Model'!$H$5:$H$23),"") -> 0.29026433 | H27: =IFERROR(XLOOKUP(A27,'Projection Assumptions'!$A$13:$A$31,'Projection Assumptions'!$E$13:$E$31),"") -> 0 | I27: =MIN(1,MAX(0,G27+(C27-2025)*H27)) -> 0.29026433 | J27: =F27*I27 -> 24.96549 | K27: =MIN(1,K26+XLOOKUP(A27,'Projection Assumptions'!$A$13:$A$31,'Projection Assumptions'!$D$13:$D$31)) -> 0.28 | L27: =IF(K27="","",J27*K27) -> 6.9903371
A28: 21 | B28: Mining, quarrying, and oil and gas extraction | C28: 2030 | D28: =IFERROR(XLOOKUP(A28,'DATA BLS Projections'!$A$5:$A$23,'DATA BLS Projections'!$E$5:$E$23),"") -> 0.00066063067 | E28: =IFERROR(XLOOKUP(A28,'Projection Assumptions'!$A$13:$A$31,'Projection Assumptions'!$C$13:$C$31),"") -> 0.03 | F28: =F27*(1+D28)*(1+E28) -> 88.648309 | G28: =IFERROR(XLOOKUP(A28,'01 Industry Model'!$A$5:$A$23,'01 Industry Model'!$H$5:$H$23),"") -> 0.29026433 | H28: =IFERROR(XLOOKUP(A28,'Projection Assumptions'!$A$13:$A$31,'Projection Assumptions'!$E$13:$E$31),"") -> 0 | I28: =MIN(1,MAX(0,G28+(C28-2025)*H28)) -> 0.29026433 | J28: =F28*I28 -> 25.731442 | K28: =MIN(1,K27+XLOOKUP(A28,'Projection Assumptions'!$A$13:$A$31,'Projection Assumptions'!$D$13:$D$31)) -> 0.33 | L28: =IF(K28="","",J28*K28) -> 8.4913759
A29: 22 | B29: Utilities | C29: 2025 | D29: =IFERROR(XLOOKUP(A29,'DATA BLS Projections'!$A$5:$A$23,'DATA BLS Projections'!$E$5:$E$23),"") -> 0.0093733937 | E29: =IFERROR(XLOOKUP(A29,'Projection Assumptions'!$A$13:$A$31,'Projection Assumptions'!$C$13:$C$31),"") -> 0.03 | F29: =IFERROR(XLOOKUP(A29,'01 Industry Model'!$A$5:$A$23,'01 Industry Model'!$C$5:$C$23),"") -> 85.024862 | G29: =IFERROR(XLOOKUP(A29,'01 Industry Model'!$A$5:$A$23,'01 Industry Model'!$H$5:$H$23),"") -> 0.3664496 | H29: =IFERROR(XLOOKUP(A29,'Projection Assumptions'!$A$13:$A$31,'Projection Assumptions'!$E$13:$E$31),"") -> 0 | I29: =MIN(1,MAX(0,G29+(C29-2025)*H29)) -> 0.3664496 | J29: =F29*I29 -> 31.157326 | K29: =IF(C29=2025,"",0) | L29: =IF(K29="","",J29*K29)
A30: 22 | B30: Utilities | C30: 2026 | D30: =IFERROR(XLOOKUP(A30,'DATA BLS Projections'!$A$5:$A$23,'DATA BLS Projections'!$E$5:$E$23),"") -> 0.0093733937 | E30: =IFERROR(XLOOKUP(A30,'Projection Assumptions'!$A$13:$A$31,'Projection Assumptions'!$C$13:$C$31),"") -> 0.03 | F30: =F29*(1+D30)*(1+E30) -> 88.396488 | G30: =IFERROR(XLOOKUP(A30,'01 Industry Model'!$A$5:$A$23,'01 Industry Model'!$H$5:$H$23),"") -> 0.3664496 | H30: =IFERROR(XLOOKUP(A30,'Projection Assumptions'!$A$13:$A$31,'Projection Assumptions'!$E$13:$E$31),"") -> 0 | I30: =MIN(1,MAX(0,G30+(C30-2025)*H30)) -> 0.3664496 | J30: =F30*I30 -> 32.392857 | K30: =IFERROR(XLOOKUP(A30,'DATA Census'!$A$2:$A$20,'DATA Census'!$C$2:$C$20),"") -> 0.167 | L30: =IF(K30="","",J30*K30) -> 5.4096072
A31: 22 | B31: Utilities | C31: 2027 | D31: =IFERROR(XLOOKUP(A31,'DATA BLS Projections'!$A$5:$A$23,'DATA BLS Projections'!$E$5:$E$23),"") -> 0.0093733937 | E31: =IFERROR(XLOOKUP(A31,'Projection Assumptions'!$A$13:$A$31,'Projection Assumptions'!$C$13:$C$31),"") -> 0.03 | F31: =F30*(1+D31)*(1+E31) -> 91.901815 | G31: =IFERROR(XLOOKUP(A31,'01 Industry Model'!$A$5:$A$23,'01 Industry Model'!$H$5:$H$23),"") -> 0.3664496 | H31: =IFERROR(XLOOKUP(A31,'Projection Assumptions'!$A$13:$A$31,'Projection Assumptions'!$E$13:$E$31),"") -> 0 | I31: =MIN(1,MAX(0,G31+(C31-2025)*H31)) -> 0.3664496 | J31: =F31*I31 -> 33.677383 | K31: =MIN(1,K30+XLOOKUP(A31,'Projection Assumptions'!$A$13:$A$31,'Projection Assumptions'!$D$13:$D$31)) -> 0.217 | L31: =IF(K31="","",J31*K31) -> 7.3079921
A32: 22 | B32: Utilities | C32: 2028 | D32: =IFERROR(XLOOKUP(A32,'DATA BLS Projections'!$A$5:$A$23,'DATA BLS Projections'!$E$5:$E$23),"") -> 0.0093733937 | E32: =IFERROR(XLOOKUP(A32,'Projection Assumptions'!$A$13:$A$31,'Projection Assumptions'!$C$13:$C$31),"") -> 0.03 | F32: =F31*(1+D32)*(1+E32) -> 95.546144 | G32: =IFERROR(XLOOKUP(A32,'01 Industry Model'!$A$5:$A$23,'01 Industry Model'!$H$5:$H$23),"") -> 0.3664496 | H32: =IFERROR(XLOOKUP(A32,'Projection Assumptions'!$A$13:$A$31,'Projection Assumptions'!$E$13:$E$31),"") -> 0 | I32: =MIN(1,MAX(0,G32+(C32-2025)*H32)) -> 0.3664496 | J32: =F32*I32 -> 35.012846 | K32: =MIN(1,K31+XLOOKUP(A32,'Projection Assumptions'!$A$13:$A$31,'Projection Assumptions'!$D$13:$D$31)) -> 0.267 | L32: =IF(K32="","",J32*K32) -> 9.3484299
A33: 22 | B33: Utilities | C33: 2029 | D33: =IFERROR(XLOOKUP(A33,'DATA BLS Projections'!$A$5:$A$23,'DATA BLS Projections'!$E$5:$E$23),"") -> 0.0093733937 | E33: =IFERROR(XLOOKUP(A33,'Projection Assumptions'!$A$13:$A$31,'Projection Assumptions'!$C$13:$C$31),"") -> 0.03 | F33: =F32*(1+D33)*(1+E33) -> 99.334988 | G33: =IFERROR(XLOOKUP(A33,'01 Industry Model'!$A$5:$A$23,'01 Industry Model'!$H$5:$H$23),"") -> 0.3664496 | H33: =IFERROR(XLOOKUP(A33,'Projection Assumptions'!$A$13:$A$31,'Projection Assumptions'!$E$13:$E$31),"") -> 0 | I33: =MIN(1,MAX(0,G33+(C33-2025)*H33)) -> 0.3664496 | J33: =F33*I33 -> 36.401266 | K33: =MIN(1,K32+XLOOKUP(A33,'Projection Assumptions'!$A$13:$A$31,'Projection Assumptions'!$D$13:$D$31)) -> 0.317 | L33: =IF(K33="","",J33*K33) -> 11.539201
A34: 22 | B34: Utilities | C34: 2030 | D34: =IFERROR(XLOOKUP(A34,'DATA BLS Projections'!$A$5:$A$23,'DATA BLS Projections'!$E$5:$E$23),"") -> 0.0093733937 | E34: =IFERROR(XLOOKUP(A34,'Projection Assumptions'!$A$13:$A$31,'Projection Assumptions'!$C$13:$C$31),"") -> 0.03 | F34: =F33*(1+D34)*(1+E34) -> 103.27408 | G34: =IFERROR(XLOOKUP(A34,'01 Industry Model'!$A$5:$A$23,'01 Industry Model'!$H$5:$H$23),"") -> 0.3664496 | H34: =IFERROR(XLOOKUP(A34,'Projection Assumptions'!$A$13:$A$31,'Projection Assumptions'!$E$13:$E$31),"") -> 0 | I34: =MIN(1,MAX(0,G34+(C34-2025)*H34)) -> 0.3664496 | J34: =F34*I34 -> 37.844744 | K34: =MIN(1,K33+XLOOKUP(A34,'Projection Assumptions'!$A$13:$A$31,'Projection Assumptions'!$D$13:$D$31)) -> 0.367 | L34: =IF(K34="","",J34*K34) -> 13.889021
A35: 23 | B35: Construction | C35: 2025 | D35: =IFERROR(XLOOKUP(A35,'DATA BLS Projections'!$A$5:$A$23,'DATA BLS Projections'!$E$5:$E$23),"") -> 0.0048604285 | E35: =IFERROR(XLOOKUP(A35,'Projection Assumptions'!$A$13:$A$31,'Projection Assumptions'!$C$13:$C$31),"") -> 0.03 | F35: =IFERROR(XLOOKUP(A35,'01 Industry Model'!$A$5:$A$23,'01 Industry Model'!$C$5:$C$23),"") -> 699.89625 | G35: =IFERROR(XLOOKUP(A35,'01 Industry Model'!$A$5:$A$23,'01 Industry Model'!$H$5:$H$23),"") -> 0.26597382 | H35: =IFERROR(XLOOKUP(A35,'Projection Assumptions'!$A$13:$A$31,'Projection Assumptions'!$E$13:$E$31),"") -> 0 | I35: =MIN(1,MAX(0,G35+(C35-2025)*H35)) -> 0.26597382 | J35: =F35*I35 -> 186.15408 | K35: =IF(C35=2025,"",0) | L35: =IF(K35="","",J35*K35)
A36: 23 | B36: Construction | C36: 2026 | D36: =IFERROR(XLOOKUP(A36,'DATA BLS Projections'!$A$5:$A$23,'DATA BLS Projections'!$E$5:$E$23),"") -> 0.0048604285 | E36: =IFERROR(XLOOKUP(A36,'Projection Assumptions'!$A$13:$A$31,'Projection Assumptions'!$C$13:$C$31),"") -> 0.03 | F36: =F35*(1+D36)*(1+E36) -> 724.39699 | G36: =IFERROR(XLOOKUP(A36,'01 Industry Model'!$A$5:$A$23,'01 Industry Model'!$H$5:$H$23),"") -> 0.26597382 | H36: =IFERROR(XLOOKUP(A36,'Projection Assumptions'!$A$13:$A$31,'Projection Assumptions'!$E$13:$E$31),"") -> 0 | I36: =MIN(1,MAX(0,G36+(C36-2025)*H36)) -> 0.26597382 | J36: =F36*I36 -> 192.67063 | K36: =IFERROR(XLOOKUP(A36,'DATA Census'!$A$2:$A$20,'DATA Census'!$C$2:$C$20),"") -> 0.172 | L36: =IF(K36="","",J36*K36) -> 33.139349
A37: 23 | B37: Construction | C37: 2027 | D37: =IFERROR(XLOOKUP(A37,'DATA BLS Projections'!$A$5:$A$23,'DATA BLS Projections'!$E$5:$E$23),"") -> 0.0048604285 | E37: =IFERROR(XLOOKUP(A37,'Projection Assumptions'!$A$13:$A$31,'Projection Assumptions'!$C$13:$C$31),"") -> 0.03 | F37: =F36*(1+D37)*(1+E37) -> 749.7554 | G37: =IFERROR(XLOOKUP(A37,'01 Industry Model'!$A$5:$A$23,'01 Industry Model'!$H$5:$H$23),"") -> 0.26597382 | H37: =IFERROR(XLOOKUP(A37,'Projection Assumptions'!$A$13:$A$31,'Projection Assumptions'!$E$13:$E$31),"") -> 0 | I37: =MIN(1,MAX(0,G37+(C37-2025)*H37)) -> 0.26597382 | J37: =F37*I37 -> 199.41531 | K37: =MIN(1,K36+XLOOKUP(A37,'Projection Assumptions'!$A$13:$A$31,'Projection Assumptions'!$D$13:$D$31)) -> 0.222 | L37: =IF(K37="","",J37*K37) -> 44.270198
A38: 23 | B38: Construction | C38: 2028 | D38: =IFERROR(XLOOKUP(A38,'DATA BLS Projections'!$A$5:$A$23,'DATA BLS Projections'!$E$5:$E$23),"") -> 0.0048604285 | E38: =IFERROR(XLOOKUP(A38,'Projection Assumptions'!$A$13:$A$31,'Projection Assumptions'!$C$13:$C$31),"") -> 0.03 | F38: =F37*(1+D38)*(1+E38) -> 776.00152 | G38: =IFERROR(XLOOKUP(A38,'01 Industry Model'!$A$5:$A$23,'01 Industry Model'!$H$5:$H$23),"") -> 0.26597382 | H38: =IFERROR(XLOOKUP(A38,'Projection Assumptions'!$A$13:$A$31,'Projection Assumptions'!$E$13:$E$31),"") -> 0 | I38: =MIN(1,MAX(0,G38+(C38-2025)*H38)) -> 0.26597382 | J38: =F38*I38 -> 206.39609 | K38: =MIN(1,K37+XLOOKUP(A38,'Projection Assumptions'!$A$13:$A$31,'Projection Assumptions'!$D$13:$D$31)) -> 0.272 | L38: =IF(K38="","",J38*K38) -> 56.139736
A39: 23 | B39: Construction | C39: 2029 | D39: =IFERROR(XLOOKUP(A39,'DATA BLS Projections'!$A$5:$A$23,'DATA BLS Projections'!$E$5:$E$23),"") -> 0.0048604285 | E39: =IFERROR(XLOOKUP(A39,'Projection Assumptions'!$A$13:$A$31,'Projection Assumptions'!$C$13:$C$31),"") -> 0.03 | F39: =F38*(1+D39)*(1+E39) -> 803.16642 | G39: =IFERROR(XLOOKUP(A39,'01 Industry Model'!$A$5:$A$23,'01 Industry Model'!$H$5:$H$23),"") -> 0.26597382 | H39: =IFERROR(XLOOKUP(A39,'Projection Assumptions'!$A$13:$A$31,'Projection Assumptions'!$E$13:$E$31),"") -> 0 | I39: =MIN(1,MAX(0,G39+(C39-2025)*H39)) -> 0.26597382 | J39: =F39*I39 -> 213.62124 | K39: =MIN(1,K38+XLOOKUP(A39,'Projection Assumptions'!$A$13:$A$31,'Projection Assumptions'!$D$13:$D$31)) -> 0.322 | L39: =IF(K39="","",J39*K39) -> 68.786039
A40: 23 | B40: Construction | C40: 2030 | D40: =IFERROR(XLOOKUP(A40,'DATA BLS Projections'!$A$5:$A$23,'DATA BLS Projections'!$E$5:$E$23),"") -> 0.0048604285 | E40: =IFERROR(XLOOKUP(A40,'Projection Assumptions'!$A$13:$A$31,'Projection Assumptions'!$C$13:$C$31),"") -> 0.03 | F40: =F39*(1+D40)*(1+E40) -> 831.28225 | G40: =IFERROR(XLOOKUP(A40,'01 Industry Model'!$A$5:$A$23,'01 Industry Model'!$H$5:$H$23),"") -> 0.26597382 | H40: =IFERROR(XLOOKUP(A40,'Projection Assumptions'!$A$13:$A$31,'Projection Assumptions'!$E$13:$E$31),"") -> 0 | I40: =MIN(1,MAX(0,G40+(C40-2025)*H40)) -> 0.26597382 | J40: =F40*I40 -> 221.09932 | K40: =MIN(1,K39+XLOOKUP(A40,'Projection Assumptions'!$A$13:$A$31,'Projection Assumptions'!$D$13:$D$31)) -> 0.372 | L40: =IF(K40="","",J40*K40) -> 82.248946
A41: 31-33 | B41: Manufacturing | C41: 2025 | D41: =IFERROR(XLOOKUP(A41,'DATA BLS Projections'!$A$5:$A$23,'DATA BLS Projections'!$E$5:$E$23),"") -> 0.00056923549 | E41: =IFERROR(XLOOKUP(A41,'Projection Assumptions'!$A$13:$A$31,'Projection Assumptions'!$C$13:$C$31),"") -> 0.03 | F41: =IFERROR(XLOOKUP(A41,'01 Industry Model'!$A$5:$A$23,'01 Industry Model'!$C$5:$C$23),"") -> 1125.5427 | G41: =IFERROR(XLOOKUP(A41,'01 Industry Model'!$A$5:$A$23,'01 Industry Model'!$H$5:$H$23),"") -> 0.33208008 | H41: =IFERROR(XLOOKUP(A41,'Projection Assumptions'!$A$13:$A$31,'Projection Assumptions'!$E$13:$E$31),"") -> 0 | I41: =MIN(1,MAX(0,G41+(C41-2025)*H41)) -> 0.33208008 | J41: =F41*I41 -> 373.7703 | K41: =IF(C41=2025,"",0) | L41: =IF(K41="","",J41*K41)
A42: 31-33 | B42: Manufacturing | C42: 2026 | D42: =IFERROR(XLOOKUP(A42,'DATA BLS Projections'!$A$5:$A$23,'DATA BLS Projections'!$E$5:$E$23),"") -> 0.00056923549 | E42: =IFERROR(XLOOKUP(A42,'Projection Assumptions'!$A$13:$A$31,'Projection Assumptions'!$C$13:$C$31),"") -> 0.03 | F42: =F41*(1+D42)*(1+E42) -> 1159.9689 | G42: =IFERROR(XLOOKUP(A42,'01 Industry Model'!$A$5:$A$23,'01 Industry Model'!$H$5:$H$23),"") -> 0.33208008 | H42: =IFERROR(XLOOKUP(A42,'Projection Assumptions'!$A$13:$A$31,'Projection Assumptions'!$E$13:$E$31),"") -> 0 | I42: =MIN(1,MAX(0,G42+(C42-2025)*H42)) -> 0.33208008 | J42: =F42*I42 -> 385.20255 | K42: =IFERROR(XLOOKUP(A42,'DATA Census'!$A$2:$A$20,'DATA Census'!$C$2:$C$20),"") -> 0.208 | L42: =IF(K42="","",J42*K42) -> 80.122131
A43: 31-33 | B43: Manufacturing | C43: 2027 | D43: =IFERROR(XLOOKUP(A43,'DATA BLS Projections'!$A$5:$A$23,'DATA BLS Projections'!$E$5:$E$23),"") -> 0.00056923549 | E43: =IFERROR(XLOOKUP(A43,'Projection Assumptions'!$A$13:$A$31,'Projection Assumptions'!$C$13:$C$31),"") -> 0.03 | F43: =F42*(1+D43)*(1+E43) -> 1195.448 | G43: =IFERROR(XLOOKUP(A43,'01 Industry Model'!$A$5:$A$23,'01 Industry Model'!$H$5:$H$23),"") -> 0.33208008 | H43: =IFERROR(XLOOKUP(A43,'Projection Assumptions'!$A$13:$A$31,'Projection Assumptions'!$E$13:$E$31),"") -> 0 | I43: =MIN(1,MAX(0,G43+(C43-2025)*H43)) -> 0.33208008 | J43: =F43*I43 -> 396.98448 | K43: =MIN(1,K42+XLOOKUP(A43,'Projection Assumptions'!$A$13:$A$31,'Projection Assumptions'!$D$13:$D$31)) -> 0.258 | L43: =IF(K43="","",J43*K43) -> 102.422
A44: 31-33 | B44: Manufacturing | C44: 2028 | D44: =IFERROR(XLOOKUP(A44,'DATA BLS Projections'!$A$5:$A$23,'DATA BLS Projections'!$E$5:$E$23),"") -> 0.00056923549 | E44: =IFERROR(XLOOKUP(A44,'Projection Assumptions'!$A$13:$A$31,'Projection Assumptions'!$C$13:$C$31),"") -> 0.03 | F44: =F43*(1+D44)*(1+E44) -> 1232.0124 | G44: =IFERROR(XLOOKUP(A44,'01 Industry Model'!$A$5:$A$23,'01 Industry Model'!$H$5:$H$23),"") -> 0.33208008 | H44: =IFERROR(XLOOKUP(A44,'Projection Assumptions'!$A$13:$A$31,'Projection Assumptions'!$E$13:$E$31),"") -> 0 | I44: =MIN(1,MAX(0,G44+(C44-2025)*H44)) -> 0.33208008 | J44: =F44*I44 -> 409.12677 | K44: =MIN(1,K43+XLOOKUP(A44,'Projection Assumptions'!$A$13:$A$31,'Projection Assumptions'!$D$13:$D$31)) -> 0.308 | L44: =IF(K44="","",J44*K44) -> 126.01105
A45: 31-33 | B45: Manufacturing | C45: 2029 | D45: =IFERROR(XLOOKUP(A45,'DATA BLS Projections'!$A$5:$A$23,'DATA BLS Projections'!$E$5:$E$23),"") -> 0.00056923549 | E45: =IFERROR(XLOOKUP(A45,'Projection Assumptions'!$A$13:$A$31,'Projection Assumptions'!$C$13:$C$31),"") -> 0.03 | F45: =F44*(1+D45)*(1+E45) -> 1269.6951 | G45: =IFERROR(XLOOKUP(A45,'01 Industry Model'!$A$5:$A$23,'01 Industry Model'!$H$5:$H$23),"") -> 0.33208008 | H45: =IFERROR(XLOOKUP(A45,'Projection Assumptions'!$A$13:$A$31,'Projection Assumptions'!$E$13:$E$31),"") -> 0 | I45: =MIN(1,MAX(0,G45+(C45-2025)*H45)) -> 0.33208008 | J45: =F45*I45 -> 421.64045 | K45: =MIN(1,K44+XLOOKUP(A45,'Projection Assumptions'!$A$13:$A$31,'Projection Assumptions'!$D$13:$D$31)) -> 0.358 | L45: =IF(K45="","",J45*K45) -> 150.94728
A46: 31-33 | B46: Manufacturing | C46: 2030 | D46: =IFERROR(XLOOKUP(A46,'DATA BLS Projections'!$A$5:$A$23,'DATA BLS Projections'!$E$5:$E$23),"") -> 0.00056923549 | E46: =IFERROR(XLOOKUP(A46,'Projection Assumptions'!$A$13:$A$31,'Projection Assumptions'!$C$13:$C$31),"") -> 0.03 | F46: =F45*(1+D46)*(1+E46) -> 1308.5304 | G46: =IFERROR(XLOOKUP(A46,'01 Industry Model'!$A$5:$A$23,'01 Industry Model'!$H$5:$H$23),"") -> 0.33208008 | H46: =IFERROR(XLOOKUP(A46,'Projection Assumptions'!$A$13:$A$31,'Projection Assumptions'!$E$13:$E$31),"") -> 0 | I46: =MIN(1,MAX(0,G46+(C46-2025)*H46)) -> 0.33208008 | J46: =F46*I46 -> 434.53688 | K46: =MIN(1,K45+XLOOKUP(A46,'Projection Assumptions'!$A$13:$A$31,'Projection Assumptions'!$D$13:$D$31)) -> 0.408 | L46: =IF(K46="","",J46*K46) -> 177.29105
A47: 42 | B47: Wholesale trade | C47: 2025 | D47: =IFERROR(XLOOKUP(A47,'DATA BLS Projections'!$A$5:$A$23,'DATA BLS Projections'!$E$5:$E$23),"") -> 0.0020472139 | E47: =IFERROR(XLOOKUP(A47,'Projection Assumptions'!$A$13:$A$31,'Projection Assumptions'!$C$13:$C$31),"") -> 0.03 | F47: =IFERROR(XLOOKUP(A47,'01 Industry Model'!$A$5:$A$23,'01 Industry Model'!$C$5:$C$23),"") -> 638.87897 | G47: =IFERROR(XLOOKUP(A47,'01 Industry Model'!$A$5:$A$23,'01 Industry Model'!$H$5:$H$23),"") -> 0.46206547 | H47: =IFERROR(XLOOKUP(A47,'Projection Assumptions'!$A$13:$A$31,'Projection Assumptions'!$E$13:$E$31),"") -> 0 | I47: =MIN(1,MAX(0,G47+(C47-2025)*H47)) -> 0.46206547 | J47: =F47*I47 -> 295.20392 | K47: =IF(C47=2025,"",0) | L47: =IF(K47="","",J47*K47)
A48: 42 | B48: Wholesale trade | C48: 2026 | D48: =IFERROR(XLOOKUP(A48,'DATA BLS Projections'!$A$5:$A$23,'DATA BLS Projections'!$E$5:$E$23),"") -> 0.0020472139 | E48: =IFERROR(XLOOKUP(A48,'Projection Assumptions'!$A$13:$A$31,'Projection Assumptions'!$C$13:$C$31),"") -> 0.03 | F48: =F47*(1+D48)*(1+E48) -> 659.3925 | G48: =IFERROR(XLOOKUP(A48,'01 Industry Model'!$A$5:$A$23,'01 Industry Model'!$H$5:$H$23),"") -> 0.46206547 | H48: =IFERROR(XLOOKUP(A48,'Projection Assumptions'!$A$13:$A$31,'Projection Assumptions'!$E$13:$E$31),"") -> 0 | I48: =MIN(1,MAX(0,G48+(C48-2025)*H48)) -> 0.46206547 | J48: =F48*I48 -> 304.68251 | K48: =IFERROR(XLOOKUP(A48,'DATA Census'!$A$2:$A$20,'DATA Census'!$C$2:$C$20),"") -> 0.216 | L48: =IF(K48="","",J48*K48) -> 65.811422
A49: 42 | B49: Wholesale trade | C49: 2027 | D49: =IFERROR(XLOOKUP(A49,'DATA BLS Projections'!$A$5:$A$23,'DATA BLS Projections'!$E$5:$E$23),"") -> 0.0020472139 | E49: =IFERROR(XLOOKUP(A49,'Projection Assumptions'!$A$13:$A$31,'Projection Assumptions'!$C$13:$C$31),"") -> 0.03 | F49: =F48*(1+D49)*(1+E49) -> 680.56469 | G49: =IFERROR(XLOOKUP(A49,'01 Industry Model'!$A$5:$A$23,'01 Industry Model'!$H$5:$H$23),"") -> 0.46206547 | H49: =IFERROR(XLOOKUP(A49,'Projection Assumptions'!$A$13:$A$31,'Projection Assumptions'!$E$13:$E$31),"") -> 0 | I49: =MIN(1,MAX(0,G49+(C49-2025)*H49)) -> 0.46206547 | J49: =F49*I49 -> 314.46545 | K49: =MIN(1,K48+XLOOKUP(A49,'Projection Assumptions'!$A$13:$A$31,'Projection Assumptions'!$D$13:$D$31)) -> 0.266 | L49: =IF(K49="","",J49*K49) -> 83.647809
A50: 42 | B50: Wholesale trade | C50: 2028 | D50: =IFERROR(XLOOKUP(A50,'DATA BLS Projections'!$A$5:$A$23,'DATA BLS Projections'!$E$5:$E$23),"") -> 0.0020472139 | E50: =IFERROR(XLOOKUP(A50,'Projection Assumptions'!$A$13:$A$31,'Projection Assumptions'!$C$13:$C$31),"") -> 0.03 | F50: =F49*(1+D50)*(1+E50) -> 702.41669 | G50: =IFERROR(XLOOKUP(A50,'01 Industry Model'!$A$5:$A$23,'01 Industry Model'!$H$5:$H$23),"") -> 0.46206547 | H50: =IFERROR(XLOOKUP(A50,'Projection Assumptions'!$A$13:$A$31,'Projection Assumptions'!$E$13:$E$31),"") -> 0 | I50: =MIN(1,MAX(0,G50+(C50-2025)*H50)) -> 0.46206547 | J50: =F50*I50 -> 324.5625 | K50: =MIN(1,K49+XLOOKUP(A50,'Projection Assumptions'!$A$13:$A$31,'Projection Assumptions'!$D$13:$D$31)) -> 0.316 | L50: =IF(K50="","",J50*K50) -> 102.56175
A51: 42 | B51: Wholesale trade | C51: 2029 | D51: =IFERROR(XLOOKUP(A51,'DATA BLS Projections'!$A$5:$A$23,'DATA BLS Projections'!$E$5:$E$23),"") -> 0.0020472139 | E51: =IFERROR(XLOOKUP(A51,'Projection Assumptions'!$A$13:$A$31,'Projection Assumptions'!$C$13:$C$31),"") -> 0.03 | F51: =F50*(1+D51)*(1+E51) -> 724.97033 | G51: =IFERROR(XLOOKUP(A51,'01 Industry Model'!$A$5:$A$23,'01 Industry Model'!$H$5:$H$23),"") -> 0.46206547 | H51: =IFERROR(XLOOKUP(A51,'Projection Assumptions'!$A$13:$A$31,'Projection Assumptions'!$E$13:$E$31),"") -> 0 | I51: =MIN(1,MAX(0,G51+(C51-2025)*H51)) -> 0.46206547 | J51: =F51*I51 -> 334.98376 | K51: =MIN(1,K50+XLOOKUP(A51,'Projection Assumptions'!$A$13:$A$31,'Projection Assumptions'!$D$13:$D$31)) -> 0.366 | L51: =IF(K51="","",J51*K51) -> 122.60406
A52: 42 | B52: Wholesale trade | C52: 2030 | D52: =IFERROR(XLOOKUP(A52,'DATA BLS Projections'!$A$5:$A$23,'DATA BLS Projections'!$E$5:$E$23),"") -> 0.0020472139 | E52: =IFERROR(XLOOKUP(A52,'Projection Assumptions'!$A$13:$A$31,'Projection Assumptions'!$C$13:$C$31),"") -> 0.03 | F52: =F51*(1+D52)*(1+E52) -> 748.24813 | G52: =IFERROR(XLOOKUP(A52,'01 Industry Model'!$A$5:$A$23,'01 Industry Model'!$H$5:$H$23),"") -> 0.46206547 | H52: =IFERROR(XLOOKUP(A52,'Projection Assumptions'!$A$13:$A$31,'Projection Assumptions'!$E$13:$E$31),"") -> 0 | I52: =MIN(1,MAX(0,G52+(C52-2025)*H52)) -> 0.46206547 | J52: =F52*I52 -> 345.73963 | K52: =MIN(1,K51+XLOOKUP(A52,'Projection Assumptions'!$A$13:$A$31,'Projection Assumptions'!$D$13:$D$31)) -> 0.416 | L52: =IF(K52="","",J52*K52) -> 143.82769
A53: 44-45 | B53: Retail trade | C53: 2025 | D53: =IFERROR(XLOOKUP(A53,'DATA BLS Projections'!$A$5:$A$23,'DATA BLS Projections'!$E$5:$E$23),"") -> -0.00017824132 | E53: =IFERROR(XLOOKUP(A53,'Projection Assumptions'!$A$13:$A$31,'Projection Assumptions'!$C$13:$C$31),"") -> 0.03 | F53: =IFERROR(XLOOKUP(A53,'01 Industry Model'!$A$5:$A$23,'01 Industry Model'!$C$5:$C$23),"") -> 668.86357 | G53: =IFERROR(XLOOKUP(A53,'01 Industry Model'!$A$5:$A$23,'01 Industry Model'!$H$5:$H$23),"") -> 0.43831363 | H53: =IFERROR(XLOOKUP(A53,'Projection Assumptions'!$A$13:$A$31,'Projection Assumptions'!$E$13:$E$31),"") -> 0 | I53: =MIN(1,MAX(0,G53+(C53-2025)*H53)) -> 0.43831363 | J53: =F53*I53 -> 293.17202 | K53: =IF(C53=2025,"",0) | L53: =IF(K53="","",J53*K53)
A54: 44-45 | B54: Retail trade | C54: 2026 | D54: =IFERROR(XLOOKUP(A54,'DATA BLS Projections'!$A$5:$A$23,'DATA BLS Projections'!$E$5:$E$23),"") -> -0.00017824132 | E54: =IFERROR(XLOOKUP(A54,'Projection Assumptions'!$A$13:$A$31,'Projection Assumptions'!$C$13:$C$31),"") -> 0.03 | F54: =F53*(1+D54)*(1+E54) -> 688.80668 | G54: =IFERROR(XLOOKUP(A54,'01 Industry Model'!$A$5:$A$23,'01 Industry Model'!$H$5:$H$23),"") -> 0.43831363 | H54: =IFERROR(XLOOKUP(A54,'Projection Assumptions'!$A$13:$A$31,'Projection Assumptions'!$E$13:$E$31),"") -> 0 | I54: =MIN(1,MAX(0,G54+(C54-2025)*H54)) -> 0.43831363 | J54: =F54*I54 -> 301.91335 | K54: =IFERROR(XLOOKUP(A54,'DATA Census'!$A$2:$A$20,'DATA Census'!$C$2:$C$20),"") -> 0.168 | L54: =IF(K54="","",J54*K54) -> 50.721443
A55: 44-45 | B55: Retail trade | C55: 2027 | D55: =IFERROR(XLOOKUP(A55,'DATA BLS Projections'!$A$5:$A$23,'DATA BLS Projections'!$E$5:$E$23),"") -> -0.00017824132 | E55: =IFERROR(XLOOKUP(A55,'Projection Assumptions'!$A$13:$A$31,'Projection Assumptions'!$C$13:$C$31),"") -> 0.03 | F55: =F54*(1+D55)*(1+E55) -> 709.34442 | G55: =IFERROR(XLOOKUP(A55,'01 Industry Model'!$A$5:$A$23,'01 Industry Model'!$H$5:$H$23),"") -> 0.43831363 | H55: =IFERROR(XLOOKUP(A55,'Projection Assumptions'!$A$13:$A$31,'Projection Assumptions'!$E$13:$E$31),"") -> 0 | I55: =MIN(1,MAX(0,G55+(C55-2025)*H55)) -> 0.43831363 | J55: =F55*I55 -> 310.91533 | K55: =MIN(1,K54+XLOOKUP(A55,'Projection Assumptions'!$A$13:$A$31,'Projection Assumptions'!$D$13:$D$31)) -> 0.218 | L55: =IF(K55="","",J55*K55) -> 67.779541
A56: 44-45 | B56: Retail trade | C56: 2028 | D56: =IFERROR(XLOOKUP(A56,'DATA BLS Projections'!$A$5:$A$23,'DATA BLS Projections'!$E$5:$E$23),"") -> -0.00017824132 | E56: =IFERROR(XLOOKUP(A56,'Projection Assumptions'!$A$13:$A$31,'Projection Assumptions'!$C$13:$C$31),"") -> 0.03 | F56: =F55*(1+D56)*(1+E56) -> 730.49453 | G56: =IFERROR(XLOOKUP(A56,'01 Industry Model'!$A$5:$A$23,'01 Industry Model'!$H$5:$H$23),"") -> 0.43831363 | H56: =IFERROR(XLOOKUP(A56,'Projection Assumptions'!$A$13:$A$31,'Projection Assumptions'!$E$13:$E$31),"") -> 0 | I56: =MIN(1,MAX(0,G56+(C56-2025)*H56)) -> 0.43831363 | J56: =F56*I56 -> 320.18571 | K56: =MIN(1,K55+XLOOKUP(A56,'Projection Assumptions'!$A$13:$A$31,'Projection Assumptions'!$D$13:$D$31)) -> 0.268 | L56: =IF(K56="","",J56*K56) -> 85.809769
A57: 44-45 | B57: Retail trade | C57: 2029 | D57: =IFERROR(XLOOKUP(A57,'DATA BLS Projections'!$A$5:$A$23,'DATA BLS Projections'!$E$5:$E$23),"") -> -0.00017824132 | E57: =IFERROR(XLOOKUP(A57,'Projection Assumptions'!$A$13:$A$31,'Projection Assumptions'!$C$13:$C$31),"") -> 0.03 | F57: =F56*(1+D57)*(1+E57) -> 752.27525 | G57: =IFERROR(XLOOKUP(A57,'01 Industry Model'!$A$5:$A$23,'01 Industry Model'!$H$5:$H$23),"") -> 0.43831363 | H57: =IFERROR(XLOOKUP(A57,'Projection Assumptions'!$A$13:$A$31,'Projection Assumptions'!$E$13:$E$31),"") -> 0 | I57: =MIN(1,MAX(0,G57+(C57-2025)*H57)) -> 0.43831363 | J57: =F57*I57 -> 329.73249 | K57: =MIN(1,K56+XLOOKUP(A57,'Projection Assumptions'!$A$13:$A$31,'Projection Assumptions'!$D$13:$D$31)) -> 0.318 | L57: =IF(K57="","",J57*K57) -> 104.85493
A58: 44-45 | B58: Retail trade | C58: 2030 | D58: =IFERROR(XLOOKUP(A58,'DATA BLS Projections'!$A$5:$A$23,'DATA BLS Projections'!$E$5:$E$23),"") -> -0.00017824132 | E58: =IFERROR(XLOOKUP(A58,'Projection Assumptions'!$A$13:$A$31,'Projection Assumptions'!$C$13:$C$31),"") -> 0.03 | F58: =F57*(1+D58)*(1+E58) -> 774.7054 | G58: =IFERROR(XLOOKUP(A58,'01 Industry Model'!$A$5:$A$23,'01 Industry Model'!$H$5:$H$23),"") -> 0.43831363 | H58: =IFERROR(XLOOKUP(A58,'Projection Assumptions'!$A$13:$A$31,'Projection Assumptions'!$E$13:$E$31),"") -> 0 | I58: =MIN(1,MAX(0,G58+(C58-2025)*H58)) -> 0.43831363 | J58: =F58*I58 -> 339.56393 | K58: =MIN(1,K57+XLOOKUP(A58,'Projection Assumptions'!$A$13:$A$31,'Projection Assumptions'!$D$13:$D$31)) -> 0.368 | L58: =IF(K58="","",J58*K58) -> 124.95953
A59: 48-49 | B59: Transportation and warehousing | C59: 2025 | D59: =IFERROR(XLOOKUP(A59,'DATA BLS Projections'!$A$5:$A$23,'DATA BLS Projections'!$E$5:$E$23),"") -> 0.0030792041 | E59: =IFERROR(XLOOKUP(A59,'Projection Assumptions'!$A$13:$A$31,'Projection Assumptions'!$C$13:$C$31),"") -> 0.03 | F59: =IFERROR(XLOOKUP(A59,'01 Industry Model'!$A$5:$A$23,'01 Industry Model'!$C$5:$C$23),"") -> 455.48394 | G59: =IFERROR(XLOOKUP(A59,'01 Industry Model'!$A$5:$A$23,'01 Industry Model'!$H$5:$H$23),"") -> 0.3291779 | H59: =IFERROR(XLOOKUP(A59,'Projection Assumptions'!$A$13:$A$31,'Projection Assumptions'!$E$13:$E$31),"") -> 0 | I59: =MIN(1,MAX(0,G59+(C59-2025)*H59)) -> 0.3291779 | J59: =F59*I59 -> 149.93525 | K59: =IF(C59=2025,"",0) | L59: =IF(K59="","",J59*K59)
A60: 48-49 | B60: Transportation and warehousing | C60: 2026 | D60: =IFERROR(XLOOKUP(A60,'DATA BLS Projections'!$A$5:$A$23,'DATA BLS Projections'!$E$5:$E$23),"") -> 0.0030792041 | E60: =IFERROR(XLOOKUP(A60,'Projection Assumptions'!$A$13:$A$31,'Projection Assumptions'!$C$13:$C$31),"") -> 0.03 | F60: =F59*(1+D60)*(1+E60) -> 470.59307 | G60: =IFERROR(XLOOKUP(A60,'01 Industry Model'!$A$5:$A$23,'01 Industry Model'!$H$5:$H$23),"") -> 0.3291779 | H60: =IFERROR(XLOOKUP(A60,'Projection Assumptions'!$A$13:$A$31,'Projection Assumptions'!$E$13:$E$31),"") -> 0 | I60: =MIN(1,MAX(0,G60+(C60-2025)*H60)) -> 0.3291779 | J60: =F60*I60 -> 154.90884 | K60: =IFERROR(XLOOKUP(A60,'DATA Census'!$A$2:$A$20,'DATA Census'!$C$2:$C$20),"") -> 0.105 | L60: =IF(K60="","",J60*K60) -> 16.265428
A61: 48-49 | B61: Transportation and warehousing | C61: 2027 | D61: =IFERROR(XLOOKUP(A61,'DATA BLS Projections'!$A$5:$A$23,'DATA BLS Projections'!$E$5:$E$23),"") -> 0.0030792041 | E61: =IFERROR(XLOOKUP(A61,'Projection Assumptions'!$A$13:$A$31,'Projection Assumptions'!$C$13:$C$31),"") -> 0.03 | F61: =F60*(1+D61)*(1+E61) -> 486.20338 | G61: =IFERROR(XLOOKUP(A61,'01 Industry Model'!$A$5:$A$23,'01 Industry Model'!$H$5:$H$23),"") -> 0.3291779 | H61: =IFERROR(XLOOKUP(A61,'Projection Assumptions'!$A$13:$A$31,'Projection Assumptions'!$E$13:$E$31),"") -> 0 | I61: =MIN(1,MAX(0,G61+(C61-2025)*H61)) -> 0.3291779 | J61: =F61*I61 -> 160.04741 | K61: =MIN(1,K60+XLOOKUP(A61,'Projection Assumptions'!$A$13:$A$31,'Projection Assumptions'!$D$13:$D$31)) -> 0.155 | L61: =IF(K61="","",J61*K61) -> 24.807348
A62: 48-49 | B62: Transportation and warehousing | C62: 2028 | D62: =IFERROR(XLOOKUP(A62,'DATA BLS Projections'!$A$5:$A$23,'DATA BLS Projections'!$E$5:$E$23),"") -> 0.0030792041 | E62: =IFERROR(XLOOKUP(A62,'Projection Assumptions'!$A$13:$A$31,'Projection Assumptions'!$C$13:$C$31),"") -> 0.03 | F62: =F61*(1+D62)*(1+E62) -> 502.33152 | G62: =IFERROR(XLOOKUP(A62,'01 Industry Model'!$A$5:$A$23,'01 Industry Model'!$H$5:$H$23),"") -> 0.3291779 | H62: =IFERROR(XLOOKUP(A62,'Projection Assumptions'!$A$13:$A$31,'Projection Assumptions'!$E$13:$E$31),"") -> 0 | I62: =MIN(1,MAX(0,G62+(C62-2025)*H62)) -> 0.3291779 | J62: =F62*I62 -> 165.35643 | K62: =MIN(1,K61+XLOOKUP(A62,'Projection Assumptions'!$A$13:$A$31,'Projection Assumptions'!$D$13:$D$31)) -> 0.205 | L62: =IF(K62="","",J62*K62) -> 33.898069
A63: 48-49 | B63: Transportation and warehousing | C63: 2029 | D63: =IFERROR(XLOOKUP(A63,'DATA BLS Projections'!$A$5:$A$23,'DATA BLS Projections'!$E$5:$E$23),"") -> 0.0030792041 | E63: =IFERROR(XLOOKUP(A63,'Projection Assumptions'!$A$13:$A$31,'Projection Assumptions'!$C$13:$C$31),"") -> 0.03 | F63: =F62*(1+D63)*(1+E63) -> 518.99465 | G63: =IFERROR(XLOOKUP(A63,'01 Industry Model'!$A$5:$A$23,'01 Industry Model'!$H$5:$H$23),"") -> 0.3291779 | H63: =IFERROR(XLOOKUP(A63,'Projection Assumptions'!$A$13:$A$31,'Projection Assumptions'!$E$13:$E$31),"") -> 0 | I63: =MIN(1,MAX(0,G63+(C63-2025)*H63)) -> 0.3291779 | J63: =F63*I63 -> 170.84157 | K63: =MIN(1,K62+XLOOKUP(A63,'Projection Assumptions'!$A$13:$A$31,'Projection Assumptions'!$D$13:$D$31)) -> 0.255 | L63: =IF(K63="","",J63*K63) -> 43.564599
A64: 48-49 | B64: Transportation and warehousing | C64: 2030 | D64: =IFERROR(XLOOKUP(A64,'DATA BLS Projections'!$A$5:$A$23,'DATA BLS Projections'!$E$5:$E$23),"") -> 0.0030792041 | E64: =IFERROR(XLOOKUP(A64,'Projection Assumptions'!$A$13:$A$31,'Projection Assumptions'!$C$13:$C$31),"") -> 0.03 | F64: =F63*(1+D64)*(1+E64) -> 536.21052 | G64: =IFERROR(XLOOKUP(A64,'01 Industry Model'!$A$5:$A$23,'01 Industry Model'!$H$5:$H$23),"") -> 0.3291779 | H64: =IFERROR(XLOOKUP(A64,'Projection Assumptions'!$A$13:$A$31,'Projection Assumptions'!$E$13:$E$31),"") -> 0 | I64: =MIN(1,MAX(0,G64+(C64-2025)*H64)) -> 0.3291779 | J64: =F64*I64 -> 176.50865 | K64: =MIN(1,K63+XLOOKUP(A64,'Projection Assumptions'!$A$13:$A$31,'Projection Assumptions'!$D$13:$D$31)) -> 0.305 | L64: =IF(K64="","",J64*K64) -> 53.835138
A65: 51 | B65: Information | C65: 2025 | D65: =IFERROR(XLOOKUP(A65,'DATA BLS Projections'!$A$5:$A$23,'DATA BLS Projections'!$E$5:$E$23),"") -> 0.0051549744 | E65: =IFERROR(XLOOKUP(A65,'Projection Assumptions'!$A$13:$A$31,'Projection Assumptions'!$C$13:$C$31),"") -> 0.03 | F65: =IFERROR(XLOOKUP(A65,'01 Industry Model'!$A$5:$A$23,'01 Industry Model'!$C$5:$C$23),"") -> 544.46957 | G65: =IFERROR(XLOOKUP(A65,'01 Industry Model'!$A$5:$A$23,'01 Industry Model'!$H$5:$H$23),"") -> 0.5643459 | H65: =IFERROR(XLOOKUP(A65,'Projection Assumptions'!$A$13:$A$31,'Projection Assumptions'!$E$13:$E$31),"") -> 0 | I65: =MIN(1,MAX(0,G65+(C65-2025)*H65)) -> 0.5643459 | J65: =F65*I65 -> 307.26917 | K65: =IF(C65=2025,"",0) | L65: =IF(K65="","",J65*K65)
A66: 51 | B66: Information | C66: 2026 | D66: =IFERROR(XLOOKUP(A66,'DATA BLS Projections'!$A$5:$A$23,'DATA BLS Projections'!$E$5:$E$23),"") -> 0.0051549744 | E66: =IFERROR(XLOOKUP(A66,'Projection Assumptions'!$A$13:$A$31,'Projection Assumptions'!$C$13:$C$31),"") -> 0.03 | F66: =F65*(1+D66)*(1+E66) -> 563.69458 | G66: =IFERROR(XLOOKUP(A66,'01 Industry Model'!$A$5:$A$23,'01 Industry Model'!$H$5:$H$23),"") -> 0.5643459 | H66: =IFERROR(XLOOKUP(A66,'Projection Assumptions'!$A$13:$A$31,'Projection Assumptions'!$E$13:$E$31),"") -> 0 | I66: =MIN(1,MAX(0,G66+(C66-2025)*H66)) -> 0.5643459 | J66: =F66*I66 -> 318.11873 | K66: =IFERROR(XLOOKUP(A66,'DATA Census'!$A$2:$A$20,'DATA Census'!$C$2:$C$20),"") -> 0.502 | L66: =IF(K66="","",J66*K66) -> 159.6956
A67: 51 | B67: Information | C67: 2027 | D67: =IFERROR(XLOOKUP(A67,'DATA BLS Projections'!$A$5:$A$23,'DATA BLS Projections'!$E$5:$E$23),"") -> 0.0051549744 | E67: =IFERROR(XLOOKUP(A67,'Projection Assumptions'!$A$13:$A$31,'Projection Assumptions'!$C$13:$C$31),"") -> 0.03 | F67: =F66*(1+D67)*(1+E67) -> 583.59842 | G67: =IFERROR(XLOOKUP(A67,'01 Industry Model'!$A$5:$A$23,'01 Industry Model'!$H$5:$H$23),"") -> 0.5643459 | H67: =IFERROR(XLOOKUP(A67,'Projection Assumptions'!$A$13:$A$31,'Projection Assumptions'!$E$13:$E$31),"") -> 0 | I67: =MIN(1,MAX(0,G67+(C67-2025)*H67)) -> 0.5643459 | J67: =F67*I67 -> 329.35138 | K67: =MIN(1,K66+XLOOKUP(A67,'Projection Assumptions'!$A$13:$A$31,'Projection Assumptions'!$D$13:$D$31)) -> 0.552 | L67: =IF(K67="","",J67*K67) -> 181.80196
A68: 51 | B68: Information | C68: 2028 | D68: =IFERROR(XLOOKUP(A68,'DATA BLS Projections'!$A$5:$A$23,'DATA BLS Projections'!$E$5:$E$23),"") -> 0.0051549744 | E68: =IFERROR(XLOOKUP(A68,'Projection Assumptions'!$A$13:$A$31,'Projection Assumptions'!$C$13:$C$31),"") -> 0.03 | F68: =F67*(1+D68)*(1+E68) -> 604.20506 | G68: =IFERROR(XLOOKUP(A68,'01 Industry Model'!$A$5:$A$23,'01 Industry Model'!$H$5:$H$23),"") -> 0.5643459 | H68: =IFERROR(XLOOKUP(A68,'Projection Assumptions'!$A$13:$A$31,'Projection Assumptions'!$E$13:$E$31),"") -> 0 | I68: =MIN(1,MAX(0,G68+(C68-2025)*H68)) -> 0.5643459 | J68: =F68*I68 -> 340.98065 | K68: =MIN(1,K67+XLOOKUP(A68,'Projection Assumptions'!$A$13:$A$31,'Projection Assumptions'!$D$13:$D$31)) -> 0.602 | L68: =IF(K68="","",J68*K68) -> 205.27035
A69: 51 | B69: Information | C69: 2029 | D69: =IFERROR(XLOOKUP(A69,'DATA BLS Projections'!$A$5:$A$23,'DATA BLS Projections'!$E$5:$E$23),"") -> 0.0051549744 | E69: =IFERROR(XLOOKUP(A69,'Projection Assumptions'!$A$13:$A$31,'Projection Assumptions'!$C$13:$C$31),"") -> 0.03 | F69: =F68*(1+D69)*(1+E69) -> 625.53932 | G69: =IFERROR(XLOOKUP(A69,'01 Industry Model'!$A$5:$A$23,'01 Industry Model'!$H$5:$H$23),"") -> 0.5643459 | H69: =IFERROR(XLOOKUP(A69,'Projection Assumptions'!$A$13:$A$31,'Projection Assumptions'!$E$13:$E$31),"") -> 0 | I69: =MIN(1,MAX(0,G69+(C69-2025)*H69)) -> 0.5643459 | J69: =F69*I69 -> 353.02055 | K69: =MIN(1,K68+XLOOKUP(A69,'Projection Assumptions'!$A$13:$A$31,'Projection Assumptions'!$D$13:$D$31)) -> 0.652 | L69: =IF(K69="","",J69*K69) -> 230.1694
A70: 51 | B70: Information | C70: 2030 | D70: =IFERROR(XLOOKUP(A70,'DATA BLS Projections'!$A$5:$A$23,'DATA BLS Projections'!$E$5:$E$23),"") -> 0.0051549744 | E70: =IFERROR(XLOOKUP(A70,'Projection Assumptions'!$A$13:$A$31,'Projection Assumptions'!$C$13:$C$31),"") -> 0.03 | F70: =F69*(1+D70)*(1+E70) -> 647.62688 | G70: =IFERROR(XLOOKUP(A70,'01 Industry Model'!$A$5:$A$23,'01 Industry Model'!$H$5:$H$23),"") -> 0.5643459 | H70: =IFERROR(XLOOKUP(A70,'Projection Assumptions'!$A$13:$A$31,'Projection Assumptions'!$E$13:$E$31),"") -> 0 | I70: =MIN(1,MAX(0,G70+(C70-2025)*H70)) -> 0.5643459 | J70: =F70*I70 -> 365.48557 | K70: =MIN(1,K69+XLOOKUP(A70,'Projection Assumptions'!$A$13:$A$31,'Projection Assumptions'!$D$13:$D$31)) -> 0.702 | L70: =IF(K70="","",J70*K70) -> 256.57087
A71: 52 | B71: Finance and insurance | C71: 2025 | D71: =IFERROR(XLOOKUP(A71,'DATA BLS Projections'!$A$5:$A$23,'DATA BLS Projections'!$E$5:$E$23),"") -> 0.0022663025 | E71: =IFERROR(XLOOKUP(A71,'Projection Assumptions'!$A$13:$A$31,'Projection Assumptions'!$C$13:$C$31),"") -> 0.03 | F71: =IFERROR(XLOOKUP(A71,'01 Industry Model'!$A$5:$A$23,'01 Industry Model'!$C$5:$C$23),"") -> 966.66675 | G71: =IFERROR(XLOOKUP(A71,'01 Industry Model'!$A$5:$A$23,'01 Industry Model'!$H$5:$H$23),"") -> 0.67885661 | H71: =IFERROR(XLOOKUP(A71,'Projection Assumptions'!$A$13:$A$31,'Projection Assumptions'!$E$13:$E$31),"") -> 0 | I71: =MIN(1,MAX(0,G71+(C71-2025)*H71)) -> 0.67885661 | J71: =F71*I71 -> 656.22812 | K71: =IF(C71=2025,"",0) | L71: =IF(K71="","",J71*K71)
A72: 52 | B72: Finance and insurance | C72: 2026 | D72: =IFERROR(XLOOKUP(A72,'DATA BLS Projections'!$A$5:$A$23,'DATA BLS Projections'!$E$5:$E$23),"") -> 0.0022663025 | E72: =IFERROR(XLOOKUP(A72,'Projection Assumptions'!$A$13:$A$31,'Projection Assumptions'!$C$13:$C$31),"") -> 0.03 | F72: =F71*(1+D72)*(1+E72) -> 997.92324 | G72: =IFERROR(XLOOKUP(A72,'01 Industry Model'!$A$5:$A$23,'01 Industry Model'!$H$5:$H$23),"") -> 0.67885661 | H72: =IFERROR(XLOOKUP(A72,'Projection Assumptions'!$A$13:$A$31,'Projection Assumptions'!$E$13:$E$31),"") -> 0 | I72: =MIN(1,MAX(0,G72+(C72-2025)*H72)) -> 0.67885661 | J72: =F72*I72 -> 677.44679 | K72: =IFERROR(XLOOKUP(A72,'DATA Census'!$A$2:$A$20,'DATA Census'!$C$2:$C$20),"") -> 0.401 | L72: =IF(K72="","",J72*K72) -> 271.65616
A73: 52 | B73: Finance and insurance | C73: 2027 | D73: =IFERROR(XLOOKUP(A73,'DATA BLS Projections'!$A$5:$A$23,'DATA BLS Projections'!$E$5:$E$23),"") -> 0.0022663025 | E73: =IFERROR(XLOOKUP(A73,'Projection Assumptions'!$A$13:$A$31,'Projection Assumptions'!$C$13:$C$31),"") -> 0.03 | F73: =F72*(1+D73)*(1+E73) -> 1030.1904 | G73: =IFERROR(XLOOKUP(A73,'01 Industry Model'!$A$5:$A$23,'01 Industry Model'!$H$5:$H$23),"") -> 0.67885661 | H73: =IFERROR(XLOOKUP(A73,'Projection Assumptions'!$A$13:$A$31,'Projection Assumptions'!$E$13:$E$31),"") -> 0 | I73: =MIN(1,MAX(0,G73+(C73-2025)*H73)) -> 0.67885661 | J73: =F73*I73 -> 699.35155 | K73: =MIN(1,K72+XLOOKUP(A73,'Projection Assumptions'!$A$13:$A$31,'Projection Assumptions'!$D$13:$D$31)) -> 0.451 | L73: =IF(K73="","",J73*K73) -> 315.40755
A74: 52 | B74: Finance and insurance | C74: 2028 | D74: =IFERROR(XLOOKUP(A74,'DATA BLS Projections'!$A$5:$A$23,'DATA BLS Projections'!$E$5:$E$23),"") -> 0.0022663025 | E74: =IFERROR(XLOOKUP(A74,'Projection Assumptions'!$A$13:$A$31,'Projection Assumptions'!$C$13:$C$31),"") -> 0.03 | F74: =F73*(1+D74)*(1+E74) -> 1063.5009 | G74: =IFERROR(XLOOKUP(A74,'01 Industry Model'!$A$5:$A$23,'01 Industry Model'!$H$5:$H$23),"") -> 0.67885661 | H74: =IFERROR(XLOOKUP(A74,'Projection Assumptions'!$A$13:$A$31,'Projection Assumptions'!$E$13:$E$31),"") -> 0 | I74: =MIN(1,MAX(0,G74+(C74-2025)*H74)) -> 0.67885661 | J74: =F74*I74 -> 721.96459 | K74: =MIN(1,K73+XLOOKUP(A74,'Projection Assumptions'!$A$13:$A$31,'Projection Assumptions'!$D$13:$D$31)) -> 0.501 | L74: =IF(K74="","",J74*K74) -> 361.70426
A75: 52 | B75: Finance and insurance | C75: 2029 | D75: =IFERROR(XLOOKUP(A75,'DATA BLS Projections'!$A$5:$A$23,'DATA BLS Projections'!$E$5:$E$23),"") -> 0.0022663025 | E75: =IFERROR(XLOOKUP(A75,'Projection Assumptions'!$A$13:$A$31,'Projection Assumptions'!$C$13:$C$31),"") -> 0.03 | F75: =F74*(1+D75)*(1+E75) -> 1097.8884 | G75: =IFERROR(XLOOKUP(A75,'01 Industry Model'!$A$5:$A$23,'01 Industry Model'!$H$5:$H$23),"") -> 0.67885661 | H75: =IFERROR(XLOOKUP(A75,'Projection Assumptions'!$A$13:$A$31,'Projection Assumptions'!$E$13:$E$31),"") -> 0 | I75: =MIN(1,MAX(0,G75+(C75-2025)*H75)) -> 0.67885661 | J75: =F75*I75 -> 745.3088 | K75: =MIN(1,K74+XLOOKUP(A75,'Projection Assumptions'!$A$13:$A$31,'Projection Assumptions'!$D$13:$D$31)) -> 0.551 | L75: =IF(K75="","",J75*K75) -> 410.66515
A76: 52 | B76: Finance and insurance | C76: 2030 | D76: =IFERROR(XLOOKUP(A76,'DATA BLS Projections'!$A$5:$A$23,'DATA BLS Projections'!$E$5:$E$23),"") -> 0.0022663025 | E76: =IFERROR(XLOOKUP(A76,'Projection Assumptions'!$A$13:$A$31,'Projection Assumptions'!$C$13:$C$31),"") -> 0.03 | F76: =F75*(1+D76)*(1+E76) -> 1133.3878 | G76: =IFERROR(XLOOKUP(A76,'01 Industry Model'!$A$5:$A$23,'01 Industry Model'!$H$5:$H$23),"") -> 0.67885661 | H76: =IFERROR(XLOOKUP(A76,'Projection Assumptions'!$A$13:$A$31,'Projection Assumptions'!$E$13:$E$31),"") -> 0 | I76: =MIN(1,MAX(0,G76+(C76-2025)*H76)) -> 0.67885661 | J76: =F76*I76 -> 769.40783 | K76: =MIN(1,K75+XLOOKUP(A76,'Projection Assumptions'!$A$13:$A$31,'Projection Assumptions'!$D$13:$D$31)) -> 0.601 | L76: =IF(K76="","",J76*K76) -> 462.41411
A77: 53 | B77: Real estate and rental and leasing | C77: 2025 | D77: =IFERROR(XLOOKUP(A77,'DATA BLS Projections'!$A$5:$A$23,'DATA BLS Projections'!$E$5:$E$23),"") -> 0.0033282241 | E77: =IFERROR(XLOOKUP(A77,'Projection Assumptions'!$A$13:$A$31,'Projection Assumptions'!$C$13:$C$31),"") -> 0.03 | F77: =IFERROR(XLOOKUP(A77,'01 Industry Model'!$A$5:$A$23,'01 Industry Model'!$C$5:$C$23),"") -> 193.52918 | G77: =IFERROR(XLOOKUP(A77,'01 Industry Model'!$A$5:$A$23,'01 Industry Model'!$H$5:$H$23),"") -> 0.46659674 | H77: =IFERROR(XLOOKUP(A77,'Projection Assumptions'!$A$13:$A$31,'Projection Assumptions'!$E$13:$E$31),"") -> 0 | I77: =MIN(1,MAX(0,G77+(C77-2025)*H77)) -> 0.46659674 | J77: =F77*I77 -> 90.300084 | K77: =IF(C77=2025,"",0) | L77: =IF(K77="","",J77*K77)
A78: 53 | B78: Real estate and rental and leasing | C78: 2026 | D78: =IFERROR(XLOOKUP(A78,'DATA BLS Projections'!$A$5:$A$23,'DATA BLS Projections'!$E$5:$E$23),"") -> 0.0033282241 | E78: =IFERROR(XLOOKUP(A78,'Projection Assumptions'!$A$13:$A$31,'Projection Assumptions'!$C$13:$C$31),"") -> 0.03 | F78: =F77*(1+D78)*(1+E78) -> 199.99849 | G78: =IFERROR(XLOOKUP(A78,'01 Industry Model'!$A$5:$A$23,'01 Industry Model'!$H$5:$H$23),"") -> 0.46659674 | H78: =IFERROR(XLOOKUP(A78,'Projection Assumptions'!$A$13:$A$31,'Projection Assumptions'!$E$13:$E$31),"") -> 0 | I78: =MIN(1,MAX(0,G78+(C78-2025)*H78)) -> 0.46659674 | J78: =F78*I78 -> 93.318641 | K78: =IFERROR(XLOOKUP(A78,'DATA Census'!$A$2:$A$20,'DATA Census'!$C$2:$C$20),"") -> 0.308 | L78: =IF(K78="","",J78*K78) -> 28.742142
A79: 53 | B79: Real estate and rental and leasing | C79: 2027 | D79: =IFERROR(XLOOKUP(A79,'DATA BLS Projections'!$A$5:$A$23,'DATA BLS Projections'!$E$5:$E$23),"") -> 0.0033282241 | E79: =IFERROR(XLOOKUP(A79,'Projection Assumptions'!$A$13:$A$31,'Projection Assumptions'!$C$13:$C$31),"") -> 0.03 | F79: =F78*(1+D79)*(1+E79) -> 206.68405 | G79: =IFERROR(XLOOKUP(A79,'01 Industry Model'!$A$5:$A$23,'01 Industry Model'!$H$5:$H$23),"") -> 0.46659674 | H79: =IFERROR(XLOOKUP(A79,'Projection Assumptions'!$A$13:$A$31,'Projection Assumptions'!$E$13:$E$31),"") -> 0 | I79: =MIN(1,MAX(0,G79+(C79-2025)*H79)) -> 0.46659674 | J79: =F79*I79 -> 96.438103 | K79: =MIN(1,K78+XLOOKUP(A79,'Projection Assumptions'!$A$13:$A$31,'Projection Assumptions'!$D$13:$D$31)) -> 0.358 | L79: =IF(K79="","",J79*K79) -> 34.524841
A80: 53 | B80: Real estate and rental and leasing | C80: 2028 | D80: =IFERROR(XLOOKUP(A80,'DATA BLS Projections'!$A$5:$A$23,'DATA BLS Projections'!$E$5:$E$23),"") -> 0.0033282241 | E80: =IFERROR(XLOOKUP(A80,'Projection Assumptions'!$A$13:$A$31,'Projection Assumptions'!$C$13:$C$31),"") -> 0.03 | F80: =F79*(1+D80)*(1+E80) -> 213.5931 | G80: =IFERROR(XLOOKUP(A80,'01 Industry Model'!$A$5:$A$23,'01 Industry Model'!$H$5:$H$23),"") -> 0.46659674 | H80: =IFERROR(XLOOKUP(A80,'Projection Assumptions'!$A$13:$A$31,'Projection Assumptions'!$E$13:$E$31),"") -> 0 | I80: =MIN(1,MAX(0,G80+(C80-2025)*H80)) -> 0.46659674 | J80: =F80*I80 -> 99.661843 | K80: =MIN(1,K79+XLOOKUP(A80,'Projection Assumptions'!$A$13:$A$31,'Projection Assumptions'!$D$13:$D$31)) -> 0.408 | L80: =IF(K80="","",J80*K80) -> 40.662032
A81: 53 | B81: Real estate and rental and leasing | C81: 2029 | D81: =IFERROR(XLOOKUP(A81,'DATA BLS Projections'!$A$5:$A$23,'DATA BLS Projections'!$E$5:$E$23),"") -> 0.0033282241 | E81: =IFERROR(XLOOKUP(A81,'Projection Assumptions'!$A$13:$A$31,'Projection Assumptions'!$C$13:$C$31),"") -> 0.03 | F81: =F80*(1+D81)*(1+E81) -> 220.7331 | G81: =IFERROR(XLOOKUP(A81,'01 Industry Model'!$A$5:$A$23,'01 Industry Model'!$H$5:$H$23),"") -> 0.46659674 | H81: =IFERROR(XLOOKUP(A81,'Projection Assumptions'!$A$13:$A$31,'Projection Assumptions'!$E$13:$E$31),"") -> 0 | I81: =MIN(1,MAX(0,G81+(C81-2025)*H81)) -> 0.46659674 | J81: =F81*I81 -> 102.99335 | K81: =MIN(1,K80+XLOOKUP(A81,'Projection Assumptions'!$A$13:$A$31,'Projection Assumptions'!$D$13:$D$31)) -> 0.458 | L81: =IF(K81="","",J81*K81) -> 47.170953
A82: 53 | B82: Real estate and rental and leasing | C82: 2030 | D82: =IFERROR(XLOOKUP(A82,'DATA BLS Projections'!$A$5:$A$23,'DATA BLS Projections'!$E$5:$E$23),"") -> 0.0033282241 | E82: =IFERROR(XLOOKUP(A82,'Projection Assumptions'!$A$13:$A$31,'Projection Assumptions'!$C$13:$C$31),"") -> 0.03 | F82: =F81*(1+D82)*(1+E82) -> 228.11179 | G82: =IFERROR(XLOOKUP(A82,'01 Industry Model'!$A$5:$A$23,'01 Industry Model'!$H$5:$H$23),"") -> 0.46659674 | H82: =IFERROR(XLOOKUP(A82,'Projection Assumptions'!$A$13:$A$31,'Projection Assumptions'!$E$13:$E$31),"") -> 0 | I82: =MIN(1,MAX(0,G82+(C82-2025)*H82)) -> 0.46659674 | J82: =F82*I82 -> 106.43622 | K82: =MIN(1,K81+XLOOKUP(A82,'Projection Assumptions'!$A$13:$A$31,'Projection Assumptions'!$D$13:$D$31)) -> 0.508 | L82: =IF(K82="","",J82*K82) -> 54.069597
A83: 54 | B83: Professional, scientific, and technical services | C83: 2025 | D83: =IFERROR(XLOOKUP(A83,'DATA BLS Projections'!$A$5:$A$23,'DATA BLS Projections'!$E$5:$E$23),"") -> 0.0082815677 | E83: =IFERROR(XLOOKUP(A83,'Projection Assumptions'!$A$13:$A$31,'Projection Assumptions'!$C$13:$C$31),"") -> 0.03 | F83: =IFERROR(XLOOKUP(A83,'01 Industry Model'!$A$5:$A$23,'01 Industry Model'!$C$5:$C$23),"") -> 1454.3907 | G83: =IFERROR(XLOOKUP(A83,'01 Industry Model'!$A$5:$A$23,'01 Industry Model'!$H$5:$H$23),"") -> 0.55465958 | H83: =IFERROR(XLOOKUP(A83,'Projection Assumptions'!$A$13:$A$31,'Projection Assumptions'!$E$13:$E$31),"") -> 0 | I83: =MIN(1,MAX(0,G83+(C83-2025)*H83)) -> 0.55465958 | J83: =F83*I83 -> 806.69172 | K83: =IF(C83=2025,"",0) | L83: =IF(K83="","",J83*K83)
A84: 54 | B84: Professional, scientific, and technical services | C84: 2026 | D84: =IFERROR(XLOOKUP(A84,'DATA BLS Projections'!$A$5:$A$23,'DATA BLS Projections'!$E$5:$E$23),"") -> 0.0082815677 | E84: =IFERROR(XLOOKUP(A84,'Projection Assumptions'!$A$13:$A$31,'Projection Assumptions'!$C$13:$C$31),"") -> 0.03 | F84: =F83*(1+D84)*(1+E84) -> 1510.4284 | G84: =IFERROR(XLOOKUP(A84,'01 Industry Model'!$A$5:$A$23,'01 Industry Model'!$H$5:$H$23),"") -> 0.55465958 | H84: =IFERROR(XLOOKUP(A84,'Projection Assumptions'!$A$13:$A$31,'Projection Assumptions'!$E$13:$E$31),"") -> 0 | I84: =MIN(1,MAX(0,G84+(C84-2025)*H84)) -> 0.55465958 | J84: =F84*I84 -> 837.77356 | K84: =IFERROR(XLOOKUP(A84,'DATA Census'!$A$2:$A$20,'DATA Census'!$C$2:$C$20),"") -> 0.427 | L84: =IF(K84="","",J84*K84) -> 357.72931
A85: 54 | B85: Professional, scientific, and technical services | C85: 2027 | D85: =IFERROR(XLOOKUP(A85,'DATA BLS Projections'!$A$5:$A$23,'DATA BLS Projections'!$E$5:$E$23),"") -> 0.0082815677 | E85: =IFERROR(XLOOKUP(A85,'Projection Assumptions'!$A$13:$A$31,'Projection Assumptions'!$C$13:$C$31),"") -> 0.03 | F85: =F84*(1+D85)*(1+E85) -> 1568.6252 | G85: =IFERROR(XLOOKUP(A85,'01 Industry Model'!$A$5:$A$23,'01 Industry Model'!$H$5:$H$23),"") -> 0.55465958 | H85: =IFERROR(XLOOKUP(A85,'Projection Assumptions'!$A$13:$A$31,'Projection Assumptions'!$E$13:$E$31),"") -> 0 | I85: =MIN(1,MAX(0,G85+(C85-2025)*H85)) -> 0.55465958 | J85: =F85*I85 -> 870.05299 | K85: =MIN(1,K84+XLOOKUP(A85,'Projection Assumptions'!$A$13:$A$31,'Projection Assumptions'!$D$13:$D$31)) -> 0.477 | L85: =IF(K85="","",J85*K85) -> 415.01527
A86: 54 | B86: Professional, scientific, and technical services | C86: 2028 | D86: =IFERROR(XLOOKUP(A86,'DATA BLS Projections'!$A$5:$A$23,'DATA BLS Projections'!$E$5:$E$23),"") -> 0.0082815677 | E86: =IFERROR(XLOOKUP(A86,'Projection Assumptions'!$A$13:$A$31,'Projection Assumptions'!$C$13:$C$31),"") -> 0.03 | F86: =F85*(1+D86)*(1+E86) -> 1629.0643 | G86: =IFERROR(XLOOKUP(A86,'01 Industry Model'!$A$5:$A$23,'01 Industry Model'!$H$5:$H$23),"") -> 0.55465958 | H86: =IFERROR(XLOOKUP(A86,'Projection Assumptions'!$A$13:$A$31,'Projection Assumptions'!$E$13:$E$31),"") -> 0 | I86: =MIN(1,MAX(0,G86+(C86-2025)*H86)) -> 0.55465958 | J86: =F86*I86 -> 903.57614 | K86: =MIN(1,K85+XLOOKUP(A86,'Projection Assumptions'!$A$13:$A$31,'Projection Assumptions'!$D$13:$D$31)) -> 0.527 | L86: =IF(K86="","",J86*K86) -> 476.18463
A87: 54 | B87: Professional, scientific, and technical services | C87: 2029 | D87: =IFERROR(XLOOKUP(A87,'DATA BLS Projections'!$A$5:$A$23,'DATA BLS Projections'!$E$5:$E$23),"") -> 0.0082815677 | E87: =IFERROR(XLOOKUP(A87,'Projection Assumptions'!$A$13:$A$31,'Projection Assumptions'!$C$13:$C$31),"") -> 0.03 | F87: =F86*(1+D87)*(1+E87) -> 1691.8322 | G87: =IFERROR(XLOOKUP(A87,'01 Industry Model'!$A$5:$A$23,'01 Industry Model'!$H$5:$H$23),"") -> 0.55465958 | H87: =IFERROR(XLOOKUP(A87,'Projection Assumptions'!$A$13:$A$31,'Projection Assumptions'!$E$13:$E$31),"") -> 0 | I87: =MIN(1,MAX(0,G87+(C87-2025)*H87)) -> 0.55465958 | J87: =F87*I87 -> 938.39094 | K87: =MIN(1,K86+XLOOKUP(A87,'Projection Assumptions'!$A$13:$A$31,'Projection Assumptions'!$D$13:$D$31)) -> 0.577 | L87: =IF(K87="","",J87*K87) -> 541.45157
A88: 54 | B88: Professional, scientific, and technical services | C88: 2030 | D88: =IFERROR(XLOOKUP(A88,'DATA BLS Projections'!$A$5:$A$23,'DATA BLS Projections'!$E$5:$E$23),"") -> 0.0082815677 | E88: =IFERROR(XLOOKUP(A88,'Projection Assumptions'!$A$13:$A$31,'Projection Assumptions'!$C$13:$C$31),"") -> 0.03 | F88: =F87*(1+D88)*(1+E88) -> 1757.0185 | G88: =IFERROR(XLOOKUP(A88,'01 Industry Model'!$A$5:$A$23,'01 Industry Model'!$H$5:$H$23),"") -> 0.55465958 | H88: =IFERROR(XLOOKUP(A88,'Projection Assumptions'!$A$13:$A$31,'Projection Assumptions'!$E$13:$E$31),"") -> 0 | I88: =MIN(1,MAX(0,G88+(C88-2025)*H88)) -> 0.55465958 | J88: =F88*I88 -> 974.54716 | K88: =MIN(1,K87+XLOOKUP(A88,'Projection Assumptions'!$A$13:$A$31,'Projection Assumptions'!$D$13:$D$31)) -> 0.627 | L88: =IF(K88="","",J88*K88) -> 611.04107
A89: 55 | B89: Management of companies and enterprises | C89: 2025 | D89: =IFERROR(XLOOKUP(A89,'DATA BLS Projections'!$A$5:$A$23,'DATA BLS Projections'!$E$5:$E$23),"") -> 0.003994214 | E89: =IFERROR(XLOOKUP(A89,'Projection Assumptions'!$A$13:$A$31,'Projection Assumptions'!$C$13:$C$31),"") -> 0.03 | F89: =IFERROR(XLOOKUP(A89,'01 Industry Model'!$A$5:$A$23,'01 Industry Model'!$C$5:$C$23),"") -> 433.01074 | G89: =IFERROR(XLOOKUP(A89,'01 Industry Model'!$A$5:$A$23,'01 Industry Model'!$H$5:$H$23),"") -> 0.58021713 | H89: =IFERROR(XLOOKUP(A89,'Projection Assumptions'!$A$13:$A$31,'Projection Assumptions'!$E$13:$E$31),"") -> 0 | I89: =MIN(1,MAX(0,G89+(C89-2025)*H89)) -> 0.58021713 | J89: =F89*I89 -> 251.24025 | K89: =IF(C89=2025,"",0) | L89: =IF(K89="","",J89*K89)
A90: 55 | B90: Management of companies and enterprises | C90: 2026 | D90: =IFERROR(XLOOKUP(A90,'DATA BLS Projections'!$A$5:$A$23,'DATA BLS Projections'!$E$5:$E$23),"") -> 0.003994214 | E90: =IFERROR(XLOOKUP(A90,'Projection Assumptions'!$A$13:$A$31,'Projection Assumptions'!$C$13:$C$31),"") -> 0.03 | F90: =F89*(1+D90)*(1+E90) -> 447.78249 | G90: =IFERROR(XLOOKUP(A90,'01 Industry Model'!$A$5:$A$23,'01 Industry Model'!$H$5:$H$23),"") -> 0.58021713 | H90: =IFERROR(XLOOKUP(A90,'Projection Assumptions'!$A$13:$A$31,'Projection Assumptions'!$E$13:$E$31),"") -> 0 | I90: =MIN(1,MAX(0,G90+(C90-2025)*H90)) -> 0.58021713 | J90: =F90*I90 -> 259.81107 | K90: =IFERROR(XLOOKUP(A90,'DATA Census'!$A$2:$A$20,'DATA Census'!$C$2:$C$20),"") -> 0.232 | L90: =IF(K90="","",J90*K90) -> 60.276168
A91: 55 | B91: Management of companies and enterprises | C91: 2027 | D91: =IFERROR(XLOOKUP(A91,'DATA BLS Projections'!$A$5:$A$23,'DATA BLS Projections'!$E$5:$E$23),"") -> 0.003994214 | E91: =IFERROR(XLOOKUP(A91,'Projection Assumptions'!$A$13:$A$31,'Projection Assumptions'!$C$13:$C$31),"") -> 0.03 | F91: =F90*(1+D91)*(1+E91) -> 463.05816 | G91: =IFERROR(XLOOKUP(A91,'01 Industry Model'!$A$5:$A$23,'01 Industry Model'!$H$5:$H$23),"") -> 0.58021713 | H91: =IFERROR(XLOOKUP(A91,'Projection Assumptions'!$A$13:$A$31,'Projection Assumptions'!$E$13:$E$31),"") -> 0 | I91: =MIN(1,MAX(0,G91+(C91-2025)*H91)) -> 0.58021713 | J91: =F91*I91 -> 268.67427 | K91: =MIN(1,K90+XLOOKUP(A91,'Projection Assumptions'!$A$13:$A$31,'Projection Assumptions'!$D$13:$D$31)) -> 0.282 | L91: =IF(K91="","",J91*K91) -> 75.766145
A92: 55 | B92: Management of companies and enterprises | C92: 2028 | D92: =IFERROR(XLOOKUP(A92,'DATA BLS Projections'!$A$5:$A$23,'DATA BLS Projections'!$E$5:$E$23),"") -> 0.003994214 | E92: =IFERROR(XLOOKUP(A92,'Projection Assumptions'!$A$13:$A$31,'Projection Assumptions'!$C$13:$C$31),"") -> 0.03 | F92: =F91*(1+D92)*(1+E92) -> 478.85494 | G92: =IFERROR(XLOOKUP(A92,'01 Industry Model'!$A$5:$A$23,'01 Industry Model'!$H$5:$H$23),"") -> 0.58021713 | H92: =IFERROR(XLOOKUP(A92,'Projection Assumptions'!$A$13:$A$31,'Projection Assumptions'!$E$13:$E$31),"") -> 0 | I92: =MIN(1,MAX(0,G92+(C92-2025)*H92)) -> 0.58021713 | J92: =F92*I92 -> 277.83984 | K92: =MIN(1,K91+XLOOKUP(A92,'Projection Assumptions'!$A$13:$A$31,'Projection Assumptions'!$D$13:$D$31)) -> 0.332 | L92: =IF(K92="","",J92*K92) -> 92.242827
A93: 55 | B93: Management of companies and enterprises | C93: 2029 | D93: =IFERROR(XLOOKUP(A93,'DATA BLS Projections'!$A$5:$A$23,'DATA BLS Projections'!$E$5:$E$23),"") -> 0.003994214 | E93: =IFERROR(XLOOKUP(A93,'Projection Assumptions'!$A$13:$A$31,'Projection Assumptions'!$C$13:$C$31),"") -> 0.03 | F93: =F92*(1+D93)*(1+E93) -> 495.19062 | G93: =IFERROR(XLOOKUP(A93,'01 Industry Model'!$A$5:$A$23,'01 Industry Model'!$H$5:$H$23),"") -> 0.58021713 | H93: =IFERROR(XLOOKUP(A93,'Projection Assumptions'!$A$13:$A$31,'Projection Assumptions'!$E$13:$E$31),"") -> 0 | I93: =MIN(1,MAX(0,G93+(C93-2025)*H93)) -> 0.58021713 | J93: =F93*I93 -> 287.31808 | K93: =MIN(1,K92+XLOOKUP(A93,'Projection Assumptions'!$A$13:$A$31,'Projection Assumptions'!$D$13:$D$31)) -> 0.382 | L93: =IF(K93="","",J93*K93) -> 109.75551
A94: 55 | B94: Management of companies and enterprises | C94: 2030 | D94: =IFERROR(XLOOKUP(A94,'DATA BLS Projections'!$A$5:$A$23,'DATA BLS Projections'!$E$5:$E$23),"") -> 0.003994214 | E94: =IFERROR(XLOOKUP(A94,'Projection Assumptions'!$A$13:$A$31,'Projection Assumptions'!$C$13:$C$31),"") -> 0.03 | F94: =F93*(1+D94)*(1+E94) -> 512.08357 | G94: =IFERROR(XLOOKUP(A94,'01 Industry Model'!$A$5:$A$23,'01 Industry Model'!$H$5:$H$23),"") -> 0.58021713 | H94: =IFERROR(XLOOKUP(A94,'Projection Assumptions'!$A$13:$A$31,'Projection Assumptions'!$E$13:$E$31),"") -> 0 | I94: =MIN(1,MAX(0,G94+(C94-2025)*H94)) -> 0.58021713 | J94: =F94*I94 -> 297.11966 | K94: =MIN(1,K93+XLOOKUP(A94,'Projection Assumptions'!$A$13:$A$31,'Projection Assumptions'!$D$13:$D$31)) -> 0.432 | L94: =IF(K94="","",J94*K94) -> 128.35569
A95: 56 | B95: Administrative and support and waste management and remediation services | C95: 2025 | D95: =IFERROR(XLOOKUP(A95,'DATA BLS Projections'!$A$5:$A$23,'DATA BLS Projections'!$E$5:$E$23),"") -> 0.00088847426 | E95: =IFERROR(XLOOKUP(A95,'Projection Assumptions'!$A$13:$A$31,'Projection Assumptions'!$C$13:$C$31),"") -> 0.03 | F95: =IFERROR(XLOOKUP(A95,'01 Industry Model'!$A$5:$A$23,'01 Industry Model'!$C$5:$C$23),"") -> 541.58241 | G95: =IFERROR(XLOOKUP(A95,'01 Industry Model'!$A$5:$A$23,'01 Industry Model'!$H$5:$H$23),"") -> 0.37108173 | H95: =IFERROR(XLOOKUP(A95,'Projection Assumptions'!$A$13:$A$31,'Projection Assumptions'!$E$13:$E$31),"") -> 0 | I95: =MIN(1,MAX(0,G95+(C95-2025)*H95)) -> 0.37108173 | J95: =F95*I95 -> 200.97134 | K95: =IF(C95=2025,"",0) | L95: =IF(K95="","",J95*K95)
A96: 56 | B96: Administrative and support and waste management and remediation services | C96: 2026 | D96: =IFERROR(XLOOKUP(A96,'DATA BLS Projections'!$A$5:$A$23,'DATA BLS Projections'!$E$5:$E$23),"") -> 0.00088847426 | E96: =IFERROR(XLOOKUP(A96,'Projection Assumptions'!$A$13:$A$31,'Projection Assumptions'!$C$13:$C$31),"") -> 0.03 | F96: =F95*(1+D96)*(1+E96) -> 558.3255 | G96: =IFERROR(XLOOKUP(A96,'01 Industry Model'!$A$5:$A$23,'01 Industry Model'!$H$5:$H$23),"") -> 0.37108173 | H96: =IFERROR(XLOOKUP(A96,'Projection Assumptions'!$A$13:$A$31,'Projection Assumptions'!$E$13:$E$31),"") -> 0 | I96: =MIN(1,MAX(0,G96+(C96-2025)*H96)) -> 0.37108173 | J96: =F96*I96 -> 207.18439 | K96: =IFERROR(XLOOKUP(A96,'DATA Census'!$A$2:$A$20,'DATA Census'!$C$2:$C$20),"") -> 0.217 | L96: =IF(K96="","",J96*K96) -> 44.959013
A97: 56 | B97: Administrative and support and waste management and remediation services | C97: 2027 | D97: =IFERROR(XLOOKUP(A97,'DATA BLS Projections'!$A$5:$A$23,'DATA BLS Projections'!$E$5:$E$23),"") -> 0.00088847426 | E97: =IFERROR(XLOOKUP(A97,'Projection Assumptions'!$A$13:$A$31,'Projection Assumptions'!$C$13:$C$31),"") -> 0.03 | F97: =F96*(1+D97)*(1+E97) -> 575.58621 | G97: =IFERROR(XLOOKUP(A97,'01 Industry Model'!$A$5:$A$23,'01 Industry Model'!$H$5:$H$23),"") -> 0.37108173 | H97: =IFERROR(XLOOKUP(A97,'Projection Assumptions'!$A$13:$A$31,'Projection Assumptions'!$E$13:$E$31),"") -> 0 | I97: =MIN(1,MAX(0,G97+(C97-2025)*H97)) -> 0.37108173 | J97: =F97*I97 -> 213.58952 | K97: =MIN(1,K96+XLOOKUP(A97,'Projection Assumptions'!$A$13:$A$31,'Projection Assumptions'!$D$13:$D$31)) -> 0.267 | L97: =IF(K97="","",J97*K97) -> 57.028403
A98: 56 | B98: Administrative and support and waste management and remediation services | C98: 2028 | D98: =IFERROR(XLOOKUP(A98,'DATA BLS Projections'!$A$5:$A$23,'DATA BLS Projections'!$E$5:$E$23),"") -> 0.00088847426 | E98: =IFERROR(XLOOKUP(A98,'Projection Assumptions'!$A$13:$A$31,'Projection Assumptions'!$C$13:$C$31),"") -> 0.03 | F98: =F97*(1+D98)*(1+E98) -> 593.38053 | G98: =IFERROR(XLOOKUP(A98,'01 Industry Model'!$A$5:$A$23,'01 Industry Model'!$H$5:$H$23),"") -> 0.37108173 | H98: =IFERROR(XLOOKUP(A98,'Projection Assumptions'!$A$13:$A$31,'Projection Assumptions'!$E$13:$E$31),"") -> 0 | I98: =MIN(1,MAX(0,G98+(C98-2025)*H98)) -> 0.37108173 | J98: =F98*I98 -> 220.19267 | K98: =MIN(1,K97+XLOOKUP(A98,'Projection Assumptions'!$A$13:$A$31,'Projection Assumptions'!$D$13:$D$31)) -> 0.317 | L98: =IF(K98="","",J98*K98) -> 69.801077
A99: 56 | B99: Administrative and support and waste management and remediation services | C99: 2029 | D99: =IFERROR(XLOOKUP(A99,'DATA BLS Projections'!$A$5:$A$23,'DATA BLS Projections'!$E$5:$E$23),"") -> 0.00088847426 | E99: =IFERROR(XLOOKUP(A99,'Projection Assumptions'!$A$13:$A$31,'Projection Assumptions'!$C$13:$C$31),"") -> 0.03 | F99: =F98*(1+D99)*(1+E99) -> 611.72496 | G99: =IFERROR(XLOOKUP(A99,'01 Industry Model'!$A$5:$A$23,'01 Industry Model'!$H$5:$H$23),"") -> 0.37108173 | H99: =IFERROR(XLOOKUP(A99,'Projection Assumptions'!$A$13:$A$31,'Projection Assumptions'!$E$13:$E$31),"") -> 0 | I99: =MIN(1,MAX(0,G99+(C99-2025)*H99)) -> 0.37108173 | J99: =F99*I99 -> 226.99996 | K99: =MIN(1,K98+XLOOKUP(A99,'Projection Assumptions'!$A$13:$A$31,'Projection Assumptions'!$D$13:$D$31)) -> 0.367 | L99: =IF(K99="","",J99*K99) -> 83.308984
A100: 56 | B100: Administrative and support and waste management and remediation services | C100: 2030 | D100: =IFERROR(XLOOKUP(A100,'DATA BLS Projections'!$A$5:$A$23,'DATA BLS Projections'!$E$5:$E$23),"") -> 0.00088847426 | E100: =IFERROR(XLOOKUP(A100,'Projection Assumptions'!$A$13:$A$31,'Projection Assumptions'!$C$13:$C$31),"") -> 0.03 | F100: =F99*(1+D100)*(1+E100) -> 630.63652 | G100: =IFERROR(XLOOKUP(A100,'01 Industry Model'!$A$5:$A$23,'01 Industry Model'!$H$5:$H$23),"") -> 0.37108173 | H100: =IFERROR(XLOOKUP(A100,'Projection Assumptions'!$A$13:$A$31,'Projection Assumptions'!$E$13:$E$31),"") -> 0 | I100: =MIN(1,MAX(0,G100+(C100-2025)*H100)) -> 0.37108173 | J100: =F100*I100 -> 234.01769 | K100: =MIN(1,K99+XLOOKUP(A100,'Projection Assumptions'!$A$13:$A$31,'Projection Assumptions'!$D$13:$D$31)) -> 0.417 | L100: =IF(K100="","",J100*K100) -> 97.585377
A101: 61 | B101: Educational services | C101: 2025 | D101: =IFERROR(XLOOKUP(A101,'DATA BLS Projections'!$A$5:$A$23,'DATA BLS Projections'!$E$5:$E$23),"") -> 0.0024935675 | E101: =IFERROR(XLOOKUP(A101,'Projection Assumptions'!$A$13:$A$31,'Projection Assumptions'!$C$13:$C$31),"") -> 0.03 | F101: =IFERROR(XLOOKUP(A101,'01 Industry Model'!$A$5:$A$23,'01 Industry Model'!$C$5:$C$23),"") -> 213.87573 | G101: =IFERROR(XLOOKUP(A101,'01 Industry Model'!$A$5:$A$23,'01 Industry Model'!$H$5:$H$23),"") -> 0.4121335 | H101: =IFERROR(XLOOKUP(A101,'Projection Assumptions'!$A$13:$A$31,'Projection Assumptions'!$E$13:$E$31),"") -> 0 | I101: =MIN(1,MAX(0,G101+(C101-2025)*H101)) -> 0.4121335 | J101: =F101*I101 -> 88.145355 | K101: =IF(C101=2025,"",0) | L101: =IF(K101="","",J101*K101)
A102: 61 | B102: Educational services | C102: 2026 | D102: =IFERROR(XLOOKUP(A102,'DATA BLS Projections'!$A$5:$A$23,'DATA BLS Projections'!$E$5:$E$23),"") -> 0.0024935675 | E102: =IFERROR(XLOOKUP(A102,'Projection Assumptions'!$A$13:$A$31,'Projection Assumptions'!$C$13:$C$31),"") -> 0.03 | F102: =F101*(1+D102)*(1+E102) -> 220.84132 | G102: =IFERROR(XLOOKUP(A102,'01 Industry Model'!$A$5:$A$23,'01 Industry Model'!$H$5:$H$23),"") -> 0.4121335 | H102: =IFERROR(XLOOKUP(A102,'Projection Assumptions'!$A$13:$A$31,'Projection Assumptions'!$E$13:$E$31),"") -> 0 | I102: =MIN(1,MAX(0,G102+(C102-2025)*H102)) -> 0.4121335 | J102: =F102*I102 -> 91.016106 | K102: =IFERROR(XLOOKUP(A102,'DATA Census'!$A$2:$A$20,'DATA Census'!$C$2:$C$20),"") -> 0.399 | L102: =IF(K102="","",J102*K102) -> 36.315426
A103: 61 | B103: Educational services | C103: 2027 | D103: =IFERROR(XLOOKUP(A103,'DATA BLS Projections'!$A$5:$A$23,'DATA BLS Projections'!$E$5:$E$23),"") -> 0.0024935675 | E103: =IFERROR(XLOOKUP(A103,'Projection Assumptions'!$A$13:$A$31,'Projection Assumptions'!$C$13:$C$31),"") -> 0.03 | F103: =F102*(1+D103)*(1+E103) -> 228.03376 | G103: =IFERROR(XLOOKUP(A103,'01 Industry Model'!$A$5:$A$23,'01 Industry Model'!$H$5:$H$23),"") -> 0.4121335 | H103: =IFERROR(XLOOKUP(A103,'Projection Assumptions'!$A$13:$A$31,'Projection Assumptions'!$E$13:$E$31),"") -> 0 | I103: =MIN(1,MAX(0,G103+(C103-2025)*H103)) -> 0.4121335 | J103: =F103*I103 -> 93.980352 | K103: =MIN(1,K102+XLOOKUP(A103,'Projection Assumptions'!$A$13:$A$31,'Projection Assumptions'!$D$13:$D$31)) -> 0.449 | L103: =IF(K103="","",J103*K103) -> 42.197178
...

Sheet Projection Assumptions
A1: PROJECTION ASSUMPTIONS | USER-EDITABLE
A2: Blue = assumption/input. Yellow = global assumption. Industry-level cells initially link to globals but may be overwritten.
B5: Nominal wage growth per employee / year | C5: 0.03 | D5: Illustrative assumption, NOT an official BLS wage forecast
B6: AI-using firms: additional percentage points / year | C6: 0.05 | D6: Illustrative linear adoption assumption after 2026; cap = 100%
B7: AI task exposure: additional percentage points / year | C7: 0 | D7: Keep 2025 Wharton exposure fixed by default; scenario knob
A9: 2025 baseline: QCEW private wages + Wharton exposure | 2026 adoption reference: Census BTOS Q7 Yes
A10: 2026 firm adoption is a CROSS-SECTION observation; using it as annual-average is a simplifying scenario assumption.
A12: NAICS | B12: Industry | C12: Nominal wage CAGR | D12: Annual adoption change (pp) | E12: Annual exposure change (pp) | F12: Notes / edit instructions
A13: 11 | B13: Agriculture, forestry, fishing and hunting | C13: =$C$5 -> 0.03 | D13: =$C$6 -> 0.05 | E13: =$C$7 -> 0 | F13: Override C/D/E for this industry if desired; global defaults above otherwise
A14: 21 | B14: Mining, quarrying, and oil and gas extraction | C14: =$C$5 -> 0.03 | D14: =$C$6 -> 0.05 | E14: =$C$7 -> 0 | F14: Override C/D/E for this industry if desired; global defaults above otherwise
A15: 22 | B15: Utilities | C15: =$C$5 -> 0.03 | D15: =$C$6 -> 0.05 | E15: =$C$7 -> 0 | F15: Override C/D/E for this industry if desired; global defaults above otherwise
A16: 23 | B16: Construction | C16: =$C$5 -> 0.03 | D16: =$C$6 -> 0.05 | E16: =$C$7 -> 0 | F16: Override C/D/E for this industry if desired; global defaults above otherwise
A17: 31-33 | B17: Manufacturing | C17: =$C$5 -> 0.03 | D17: =$C$6 -> 0.05 | E17: =$C$7 -> 0 | F17: Override C/D/E for this industry if desired; global defaults above otherwise
A18: 42 | B18: Wholesale trade | C18: =$C$5 -> 0.03 | D18: =$C$6 -> 0.05 | E18: =$C$7 -> 0 | F18: Override C/D/E for this industry if desired; global defaults above otherwise
A19: 44-45 | B19: Retail trade | C19: =$C$5 -> 0.03 | D19: =$C$6 -> 0.05 | E19: =$C$7 -> 0 | F19: Override C/D/E for this industry if desired; global defaults above otherwise
A20: 48-49 | B20: Transportation and warehousing | C20: =$C$5 -> 0.03 | D20: =$C$6 -> 0.05 | E20: =$C$7 -> 0 | F20: Override C/D/E for this industry if desired; global defaults above otherwise
A21: 51 | B21: Information | C21: =$C$5 -> 0.03 | D21: =$C$6 -> 0.05 | E21: =$C$7 -> 0 | F21: Override C/D/E for this industry if desired; global defaults above otherwise
A22: 52 | B22: Finance and insurance | C22: =$C$5 -> 0.03 | D22: =$C$6 -> 0.05 | E22: =$C$7 -> 0 | F22: Override C/D/E for this industry if desired; global defaults above otherwise
A23: 53 | B23: Real estate and rental and leasing | C23: =$C$5 -> 0.03 | D23: =$C$6 -> 0.05 | E23: =$C$7 -> 0 | F23: Override C/D/E for this industry if desired; global defaults above otherwise
A24: 54 | B24: Professional, scientific, and technical services | C24: =$C$5 -> 0.03 | D24: =$C$6 -> 0.05 | E24: =$C$7 -> 0 | F24: Override C/D/E for this industry if desired; global defaults above otherwise
... A31: 81 | B31: Other services (except public administration) | C31: =$C$5 -> 0.03 | D31: =$C$6 -> 0.05 | E31: =$C$7 -> 0 | F31: Override C/D/E for this industry if desired; global defaults above otherwise
A33: Important: Firm-level AI Use × gross exposed wages is ONLY a sensitivity proxy, not measured labor savings.
A34: BLS employment source: https://www.bls.gov/emp/tables/employment-by-major-industry-sector.htm
A35: Census AI Use source: https://www.census.gov/hfp/btos/data_downloads

Sheet DATA BLS Projections
A1: DATA BLS EMPLOYMENT PROJECTIONS | 2025-2035
A2: BLS Employment Projections Table 2.1 (updated September 8, 2026) | 2025 & 2035 employees in thousands; compound annual growth for 2026-2030
A3: Official table: | B3: https://www.bls.gov/emp/tables/employment-by-major-industry-sector.htm
A4: NAICS (model) | B4: BLS Industry Sector | C4: 2025 Employment (000s) | D4: 2035 Employment (000s) | E4: Employment CAGR 2025–35 | F4: Coverage / NAICS mapping note | G4: Official Download / Source
A5: 11 | B5: Agriculture, forestry, fishing and hunting | C5: 1462.4 | D5: 1484.1 | E5: =(D5/C5)^(1/(2035-2025))-1 -> 0.001474046 | F5: Corresponding private-sector NAICS major sector; rounded BLS 2025 & 2035 employment | G5: https://www.bls.gov/emp/tables/employment-by-major-industry-sector.htm
A6: 21 | B6: Mining, quarrying, and oil and gas extraction | C6: 573.5 | D6: 577.3 | E6: =(D6/C6)^(1/(2035-2025))-1 -> 0.00066063067 | F6: Corresponding private-sector NAICS major sector; rounded BLS 2025 & 2035 employment | G6: https://www.bls.gov/emp/tables/employment-by-major-industry-sector.htm
A7: 22 | B7: Utilities | C7: 601.3 | D7: 660.1 | E7: =(D7/C7)^(1/(2035-2025))-1 -> 0.0093733937 | F7: Corresponding private-sector NAICS major sector; rounded BLS 2025 & 2035 employment | G7: https://www.bls.gov/emp/tables/employment-by-major-industry-sector.htm
A8: 23 | B8: Construction | C8: 8266.7 | D8: 8677.4 | E8: =(D8/C8)^(1/(2035-2025))-1 -> 0.0048604285 | F8: Corresponding private-sector NAICS major sector; rounded BLS 2025 & 2035 employment | G8: https://www.bls.gov/emp/tables/employment-by-major-industry-sector.htm
A9: 31-33 | B9: Manufacturing | C9: 12633.7 | D9: 12705.8 | E9: =(D9/C9)^(1/(2035-2025))-1 -> 0.00056923549 | F9: Corresponding private-sector NAICS major sector; rounded BLS 2025 & 2035 employment | G9: https://www.bls.gov/emp/tables/employment-by-major-industry-sector.htm
A10: 42 | B10: Wholesale trade | C10: 6059.5 | D10: 6184.7 | E10: =(D10/C10)^(1/(2035-2025))-1 -> 0.0020472139 | F10: Corresponding private-sector NAICS major sector; rounded BLS 2025 & 2035 employment | G10: https://www.bls.gov/emp/tables/employment-by-major-industry-sector.htm
A11: 44-45 | B11: Retail trade | C11: 15440.9 | D11: 15413.4 | E11: =(D11/C11)^(1/(2035-2025))-1 -> -0.00017824132 | F11: Corresponding private-sector NAICS major sector; rounded BLS 2025 & 2035 employment | G11: https://www.bls.gov/emp/tables/employment-by-major-industry-sector.htm
A12: 48-49 | B12: Transportation and warehousing | C12: 6639.5 | D12: 6846.8 | E12: =(D12/C12)^(1/(2035-2025))-1 -> 0.0030792041 | F12: BLS transportation excludes postal service; minor NAICS scope mismatch | G12: https://www.bls.gov/emp/tables/employment-by-major-industry-sector.htm
A13: 51 | B13: Information | C13: 2861.9 | D13: 3012.9 | E13: =(D13/C13)^(1/(2035-2025))-1 -> 0.0051549744 | F13: Corresponding private-sector NAICS major sector; rounded BLS 2025 & 2035 employment | G13: https://www.bls.gov/emp/tables/employment-by-major-industry-sector.htm
A14: 52 | B14: Finance and insurance | C14: 6739.3 | D14: 6893.6 | E14: =(D14/C14)^(1/(2035-2025))-1 -> 0.0022663025 | F14: Corresponding private-sector NAICS major sector; rounded BLS 2025 & 2035 employment | G14: https://www.bls.gov/emp/tables/employment-by-major-industry-sector.htm
A15: 53 | B15: Real estate and rental and leasing | C15: 2456.7 | D15: 2539.7 | E15: =(D15/C15)^(1/(2035-2025))-1 -> 0.0033282241 | F15: Corresponding private-sector NAICS major sector; rounded BLS 2025 & 2035 employment | G15: https://www.bls.gov/emp/tables/employment-by-major-industry-sector.htm
A16: 54 | B16: Professional, scientific, and technical services | C16: 10779.2 | D16: 11705.9 | E16: =(D16/C16)^(1/(2035-2025))-1 -> 0.0082815677 | F16: Corresponding private-sector NAICS major sector; rounded BLS 2025 & 2035 employment | G16: https://www.bls.gov/emp/tables/employment-by-major-industry-sector.htm
... A23: 81 | B23: Other services (except public administration) | C23: 6575.7 | D23: 6822.6 | E23: =(D23/C23)^(1/(2035-2025))-1 -> 0.003692761 | F23: Corresponding private-sector NAICS major sector; rounded BLS 2025 & 2035 employment | G23: https://www.bls.gov/emp/tables/employment-by-major-industry-sector.htm
A25: Scope: BLS projections are employment forecasts, not industry wage or AI adoption forecasts.
A26: BLS 2025–2035 employment CAGR is interpolated geometrically to 2030. QCEW private wage bill remains the 2025 baseline.

Sheet 02 Verified Inputs
A1: VERIFIED INPUTS | SOURCE DATA
A2: QCEW 2025 US000 / own_code 5; OEWS May 2025 detailed SOC, Wharton 2025 score; BTOS 202620 Q7=Yes. Currency: current dollars.
A4: NAICS | B4: Industry | C4: QCEW Private Annual Wages ($) | D4: OEWS Detailed Wages ($) | E4: Wharton Matched Wages ($) | F4: Wharton Exposure-Weighted Wages ($) | G4: Census BTOS Firms Using AI | H4: Census AI Supplement Firms Using AI | I4: OEWS Ownership Treatment / QA
A5: 11 | B5: Agriculture, forestry, fishing and hunting | C5: 60088224865 | D5: 18024128600 | E5: 17900932800 | F5: 3.2456895e+09 | G5: 0.095 | H5: 0.051 | I5: OEWS private sector 5
A6: 21 | B6: Mining, quarrying, and oil and gas extraction | C6: 76216722054 | D6: 46718540800 | E6: 46156543200 | F6: 1.3397598e+10 | G6: 0.13 | H6: 0.077 | I6: OEWS private sector 5
A7: 22 | B7: Utilities | C7: 85024861666 | D7: 61892073000 | E7: 61630077300 | F7: 2.2584317e+10 | G7: 0.167 | H7: 0.137 | I7: OEWS private sector 5
A8: 23 | B8: Construction | C8: 699896249139 | D8: 598121924700 | E8: 596275773800 | F8: 1.5859374e+11 | G8: 0.172 | H8: 0.092 | I8: OEWS private sector 5
A9: 31-33 | B9: Manufacturing | C9: 1125542676332 | D9: 874493524800 | E9: 864066610900 | F9: 2.8693931e+11 | G9: 0.208 | H9: 0.124 | I9: OEWS private sector 5
A10: 42 | B10: Wholesale trade | C10: 638878973832 | D10: 458154842200 | E10: 455375229800 | F10: 2.1041317e+11 | G10: 0.216 | H10: 0.136 | I10: OEWS private sector 5
A11: 44-45 | B11: Retail trade | C11: 668863568474 | D11: 693029757900 | E11: 689445511900 | F11: 3.0219336e+11 | G11: 0.168 | H11: 0.126 | I11: OEWS private sector 5
A12: 48-49 | B12: Transportation and warehousing | C12: 455483942924 | D12: 478826169400 | E12: 477192875600 | F12: 1.5708135e+11 | G12: 0.105 | H12: 0.076 | I12: MIXED: includes public postal service in OEWS weights
A13: 51 | B13: Information | C13: 544469565204 | D13: 323626172500 | E13: 321614756900 | F13: 1.8150197e+11 | G13: 0.502 | H13: 0.376 | I13: OEWS private sector 5
A14: 52 | B14: Finance and insurance | C14: 966666752201 | D14: 632312197400 | E14: 628985978900 | F14: 4.2699129e+11 | G14: 0.401 | H14: 0.304 | I14: OEWS private sector 5
A15: 53 | B15: Real estate and rental and leasing | C15: 193529178704 | D15: 157850571500 | E15: 156904776000 | F15: 7.3211257e+10 | G15: 0.308 | H15: 0.235 | I15: OEWS private sector 5
A16: 54 | B16: Professional, scientific, and technical services | C16: 1454390668355 | D16: 1171256518800 | E16: 1167218193400 | F16: 6.4740875e+11 | G16: 0.427 | H16: 0.342 | I16: OEWS private sector 5
... A23: 81 | B23: Other services (except public administration) | C23: 254468914292 | D23: 254714435300 | E23: 250743090000 | F23: 9.0672712e+10 | G23: 0.127 | H23: 0.098 | I23: OEWS private sector 5
A25: US QCEW control | B25: Private wage total including NAICS 99 | C25: 10532191402092
A26: NAICS 99 excluded | B26: Private unclassified annual wages | C26: 16545877587
A28: SOURCE NOTES: OEWS Exposure-Weighted Wages are SUM(Employment x Mean Annual Wage x Wharton SOC task-exposure score).

Sheet 03 Sources and QA
A1: DATA SOURCES, INDUSTRY MAPPING AND LIMITATIONS
A4: Data | B4: Official Source URL | C4: Uploaded Original | D4: Usage / filters
A5: BLS QCEW annual 2025 | B5: https://www.bls.gov/cew/downloadable-data-files.htm | C5: 2025_annual_by_industry (1).zip | D5: US000, own_code=5, annual total_annual_wages, NAICS 19 sectors plus 99
A6: BLS OEWS May 2025 | B6: https://www.bls.gov/oes/tables.htm | C6: natsector_M2025_dl.xlsx | D6: Sector x SOC detailed: TOT_EMP x A_MEAN; 61/62 ownership-adjusted
A7: BLS OEWS May 2025 ownership | B7: https://www.bls.gov/oes/2025/may/oessrci.htm | C7: nat3d_owner_M2025_dl.xlsx | D7: NAICS 611000 private only; subtract NAICS 622000 public hospital wages
A8: Penn Wharton occupational AI exposure | B8: https://budgetmodel.wharton.upenn.edu/p/2025-09-08-the-projected-impact-of-generative-ai-on-future-productivity-growth/ | C8: supp_exposure_by_occupation (1).csv | D8: 784 SOC; exposure (%) mapped to exact detailed occupation
A9: Census BTOS 202620 | B9: https://www.census.gov/hfp/btos/data_downloads | C9: Sector (3).xlsx | D9: Question ID 7 / Answer ID 1 / cycle 202620; share of BUSINESSES using AI
A10: Census AI Supplement 2026 | B10: https://www.census.gov/hfp/btos/data_downloads | C10: AI_Supplement_Table_2026 (1).xlsx | D10: Scope 1 / Question ID 1 / Answer ID 1 Yes; comparison only
A11: Detailed audit CSV | B11: https://www.bls.gov/oes/tables.htm | C11: AI_Wage_Exposure_Private_Adjusted_Detail.csv | D11: Detailed sector x SOC source with employment, annual wages, Wharton SOC score and match status
A14: Step 1 | B14: QCEW Annual Wages ($) for each 2025 private NAICS industry.
A15: Step 2 | B15: OEWS wage share by SOC = detailed occupation employment x mean annual wage.
A16: Step 3 | B16: Exact 6-digit SOC join to 784 Wharton task exposure scores.
A17: Step 4 | B17: OEWS task exposure share = Sum(matched wage x exposure)/Sum(matched wage).
A18: Step 5 | B18: Gross AI-exposed wage pool = QCEW private annual wage x Task Exposure Share.
A19: Formula workflow | B19: DATA OEWS: E×F; XLOOKUP SOC from DATA Wharton; matched and exposed wages. Main: SUMIF by NAICS, XLOOKUP QCEW/Census.
A20: Matching | B20: Missing Wharton SOC codes are omitted from numerator AND exposure denominator. Match coverage disclosed.
A21: Ownership | B21: Private QCEW always. OEWS 61 private from 611000, 62 subtract public hospitals, 48/71/72 mixed proxies.
A22: Mapping | B22: QCEW 31-33 / 44-45 / 48-49 map to Census sector codes 31 / 44 / 48.
A23: Reconcile | B23: QCEW private all-industries = sum 19 sector wage bills + NAICS 99 wage bill.

Sheet DATA QCEW
A1: NAICS | B1: Industry | C1: QCEW 2025 private annual wages ($) | D1: QCEW source
A2: 11 | B2: Agriculture, forestry, fishing and hunting | C2: 60088224865 | D2: https://www.bls.gov/cew/downloadable-data-files.htm
A3: 21 | B3: Mining, quarrying, and oil and gas extraction | C3: 76216722054 | D3: https://www.bls.gov/cew/downloadable-data-files.htm
A4: 22 | B4: Utilities | C4: 85024861666 | D4: https://www.bls.gov/cew/downloadable-data-files.htm
A5: 23 | B5: Construction | C5: 699896249139 | D5: https://www.bls.gov/cew/downloadable-data-files.htm
A6: 31-33 | B6: Manufacturing | C6: 1125542676332 | D6: https://www.bls.gov/cew/downloadable-data-files.htm
A7: 42 | B7: Wholesale trade | C7: 638878973832 | D7: https://www.bls.gov/cew/downloadable-data-files.htm
A8: 44-45 | B8: Retail trade | C8: 668863568474 | D8: https://www.bls.gov/cew/downloadable-data-files.htm
A9: 48-49 | B9: Transportation and warehousing | C9: 455483942924 | D9: https://www.bls.gov/cew/downloadable-data-files.htm
A10: 51 | B10: Information | C10: 544469565204 | D10: https://www.bls.gov/cew/downloadable-data-files.htm
A11: 52 | B11: Finance and insurance | C11: 966666752201 | D11: https://www.bls.gov/cew/downloadable-data-files.htm
A12: 53 | B12: Real estate and rental and leasing | C12: 193529178704 | D12: https://www.bls.gov/cew/downloadable-data-files.htm
A13: 54 | B13: Professional, scientific, and technical services | C13: 1454390668355 | D13: https://www.bls.gov/cew/downloadable-data-files.htm
... A20: 81 | B20: Other services (except public administration) | C20: 254468914292 | D20: https://www.bls.gov/cew/downloadable-data-files.htm

Sheet DATA OEWS
A1: NAICS | B1: Industry | C1: SOC code | D1: Occupation | E1: Employees | F1: Annual mean wage ($) | G1: Known occupation wages ($) | H1: Wharton task exposure | I1: Matched occupation wages ($) | J1: Exposure-weighted wages ($) | K1: Mapping status
A2: 11 | B2: Agriculture, Forestry, Fishing and Hunting | C2: 11-1011 | D2: Chief Executives | E2: 170 | F2: 277000 | G2: =IF(OR(E2="",F2=""),"",E2*F2) | H2: =IFERROR(XLOOKUP(C2,'DATA Wharton'!$A$2:$A$785,'DATA Wharton'!$C$2:$C$785),"") | I2: =IF(OR(G2="",H2=""),"",G2) | J2: =IF(OR(I2="",H2=""),"",I2*H2) | K2: =IF(G2="","Missing OEWS wage",IF(H2="","Missing Wharton SOC","Matched"))
A3: 11 | B3: Agriculture, Forestry, Fishing and Hunting | C3: 11-1021 | D3: General and Operations Managers | E3: 5660 | F3: 99340 | G3: =IF(OR(E3="",F3=""),"",E3*F3) | H3: =IFERROR(XLOOKUP(C3,'DATA Wharton'!$A$2:$A$785,'DATA Wharton'!$C$2:$C$785),"") | I3: =IF(OR(G3="",H3=""),"",G3) | J3: =IF(OR(I3="",H3=""),"",I3*H3) | K3: =IF(G3="","Missing OEWS wage",IF(H3="","Missing Wharton SOC","Matched"))
A4: 11 | B4: Agriculture, Forestry, Fishing and Hunting | C4: 11-2021 | D4: Marketing Managers | E4: 70 | F4: 129740 | G4: =IF(OR(E4="",F4=""),"",E4*F4) | H4: =IFERROR(XLOOKUP(C4,'DATA Wharton'!$A$2:$A$785,'DATA Wharton'!$C$2:$C$785),"") | I4: =IF(OR(G4="",H4=""),"",G4) | J4: =IF(OR(I4="",H4=""),"",I4*H4) | K4: =IF(G4="","Missing OEWS wage",IF(H4="","Missing Wharton SOC","Matched"))
A5: 11 | B5: Agriculture, Forestry, Fishing and Hunting | C5: 11-2022 | D5: Sales Managers | E5: 330 | F5: 162490 | G5: =IF(OR(E5="",F5=""),"",E5*F5) | H5: =IFERROR(XLOOKUP(C5,'DATA Wharton'!$A$2:$A$785,'DATA Wharton'!$C$2:$C$785),"") | I5: =IF(OR(G5="",H5=""),"",G5) | J5: =IF(OR(I5="",H5=""),"",I5*H5) | K5: =IF(G5="","Missing OEWS wage",IF(H5="","Missing Wharton SOC","Matched"))
A6: 11 | B6: Agriculture, Forestry, Fishing and Hunting | C6: 11-3012 | D6: Administrative Services Managers | E6: 150 | F6: 124650 | G6: =IF(OR(E6="",F6=""),"",E6*F6) | H6: =IFERROR(XLOOKUP(C6,'DATA Wharton'!$A$2:$A$785,'DATA Wharton'!$C$2:$C$785),"") | I6: =IF(OR(G6="",H6=""),"",G6) | J6: =IF(OR(I6="",H6=""),"",I6*H6) | K6: =IF(G6="","Missing OEWS wage",IF(H6="","Missing Wharton SOC","Matched"))
A7: 11 | B7: Agriculture, Forestry, Fishing and Hunting | C7: 11-3013 | D7: Facilities Managers | E7: 300 | F7: 115030 | G7: =IF(OR(E7="",F7=""),"",E7*F7) | H7: =IFERROR(XLOOKUP(C7,'DATA Wharton'!$A$2:$A$785,'DATA Wharton'!$C$2:$C$785),"") | I7: =IF(OR(G7="",H7=""),"",G7) | J7: =IF(OR(I7="",H7=""),"",I7*H7) | K7: =IF(G7="","Missing OEWS wage",IF(H7="","Missing Wharton SOC","Matched"))
A8: 11 | B8: Agriculture, Forestry, Fishing and Hunting | C8: 11-3021 | D8: Computer and Information Systems Managers | E8: 140 | F8: 160470 | G8: =IF(OR(E8="",F8=""),"",E8*F8) | H8: =IFERROR(XLOOKUP(C8,'DATA Wharton'!$A$2:$A$785,'DATA Wharton'!$C$2:$C$785),"") | I8: =IF(OR(G8="",H8=""),"",G8) | J8: =IF(OR(I8="",H8=""),"",I8*H8) | K8: =IF(G8="","Missing OEWS wage",IF(H8="","Missing Wharton SOC","Matched"))
A9: 11 | B9: Agriculture, Forestry, Fishing and Hunting | C9: 11-3031 | D9: Financial Managers | E9: 460 | F9: 156410 | G9: =IF(OR(E9="",F9=""),"",E9*F9) | H9: =IFERROR(XLOOKUP(C9,'DATA Wharton'!$A$2:$A$785,'DATA Wharton'!$C$2:$C$785),"") | I9: =IF(OR(G9="",H9=""),"",G9) | J9: =IF(OR(I9="",H9=""),"",I9*H9) | K9: =IF(G9="","Missing OEWS wage",IF(H9="","Missing Wharton SOC","Matched"))
A10: 11 | B10: Agriculture, Forestry, Fishing and Hunting | C10: 11-3051 | D10: Industrial Production Managers | E10: 580 | F10: 108020 | G10: =IF(OR(E10="",F10=""),"",E10*F10) | H10: =IFERROR(XLOOKUP(C10,'DATA Wharton'!$A$2:$A$785,'DATA Wharton'!$C$2:$C$785),"") | I10: =IF(OR(G10="",H10=""),"",G10) | J10: =IF(OR(I10="",H10=""),"",I10*H10) | K10: =IF(G10="","Missing OEWS wage",IF(H10="","Missing Wharton SOC","Matched"))
A11: 11 | B11: Agriculture, Forestry, Fishing and Hunting | C11: 11-3061 | D11: Purchasing Managers | E11: 50 | F11: 144980 | G11: =IF(OR(E11="",F11=""),"",E11*F11) | H11: =IFERROR(XLOOKUP(C11,'DATA Wharton'!$A$2:$A$785,'DATA Wharton'!$C$2:$C$785),"") | I11: =IF(OR(G11="",H11=""),"",G11) | J11: =IF(OR(I11="",H11=""),"",I11*H11) | K11: =IF(G11="","Missing OEWS wage",IF(H11="","Missing Wharton SOC","Matched"))
A12: 11 | B12: Agriculture, Forestry, Fishing and Hunting | C12: 11-3071 | D12: Transportation, Storage, and Distribution Managers | E12: 320 | F12: 100610 | G12: =IF(OR(E12="",F12=""),"",E12*F12) | H12: =IFERROR(XLOOKUP(C12,'DATA Wharton'!$A$2:$A$785,'DATA Wharton'!$C$2:$C$785),"") | I12: =IF(OR(G12="",H12=""),"",G12) | J12: =IF(OR(I12="",H12=""),"",I12*H12) | K12: =IF(G12="","Missing OEWS wage",IF(H12="","Missing Wharton SOC","Matched"))
A13: 11 | B13: Agriculture, Forestry, Fishing and Hunting | C13: 11-3121 | D13: Human Resources Managers | E13: 100 | F13: 141370 | G13: =IF(OR(E13="",F13=""),"",E13*F13) | H13: =IFERROR(XLOOKUP(C13,'DATA Wharton'!$A$2:$A$785,'DATA Wharton'!$C$2:$C$785),"") | I13: =IF(OR(G13="",H13=""),"",G13) | J13: =IF(OR(I13="",H13=""),"",I13*H13) | K13: =IF(G13="","Missing OEWS wage",IF(H13="","Missing Wharton SOC","Matched"))
... A15: 11 | B15: Agriculture, Forestry, Fishing and Hunting | C15: 11-9121 | D15: Natural Sciences Managers | E15: 50 | F15: 120590 | G15: =IF(OR(E15="",F15=""),"",E15*F15) | H15: =IFERROR(XLOOKUP(C15,'DATA Wharton'!$A$2:$A$785,'DATA Wharton'!$C$2:$C$785),"") | I15: =IF(OR(G15="",H15=""),"",G15) | J15: =IF(OR(I15="",H15=""),"",I15*H15) | K15: =IF(G15="","Missing OEWS wage",IF(H15="","Missing Wharton SOC","Matched"))
A16: 11 | B16: Agriculture, Forestry, Fishing and Hunting | C16: 11-9199 | D16: Managers, All Other | E16: 470 | G16: =IF(OR(E16="",F16=""),"",E16*F16) | H16: =IFERROR(XLOOKUP(C16,'DATA Wharton'!$A$2:$A$785,'DATA Wharton'!$C$2:$C$785),"") | I16: =IF(OR(G16="",H16=""),"",G16) | J16: =IF(OR(I16="",H16=""),"",I16*H16) | K16: =IF(G16="","Missing OEWS wage",IF(H16="","Missing Wharton SOC","Matched"))
A17: 11 | B17: Agriculture, Forestry, Fishing and Hunting | C17: 13-1020 | D17: Buyers and Purchasing Agents | E17: 520 | F17: 81950 | G17: =IF(OR(E17="",F17=""),"",E17*F17) | H17: =IFERROR(XLOOKUP(C17,'DATA Wharton'!$A$2:$A$785,'DATA Wharton'!$C$2:$C$785),"") | I17: =IF(OR(G17="",H17=""),"",G17) | J17: =IF(OR(I17="",H17=""),"",I17*H17) | K17: =IF(G17="","Missing OEWS wage",IF(H17="","Missing Wharton SOC","Matched"))
A18: 11 | B18: Agriculture, Forestry, Fishing and Hunting | C18: 13-1041 | D18: Compliance Officers | E18: 60 | F18: 67290 | G18: =IF(OR(E18="",F18=""),"",E18*F18) | H18: =IFERROR(XLOOKUP(C18,'DATA Wharton'!$A$2:$A$785,'DATA Wharton'!$C$2:$C$785),"") | I18: =IF(OR(G18="",H18=""),"",G18) | J18: =IF(OR(I18="",H18=""),"",I18*H18) | K18: =IF(G18="","Missing OEWS wage",IF(H18="","Missing Wharton SOC","Matched"))
A19: 11 | B19: Agriculture, Forestry, Fishing and Hunting | C19: 13-1071 | D19: Human Resources Specialists | E19: 700 | F19: 74400 | G19: =IF(OR(E19="",F19=""),"",E19*F19) | H19: =IFERROR(XLOOKUP(C19,'DATA Wharton'!$A$2:$A$785,'DATA Wharton'!$C$2:$C$785),"") | I19: =IF(OR(G19="",H19=""),"",G19) | J19: =IF(OR(I19="",H19=""),"",I19*H19) | K19: =IF(G19="","Missing OEWS wage",IF(H19="","Missing Wharton SOC","Matched"))
A20: 11 | B20: Agriculture, Forestry, Fishing and Hunting | C20: 13-1074 | D20: Farm Labor Contractors | E20: 270 | F20: 62420 | G20: =IF(OR(E20="",F20=""),"",E20*F20) | H20: =IFERROR(XLOOKUP(C20,'DATA Wharton'!$A$2:$A$785,'DATA Wharton'!$C$2:$C$785),"") | I20: =IF(OR(G20="",H20=""),"",G20) | J20: =IF(OR(I20="",H20=""),"",I20*H20) | K20: =IF(G20="","Missing OEWS wage",IF(H20="","Missing Wharton SOC","Matched"))
A21: 11 | B21: Agriculture, Forestry, Fishing and Hunting | C21: 13-1081 | D21: Logisticians | E21: 250 | F21: 75350 | G21: =IF(OR(E21="",F21=""),"",E21*F21) | H21: =IFERROR(XLOOKUP(C21,'DATA Wharton'!$A$2:$A$785,'DATA Wharton'!$C$2:$C$785),"") | I21: =IF(OR(G21="",H21=""),"",G21) | J21: =IF(OR(I21="",H21=""),"",I21*H21) | K21: =IF(G21="","Missing OEWS wage",IF(H21="","Missing Wharton SOC","Matched"))
A22: 11 | B22: Agriculture, Forestry, Fishing and Hunting | C22: 13-1082 | D22: Project Management Specialists | E22: 130 | F22: 90840 | G22: =IF(OR(E22="",F22=""),"",E22*F22) | H22: =IFERROR(XLOOKUP(C22,'DATA Wharton'!$A$2:$A$785,'DATA Wharton'!$C$2:$C$785),"") | I22: =IF(OR(G22="",H22=""),"",G22) | J22: =IF(OR(I22="",H22=""),"",I22*H22) | K22: =IF(G22="","Missing OEWS wage",IF(H22="","Missing Wharton SOC","Matched"))
A23: 11 | B23: Agriculture, Forestry, Fishing and Hunting | C23: 13-1111 | D23: Management Analysts | E23: 120 | G23: =IF(OR(E23="",F23=""),"",E23*F23) | H23: =IFERROR(XLOOKUP(C23,'DATA Wharton'!$A$2:$A$785,'DATA Wharton'!$C$2:$C$785),"") | I23: =IF(OR(G23="",H23=""),"",G23) | J23: =IF(OR(I23="",H23=""),"",I23*H23) | K23: =IF(G23="","Missing OEWS wage",IF(H23="","Missing Wharton SOC","Matched"))
A24: 11 | B24: Agriculture, Forestry, Fishing and Hunting | C24: 13-1121 | D24: Meeting, Convention, and Event Planners | E24: 50 | F24: 48850 | G24: =IF(OR(E24="",F24=""),"",E24*F24) | H24: =IFERROR(XLOOKUP(C24,'DATA Wharton'!$A$2:$A$785,'DATA Wharton'!$C$2:$C$785),"") | I24: =IF(OR(G24="",H24=""),"",G24) | J24: =IF(OR(I24="",H24=""),"",I24*H24) | K24: =IF(G24="","Missing OEWS wage",IF(H24="","Missing Wharton SOC","Matched"))
A25: 11 | B25: Agriculture, Forestry, Fishing and Hunting | C25: 13-1141 | D25: Compensation, Benefits, and Job Analysis Specialists | E25: 30 | G25: =IF(OR(E25="",F25=""),"",E25*F25) | H25: =IFERROR(XLOOKUP(C25,'DATA Wharton'!$A$2:$A$785,'DATA Wharton'!$C$2:$C$785),"") | I25: =IF(OR(G25="",H25=""),"",G25) | J25: =IF(OR(I25="",H25=""),"",I25*H25) | K25: =IF(G25="","Missing OEWS wage",IF(H25="","Missing Wharton SOC","Matched"))
A26: 11 | B26: Agriculture, Forestry, Fishing and Hunting | C26: 13-1151 | D26: Training and Development Specialists | E26: 100 | G26: =IF(OR(E26="",F26=""),"",E26*F26) | H26: =IFERROR(XLOOKUP(C26,'DATA Wharton'!$A$2:$A$785,'DATA Wharton'!$C$2:$C$785),"") | I26: =IF(OR(G26="",H26=""),"",G26) | J26: =IF(OR(I26="",H26=""),"",I26*H26) | K26: =IF(G26="","Missing OEWS wage",IF(H26="","Missing Wharton SOC","Matched"))
A27: 11 | B27: Agriculture, Forestry, Fishing and Hunting | C27: 13-1161 | D27: Market Research Analysts and Marketing Specialists | E27: 210 | F27: 92250 | G27: =IF(OR(E27="",F27=""),"",E27*F27) | H27: =IFERROR(XLOOKUP(C27,'DATA Wharton'!$A$2:$A$785,'DATA Wharton'!$C$2:$C$785),"") | I27: =IF(OR(G27="",H27=""),"",G27) | J27: =IF(OR(I27="",H27=""),"",I27*H27) | K27: =IF(G27="","Missing OEWS wage",IF(H27="","Missing Wharton SOC","Matched"))
A28: 11 | B28: Agriculture, Forestry, Fishing and Hunting | C28: 13-1199 | D28: Business Operations Specialists, All Other | E28: 660 | G28: =IF(OR(E28="",F28=""),"",E28*F28) | H28: =IFERROR(XLOOKUP(C28,'DATA Wharton'!$A$2:$A$785,'DATA Wharton'!$C$2:$C$785),"") | I28: =IF(OR(G28="",H28=""),"",G28) | J28: =IF(OR(I28="",H28=""),"",I28*H28) | K28: =IF(G28="","Missing OEWS wage",IF(H28="","Missing Wharton SOC","Matched"))
A29: 11 | B29: Agriculture, Forestry, Fishing and Hunting | C29: 13-2011 | D29: Accountants and Auditors | E29: 1110 | F29: 83410 | G29: =IF(OR(E29="",F29=""),"",E29*F29) | H29: =IFERROR(XLOOKUP(C29,'DATA Wharton'!$A$2:$A$785,'DATA Wharton'!$C$2:$C$785),"") | I29: =IF(OR(G29="",H29=""),"",G29) | J29: =IF(OR(I29="",H29=""),"",I29*H29) | K29: =IF(G29="","Missing OEWS wage",IF(H29="","Missing Wharton SOC","Matched"))
A30: 11 | B30: Agriculture, Forestry, Fishing and Hunting | C30: 15-1211 | D30: Computer Systems Analysts | E30: 40 | F30: 107730 | G30: =IF(OR(E30="",F30=""),"",E30*F30) | H30: =IFERROR(XLOOKUP(C30,'DATA Wharton'!$A$2:$A$785,'DATA Wharton'!$C$2:$C$785),"") | I30: =IF(OR(G30="",H30=""),"",G30) | J30: =IF(OR(I30="",H30=""),"",I30*H30) | K30: =IF(G30="","Missing OEWS wage",IF(H30="","Missing Wharton SOC","Matched"))
A31: 11 | B31: Agriculture, Forestry, Fishing and Hunting | C31: 15-1232 | D31: Computer User Support Specialists | E31: 230 | F31: 65730 | G31: =IF(OR(E31="",F31=""),"",E31*F31) | H31: =IFERROR(XLOOKUP(C31,'DATA Wharton'!$A$2:$A$785,'DATA Wharton'!$C$2:$C$785),"") | I31: =IF(OR(G31="",H31=""),"",G31) | J31: =IF(OR(I31="",H31=""),"",I31*H31) | K31: =IF(G31="","Missing OEWS wage",IF(H31="","Missing Wharton SOC","Matched"))
A32: 11 | B32: Agriculture, Forestry, Fishing and Hunting | C32: 15-1244 | D32: Network and Computer Systems Administrators | E32: 80 | G32: =IF(OR(E32="",F32=""),"",E32*F32) | H32: =IFERROR(XLOOKUP(C32,'DATA Wharton'!$A$2:$A$785,'DATA Wharton'!$C$2:$C$785),"") | I32: =IF(OR(G32="",H32=""),"",G32) | J32: =IF(OR(I32="",H32=""),"",I32*H32) | K32: =IF(G32="","Missing OEWS wage",IF(H32="","Missing Wharton SOC","Matched"))
A33: 11 | B33: Agriculture, Forestry, Fishing and Hunting | C33: 15-1252 | D33: Software Developers | E33: 90 | G33: =IF(OR(E33="",F33=""),"",E33*F33) | H33: =IFERROR(XLOOKUP(C33,'DATA Wharton'!$A$2:$A$785,'DATA Wharton'!$C$2:$C$785),"") | I33: =IF(OR(G33="",H33=""),"",G33) | J33: =IF(OR(I33="",H33=""),"",I33*H33) | K33: =IF(G33="","Missing OEWS wage",IF(H33="","Missing Wharton SOC","Matched"))
A34: 11 | B34: Agriculture, Forestry, Fishing and Hunting | C34: 15-1299 | D34: Computer Occupations, All Other | E34: 50 | F34: 101700 | G34: =IF(OR(E34="",F34=""),"",E34*F34) | H34: =IFERROR(XLOOKUP(C34,'DATA Wharton'!$A$2:$A$785,'DATA Wharton'!$C$2:$C$785),"") | I34: =IF(OR(G34="",H34=""),"",G34) | J34: =IF(OR(I34="",H34=""),"",I34*H34) | K34: =IF(G34="","Missing OEWS wage",IF(H34="","Missing Wharton SOC","Matched"))
A35: 11 | B35: Agriculture, Forestry, Fishing and Hunting | C35: 17-2112 | D35: Industrial Engineers | E35: 100 | F35: 87540 | G35: =IF(OR(E35="",F35=""),"",E35*F35) | H35: =IFERROR(XLOOKUP(C35,'DATA Wharton'!$A$2:$A$785,'DATA Wharton'!$C$2:$C$785),"") | I35: =IF(OR(G35="",H35=""),"",G35) | J35: =IF(OR(I35="",H35=""),"",I35*H35) | K35: =IF(G35="","Missing OEWS wage",IF(H35="","Missing Wharton SOC","Matched"))
A36: 11 | B36: Agriculture, Forestry, Fishing and Hunting | C36: 19-1011 | D36: Animal Scientists | E36: 220 | F36: 75660 | G36: =IF(OR(E36="",F36=""),"",E36*F36) | H36: =IFERROR(XLOOKUP(C36,'DATA Wharton'!$A$2:$A$785,'DATA Wharton'!$C$2:$C$785),"") | I36: =IF(OR(G36="",H36=""),"",G36) | J36: =IF(OR(I36="",H36=""),"",I36*H36) | K36: =IF(G36="","Missing OEWS wage",IF(H36="","Missing Wharton SOC","Matched"))
A37: 11 | B37: Agriculture, Forestry, Fishing and Hunting | C37: 19-1012 | D37: Food Scientists and Technologists | E37: 230 | F37: 73850 | G37: =IF(OR(E37="",F37=""),"",E37*F37) | H37: =IFERROR(XLOOKUP(C37,'DATA Wharton'!$A$2:$A$785,'DATA Wharton'!$C$2:$C$785),"") | I37: =IF(OR(G37="",H37=""),"",G37) | J37: =IF(OR(I37="",H37=""),"",I37*H37) | K37: =IF(G37="","Missing OEWS wage",IF(H37="","Missing Wharton SOC","Matched"))
A38: 11 | B38: Agriculture, Forestry, Fishing and Hunting | C38: 19-1013 | D38: Soil and Plant Scientists | E38: 770 | F38: 87270 | G38: =IF(OR(E38="",F38=""),"",E38*F38) | H38: =IFERROR(XLOOKUP(C38,'DATA Wharton'!$A$2:$A$785,'DATA Wharton'!$C$2:$C$785),"") | I38: =IF(OR(G38="",H38=""),"",G38) | J38: =IF(OR(I38="",H38=""),"",I38*H38) | K38: =IF(G38="","Missing OEWS wage",IF(H38="","Missing Wharton SOC","Matched"))
A39: 11 | B39: Agriculture, Forestry, Fishing and Hunting | C39: 19-1029 | D39: Biological Scientists, All Other | E39: 210 | F39: 60360 | G39: =IF(OR(E39="",F39=""),"",E39*F39) | H39: =IFERROR(XLOOKUP(C39,'DATA Wharton'!$A$2:$A$785,'DATA Wharton'!$C$2:$C$785),"") | I39: =IF(OR(G39="",H39=""),"",G39) | J39: =IF(OR(I39="",H39=""),"",I39*H39) | K39: =IF(G39="","Missing OEWS wage",IF(H39="","Missing Wharton SOC","Matched"))
A40: 11 | B40: Agriculture, Forestry, Fishing and Hunting | C40: 19-1032 | D40: Foresters | E40: 650 | F40: 81500 | G40: =IF(OR(E40="",F40=""),"",E40*F40) | H40: =IFERROR(XLOOKUP(C40,'DATA Wharton'!$A$2:$A$785,'DATA Wharton'!$C$2:$C$785),"") | I40: =IF(OR(G40="",H40=""),"",G40) | J40: =IF(OR(I40="",H40=""),"",I40*H40) | K40: =IF(G40="","Missing OEWS wage",IF(H40="","Missing Wharton SOC","Matched"))
A41: 11 | B41: Agriculture, Forestry, Fishing and Hunting | C41: 19-4012 | D41: Agricultural Technicians | E41: 1270 | F41: 52540 | G41: =IF(OR(E41="",F41=""),"",E41*F41) | H41: =IFERROR(XLOOKUP(C41,'DATA Wharton'!$A$2:$A$785,'DATA Wharton'!$C$2:$C$785),"") | I41: =IF(OR(G41="",H41=""),"",G41) | J41: =IF(OR(I41="",H41=""),"",I41*H41) | K41: =IF(G41="","Missing OEWS wage",IF(H41="","Missing Wharton SOC","Matched"))
A42: 11 | B42: Agriculture, Forestry, Fishing and Hunting | C42: 19-4013 | D42: Food Science Technicians | F42: 50010 | G42: =IF(OR(E42="",F42=""),"",E42*F42) | H42: =IFERROR(XLOOKUP(C42,'DATA Wharton'!$A$2:$A$785,'DATA Wharton'!$C$2:$C$785),"") | I42: =IF(OR(G42="",H42=""),"",G42) | J42: =IF(OR(I42="",H42=""),"",I42*H42) | K42: =IF(G42="","Missing OEWS wage",IF(H42="","Missing Wharton SOC","Matched"))
A43: 11 | B43: Agriculture, Forestry, Fishing and Hunting | C43: 19-4021 | D43: Biological Technicians | E43: 50 | F43: 63050 | G43: =IF(OR(E43="",F43=""),"",E43*F43) | H43: =IFERROR(XLOOKUP(C43,'DATA Wharton'!$A$2:$A$785,'DATA Wharton'!$C$2:$C$785),"") | I43: =IF(OR(G43="",H43=""),"",G43) | J43: =IF(OR(I43="",H43=""),"",I43*H43) | K43: =IF(G43="","Missing OEWS wage",IF(H43="","Missing Wharton SOC","Matched"))
A44: 11 | B44: Agriculture, Forestry, Fishing and Hunting | C44: 19-5011 | D44: Occupational Health and Safety Specialists | E44: 330 | F44: 65690 | G44: =IF(OR(E44="",F44=""),"",E44*F44) | H44: =IFERROR(XLOOKUP(C44,'DATA Wharton'!$A$2:$A$785,'DATA Wharton'!$C$2:$C$785),"") | I44: =IF(OR(G44="",H44=""),"",G44) | J44: =IF(OR(I44="",H44=""),"",I44*H44) | K44: =IF(G44="","Missing OEWS wage",IF(H44="","Missing Wharton SOC","Matched"))
A45: 11 | B45: Agriculture, Forestry, Fishing and Hunting | C45: 25-3021 | D45: Self-Enrichment Teachers | E45: 320 | F45: 41710 | G45: =IF(OR(E45="",F45=""),"",E45*F45) | H45: =IFERROR(XLOOKUP(C45,'DATA Wharton'!$A$2:$A$785,'DATA Wharton'!$C$2:$C$785),"") | I45: =IF(OR(G45="",H45=""),"",G45) | J45: =IF(OR(I45="",H45=""),"",I45*H45) | K45: =IF(G45="","Missing OEWS wage",IF(H45="","Missing Wharton SOC","Matched"))
A46: 11 | B46: Agriculture, Forestry, Fishing and Hunting | C46: 27-3031 | D46: Public Relations Specialists | E46: 60 | G46: =IF(OR(E46="",F46=""),"",E46*F46) | H46: =IFERROR(XLOOKUP(C46,'DATA Wharton'!$A$2:$A$785,'DATA Wharton'!$C$2:$C$785),"") | I46: =IF(OR(G46="",H46=""),"",G46) | J46: =IF(OR(I46="",H46=""),"",I46*H46) | K46: =IF(G46="","Missing OEWS wage",IF(H46="","Missing Wharton SOC","Matched"))
A47: 11 | B47: Agriculture, Forestry, Fishing and Hunting | C47: 29-1131 | D47: Veterinarians | E47: 150 | F47: 134040 | G47: =IF(OR(E47="",F47=""),"",E47*F47) | H47: =IFERROR(XLOOKUP(C47,'DATA Wharton'!$A$2:$A$785,'DATA Wharton'!$C$2:$C$785),"") | I47: =IF(OR(G47="",H47=""),"",G47) | J47: =IF(OR(I47="",H47=""),"",I47*H47) | K47: =IF(G47="","Missing OEWS wage",IF(H47="","Missing Wharton SOC","Matched"))
A48: 11 | B48: Agriculture, Forestry, Fishing and Hunting | C48: 29-2056 | D48: Veterinary Technologists and Technicians | E48: 210 | F48: 61840 | G48: =IF(OR(E48="",F48=""),"",E48*F48) | H48: =IFERROR(XLOOKUP(C48,'DATA Wharton'!$A$2:$A$785,'DATA Wharton'!$C$2:$C$785),"") | I48: =IF(OR(G48="",H48=""),"",G48) | J48: =IF(OR(I48="",H48=""),"",I48*H48) | K48: =IF(G48="","Missing OEWS wage",IF(H48="","Missing Wharton SOC","Matched"))
A49: 11 | B49: Agriculture, Forestry, Fishing and Hunting | C49: 33-9032 | D49: Security Guards | E49: 480 | F49: 37550 | G49: =IF(OR(E49="",F49=""),"",E49*F49) | H49: =IFERROR(XLOOKUP(C49,'DATA Wharton'!$A$2:$A$785,'DATA Wharton'!$C$2:$C$785),"") | I49: =IF(OR(G49="",H49=""),"",G49) | J49: =IF(OR(I49="",H49=""),"",I49*H49) | K49: =IF(G49="","Missing OEWS wage",IF(H49="","Missing Wharton SOC","Matched"))
A50: 11 | B50: Agriculture, Forestry, Fishing and Hunting | C50: 37-1011 | D50: First-Line Supervisors of Housekeeping and Janitorial Workers | E50: 80 | F50: 55650 | G50: =IF(OR(E50="",F50=""),"",E50*F50) | H50: =IFERROR(XLOOKUP(C50,'DATA Wharton'!$A$2:$A$785,'DATA Wharton'!$C$2:$C$785),"") | I50: =IF(OR(G50="",H50=""),"",G50) | J50: =IF(OR(I50="",H50=""),"",I50*H50) | K50: =IF(G50="","Missing OEWS wage",IF(H50="","Missing Wharton SOC","Matched"))
A51: 11 | B51: Agriculture, Forestry, Fishing and Hunting | C51: 37-1012 | D51: First-Line Supervisors of Landscaping, Lawn Service, and Groundskeeping Workers | E51: 180 | F51: 65570 | G51: =IF(OR(E51="",F51=""),"",E51*F51) | H51: =IFERROR(XLOOKUP(C51,'DATA Wharton'!$A$2:$A$785,'DATA Wharton'!$C$2:$C$785),"") | I51: =IF(OR(G51="",H51=""),"",G51) | J51: =IF(OR(I51="",H51=""),"",I51*H51) | K51: =IF(G51="","Missing OEWS wage",IF(H51="","Missing Wharton SOC","Matched"))
A52: 11 | B52: Agriculture, Forestry, Fishing and Hunting | C52: 37-2011 | D52: Janitors and Cleaners, Except Maids and Housekeeping Cleaners | E52: 2650 | F52: 37340 | G52: =IF(OR(E52="",F52=""),"",E52*F52) | H52: =IFERROR(XLOOKUP(C52,'DATA Wharton'!$A$2:$A$785,'DATA Wharton'!$C$2:$C$785),"") | I52: =IF(OR(G52="",H52=""),"",G52) | J52: =IF(OR(I52="",H52=""),"",I52*H52) | K52: =IF(G52="","Missing OEWS wage",IF(H52="","Missing Wharton SOC","Matched"))
A53: 11 | B53: Agriculture, Forestry, Fishing and Hunting | C53: 37-2012 | D53: Maids and Housekeeping Cleaners | E53: 140 | F53: 37400 | G53: =IF(OR(E53="",F53=""),"",E53*F53) | H53: =IFERROR(XLOOKUP(C53,'DATA Wharton'!$A$2:$A$785,'DATA Wharton'!$C$2:$C$785),"") | I53: =IF(OR(G53="",H53=""),"",G53) | J53: =IF(OR(I53="",H53=""),"",I53*H53) | K53: =IF(G53="","Missing OEWS wage",IF(H53="","Missing Wharton SOC","Matched"))
A54: 11 | B54: Agriculture, Forestry, Fishing and Hunting | C54: 37-2021 | D54: Pest Control Workers | E54: 70 | F54: 41940 | G54: =IF(OR(E54="",F54=""),"",E54*F54) | H54: =IFERROR(XLOOKUP(C54,'DATA Wharton'!$A$2:$A$785,'DATA Wharton'!$C$2:$C$785),"") | I54: =IF(OR(G54="",H54=""),"",G54) | J54: =IF(OR(I54="",H54=""),"",I54*H54) | K54: =IF(G54="","Missing OEWS wage",IF(H54="","Missing Wharton SOC","Matched"))
A55: 11 | B55: Agriculture, Forestry, Fishing and Hunting | C55: 37-3011 | D55: Landscaping and Groundskeeping Workers | E55: 1090 | F55: 42480 | G55: =IF(OR(E55="",F55=""),"",E55*F55) | H55: =IFERROR(XLOOKUP(C55,'DATA Wharton'!$A$2:$A$785,'DATA Wharton'!$C$2:$C$785),"") | I55: =IF(OR(G55="",H55=""),"",G55) | J55: =IF(OR(I55="",H55=""),"",I55*H55) | K55: =IF(G55="","Missing OEWS wage",IF(H55="","Missing Wharton SOC","Matched"))
A56: 11 | B56: Agriculture, Forestry, Fishing and Hunting | C56: 37-3012 | D56: Pesticide Handlers, Sprayers, and Applicators, Vegetation | E56: 2030 | F56: 43690 | G56: =IF(OR(E56="",F56=""),"",E56*F56) | H56: =IFERROR(XLOOKUP(C56,'DATA Wharton'!$A$2:$A$785,'DATA Wharton'!$C$2:$C$785),"") | I56: =IF(OR(G56="",H56=""),"",G56) | J56: =IF(OR(I56="",H56=""),"",I56*H56) | K56: =IF(G56="","Missing OEWS wage",IF(H56="","Missing Wharton SOC","Matched"))
A57: 11 | B57: Agriculture, Forestry, Fishing and Hunting | C57: 37-3013 | D57: Tree Trimmers and Pruners | F57: 50420 | G57: =IF(OR(E57="",F57=""),"",E57*F57) | H57: =IFERROR(XLOOKUP(C57,'DATA Wharton'!$A$2:$A$785,'DATA Wharton'!$C$2:$C$785),"") | I57: =IF(OR(G57="",H57=""),"",G57) | J57: =IF(OR(I57="",H57=""),"",I57*H57) | K57: =IF(G57="","Missing OEWS wage",IF(H57="","Missing Wharton SOC","Matched"))
A58: 11 | B58: Agriculture, Forestry, Fishing and Hunting | C58: 39-1014 | D58: First-Line Supervisors of Entertainment and Recreation Workers, Except Gambling Services | E58: 30 | F58: 49590 | G58: =IF(OR(E58="",F58=""),"",E58*F58) | H58: =IFERROR(XLOOKUP(C58,'DATA Wharton'!$A$2:$A$785,'DATA Wharton'!$C$2:$C$785),"") | I58: =IF(OR(G58="",H58=""),"",G58) | J58: =IF(OR(I58="",H58=""),"",I58*H58) | K58: =IF(G58="","Missing OEWS wage",IF(H58="","Missing Wharton SOC","Matched"))
A59: 11 | B59: Agriculture, Forestry, Fishing and Hunting | C59: 39-1022 | D59: First-Line Supervisors of Personal Service Workers | E59: 240 | F59: 52370 | G59: =IF(OR(E59="",F59=""),"",E59*F59) | H59: =IFERROR(XLOOKUP(C59,'DATA Wharton'!$A$2:$A$785,'DATA Wharton'!$C$2:$C$785),"") | I59: =IF(OR(G59="",H59=""),"",G59) | J59: =IF(OR(I59="",H59=""),"",I59*H59) | K59: =IF(G59="","Missing OEWS wage",IF(H59="","Missing Wharton SOC","Matched"))
A60: 11 | B60: Agriculture, Forestry, Fishing and Hunting | C60: 39-2011 | D60: Animal Trainers | E60: 1430 | F60: 48390 | G60: =IF(OR(E60="",F60=""),"",E60*F60) | H60: =IFERROR(XLOOKUP(C60,'DATA Wharton'!$A$2:$A$785,'DATA Wharton'!$C$2:$C$785),"") | I60: =IF(OR(G60="",H60=""),"",G60) | J60: =IF(OR(I60="",H60=""),"",I60*H60) | K60: =IF(G60="","Missing OEWS wage",IF(H60="","Missing Wharton SOC","Matched"))
A61: 11 | B61: Agriculture, Forestry, Fishing and Hunting | C61: 39-2021 | D61: Animal Caretakers | E61: 5870 | F61: 38710 | G61: =IF(OR(E61="",F61=""),"",E61*F61) | H61: =IFERROR(XLOOKUP(C61,'DATA Wharton'!$A$2:$A$785,'DATA Wharton'!$C$2:$C$785),"") | I61: =IF(OR(G61="",H61=""),"",G61) | J61: =IF(OR(I61="",H61=""),"",I61*H61) | K61: =IF(G61="","Missing OEWS wage",IF(H61="","Missing Wharton SOC","Matched"))
A62: 11 | B62: Agriculture, Forestry, Fishing and Hunting | C62: 41-1011 | D62: First-Line Supervisors of Retail Sales Workers | E62: 40 | G62: =IF(OR(E62="",F62=""),"",E62*F62) | H62: =IFERROR(XLOOKUP(C62,'DATA Wharton'!$A$2:$A$785,'DATA Wharton'!$C$2:$C$785),"") | I62: =IF(OR(G62="",H62=""),"",G62) | J62: =IF(OR(I62="",H62=""),"",I62*H62) | K62: =IF(G62="","Missing OEWS wage",IF(H62="","Missing Wharton SOC","Matched"))
A63: 11 | B63: Agriculture, Forestry, Fishing and Hunting | C63: 41-1012 | D63: First-Line Supervisors of Non-Retail Sales Workers | E63: 50 | F63: 112040 | G63: =IF(OR(E63="",F63=""),"",E63*F63) | H63: =IFERROR(XLOOKUP(C63,'DATA Wharton'!$A$2:$A$785,'DATA Wharton'!$C$2:$C$785),"") | I63: =IF(OR(G63="",H63=""),"",G63) | J63: =IF(OR(I63="",H63=""),"",I63*H63) | K63: =IF(G63="","Missing OEWS wage",IF(H63="","Missing Wharton SOC","Matched"))
A64: 11 | B64: Agriculture, Forestry, Fishing and Hunting | C64: 41-2031 | D64: Retail Salespersons | E64: 340 | F64: 43990 | G64: =IF(OR(E64="",F64=""),"",E64*F64) | H64: =IFERROR(XLOOKUP(C64,'DATA Wharton'!$A$2:$A$785,'DATA Wharton'!$C$2:$C$785),"") | I64: =IF(OR(G64="",H64=""),"",G64) | J64: =IF(OR(I64="",H64=""),"",I64*H64) | K64: =IF(G64="","Missing OEWS wage",IF(H64="","Missing Wharton SOC","Matched"))
A65: 11 | B65: Agriculture, Forestry, Fishing and Hunting | C65: 41-3091 | D65: Sales Representatives of Services, Except Advertising, Insurance, Financial Services, and Travel | E65: 670 | F65: 81740 | G65: =IF(OR(E65="",F65=""),"",E65*F65) | H65: =IFERROR(XLOOKUP(C65,'DATA Wharton'!$A$2:$A$785,'DATA Wharton'!$C$2:$C$785),"") | I65: =IF(OR(G65="",H65=""),"",G65) | J65: =IF(OR(I65="",H65=""),"",I65*H65) | K65: =IF(G65="","Missing OEWS wage",IF(H65="","Missing Wharton SOC","Matched"))
A66: 11 | B66: Agriculture, Forestry, Fishing and Hunting | C66: 41-4012 | D66: Sales Representatives, Wholesale and Manufacturing, Except Technical and Scientific Products | E66: 1600 | F66: 76540 | G66: =IF(OR(E66="",F66=""),"",E66*F66) | H66: =IFERROR(XLOOKUP(C66,'DATA Wharton'!$A$2:$A$785,'DATA Wharton'!$C$2:$C$785),"") | I66: =IF(OR(G66="",H66=""),"",G66) | J66: =IF(OR(I66="",H66=""),"",I66*H66) | K66: =IF(G66="","Missing OEWS wage",IF(H66="","Missing Wharton SOC","Matched"))
A67: 11 | B67: Agriculture, Forestry, Fishing and Hunting | C67: 41-9099 | D67: Sales and Related Workers, All Other | E67: 70 | F67: 66120 | G67: =IF(OR(E67="",F67=""),"",E67*F67) | H67: =IFERROR(XLOOKUP(C67,'DATA Wharton'!$A$2:$A$785,'DATA Wharton'!$C$2:$C$785),"") | I67: =IF(OR(G67="",H67=""),"",G67) | J67: =IF(OR(I67="",H67=""),"",I67*H67) | K67: =IF(G67="","Missing OEWS wage",IF(H67="","Missing Wharton SOC","Matched"))
A68: 11 | B68: Agriculture, Forestry, Fishing and Hunting | C68: 43-1011 | D68: First-Line Supervisors of Office and Administrative Support Workers | E68: 1620 | F68: 70640 | G68: =IF(OR(E68="",F68=""),"",E68*F68) | H68: =IFERROR(XLOOKUP(C68,'DATA Wharton'!$A$2:$A$785,'DATA Wharton'!$C$2:$C$785),"") | I68: =IF(OR(G68="",H68=""),"",G68) | J68: =IF(OR(I68="",H68=""),"",I68*H68) | K68: =IF(G68="","Missing OEWS wage",IF(H68="","Missing Wharton SOC","Matched"))
A69: 11 | B69: Agriculture, Forestry, Fishing and Hunting | C69: 43-3021 | D69: Billing and Posting Clerks | E69: 50 | F69: 50560 | G69: =IF(OR(E69="",F69=""),"",E69*F69) | H69: =IFERROR(XLOOKUP(C69,'DATA Wharton'!$A$2:$A$785,'DATA Wharton'!$C$2:$C$785),"") | I69: =IF(OR(G69="",H69=""),"",G69) | J69: =IF(OR(I69="",H69=""),"",I69*H69) | K69: =IF(G69="","Missing OEWS wage",IF(H69="","Missing Wharton SOC","Matched"))
A70: 11 | B70: Agriculture, Forestry, Fishing and Hunting | C70: 43-3031 | D70: Bookkeeping, Accounting, and Auditing Clerks | E70: 4100 | F70: 51280 | G70: =IF(OR(E70="",F70=""),"",E70*F70) | H70: =IFERROR(XLOOKUP(C70,'DATA Wharton'!$A$2:$A$785,'DATA Wharton'!$C$2:$C$785),"") | I70: =IF(OR(G70="",H70=""),"",G70) | J70: =IF(OR(I70="",H70=""),"",I70*H70) | K70: =IF(G70="","Missing OEWS wage",IF(H70="","Missing Wharton SOC","Matched"))
A71: 11 | B71: Agriculture, Forestry, Fishing and Hunting | C71: 43-3051 | D71: Payroll and Timekeeping Clerks | E71: 1180 | F71: 50080 | G71: =IF(OR(E71="",F71=""),"",E71*F71) | H71: =IFERROR(XLOOKUP(C71,'DATA Wharton'!$A$2:$A$785,'DATA Wharton'!$C$2:$C$785),"") | I71: =IF(OR(G71="",H71=""),"",G71) | J71: =IF(OR(I71="",H71=""),"",I71*H71) | K71: =IF(G71="","Missing OEWS wage",IF(H71="","Missing Wharton SOC","Matched"))
A72: 11 | B72: Agriculture, Forestry, Fishing and Hunting | C72: 43-3061 | D72: Procurement Clerks | E72: 60 | F72: 54540 | G72: =IF(OR(E72="",F72=""),"",E72*F72) | H72: =IFERROR(XLOOKUP(C72,'DATA Wharton'!$A$2:$A$785,'DATA Wharton'!$C$2:$C$785),"") | I72: =IF(OR(G72="",H72=""),"",G72) | J72: =IF(OR(I72="",H72=""),"",I72*H72) | K72: =IF(G72="","Missing OEWS wage",IF(H72="","Missing Wharton SOC","Matched"))
A73: 11 | B73: Agriculture, Forestry, Fishing and Hunting | C73: 43-4051 | D73: Customer Service Representatives | E73: 510 | F73: 44350 | G73: =IF(OR(E73="",F73=""),"",E73*F73) | H73: =IFERROR(XLOOKUP(C73,'DATA Wharton'!$A$2:$A$785,'DATA Wharton'!$C$2:$C$785),"") | I73: =IF(OR(G73="",H73=""),"",G73) | J73: =IF(OR(I73="",H73=""),"",I73*H73) | K73: =IF(G73="","Missing OEWS wage",IF(H73="","Missing Wharton SOC","Matched"))
A74: 11 | B74: Agriculture, Forestry, Fishing and Hunting | C74: 43-4071 | D74: File Clerks | E74: 50 | F74: 36750 | G74: =IF(OR(E74="",F74=""),"",E74*F74) | H74: =IFERROR(XLOOKUP(C74,'DATA Wharton'!$A$2:$A$785,'DATA Wharton'!$C$2:$C$785),"") | I74: =IF(OR(G74="",H74=""),"",G74) | J74: =IF(OR(I74="",H74=""),"",I74*H74) | K74: =IF(G74="","Missing OEWS wage",IF(H74="","Missing Wharton SOC","Matched"))
... A109: 11 | B109: Agriculture, Forestry, Fishing and Hunting | C109: 49-9071 | D109: Maintenance and Repair Workers, General | E109: 3160 | F109: 47020 | G109: =IF(OR(E109="",F109=""),"",E109*F109) | H109: =IFERROR(XLOOKUP(C109,'DATA Wharton'!$A$2:$A$785,'DATA Wharton'!$C$2:$C$785),"") | I109: =IF(OR(G109="",H109=""),"",G109) | J109: =IF(OR(I109="",H109=""),"",I109*H109) | K109: =IF(G109="","Missing OEWS wage",IF(H109="","Missing Wharton SOC","Matched"))
A110: 11 | B110: Agriculture, Forestry, Fishing and Hunting | C110: 49-9098 | D110: Helpers--Installation, Maintenance, and Repair Workers | E110: 220 | G110: =IF(OR(E110="",F110=""),"",E110*F110) | H110: =IFERROR(XLOOKUP(C110,'DATA Wharton'!$A$2:$A$785,'DATA Wharton'!$C$2:$C$785),"") | I110: =IF(OR(G110="",H110=""),"",G110) | J110: =IF(OR(I110="",H110=""),"",I110*H110) | K110: =IF(G110="","Missing OEWS wage",IF(H110="","Missing Wharton SOC","Matched"))
A111: 11 | B111: Agriculture, Forestry, Fishing and Hunting | C111: 49-9099 | D111: Installation, Maintenance, and Repair Workers, All Other | E111: 60 | F111: 50350 | G111: =IF(OR(E111="",F111=""),"",E111*F111) | H111: =IFERROR(XLOOKUP(C111,'DATA Wharton'!$A$2:$A$785,'DATA Wharton'!$C$2:$C$785),"") | I111: =IF(OR(G111="",H111=""),"",G111) | J111: =IF(OR(I111="",H111=""),"",I111*H111) | K111: =IF(G111="","Missing OEWS wage",IF(H111="","Missing Wharton SOC","Matched"))
A112: 11 | B112: Agriculture, Forestry, Fishing and Hunting | C112: 51-1011 | D112: First-Line Supervisors of Production and Operating Workers | E112: 1500 | F112: 62390 | G112: =IF(OR(E112="",F112=""),"",E112*F112) | H112: =IFERROR(XLOOKUP(C112,'DATA Wharton'!$A$2:$A$785,'DATA Wharton'!$C$2:$C$785),"") | I112: =IF(OR(G112="",H112=""),"",G112) | J112: =IF(OR(I112="",H112=""),"",I112*H112) | K112: =IF(G112="","Missing OEWS wage",IF(H112="","Missing Wharton SOC","Matched"))
A113: 11 | B113: Agriculture, Forestry, Fishing and Hunting | C113: 51-2090 | D113: Miscellaneous Assemblers and Fabricators | E113: 50 | F113: 37370 | G113: =IF(OR(E113="",F113=""),"",E113*F113) | H113: =IFERROR(XLOOKUP(C113,'DATA Wharton'!$A$2:$A$785,'DATA Wharton'!$C$2:$C$785),"") | I113: =IF(OR(G113="",H113=""),"",G113) | J113: =IF(OR(I113="",H113=""),"",I113*H113) | K113: =IF(G113="","Missing OEWS wage",IF(H113="","Missing Wharton SOC","Matched"))
A114: 11 | B114: Agriculture, Forestry, Fishing and Hunting | C114: 51-3091 | D114: Food and Tobacco Roasting, Baking, and Drying Machine Operators and Tenders | E114: 570 | F114: 41400 | G114: =IF(OR(E114="",F114=""),"",E114*F114) | H114: =IFERROR(XLOOKUP(C114,'DATA Wharton'!$A$2:$A$785,'DATA Wharton'!$C$2:$C$785),"") | I114: =IF(OR(G114="",H114=""),"",G114) | J114: =IF(OR(I114="",H114=""),"",I114*H114) | K114: =IF(G114="","Missing OEWS wage",IF(H114="","Missing Wharton SOC","Matched"))
A115: 11 | B115: Agriculture, Forestry, Fishing and Hunting | C115: 51-3092 | D115: Food Batchmakers | F115: 37950 | G115: =IF(OR(E115="",F115=""),"",E115*F115) | H115: =IFERROR(XLOOKUP(C115,'DATA Wharton'!$A$2:$A$785,'DATA Wharton'!$C$2:$C$785),"") | I115: =IF(OR(G115="",H115=""),"",G115) | J115: =IF(OR(I115="",H115=""),"",I115*H115) | K115: =IF(G115="","Missing OEWS wage",IF(H115="","Missing Wharton SOC","Matched"))
A116: 11 | B116: Agriculture, Forestry, Fishing and Hunting | C116: 51-3099 | D116: Food Processing Workers, All Other | E116: 360 | F116: 31980 | G116: =IF(OR(E116="",F116=""),"",E116*F116) | H116: =IFERROR(XLOOKUP(C116,'DATA Wharton'!$A$2:$A$785,'DATA Wharton'!$C$2:$C$785),"") | I116: =IF(OR(G116="",H116=""),"",G116) | J116: =IF(OR(I116="",H116=""),"",I116*H116) | K116: =IF(G116="","Missing OEWS wage",IF(H116="","Missing Wharton SOC","Matched"))
A117: 11 | B117: Agriculture, Forestry, Fishing and Hunting | C117: 51-4121 | D117: Welders, Cutters, Solderers, and Brazers | E117: 280 | F117: 49290 | G117: =IF(OR(E117="",F117=""),"",E117*F117) | H117: =IFERROR(XLOOKUP(C117,'DATA Wharton'!$A$2:$A$785,'DATA Wharton'!$C$2:$C$785),"") | I117: =IF(OR(G117="",H117=""),"",G117) | J117: =IF(OR(I117="",H117=""),"",I117*H117) | K117: =IF(G117="","Missing OEWS wage",IF(H117="","Missing Wharton SOC","Matched"))
A118: 11 | B118: Agriculture, Forestry, Fishing and Hunting | C118: 51-7041 | D118: Sawing Machine Setters, Operators, and Tenders, Wood | E118: 430 | F118: 50280 | G118: =IF(OR(E118="",F118=""),"",E118*F118) | H118: =IFERROR(XLOOKUP(C118,'DATA Wharton'!$A$2:$A$785,'DATA Wharton'!$C$2:$C$785),"") | I118: =IF(OR(G118="",H118=""),"",G118) | J118: =IF(OR(I118="",H118=""),"",I118*H118) | K118: =IF(G118="","Missing OEWS wage",IF(H118="","Missing Wharton SOC","Matched"))
A119: 11 | B119: Agriculture, Forestry, Fishing and Hunting | C119: 51-9012 | D119: Separating, Filtering, Clarifying, Precipitating, and Still Machine Setters, Operators, and Tenders | E119: 740 | F119: 44300 | G119: =IF(OR(E119="",F119=""),"",E119*F119) | H119: =IFERROR(XLOOKUP(C119,'DATA Wharton'!$A$2:$A$785,'DATA Wharton'!$C$2:$C$785),"") | I119: =IF(OR(G119="",H119=""),"",G119) | J119: =IF(OR(I119="",H119=""),"",I119*H119) | K119: =IF(G119="","Missing OEWS wage",IF(H119="","Missing Wharton SOC","Matched"))
A120: 11 | B120: Agriculture, Forestry, Fishing and Hunting | C120: 51-9021 | D120: Crushing, Grinding, and Polishing Machine Setters, Operators, and Tenders | E120: 130 | F120: 47210 | G120: =IF(OR(E120="",F120=""),"",E120*F120) | H120: =IFERROR(XLOOKUP(C120,'DATA Wharton'!$A$2:$A$785,'DATA Wharton'!$C$2:$C$785),"") | I120: =IF(OR(G120="",H120=""),"",G120) | J120: =IF(OR(I120="",H120=""),"",I120*H120) | K120: =IF(G120="","Missing OEWS wage",IF(H120="","Missing Wharton SOC","Matched"))
A121: 11 | B121: Agriculture, Forestry, Fishing and Hunting | C121: 51-9023 | D121: Mixing and Blending Machine Setters, Operators, and Tenders | E121: 230 | F121: 44480 | G121: =IF(OR(E121="",F121=""),"",E121*F121) | H121: =IFERROR(XLOOKUP(C121,'DATA Wharton'!$A$2:$A$785,'DATA Wharton'!$C$2:$C$785),"") | I121: =IF(OR(G121="",H121=""),"",G121) | J121: =IF(OR(I121="",H121=""),"",I121*H121) | K121: =IF(G121="","Missing OEWS wage",IF(H121="","Missing Wharton SOC","Matched"))
A122: 11 | B122: Agriculture, Forestry, Fishing and Hunting | C122: 51-9031 | D122: Cutters and Trimmers, Hand | F122: 36820 | G122: =IF(OR(E122="",F122=""),"",E122*F122) | H122: =IFERROR(XLOOKUP(C122,'DATA Wharton'!$A$2:$A$785,'DATA Wharton'!$C$2:$C$785),"") | I122: =IF(OR(G122="",H122=""),"",G122) | J122: =IF(OR(I122="",H122=""),"",I122*H122) | K122: =IF(G122="","Missing OEWS wage",IF(H122="","Missing Wharton SOC","Matched"))
A123: 11 | B123: Agriculture, Forestry, Fishing and Hunting | C123: 51-9032 | D123: Cutting and Slicing Machine Setters, Operators, and Tenders | E123: 100 | F123: 45530 | G123: =IF(OR(E123="",F123=""),"",E123*F123) | H123: =IFERROR(XLOOKUP(C123,'DATA Wharton'!$A$2:$A$785,'DATA Wharton'!$C$2:$C$785),"") | I123: =IF(OR(G123="",H123=""),"",G123) | J123: =IF(OR(I123="",H123=""),"",I123*H123) | K123: =IF(G123="","Missing OEWS wage",IF(H123="","Missing Wharton SOC","Matched"))
A124: 11 | B124: Agriculture, Forestry, Fishing and Hunting | C124: 51-9041 | D124: Extruding, Forming, Pressing, and Compacting Machine Setters, Operators, and Tenders | E124: 70 | G124: =IF(OR(E124="",F124=""),"",E124*F124) | H124: =IFERROR(XLOOKUP(C124,'DATA Wharton'!$A$2:$A$785,'DATA Wharton'!$C$2:$C$785),"") | I124: =IF(OR(G124="",H124=""),"",G124) | J124: =IF(OR(I124="",H124=""),"",I124*H124) | K124: =IF(G124="","Missing OEWS wage",IF(H124="","Missing Wharton SOC","Matched"))
A125: 11 | B125: Agriculture, Forestry, Fishing and Hunting | C125: 51-9061 | D125: Inspectors, Testers, Sorters, Samplers, and Weighers | E125: 2080 | F125: 41850 | G125: =IF(OR(E125="",F125=""),"",E125*F125) | H125: =IFERROR(XLOOKUP(C125,'DATA Wharton'!$A$2:$A$785,'DATA Wharton'!$C$2:$C$785),"") | I125: =IF(OR(G125="",H125=""),"",G125) | J125: =IF(OR(I125="",H125=""),"",I125*H125) | K125: =IF(G125="","Missing OEWS wage",IF(H125="","Missing Wharton SOC","Matched"))
A126: 11 | B126: Agriculture, Forestry, Fishing and Hunting | C126: 51-9111 | D126: Packaging and Filling Machine Operators and Tenders | E126: 4740 | F126: 39870 | G126: =IF(OR(E126="",F126=""),"",E126*F126) | H126: =IFERROR(XLOOKUP(C126,'DATA Wharton'!$A$2:$A$785,'DATA Wharton'!$C$2:$C$785),"") | I126: =IF(OR(G126="",H126=""),"",G126) | J126: =IF(OR(I126="",H126=""),"",I126*H126) | K126: =IF(G126="","Missing OEWS wage",IF(H126="","Missing Wharton SOC","Matched"))
A127: 11 | B127: Agriculture, Forestry, Fishing and Hunting | C127: 51-9192 | D127: Cleaning, Washing, and Metal Pickling Equipment Operators and Tenders | E127: 130 | F127: 42800 | G127: =IF(OR(E127="",F127=""),"",E127*F127) | H127: =IFERROR(XLOOKUP(C127,'DATA Wharton'!$A$2:$A$785,'DATA Wharton'!$C$2:$C$785),"") | I127: =IF(OR(G127="",H127=""),"",G127) | J127: =IF(OR(I127="",H127=""),"",I127*H127) | K127: =IF(G127="","Missing OEWS wage",IF(H127="","Missing Wharton SOC","Matched"))
A128: 11 | B128: Agriculture, Forestry, Fishing and Hunting | C128: 51-9196 | D128: Paper Goods Machine Setters, Operators, and Tenders | E128: 320 | F128: 38480 | G128: =IF(OR(E128="",F128=""),"",E128*F128) | H128: =IFERROR(XLOOKUP(C128,'DATA Wharton'!$A$2:$A$785,'DATA Wharton'!$C$2:$C$785),"") | I128: =IF(OR(G128="",H128=""),"",G128) | J128: =IF(OR(I128="",H128=""),"",I128*H128) | K128: =IF(G128="","Missing OEWS wage",IF(H128="","Missing Wharton SOC","Matched"))
A129: 11 | B129: Agriculture, Forestry, Fishing and Hunting | C129: 51-9198 | D129: Helpers--Production Workers | E129: 240 | F129: 40280 | G129: =IF(OR(E129="",F129=""),"",E129*F129) | H129: =IFERROR(XLOOKUP(C129,'DATA Wharton'!$A$2:$A$785,'DATA Wharton'!$C$2:$C$785),"") | I129: =IF(OR(G129="",H129=""),"",G129) | J129: =IF(OR(I129="",H129=""),"",I129*H129) | K129: =IF(G129="","Missing OEWS wage",IF(H129="","Missing Wharton SOC","Matched"))
A130: 11 | B130: Agriculture, Forestry, Fishing and Hunting | C130: 51-9199 | D130: Production Workers, All Other | E130: 210 | F130: 42180 | G130: =IF(OR(E130="",F130=""),"",E130*F130) | H130: =IFERROR(XLOOKUP(C130,'DATA Wharton'!$A$2:$A$785,'DATA Wharton'!$C$2:$C$785),"") | I130: =IF(OR(G130="",H130=""),"",G130) | J130: =IF(OR(I130="",H130=""),"",I130*H130) | K130: =IF(G130="","Missing OEWS wage",IF(H130="","Missing Wharton SOC","Matched"))
A131: 11 | B131: Agriculture, Forestry, Fishing and Hunting | C131: 53-1047 | D131: First-Line Supervisors of Transportation and Material Moving Workers, Except Aircraft Cargo Handling Supervisors | E131: 1860 | F131: 60310 | G131: =IF(OR(E131="",F131=""),"",E131*F131) | H131: =IFERROR(XLOOKUP(C131,'DATA Wharton'!$A$2:$A$785,'DATA Wharton'!$C$2:$C$785),"") | I131: =IF(OR(G131="",H131=""),"",G131) | J131: =IF(OR(I131="",H131=""),"",I131*H131) | K131: =IF(G131="","Missing OEWS wage",IF(H131="","Missing Wharton SOC","Matched"))
A132: 11 | B132: Agriculture, Forestry, Fishing and Hunting | C132: 53-2012 | D132: Commercial Pilots | E132: 830 | F132: 84540 | G132: =IF(OR(E132="",F132=""),"",E132*F132) | H132: =IFERROR(XLOOKUP(C132,'DATA Wharton'!$A$2:$A$785,'DATA Wharton'!$C$2:$C$785),"") | I132: =IF(OR(G132="",H132=""),"",G132) | J132: =IF(OR(I132="",H132=""),"",I132*H132) | K132: =IF(G132="","Missing OEWS wage",IF(H132="","Missing Wharton SOC","Matched"))
A133: 11 | B133: Agriculture, Forestry, Fishing and Hunting | C133: 53-3031 | D133: Driver/Sales Workers | E133: 50 | F133: 41570 | G133: =IF(OR(E133="",F133=""),"",E133*F133) | H133: =IFERROR(XLOOKUP(C133,'DATA Wharton'!$A$2:$A$785,'DATA Wharton'!$C$2:$C$785),"") | I133: =IF(OR(G133="",H133=""),"",G133) | J133: =IF(OR(I133="",H133=""),"",I133*H133) | K133: =IF(G133="","Missing OEWS wage",IF(H133="","Missing Wharton SOC","Matched"))
A134: 11 | B134: Agriculture, Forestry, Fishing and Hunting | C134: 53-3032 | D134: Heavy and Tractor-Trailer Truck Drivers | E134: 14930 | F134: 51330 | G134: =IF(OR(E134="",F134=""),"",E134*F134) | H134: =IFERROR(XLOOKUP(C134,'DATA Wharton'!$A$2:$A$785,'DATA Wharton'!$C$2:$C$785),"") | I134: =IF(OR(G134="",H134=""),"",G134) | J134: =IF(OR(I134="",H134=""),"",I134*H134) | K134: =IF(G134="","Missing OEWS wage",IF(H134="","Missing Wharton SOC","Matched"))
A135: 11 | B135: Agriculture, Forestry, Fishing and Hunting | C135: 53-3033 | D135: Light Truck Drivers | E135: 660 | F135: 39350 | G135: =IF(OR(E135="",F135=""),"",E135*F135) | H135: =IFERROR(XLOOKUP(C135,'DATA Wharton'!$A$2:$A$785,'DATA Wharton'!$C$2:$C$785),"") | I135: =IF(OR(G135="",H135=""),"",G135) | J135: =IF(OR(I135="",H135=""),"",I135*H135) | K135: =IF(G135="","Missing OEWS wage",IF(H135="","Missing Wharton SOC","Matched"))
...

Sheet DATA Wharton
A1: SOC code | B1: Occupation | C1: Wharton AI task exposure | D1: Wharton source
A2: 11-1011 | B2: Chief Executives | C2: 0.4775 | D2: https://budgetmodel.wharton.upenn.edu/p/2025-09-08-the-projected-impact-of-generative-ai-on-future-productivity-growth/
A3: 11-1021 | B3: General and Operations Managers | C3: 0.5382 | D3: https://budgetmodel.wharton.upenn.edu/p/2025-09-08-the-projected-impact-of-generative-ai-on-future-productivity-growth/
A4: 11-1031 | B4: Legislators | C4: 0.1967 | D4: https://budgetmodel.wharton.upenn.edu/p/2025-09-08-the-projected-impact-of-generative-ai-on-future-productivity-growth/
A5: 11-2011 | B5: Advertising and Promotions Managers | C5: 0.5583 | D5: https://budgetmodel.wharton.upenn.edu/p/2025-09-08-the-projected-impact-of-generative-ai-on-future-productivity-growth/
A6: 11-2021 | B6: Marketing Managers | C6: 0.445 | D6: https://budgetmodel.wharton.upenn.edu/p/2025-09-08-the-projected-impact-of-generative-ai-on-future-productivity-growth/
A7: 11-2022 | B7: Sales Managers | C7: 0.3735 | D7: https://budgetmodel.wharton.upenn.edu/p/2025-09-08-the-projected-impact-of-generative-ai-on-future-productivity-growth/
A8: 11-2032 | B8: Public Relations Managers | C8: 0.53 | D8: https://budgetmodel.wharton.upenn.edu/p/2025-09-08-the-projected-impact-of-generative-ai-on-future-productivity-growth/
A9: 11-2033 | B9: Fundraising Managers | C9: 0.5594 | D9: https://budgetmodel.wharton.upenn.edu/p/2025-09-08-the-projected-impact-of-generative-ai-on-future-productivity-growth/
A10: 11-3012 | B10: Administrative Services Managers | C10: 0.4444 | D10: https://budgetmodel.wharton.upenn.edu/p/2025-09-08-the-projected-impact-of-generative-ai-on-future-productivity-growth/
A11: 11-3013 | B11: Facilities Managers | C11: 0.2907 | D11: https://budgetmodel.wharton.upenn.edu/p/2025-09-08-the-projected-impact-of-generative-ai-on-future-productivity-growth/
A12: 11-3021 | B12: Computer and Information Systems Managers | C12: 0.5265 | D12: https://budgetmodel.wharton.upenn.edu/p/2025-09-08-the-projected-impact-of-generative-ai-on-future-productivity-growth/
A13: 11-3031 | B13: Financial Managers | C13: 0.7221 | D13: https://budgetmodel.wharton.upenn.edu/p/2025-09-08-the-projected-impact-of-generative-ai-on-future-productivity-growth/
... A785: 53-7121 | B785: Tank Car, Truck, and Ship Loaders | C785: 0.05 | D785: https://budgetmodel.wharton.upenn.edu/p/2025-09-08-the-projected-impact-of-generative-ai-on-future-productivity-growth/

Sheet DATA Census
A1: NAICS | B1: Industry | C1: BTOS AI-using firms | D1: Census source
A2: 11 | B2: Agriculture, forestry, fishing and hunting | C2: 0.095 | D2: https://www.census.gov/hfp/btos/data_downloads
A3: 21 | B3: Mining, quarrying, and oil and gas extraction | C3: 0.13 | D3: https://www.census.gov/hfp/btos/data_downloads
A4: 22 | B4: Utilities | C4: 0.167 | D4: https://www.census.gov/hfp/btos/data_downloads
A5: 23 | B5: Construction | C5: 0.172 | D5: https://www.census.gov/hfp/btos/data_downloads
A6: 31-33 | B6: Manufacturing | C6: 0.208 | D6: https://www.census.gov/hfp/btos/data_downloads
A7: 42 | B7: Wholesale trade | C7: 0.216 | D7: https://www.census.gov/hfp/btos/data_downloads
A8: 44-45 | B8: Retail trade | C8: 0.168 | D8: https://www.census.gov/hfp/btos/data_downloads
A9: 48-49 | B9: Transportation and warehousing | C9: 0.105 | D9: https://www.census.gov/hfp/btos/data_downloads
A10: 51 | B10: Information | C10: 0.502 | D10: https://www.census.gov/hfp/btos/data_downloads
A11: 52 | B11: Finance and insurance | C11: 0.401 | D11: https://www.census.gov/hfp/btos/data_downloads
A12: 53 | B12: Real estate and rental and leasing | C12: 0.308 | D12: https://www.census.gov/hfp/btos/data_downloads
A13: 54 | B13: Professional, scientific, and technical services | C13: 0.427 | D13: https://www.census.gov/hfp/btos/data_downloads
... A20: 81 | B20: Other services (except public administration) | C20: 0.127 | D20: https://www.census.gov/hfp/btos/data_downloads
