Workbook

Sheet Dashboard
A1: AI Infrastructure Monetization Hurdle
A2: Flexible replication of Van Nieuwerburgh (2026): how much mature annual revenue is required to support the modeled AI infrastructure buildout?
A4: Core Outputs
A5: Capacity completed by 2032 (GW) | B5: ='Revenue Model'!$B$13 -> 188.285 | C5: Initial investment ($tn) | D5: ='Revenue Model'!$D$13/1000 -> 8.7610943 | E5: Capital base ($tn) | F5: ='Revenue Model'!$F$13/1000 -> 9.157718 | G5: Required mature revenue ($tn) | H5: ='Revenue Model'!$J$13/1000 -> 3.5480681
A8: Required annual OCF ($tn) | B8: ='Revenue Model'!$H$13/1000 -> 1.774034 | C8: 2032 GDP share | D8: ='Revenue Model'!$J$13/(Assumptions!$B$7*1000) -> 0.087647738 | E8: Installed GPU-hour hurdle | F8: ='Revenue Model'!$O$13 -> 5.0910716 | G8: Billed GPU-hour @ selected util. | H8: ='Revenue Model'!$P$13 -> 6.3638395
A11: Monetization Gap vs Model-Firm Revenue
A12: Metric | B12: Value | C12: Units | D12: Interpretation | F12: Optional 2032 User Forecast | G12: Value | H12: Units
A13: Active current model-firm revenue | B13: ='Model Firms'!$B$8 -> 100 | C13: $bn | D13: Uses company-level inputs if entered; otherwise paper's $100bn benchmark | F13: User-entered model-firm 2032 revenue | G13: ='Model Firms'!$B$9 -> 0 | H13: $bn
A14: Required mature annual revenue | B14: ='Revenue Model'!$J$13 -> 3548.0681 | C14: $bn | D14: Revenue hurdle from infrastructure model | F14: Coverage of hurdle | G14: =IF(G13>0,G13/$B$14,0) -> 0 | H14: %
A15: Remaining revenue gap | B15: =B14-B13 -> 3448.0681 | C15: $bn | D15: Required revenue less current model-firm revenue | F15: Gap vs hurdle | G15: =IF(G13>0,$B$14-G13,0) -> 0 | H15: $bn
A16: Current revenue / hurdle | B16: =B13/B14 -> 0.028184352 | C16: % | D16: How much of the hurdle is covered today | F16: Replication variance vs paper | G16: =('Revenue Model'!$J$13-Assumptions!$B$12)/Assumptions!$B$12 -> -0.00012172245 | H16: %
A17: Required CAGR to 2032 | B17: ='Model Firms'!$B$12 -> 0.81272528 | C17: % | D17: Growth required from current aggregate revenue to the hurdle | F17: Selected utilization | G17: =Assumptions!$B$37 -> 0.8 | H17: %
A20: Revenue Comparison | B20: $bn
A21: Current model-firm revenue | B21: ='Model Firms'!$B$8 -> 100
A22: User 2032 model-firm forecast | B22: ='Model Firms'!$B$9 -> 0
A23: Required mature revenue | B23: ='Revenue Model'!$J$13 -> 3548.0681
A42: How to Use This Model
A43: 1) Change yellow/blue assumptions in the Assumptions and Capacity Buildout sheets. 2) The Revenue Model recalculates the mature revenue hurdle by completion cohort. 3) Add current / 2032 model-firm revenue estimates in Model Firms. 4) Use Sensitivity to test return, margin, IT life and utilization. 5) The key question is the revenue gap: how much monetization must still be created to justify the infrastructure capital base.
A49: Important: this is a required-return framework, not an AI revenue forecast. The paper's central case assumes a 10% unlevered return, 50% operating cash-flow margin, 6-year IT life, 20-year non-IT life and the modeled 2025–32 completion cohorts.

Sheet Assumptions
A1: Assumptions
A3: Core Buildout & Cost Assumptions
A4: Assumption | B4: Value | C4: Units | D4: Description | E4: Source / Note
A5: Base cost per MW (2025) | B5: 41 | C5: $mm / MW | D5: Fully equipped AI campus: facility + power + IT | E5: Van Nieuwerburgh (2026), Appendix A / Table 2
A6: Annual completion-cohort cost growth | B6: 0.04 | C6: % | D6: Applied to cost per MW by completion year | E6: Paper assumption
A7: 2032 nominal GDP | B7: 40.481 | C7: $tn | D7: Used only for GDP-share comparison | E7: Paper central assumption
A8: Target completion year | B8: 2032 | C8: Year | D8: Revenue hurdle is measured once 2025–32 cohorts are mature | E8: Paper setup
A9: No-date allocation start | B9: 2028 | C9: Year | D9: No-date capacity completed by 2032 allocated evenly | E9: Paper assumption
A10: No-date allocation end | B10: 2032 | C10: Year | D10: No-date capacity completed by 2032 allocated evenly | E10: Paper assumption
A11: Hours per year | B11: 8760 | C11: Hours | D11: Used for GPU-hour economics | E11: Calendar convention
A12: Article reported mature revenue | B12: 3548.5 | C12: $bn | D12: Published Table 6 total; used as replication check only | E12: Van Nieuwerburgh (2026), Table 6
A14: Construction Spend Timing
A15: Timing | B15: Share | C15: Units | D15: Description | E15: Source / Note
A16: t - 3 | B16: 0.05122 | C16: % of cohort cost | D16: Early power / real-estate spend | E16: Appendix B
A17: t - 2 | B17: 0.05122 | C17: % of cohort cost | D17: Early power / real-estate spend | E17: Appendix B
A18: t - 1 | B18: 0.17561 | C18: % of cohort cost | D18: Building/equipment + 10% of IT | E18: Appendix B
A19: t | B19: 0.72195 | C19: % of cohort cost | D19: Completion-year spend; majority of IT | E19: Appendix B
A21: Capital Recovery & Operating Economics
A22: Assumption | B22: Value | C22: Units | D22: Description | E22: Source / Note
A23: IT share of total capital | B23: 0.68 | C23: % | D23: GPU / networking / storage / integration share | E23: Paper assumption
A24: IT economic life | B24: 6 | C24: Years | D24: Central case | E24: Paper assumption
A25: Non-IT share of total capital | B25: =1-B23 -> 0.32 | C25: % | D25: Building / power / cooling share | E25: Formula = 1 - IT share
A26: Non-IT economic life | B26: 20 | C26: Years | D26: Central case | E26: Paper assumption
A27: Required unlevered return | B27: 0.1 | C27: % | D27: Target asset-level return before financing mix | E27: Paper central case
A28: Operating cash-flow margin | B28: 0.5 | C28: % | D28: Operating cash flow / revenue | E28: Paper central case
A29: Construction capital factor (phi) | B29: =B16*(1+B27)^3+B17*(1+B27)^2+B18*(1+B27)+B19 -> 1.045271 | C29: x | D29: Compensates capital committed before commissioning | E29: Equation (3)
A30: Weighted annual capital charge | B30: =B23*(B27*(1+B27)^B24/((1+B27)^B24-1))+B25*(B27*(1+B27)^B26/((1+B27)^B26-1)) -> 0.1937201 | C30: % | D30: IT/non-IT capital recovery factors weighted by cost share | E30: Equation (6)
A32: Compute Economics
A33: Assumption | B33: Value | C33: Units | D33: Description | E33: Source / Note
A34: PUE | B34: 1.2 | C34: x | D34: Total facility power / critical IT power | E34: Paper central case
A35: Rack power | B35: 142 | C35: kW / rack | D35: NVIDIA GB300 NVL72 configuration | E35: Appendix A
A36: GPUs per rack | B36: 72 | C36: GPUs | D36: NVL72 configuration | E36: Appendix A
A37: Selected utilization | B37: 0.8 | C37: % | D37: Used for billed GPU-hour price | E37: Editable scenario input
A38: Reference frontier GPU rental price | B38: 6.07 | C38: $ / GPU-hour | D38: B200 rental price cited in paper as of Aug. 31, 2026 | E38: Ornn Compute Price Index (paper citation)
A39: Comparison base year | B39: 2026 | C39: Year | D39: For CAGR to monetization hurdle | E39: Paper contextual example
A41: Important Interpretation
A42: The model calculates a required mature annual revenue hurdle, not a forecast of AI revenues. It asks how much annual revenue the completed infrastructure must support to recover capital, replace depreciating assets, and earn the selected unlevered return.

Sheet Capacity Buildout
A1: Capacity Buildout Replication
A3: Table 3 / Table 4 Replication: Pipeline to Realized Capacity
A4: Completion | B4: Observed Projects | C4: Observed GW | D4: Imputed Projects | E4: Imputed GW | F4: Total Projects | G4: Total GW | H4: Fixed / Included by 2032 GW | I4: Observed: By 2032 | J4: Observed: After 2032 | K4: Imputed: By 2032 | L4: Imputed: After 2032 | M4: Outcome: By 2032 GW | N4: Outcome: After 2032 GW | O4: Outcome: Never GW
A5: Before 2025 | B5: 971 | C5: 39.1 | D5: 38 | E5: 1.3 | F5: =B5+D5 -> 1009 | G5: =C5+E5 -> 40.4 | H5: 0 | M5: =IF(A5="Before 2025",0,IF(A5="2025",H5,H5+MAX(C5-H5,0)*I5+E5*K5)) -> 0 | N5: =IF(OR(A5="Before 2025",A5="2025"),0,MAX(C5-H5,0)*J5+E5*L5) -> 0 | O5: =IF(A5="Before 2025",0,G5-M5-N5) -> 0
A6: 2025 | B6: 184 | C6: 13.6 | D6: 3 | E6: 0.1 | F6: =B6+D6 -> 187 | G6: =C6+E6 -> 13.7 | H6: 13.8 | M6: =IF(A6="Before 2025",0,IF(A6="2025",H6,H6+MAX(C6-H6,0)*I6+E6*K6)) -> 13.8 | N6: =IF(OR(A6="Before 2025",A6="2025"),0,MAX(C6-H6,0)*J6+E6*L6) -> 0 | O6: =IF(A6="Before 2025",0,G6-M6-N6) -> -0.1
A7: 2026 | B7: 281 | C7: 26.9 | D7: 12 | E7: 1.7 | F7: =B7+D7 -> 293 | G7: =C7+E7 -> 28.6 | H7: 9.4 | I7: 0.9 | J7: 0 | K7: 0.8 | L7: 0 | M7: =IF(A7="Before 2025",0,IF(A7="2025",H7,H7+MAX(C7-H7,0)*I7+E7*K7)) -> 26.51 | N7: =IF(OR(A7="Before 2025",A7="2025"),0,MAX(C7-H7,0)*J7+E7*L7) -> 0 | O7: =IF(A7="Before 2025",0,G7-M7-N7) -> 2.09
A8: 2027 | B8: 381 | C8: 41 | D8: 24 | E8: 4.7 | F8: =B8+D8 -> 405 | G8: =C8+E8 -> 45.7 | H8: 0 | I8: 0.8 | J8: 0.05 | K8: 0.65 | L8: 0.1 | M8: =IF(A8="Before 2025",0,IF(A8="2025",H8,H8+MAX(C8-H8,0)*I8+E8*K8)) -> 35.855 | N8: =IF(OR(A8="Before 2025",A8="2025"),0,MAX(C8-H8,0)*J8+E8*L8) -> 2.52 | O8: =IF(A8="Before 2025",0,G8-M8-N8) -> 7.325
A9: 2028 | B9: 346 | C9: 42.4 | D9: 23 | E9: 5.4 | F9: =B9+D9 -> 369 | G9: =C9+E9 -> 47.8 | H9: 0 | I9: 0.7 | J9: 0.1 | K9: 0.55 | L9: 0.15 | M9: =IF(A9="Before 2025",0,IF(A9="2025",H9,H9+MAX(C9-H9,0)*I9+E9*K9)) -> 32.65 | N9: =IF(OR(A9="Before 2025",A9="2025"),0,MAX(C9-H9,0)*J9+E9*L9) -> 5.05 | O9: =IF(A9="Before 2025",0,G9-M9-N9) -> 10.1
A10: 2029 | B10: 145 | C10: 16.7 | D10: 8 | E10: 1.5 | F10: =B10+D10 -> 153 | G10: =C10+E10 -> 18.2 | H10: 0 | I10: 0.6 | J10: 0.15 | K10: 0.45 | L10: 0.2 | M10: =IF(A10="Before 2025",0,IF(A10="2025",H10,H10+MAX(C10-H10,0)*I10+E10*K10)) -> 10.695 | N10: =IF(OR(A10="Before 2025",A10="2025"),0,MAX(C10-H10,0)*J10+E10*L10) -> 2.805 | O10: =IF(A10="Before 2025",0,G10-M10-N10) -> 4.7
A11: 2030 | B11: 103 | C11: 12.5 | D11: 6 | E11: 1.8 | F11: =B11+D11 -> 109 | G11: =C11+E11 -> 14.3 | H11: 0 | I11: 0.5 | J11: 0.2 | K11: 0.35 | L11: 0.25 | M11: =IF(A11="Before 2025",0,IF(A11="2025",H11,H11+MAX(C11-H11,0)*I11+E11*K11)) -> 6.88 | N11: =IF(OR(A11="Before 2025",A11="2025"),0,MAX(C11-H11,0)*J11+E11*L11) -> 2.95 | O11: =IF(A11="Before 2025",0,G11-M11-N11) -> 4.47
A12: 2031 | B12: 55 | C12: 11.7 | D12: 5 | E12: 2.5 | F12: =B12+D12 -> 60 | G12: =C12+E12 -> 14.2 | H12: 0 | I12: 0.4 | J12: 0.25 | K12: 0.25 | L12: 0.3 | M12: =IF(A12="Before 2025",0,IF(A12="2025",H12,H12+MAX(C12-H12,0)*I12+E12*K12)) -> 5.305 | N12: =IF(OR(A12="Before 2025",A12="2025"),0,MAX(C12-H12,0)*J12+E12*L12) -> 3.675 | O12: =IF(A12="Before 2025",0,G12-M12-N12) -> 5.22
A13: 2032 | B13: 41 | C13: 7.1 | D13: 5 | E13: 2.5 | F13: =B13+D13 -> 46 | G13: =C13+E13 -> 9.6 | H13: 0 | I13: 0.3 | J13: 0.3 | K13: 0.2 | L13: 0.3 | M13: =IF(A13="Before 2025",0,IF(A13="2025",H13,H13+MAX(C13-H13,0)*I13+E13*K13)) -> 2.63 | N13: =IF(OR(A13="Before 2025",A13="2025"),0,MAX(C13-H13,0)*J13+E13*L13) -> 2.88 | O13: =IF(A13="Before 2025",0,G13-M13-N13) -> 4.09
A14: After 2032 | B14: 20 | C14: 2.2 | D14: 9 | E14: 8.3 | F14: =B14+D14 -> 29 | G14: =C14+E14 -> 10.5 | H14: 0 | I14: 0 | J14: 0.5 | K14: 0 | L14: 0.5 | M14: =IF(A14="Before 2025",0,IF(A14="2025",H14,H14+MAX(C14-H14,0)*I14+E14*K14)) -> 0 | N14: =IF(OR(A14="Before 2025",A14="2025"),0,MAX(C14-H14,0)*J14+E14*L14) -> 5.25 | O14: =IF(A14="Before 2025",0,G14-M14-N14) -> 5.25
A15: Planned, no date | B15: 483 | C15: 225.6 | D15: 234 | E15: 88.4 | F15: =B15+D15 -> 717 | G15: =C15+E15 -> 314 | H15: 0 | I15: 0.2 | J15: 0.3 | K15: 0.1 | L15: 0.25 | M15: =IF(A15="Before 2025",0,IF(A15="2025",H15,H15+MAX(C15-H15,0)*I15+E15*K15)) -> 53.96 | N15: =IF(OR(A15="Before 2025",A15="2025"),0,MAX(C15-H15,0)*J15+E15*L15) -> 89.78 | O15: =IF(A15="Before 2025",0,G15-M15-N15) -> 170.26
A16: Total / Pipeline | B16: =SUM(B5:B15) -> 3010 | C16: =SUM(C5:C15) -> 438.8 | D16: =SUM(D5:D15) -> 367 | E16: =SUM(E5:E15) -> 118.2 | F16: =SUM(F5:F15) -> 3377 | G16: =SUM(G5:G15) -> 557 | M16: =SUM(M5:M15) -> 188.285 | N16: =SUM(N5:N15) -> 114.91 | O16: =SUM(O5:O15) -> 213.405
A17: Imputed capacity = projects with missing MW where capacity is estimated from project characteristics. Realization rates are lower for imputed capacity to reflect greater uncertainty. The output is a scenario, not a forecast.
A19: 2025–2032 Completion Cohorts Used in Revenue Model
A20: Year | B20: Dated Capacity Realized by 2032 (GW) | C20: Allocated No-Date Capacity (GW) | D20: Total Completion Cohort Kt (GW) | E20: Article Table 6 Rounded GW
A21: 2025 | B21: =M6 -> 13.8 | C21: =IF(AND(A21>=Assumptions!$B$9,A21<=Assumptions!$B$10),$M$15/(Assumptions!$B$10-Assumptions!$B$9+1),0) -> 0 | D21: =B21+C21 -> 13.8 | E21: 13.8
A22: 2026 | B22: =M7 -> 26.51 | C22: =IF(AND(A22>=Assumptions!$B$9,A22<=Assumptions!$B$10),$M$15/(Assumptions!$B$10-Assumptions!$B$9+1),0) -> 0 | D22: =B22+C22 -> 26.51 | E22: 26.6
A23: 2027 | B23: =M8 -> 35.855 | C23: =IF(AND(A23>=Assumptions!$B$9,A23<=Assumptions!$B$10),$M$15/(Assumptions!$B$10-Assumptions!$B$9+1),0) -> 0 | D23: =B23+C23 -> 35.855 | E23: 35.8
A24: 2028 | B24: =M9 -> 32.65 | C24: =IF(AND(A24>=Assumptions!$B$9,A24<=Assumptions!$B$10),$M$15/(Assumptions!$B$10-Assumptions!$B$9+1),0) -> 10.792 | D24: =B24+C24 -> 43.442 | E24: 43.5
A25: 2029 | B25: =M10 -> 10.695 | C25: =IF(AND(A25>=Assumptions!$B$9,A25<=Assumptions!$B$10),$M$15/(Assumptions!$B$10-Assumptions!$B$9+1),0) -> 10.792 | D25: =B25+C25 -> 21.487 | E25: 21.5
A26: 2030 | B26: =M11 -> 6.88 | C26: =IF(AND(A26>=Assumptions!$B$9,A26<=Assumptions!$B$10),$M$15/(Assumptions!$B$10-Assumptions!$B$9+1),0) -> 10.792 | D26: =B26+C26 -> 17.672 | E26: 17.7
A27: 2031 | B27: =M12 -> 5.305 | C27: =IF(AND(A27>=Assumptions!$B$9,A27<=Assumptions!$B$10),$M$15/(Assumptions!$B$10-Assumptions!$B$9+1),0) -> 10.792 | D27: =B27+C27 -> 16.097 | E27: 16.1
A28: 2032 | B28: =M13 -> 2.63 | C28: =IF(AND(A28>=Assumptions!$B$9,A28<=Assumptions!$B$10),$M$15/(Assumptions!$B$10-Assumptions!$B$9+1),0) -> 10.792 | D28: =B28+C28 -> 13.422 | E28: 13.4
A29: Total | D29: =SUM(D21:D28) -> 188.285 | E29: =SUM(E21:E28) -> 188.4
A31: Replication Check | B31: Live Model | C31: Paper Reported | D31: Variance | E31: Variance %
A32: Capacity completed 2025–32 (GW) | B32: =D29 -> 188.285 | C32: 188.3 | D32: =B32-C32 -> -0.015 | E32: =D32/C32 -> -7.9660117e-05

Sheet Revenue Model
A1: Required Revenue Model
A3: Appendix D Replication — Revenue Required to Support the Investment
A4: Year | B4: Capacity (GW) | C4: Cost / MW ($mm) | D4: Initial Cost Q ($bn) | E4: Construction Factor φ | F4: Capital Base B ($bn) | G4: Annual Capital Charge | H4: Required OCF ($bn) | I4: OCF Margin | J4: Required Mature Revenue ($bn) | K4: Revenue / MW-year ($mm) | L4: Critical IT Load (GW) | M4: Racks (000s) | N4: GPUs (mm) | O4: $ / Installed GPU-hour | P4: $ / Billed GPU-hour
A5: 2025 | B5: ='Capacity Buildout'!D21 -> 13.8 | C5: =Assumptions!$B$5*(1+Assumptions!$B$6)^(A5-2025) -> 41 | D5: =B5*C5 -> 565.8 | E5: =Assumptions!$B$29 -> 1.045271 | F5: =D5*E5 -> 591.41434 | G5: =Assumptions!$B$30 -> 0.1937201 | H5: =F5*G5 -> 114.56884 | I5: =Assumptions!$B$28 -> 0.5 | J5: =H5/I5 -> 229.13769 | K5: =J5/B5 -> 16.60418 | L5: =B5/Assumptions!$B$34 -> 11.5 | M5: =L5*1000/Assumptions!$B$35 -> 80.985915 | N5: =M5*Assumptions!$B$36/1000 -> 5.8309859 | O5: =J5*1000/(N5*Assumptions!$B$11) -> 4.4859087 | P5: =O5/Assumptions!$B$37 -> 5.6073859
A6: 2026 | B6: ='Capacity Buildout'!D22 -> 26.51 | C6: =Assumptions!$B$5*(1+Assumptions!$B$6)^(A6-2025) -> 42.64 | D6: =B6*C6 -> 1130.3864 | E6: =Assumptions!$B$29 -> 1.045271 | F6: =D6*E6 -> 1181.5601 | G6: =Assumptions!$B$30 -> 0.1937201 | H6: =F6*G6 -> 228.89195 | I6: =Assumptions!$B$28 -> 0.5 | J6: =H6/I6 -> 457.7839 | K6: =J6/B6 -> 17.268348 | L6: =B6/Assumptions!$B$34 -> 22.091667 | M6: =L6*1000/Assumptions!$B$35 -> 155.57512 | N6: =M6*Assumptions!$B$36/1000 -> 11.201408 | O6: =J6*1000/(N6*Assumptions!$B$11) -> 4.6653451 | P6: =O6/Assumptions!$B$37 -> 5.8316813
A7: 2027 | B7: ='Capacity Buildout'!D23 -> 35.855 | C7: =Assumptions!$B$5*(1+Assumptions!$B$6)^(A7-2025) -> 44.3456 | D7: =B7*C7 -> 1590.0115 | E7: =Assumptions!$B$29 -> 1.045271 | F7: =D7*E7 -> 1661.9929 | G7: =Assumptions!$B$30 -> 0.1937201 | H7: =F7*G7 -> 321.96143 | I7: =Assumptions!$B$28 -> 0.5 | J7: =H7/I7 -> 643.92287 | K7: =J7/B7 -> 17.959082 | L7: =B7/Assumptions!$B$34 -> 29.879167 | M7: =L7*1000/Assumptions!$B$35 -> 210.41667 | N7: =M7*Assumptions!$B$36/1000 -> 15.15 | O7: =J7*1000/(N7*Assumptions!$B$11) -> 4.8519589 | P7: =O7/Assumptions!$B$37 -> 6.0649486
A8: 2028 | B8: ='Capacity Buildout'!D24 -> 43.442 | C8: =Assumptions!$B$5*(1+Assumptions!$B$6)^(A8-2025) -> 46.119424 | D8: =B8*C8 -> 2003.52 | E8: =Assumptions!$B$29 -> 1.045271 | F8: =D8*E8 -> 2094.2214 | G8: =Assumptions!$B$30 -> 0.1937201 | H8: =F8*G8 -> 405.69278 | I8: =Assumptions!$B$28 -> 0.5 | J8: =H8/I8 -> 811.38556 | K8: =J8/B8 -> 18.677445 | L8: =B8/Assumptions!$B$34 -> 36.201667 | M8: =L8*1000/Assumptions!$B$35 -> 254.94131 | N8: =M8*Assumptions!$B$36/1000 -> 18.355775 | O8: =J8*1000/(N8*Assumptions!$B$11) -> 5.0460372 | P8: =O8/Assumptions!$B$37 -> 6.3075465
A9: 2029 | B9: ='Capacity Buildout'!D25 -> 21.487 | C9: =Assumptions!$B$5*(1+Assumptions!$B$6)^(A9-2025) -> 47.964201 | D9: =B9*C9 -> 1030.6068 | E9: =Assumptions!$B$29 -> 1.045271 | F9: =D9*E9 -> 1077.2634 | G9: =Assumptions!$B$30 -> 0.1937201 | H9: =F9*G9 -> 208.68757 | I9: =Assumptions!$B$28 -> 0.5 | J9: =H9/I9 -> 417.37515 | K9: =J9/B9 -> 19.424543 | L9: =B9/Assumptions!$B$34 -> 17.905833 | M9: =L9*1000/Assumptions!$B$35 -> 126.09742 | N9: =M9*Assumptions!$B$36/1000 -> 9.0790141 | O9: =J9*1000/(N9*Assumptions!$B$11) -> 5.2478787 | P9: =O9/Assumptions!$B$37 -> 6.5598484
A10: 2030 | B10: ='Capacity Buildout'!D26 -> 17.672 | C10: =Assumptions!$B$5*(1+Assumptions!$B$6)^(A10-2025) -> 49.882769 | D10: =B10*C10 -> 881.52829 | E10: =Assumptions!$B$29 -> 1.045271 | F10: =D10*E10 -> 921.43598 | G10: =Assumptions!$B$30 -> 0.1937201 | H10: =F10*G10 -> 178.50067 | I10: =Assumptions!$B$28 -> 0.5 | J10: =H10/I10 -> 357.00134 | K10: =J10/B10 -> 20.201524 | L10: =B10/Assumptions!$B$34 -> 14.726667 | M10: =L10*1000/Assumptions!$B$35 -> 103.70892 | N10: =M10*Assumptions!$B$36/1000 -> 7.4670423 | O10: =J10*1000/(N10*Assumptions!$B$11) -> 5.4577939 | P10: =O10/Assumptions!$B$37 -> 6.8222423
A11: 2031 | B11: ='Capacity Buildout'!D27 -> 16.097 | C11: =Assumptions!$B$5*(1+Assumptions!$B$6)^(A11-2025) -> 51.87808 | D11: =B11*C11 -> 835.08145 | E11: =Assumptions!$B$29 -> 1.045271 | F11: =D11*E11 -> 872.88644 | G11: =Assumptions!$B$30 -> 0.1937201 | H11: =F11*G11 -> 169.09565 | I11: =Assumptions!$B$28 -> 0.5 | J11: =H11/I11 -> 338.19129 | K11: =J11/B11 -> 21.009585 | L11: =B11/Assumptions!$B$34 -> 13.414167 | M11: =L11*1000/Assumptions!$B$35 -> 94.465962 | N11: =M11*Assumptions!$B$36/1000 -> 6.8015493 | O11: =J11*1000/(N11*Assumptions!$B$11) -> 5.6761056 | P11: =O11/Assumptions!$B$37 -> 7.095132
A12: 2032 | B12: ='Capacity Buildout'!D28 -> 13.422 | C12: =Assumptions!$B$5*(1+Assumptions!$B$6)^(A12-2025) -> 53.953203 | D12: =B12*C12 -> 724.15989 | E12: =Assumptions!$B$29 -> 1.045271 | F12: =D12*E12 -> 756.94335 | G12: =Assumptions!$B$30 -> 0.1937201 | H12: =F12*G12 -> 146.63514 | I12: =Assumptions!$B$28 -> 0.5 | J12: =H12/I12 -> 293.27028 | K12: =J12/B12 -> 21.849969 | L12: =B12/Assumptions!$B$34 -> 11.185 | M12: =L12*1000/Assumptions!$B$35 -> 78.767606 | N12: =M12*Assumptions!$B$36/1000 -> 5.6712676 | O12: =J12*1000/(N12*Assumptions!$B$11) -> 5.9031498 | P12: =O12/Assumptions!$B$37 -> 7.3789373
A13: Total / Mature Run-Rate | B13: =SUM(B5:B12) -> 188.285 | D13: =SUM(D5:D12) -> 8761.0943 | F13: =SUM(F5:F12) -> 9157.718 | H13: =SUM(H5:H12) -> 1774.034 | J13: =SUM(J5:J12) -> 3548.0681 | K13: =J13/B13 -> 18.844136 | L13: =SUM(L5:L12) -> 156.90417 | M13: =SUM(M5:M12) -> 1104.9589 | N13: =SUM(N5:N12) -> 79.557042 | O13: =J13*1000/(N13*Assumptions!$B$11) -> 5.0910716 | P13: =O13/Assumptions!$B$37 -> 6.3638395
A16: Replication Check vs Paper Table 6
A17: Metric | B17: Live Replication | C17: Paper Reported | D17: Variance | E17: Variance %
A18: Initial cost ($bn) | B18: =D13 -> 8761.0943 | C18: 8762.2 | D18: =B18-C18 -> -1.105675 | E18: =D18/C18 -> -0.00012618691
A19: Capital base at commissioning ($bn) | B19: =F13 -> 9157.718 | C19: 9158.8 | D19: =B19-C19 -> -1.0819986 | E19: =D19/C19 -> -0.00011813759
A20: Required annual operating cash flow ($bn) | B20: =H13 -> 1774.034 | C20: 1774.3 | D20: =B20-C20 -> -0.26596605 | E20: =D20/C20 -> -0.00014989914
A21: Required mature annual revenue ($bn) | B21: =J13 -> 3548.0681 | C21: 3548.5 | D21: =B21-C21 -> -0.4319321 | E21: =D21/C21 -> -0.00012172245
A23: Interpretation: Required mature annual revenue is the run-rate needed once the 2025–32 completion cohorts are operational and mature. It is not a forecast of AI industry revenue.

Sheet Sensitivity
A1: Sensitivity Analysis
A3: Required Mature Annual Revenue Sensitivity ($bn) | F3: GPU-Hour Economics
A4: Required Return \ OCF Margin | B4: 0.33 | C4: 0.5 | D4: 0.67 | E4: Notes | F4: Utilization | G4: Installed $ / GPU-hour | H4: Required Billed $ / GPU-hour | I4: Reference Price
A5: 0.05 | B5: ='Revenue Model'!$D$13*(Assumptions!$B$16*(1+$A5)^3+Assumptions!$B$17*(1+$A5)^2+Assumptions!$B$18*(1+$A5)+Assumptions!$B$19)*(Assumptions!$B$23*($A5*(1+$A5)^Assumptions!$B$24/((1+$A5)^Assumptions!$B$24-1))+Assumptions!$B$25*($A5*(1+$A5)^Assumptions!$B$26/((1+$A5)^Assumptions!$B$26-1)))/B$4 -> 4332.1863 | C5: ='Revenue Model'!$D$13*(Assumptions!$B$16*(1+$A5)^3+Assumptions!$B$17*(1+$A5)^2+Assumptions!$B$18*(1+$A5)+Assumptions!$B$19)*(Assumptions!$B$23*($A5*(1+$A5)^Assumptions!$B$24/((1+$A5)^Assumptions!$B$24-1))+Assumptions!$B$25*($A5*(1+$A5)^Assumptions!$B$26/((1+$A5)^Assumptions!$B$26-1)))/C$4 -> 2859.243 | D5: ='Revenue Model'!$D$13*(Assumptions!$B$16*(1+$A5)^3+Assumptions!$B$17*(1+$A5)^2+Assumptions!$B$18*(1+$A5)+Assumptions!$B$19)*(Assumptions!$B$23*($A5*(1+$A5)^Assumptions!$B$24/((1+$A5)^Assumptions!$B$24-1))+Assumptions!$B$25*($A5*(1+$A5)^Assumptions!$B$26/((1+$A5)^Assumptions!$B$26-1)))/D$4 -> 2133.7634 | E5: Lower required return | F5: 0.5 | G5: ='Revenue Model'!$O$13 -> 5.0910716 | H5: =G5/F5 -> 10.182143 | I5: =Assumptions!$B$38 -> 6.07
A6: 0.1 | B6: ='Revenue Model'!$D$13*(Assumptions!$B$16*(1+$A6)^3+Assumptions!$B$17*(1+$A6)^2+Assumptions!$B$18*(1+$A6)+Assumptions!$B$19)*(Assumptions!$B$23*($A6*(1+$A6)^Assumptions!$B$24/((1+$A6)^Assumptions!$B$24-1))+Assumptions!$B$25*($A6*(1+$A6)^Assumptions!$B$26/((1+$A6)^Assumptions!$B$26-1)))/B$4 -> 5375.8607 | C6: ='Revenue Model'!$D$13*(Assumptions!$B$16*(1+$A6)^3+Assumptions!$B$17*(1+$A6)^2+Assumptions!$B$18*(1+$A6)+Assumptions!$B$19)*(Assumptions!$B$23*($A6*(1+$A6)^Assumptions!$B$24/((1+$A6)^Assumptions!$B$24-1))+Assumptions!$B$25*($A6*(1+$A6)^Assumptions!$B$26/((1+$A6)^Assumptions!$B$26-1)))/C$4 -> 3548.0681 | D6: ='Revenue Model'!$D$13*(Assumptions!$B$16*(1+$A6)^3+Assumptions!$B$17*(1+$A6)^2+Assumptions!$B$18*(1+$A6)+Assumptions!$B$19)*(Assumptions!$B$23*($A6*(1+$A6)^Assumptions!$B$24/((1+$A6)^Assumptions!$B$24-1))+Assumptions!$B$25*($A6*(1+$A6)^Assumptions!$B$26/((1+$A6)^Assumptions!$B$26-1)))/D$4 -> 2647.812 | E6: Paper central case | F6: 0.55 | G6: ='Revenue Model'!$O$13 -> 5.0910716 | H6: =G6/F6 -> 9.2564939 | I6: =Assumptions!$B$38 -> 6.07
A7: 0.15 | B7: ='Revenue Model'!$D$13*(Assumptions!$B$16*(1+$A7)^3+Assumptions!$B$17*(1+$A7)^2+Assumptions!$B$18*(1+$A7)+Assumptions!$B$19)*(Assumptions!$B$23*($A7*(1+$A7)^Assumptions!$B$24/((1+$A7)^Assumptions!$B$24-1))+Assumptions!$B$25*($A7*(1+$A7)^Assumptions!$B$26/((1+$A7)^Assumptions!$B$26-1)))/B$4 -> 6553.6898 | C7: ='Revenue Model'!$D$13*(Assumptions!$B$16*(1+$A7)^3+Assumptions!$B$17*(1+$A7)^2+Assumptions!$B$18*(1+$A7)+Assumptions!$B$19)*(Assumptions!$B$23*($A7*(1+$A7)^Assumptions!$B$24/((1+$A7)^Assumptions!$B$24-1))+Assumptions!$B$25*($A7*(1+$A7)^Assumptions!$B$26/((1+$A7)^Assumptions!$B$26-1)))/C$4 -> 4325.4353 | D7: ='Revenue Model'!$D$13*(Assumptions!$B$16*(1+$A7)^3+Assumptions!$B$17*(1+$A7)^2+Assumptions!$B$18*(1+$A7)+Assumptions!$B$19)*(Assumptions!$B$23*($A7*(1+$A7)^Assumptions!$B$24/((1+$A7)^Assumptions!$B$24-1))+Assumptions!$B$25*($A7*(1+$A7)^Assumptions!$B$26/((1+$A7)^Assumptions!$B$26-1)))/D$4 -> 3227.9368 | E7: Higher required return | F7: 0.6 | G7: ='Revenue Model'!$O$13 -> 5.0910716 | H7: =G7/F7 -> 8.4851194 | I7: =Assumptions!$B$38 -> 6.07
F8: 0.65 | G8: ='Revenue Model'!$O$13 -> 5.0910716 | H8: =G8/F8 -> 7.8324179 | I8: =Assumptions!$B$38 -> 6.07
A9: Paper Table 7 (Reported, $bn) | F9: 0.7 | G9: ='Revenue Model'!$O$13 -> 5.0910716 | H9: =G9/F9 -> 7.2729595 | I9: =Assumptions!$B$38 -> 6.07
A10: Required Return \ OCF Margin | B10: 33% | C10: 50% | D10: 67% | F10: 0.75 | G10: ='Revenue Model'!$O$13 -> 5.0910716 | H10: =G10/F10 -> 6.7880955 | I10: =Assumptions!$B$38 -> 6.07
A11: 5% | B11: 4333 | C11: 2860 | D11: 2134 | F11: 0.8 | G11: ='Revenue Model'!$O$13 -> 5.0910716 | H11: =G11/F11 -> 6.3638395 | I11: =Assumptions!$B$38 -> 6.07
A12: 10% | B12: 5377 | C12: 3549 | D12: 2648 | F12: 0.85 | G12: ='Revenue Model'!$O$13 -> 5.0910716 | H12: =G12/F12 -> 5.989496 | I12: =Assumptions!$B$38 -> 6.07
A13: 15% | B13: 6554 | C13: 4326 | D13: 3228 | F13: 0.9 | G13: ='Revenue Model'!$O$13 -> 5.0910716 | H13: =G13/F13 -> 5.6567463 | I13: =Assumptions!$B$38 -> 6.07
F14: 0.95 | G14: ='Revenue Model'!$O$13 -> 5.0910716 | H14: =G14/F14 -> 5.3590228 | I14: =Assumptions!$B$38 -> 6.07
F15: 1 | G15: ='Revenue Model'!$O$13 -> 5.0910716 | H15: =G15/F15 -> 5.0910716 | I15: =Assumptions!$B$38 -> 6.07
A16: IT Economic Life Sensitivity
A17: IT Life (Years) | B17: Weighted Capital Charge | C17: Required Revenue ($bn) | D17: 2032 GDP % | F17: The total revenue hurdle does not change with utilization in this model. Lower utilization mechanically raises the billed price required per GPU-hour because fewer hours are monetized.
A18: 3 | B18: =Assumptions!$B$23*(Assumptions!$B$27*(1+Assumptions!$B$27)^A18/((1+Assumptions!$B$27)^A18-1))+Assumptions!$B$25*(Assumptions!$B$27*(1+Assumptions!$B$27)^Assumptions!$B$26/((1+Assumptions!$B$27)^Assumptions!$B$26-1)) -> 0.31102515 | C18: ='Revenue Model'!$F$13*B18/Assumptions!$B$28 -> 5696.5612 | D18: =C18/(Assumptions!$B$7*1000) -> 0.14072185
A19: 4 | B19: =Assumptions!$B$23*(Assumptions!$B$27*(1+Assumptions!$B$27)^A19/((1+Assumptions!$B$27)^A19-1))+Assumptions!$B$25*(Assumptions!$B$27*(1+Assumptions!$B$27)^Assumptions!$B$26/((1+Assumptions!$B$27)^Assumptions!$B$26-1)) -> 0.25210723 | C19: ='Revenue Model'!$F$13*B19/Assumptions!$B$28 -> 4617.4538 | D19: =C19/(Assumptions!$B$7*1000) -> 0.11406472
A20: 5 | B20: =Assumptions!$B$23*(Assumptions!$B$27*(1+Assumptions!$B$27)^A20/((1+Assumptions!$B$27)^A20-1))+Assumptions!$B$25*(Assumptions!$B$27*(1+Assumptions!$B$27)^Assumptions!$B$26/((1+Assumptions!$B$27)^Assumptions!$B$26-1)) -> 0.21696937 | C20: ='Revenue Model'!$F$13*B20/Assumptions!$B$28 -> 3973.8886 | D20: =C20/(Assumptions!$B$7*1000) -> 0.098166759
A21: 6 | B21: =Assumptions!$B$23*(Assumptions!$B$27*(1+Assumptions!$B$27)^A21/((1+Assumptions!$B$27)^A21-1))+Assumptions!$B$25*(Assumptions!$B$27*(1+Assumptions!$B$27)^Assumptions!$B$26/((1+Assumptions!$B$27)^Assumptions!$B$26-1)) -> 0.1937201 | C21: ='Revenue Model'!$F$13*B21/Assumptions!$B$28 -> 3548.0681 | D21: =C21/(Assumptions!$B$7*1000) -> 0.087647738
A22: 7 | B22: =Assumptions!$B$23*(Assumptions!$B$27*(1+Assumptions!$B$27)^A22/((1+Assumptions!$B$27)^A22-1))+Assumptions!$B$25*(Assumptions!$B$27*(1+Assumptions!$B$27)^Assumptions!$B$26/((1+Assumptions!$B$27)^Assumptions!$B$26-1)) -> 0.17726282 | C22: ='Revenue Model'!$F$13*B22/Assumptions!$B$28 -> 3246.6458 | D22: =C22/(Assumptions!$B$7*1000) -> 0.08020172
A23: 8 | B23: =Assumptions!$B$23*(Assumptions!$B$27*(1+Assumptions!$B$27)^A23/((1+Assumptions!$B$27)^A23-1))+Assumptions!$B$25*(Assumptions!$B$27*(1+Assumptions!$B$27)^Assumptions!$B$26/((1+Assumptions!$B$27)^Assumptions!$B$26-1)) -> 0.16504901 | C23: ='Revenue Model'!$F$13*B23/Assumptions!$B$28 -> 3022.9446 | D23: =C23/(Assumptions!$B$7*1000) -> 0.074675641
A24: 9 | B24: =Assumptions!$B$23*(Assumptions!$B$27*(1+Assumptions!$B$27)^A24/((1+Assumptions!$B$27)^A24-1))+Assumptions!$B$25*(Assumptions!$B$27*(1+Assumptions!$B$27)^Assumptions!$B$26/((1+Assumptions!$B$27)^Assumptions!$B$26-1)) -> 0.15566265 | C24: ='Revenue Model'!$F$13*B24/Assumptions!$B$28 -> 2851.0292 | D24: =C24/(Assumptions!$B$7*1000) -> 0.070428824
A25: 10 | B25: =Assumptions!$B$23*(Assumptions!$B$27*(1+Assumptions!$B$27)^A25/((1+Assumptions!$B$27)^A25-1))+Assumptions!$B$25*(Assumptions!$B$27*(1+Assumptions!$B$27)^Assumptions!$B$26/((1+Assumptions!$B$27)^Assumptions!$B$26-1)) -> 0.14825395 | C25: ='Revenue Model'!$F$13*B25/Assumptions!$B$28 -> 2715.3357 | D25: =C25/(Assumptions!$B$7*1000) -> 0.067076794

Sheet Model Firms
A1: Model Firm Revenue Comparison
A3: Aggregate Comparison
A4: Metric | B4: Value | C4: Units | D4: Formula / Meaning | E4: Source / Note
A5: Paper benchmark: OpenAI + Anthropic combined revenue | B5: 100 | C5: $bn | D5: Contextual benchmark only | E5: Paper Appendix D
A6: Comparison base year | B6: =Assumptions!$B$39 -> 2026 | C6: Year | D6: Linked to assumptions | E6: Assumptions sheet
A7: Detailed current revenue total | B7: =SUM(B17:B26) -> 0 | C7: $bn | D7: Sum of company-level inputs below | E7: User inputs
A8: Active current model-firm revenue | B8: =IF(B7>0,B7,B5) -> 100 | C8: $bn | D8: Uses detailed total if entered; otherwise paper $100bn benchmark | E8: Model logic
A9: User-entered 2032 model-firm forecast | B9: =SUM(D17:D26) -> 0 | C9: $bn | D9: Sum of optional 2032 estimates below | E9: User inputs
A10: Required mature revenue hurdle | B10: ='Revenue Model'!$J$13 -> 3548.0681 | C10: $bn | D10: Live model output | E10: Revenue Model
A11: Revenue gap vs current model-firm revenue | B11: =B10-B8 -> 3448.0681 | C11: $bn | D11: Required hurdle less current model-firm revenue | E11: Model output
A12: Required CAGR from current revenue to hurdle | B12: =(B10/B8)^(1/(Assumptions!$B$8-B6))-1 -> 0.81272528 | C12: % | D12: Growth required from base year through 2032 | E12: Model output
A15: Company-Level Inputs (Optional)
A16: Model Firm | B16: Current Revenue ($bn) | C16: Current Year | D16: 2032 Revenue Estimate ($bn) | E16: Source / Notes
A17: OpenAI | C17: 2026
A18: Anthropic | C18: 2026
A19: xAI | C19: 2026
A20: Other model developer | C20: 2026
A21: Other AI applications / agents | C21: 2026
C22: 2026
C23: 2026
C24: 2026
C25: 2026
C26: 2026
A28: Use this section to replace the paper's aggregate $100bn benchmark with your own current revenue estimates and/or 2032 revenue forecasts. The dashboard will automatically use company-level current revenue once any values are entered.

Sheet Sources
A1: Sources & Model Notes
A3: Primary Sources
A4: Source | B4: URL | C4: Use in Workbook | D4: Notes
A5: Van Nieuwerburgh (2026), Financing the AI Buildout — SSRN revised draft | B5: https://papers.ssrn.com/sol3/Delivery.cfm/6444363.pdf?abstractid=6444363&mirid=1&type=2 | C5: Capacity assumptions, cost per MW, construction timing, Appendix D revenue equations, Table 6/7 | D5: User-provided paper corresponds to the revised Oct. 2, 2026 draft.
A6: NBER Working Paper 35865 | B6: https://www.nber.org/papers/w35865 | C6: Public paper landing page / citation | D6: Useful for sharing with colleagues.
A7: Brookings BPEA summary | B7: https://www.brookings.edu/articles/financing-the-ai-buildout/ | C7: Public summary / context | D7: Summary page may reflect an earlier conference version; the workbook follows the user-provided revised paper.
A8: Ornn Compute Price Index | B8: https://data.ornn.com/preview | C8: Reference frontier GPU rental price | D8: Paper cites $6.07 per GPU-hour for B200 on Aug. 31, 2026.
A10: Model Architecture
A11: Step | B11: Calculation | C11: Workbook Location | D11: Why It Matters
A12: 1 | B12: Gross pipeline + imputed capacity + realization assumptions → completion cohorts | C12: Capacity Buildout | D12: Converts announced projects into a realized-capacity scenario.
A13: 2 | B13: Completion cohort GW × cost per MW → initial cost | C13: Revenue Model | D13: Translates physical capacity into capital required.
A14: 3 | B14: Construction timing + required return → capital base at commissioning | C14: Assumptions / Revenue Model | D14: Compensates capital committed before revenue begins.
A15: 4 | B15: IT/non-IT economic lives → weighted annual capital recovery charge | C15: Assumptions | D15: Captures depreciation / replacement and opportunity cost.
A16: 5 | B16: Required OCF ÷ OCF margin → mature annual revenue hurdle | C16: Revenue Model | D16: Core monetization hurdle.
A17: 6 | B17: Compare hurdle with model-firm revenues and GPU rental economics | C17: Dashboard / Model Firms / Sensitivity | D17: Shows how much monetization still needs to be created.
A19: Editable Inputs Guide
A20: Area | B20: Key Editable Inputs | C20: Color | D20: Comment
A21: Capacity realization | B21: Observed/imputed realization rates and fixed operational capacity | C21: Blue text / yellow fill | D21: Adjust if the pipeline changes.
A22: Cost | B22: 2025 $/MW and annual cost growth | C22: Blue text / yellow fill | D22: Useful for hardware deflation/inflation scenarios.
A23: Asset life | B23: IT life and non-IT life | C23: Blue text / yellow fill | D23: Major driver of the revenue hurdle.
A24: Return / margin | B24: Required unlevered return and OCF margin | C24: Blue text / yellow fill | D24: Replicates Table 7 sensitivities.
A25: Compute | B25: PUE, rack power, GPUs/rack, utilization | C25: Blue text / yellow fill | D25: Converts revenue hurdle into GPU-hour economics.
A26: Model firms | B26: Current revenue and optional 2032 revenue estimates | C26: Blue text / yellow fill | D26: Lets you compare monetization achieved vs required.
A27: Formula cells | B27: Do not overwrite unless changing model design | C27: Black or green text | D27: Green = links across worksheets; black = local calculations.

Sheet Investment Schedule
A1: AI Infrastructure Investment Schedule
A3: Annual Investment — Formula Replication vs Paper Table 5
A4: Year | B4: Modeled Spend on 2025–32 Cohorts ($bn) | C4: Paper Reported Investment ($bn) | D4: Difference ($bn) | E4: Nominal GDP ($bn) | F4: Paper Investment / GDP | G4: Modeled 2025–32 Cohort Spend / GDP | H4: Comment
A5: 2025 | B5: =Assumptions!$B$19*'Revenue Model'!$D$5+Assumptions!$B$18*'Revenue Model'!$D$6+Assumptions!$B$17*'Revenue Model'!$D$7+Assumptions!$B$16*'Revenue Model'!$D$8 -> 791.04715 | C5: 790 | D5: =B5-C5 -> 1.0471494 | E5: 30762 | F5: =C5/E5 -> 0.025681035 | G5: =B5/E5 -> 0.025715075 | H5: Close replication using 2025–32 completion cohorts.
A6: 2026 | B6: =Assumptions!$B$19*'Revenue Model'!$D$6+Assumptions!$B$18*'Revenue Model'!$D$7+Assumptions!$B$17*'Revenue Model'!$D$8+Assumptions!$B$16*'Revenue Model'!$D$9 -> 1250.7124 | C6: 1253 | D6: =B6-C6 -> -2.2876462 | E6: 31992 | F6: =C6/E6 -> 0.039166042 | G6: =B6/E6 -> 0.039094535 | H6: Close replication using 2025–32 completion cohorts.
A7: 2027 | B7: =Assumptions!$B$19*'Revenue Model'!$D$7+Assumptions!$B$18*'Revenue Model'!$D$8+Assumptions!$B$17*'Revenue Model'!$D$9+Assumptions!$B$16*'Revenue Model'!$D$10 -> 1597.6865 | C7: 1597 | D7: =B7-C7 -> 0.6865028 | E7: 33272 | F7: =C7/E7 -> 0.047998317 | G7: =B7/E7 -> 0.04801895 | H7: Close replication using 2025–32 completion cohorts.
A8: 2028 | B8: =Assumptions!$B$19*'Revenue Model'!$D$8+Assumptions!$B$18*'Revenue Model'!$D$9+Assumptions!$B$17*'Revenue Model'!$D$10+Assumptions!$B$16*'Revenue Model'!$D$11 -> 1715.3509 | C8: 1717 | D8: =B8-C8 -> -1.6491147 | E8: 34603 | F8: =C8/E8 -> 0.049619975 | G8: =B8/E8 -> 0.049572317 | H8: Close replication using 2025–32 completion cohorts.
A9: 2029 | B9: =Assumptions!$B$19*'Revenue Model'!$D$9+Assumptions!$B$18*'Revenue Model'!$D$10+Assumptions!$B$17*'Revenue Model'!$D$11+Assumptions!$B$16*'Revenue Model'!$D$12 -> 978.71609 | C9: 978 | D9: =B9-C9 -> 0.71609426 | E9: 35987 | F9: =C9/E9 -> 0.02717648 | G9: =B9/E9 -> 0.027196379 | H9: Close replication using 2025–32 completion cohorts.
A10: 2030 | B10: =Assumptions!$B$19*'Revenue Model'!$D$10+Assumptions!$B$18*'Revenue Model'!$D$11+Assumptions!$B$17*'Revenue Model'!$D$12 -> 820.15947 | C10: 886 | D10: =B10-C10 -> -65.840525 | E10: 37427 | F10: =C10/E10 -> 0.02367275 | G10: =B10/E10 -> 0.021913578 | H10: Paper total includes pre-completion spend on post-2032 projects.
A11: 2031 | B11: =Assumptions!$B$19*'Revenue Model'!$D$11+Assumptions!$B$18*'Revenue Model'!$D$12 -> 730.05677 | C11: 863 | D11: =B11-C11 -> -132.94323 | E11: 38924 | F11: =C11/E11 -> 0.022171411 | G11: =B11/E11 -> 0.018755954 | H11: Paper total includes pre-completion spend on post-2032 projects.
A12: 2032 | B12: =Assumptions!$B$19*'Revenue Model'!$D$12 -> 522.80723 | C12: 889 | D12: =B12-C12 -> -366.19277 | E12: 40481 | F12: =C12/E12 -> 0.02196092 | G12: =B12/E12 -> 0.012914879 | H12: Paper total includes pre-completion spend on post-2032 projects.
A13: 2025–32 Total | B13: =SUM(B5:B12) -> 8406.5365 | C13: =SUM(C5:C12) -> 8973 | D13: =B13-C13 -> -566.46354 | E13: =SUM(E5:E12) -> 283448 | F13: =C13/E13 -> 0.0316566 | G13: =B13/E13 -> 0.029658126
A15: Why the model differs from Table 5 after 2029: the paper's Table 5 also includes construction spending during 2025–32 for projects that do not become operational until after 2032. The flexible revenue model intentionally focuses on the 188.3 GW completed during 2025–32, matching Appendix D's revenue-hurdle scope.
