Workbook

Sheet READ ME
A1: AI-EXPOSED WAGE POOL | COMPANY REBUILD GUIDE
A2: Formula-driven • Official data in local tabs • No website or external-workbook links • Blue = source inputs / Green = cross-sheet links
A4: STEP | B4: ACTION | C4: WHAT TO DO | D4: RESULT | E4: IMPORTANT
A5: 01 | B5: QCEW raw | C5: Paste the BLS Industry column into DATA QCEW Raw A, and Total Annual Wages into D. You may paste all ~2,000 rows. | D5: Columns E:G parse the NAICS codes automatically. | E5: Do not sum parent and child industries.
A6: 02 | B6: QCEW mapping | C6: DATA QCEW uses one XLOOKUP per 19 industry codes. | D6: Annual industry wage totals pulled from raw table. | E6: Rows labelled 1013 / 1022 are BLS aggregation IDs, not NAICS.
A7: 03 | B7: Wharton | C7: DATA Wharton has 784 SOC codes with task exposure as 0–1 fractions. | D7: Occupation-level AI task exposure. | E7: Original 47.75% in CSV must be 0.4775 internally.
A8: 04 | B8: OEWS | C8: DATA OEWS contains 7,805 unique sector × detailed SOC records. G/I/J/K are drag-down formulas; H is a verified 2025 Wharton SOC join (replace with XLOOKUP if scores change). | D8: G:K are simple drag-down formulas. | E8: Some suppressed occupations have blank wages.
A9: 05 | B9: Industry Model | C9: Read C:K in 01 Industry Model. | D9: QCEW wage bill × (OEWS weighted Wharton exposure). | E9: The base projection A:K is unchanged. New employee / price revenue scenarios are separate in columns L:Q.
A10: 06 | B10: Projection | C10: Five-Year Projection: 2025–2030 driven by BLS employment CAGR and editable wage / adoption growth. | D10: Simple annual sector forecast. | E10: No AI economic savings / revenue estimation.
A11: QA | B11: Reconciliation | C11: 19 industry wages + NAICS 99 must equal $10,532,191,402,092 in 2025. | D11: 0 reconciliation difference. | E11: Raw QCEW source must be US TOTAL, private, all sizes.
B13: Formula in DATA QCEW Raw!E2
A14: KEY FORMULA | B14: EXCEL EXAMPLE | C14: WHY
A15: Extract code from BLS Industry | B15: NAICS 31-33 Manufacturing → 31-33 | C15: Extract the code between NAICS and first following space.
A16: Wage weight | B16: SUMIF of occupation wage bills by NAICS | C16: Use occupation structure to compute exposure, not sector wages.
A17: Final Gross Exposure | B17: QCEW Annual Wages × Exposure Share | C17: Exposure value ≠ cost saved / layoffs.
A20: OPTIONAL LIVE WHARTON REFRESH | B20: DATA OEWS H2: paste this formula and drag down to H7806
A21: SOC lookup formula | B21: =IFERROR(XLOOKUP(C2,'DATA Wharton'!$A$2:$A$785,'DATA Wharton'!$C$2:$C$785),) | C21: Use only if Wharton scores changed; baseline H values already verified against the 2025 source.
A23: NEW | B23: QCEW employment | C23: Use BLS QCEW annual_avg_emplvl, filtered US000 + own_code 5 + 2025 + annual + all sizes. | D23: DATA QCEW Raw C → DATA QCEW F → Industry Model L. | E23: All data from supplied 2025 QCEW ZIP.
A24: NEW | B24: 2025 revenue proxy | C24: Task-exposed equivalents = QCEW employment × Wharton weighted task exposure. | D24: Industry Model M = L × H; implied revenue O = M × N × 12 / 1e9. | E24: Exposure ≠ actual employee AI-use or paid seat count.
A25: NEW | B25: Pricing | C25: Projection Assumptions C9 = editable monthly AI spend per seat; C10 = annual price growth. | D25: Industry Model N and Projection N pull price assumptions. | E25: $30 / month is illustrative, not observed market revenue.
A26: NEW | B26: Five-year AI revenue | C26: Projection L:Q derive employees, proxy seats, price and enterprise revenue independently of A:K. | D26: Revenue summary added Five-Year Projection rows 10–14. | E26: BTOS-adjusted seats multiply a firm-use rate, NOT an employee-use rate.

Sheet 01 Industry Model
A1: AI-EXPOSED WAGE POOL | U.S. PRIVATE INDUSTRIES (2025)
A2: Source → DATA QCEW Raw → DATA QCEW. SOC mapping is done in DATA OEWS against DATA Wharton. Gross exposure is NOT AI cost savings.
L3: AI SOFTWARE SEAT & REVENUE SCENARIO | NOT OBSERVED PAID USERS
A4: NAICS | B4: Industry | C4: QCEW Wages ($bn) | D4: OEWS Wages ($bn) | E4: Matched Wages ($bn) | F4: Exposure-Weighted Wages ($bn) | G4: Wharton Match Rate | H4: Weighted Task Exposure | I4: GROSS EXPOSED ($bn) | J4: BTOS Firms Using AI | K4: Firm-Use Proxy ($bn) | L4: 2025 Employees (QCEW) | M4: Task-Exposed Seat Eq. (Proxy) | N4: AI Price ($/seat/month) | O4: Task-Equivalent Revenue ($bn) | P4: BTOS-Adjusted Seat Eq. (Proxy) | Q4: BTOS-Adjusted Revenue ($bn)
A5: 11 | B5: Agriculture, forestry, fishing and hunting | C5: =IFERROR(_xlfn.XLOOKUP(A5,'DATA QCEW'!$A$2:$A$20,'DATA QCEW'!$C$2:$C$20)/1000000000,"") -> 60.088225 | D5: =SUMIF('DATA OEWS'!$A$2:$A$7806,A5,'DATA OEWS'!$G$2:$G$7806)/1000000000 -> 18.024129 | E5: =SUMIF('DATA OEWS'!$A$2:$A$7806,A5,'DATA OEWS'!$I$2:$I$7806)/1000000000 -> 17.900933 | F5: =SUMIF('DATA OEWS'!$A$2:$A$7806,A5,'DATA OEWS'!$J$2:$J$7806)/1000000000 -> 3.2456895 | G5: =IF(D5=0,"",E5/D5) -> 0.99316495 | H5: =IF(E5=0,"",F5/E5) -> 0.18131399 | I5: =IF(OR(C5="",H5=""),"",C5*H5) -> 10.894836 | J5: =IFERROR(_xlfn.XLOOKUP(A5,'DATA Census'!$A$2:$A$20,'DATA Census'!$C$2:$C$20),"") -> 0.095 | K5: =IF(OR(I5="",J5=""),"",I5*J5) -> 1.0350094 | L5: =IFERROR(_xlfn.XLOOKUP(A5,'DATA QCEW'!$A$2:$A$20,'DATA QCEW'!$F$2:$F$20),"") -> 1231078 | M5: =IF(OR(L5="",H5=""),"",L5*H5) -> 223211.66 | N5: ='Projection Assumptions'!$C$9 -> 30 | O5: =IF(OR(M5="",N5=""),"",M5*N5*12/1000000000) -> 0.080356199 | P5: =IF(OR(M5="",J5=""),"",M5*J5) -> 21205.108 | Q5: =IF(OR(P5="",N5=""),"",P5*N5*12/1000000000) -> 0.0076338389
A6: 21 | B6: Mining, quarrying, and oil and gas extraction | C6: =IFERROR(_xlfn.XLOOKUP(A6,'DATA QCEW'!$A$2:$A$20,'DATA QCEW'!$C$2:$C$20)/1000000000,"") -> 76.216722 | D6: =SUMIF('DATA OEWS'!$A$2:$A$7806,A6,'DATA OEWS'!$G$2:$G$7806)/1000000000 -> 46.718541 | E6: =SUMIF('DATA OEWS'!$A$2:$A$7806,A6,'DATA OEWS'!$I$2:$I$7806)/1000000000 -> 46.156543 | F6: =SUMIF('DATA OEWS'!$A$2:$A$7806,A6,'DATA OEWS'!$J$2:$J$7806)/1000000000 -> 13.397598 | G6: =IF(D6=0,"",E6/D6) -> 0.98797057 | H6: =IF(E6=0,"",F6/E6) -> 0.29026433 | I6: =IF(OR(C6="",H6=""),"",C6*H6) -> 22.122996 | J6: =IFERROR(_xlfn.XLOOKUP(A6,'DATA Census'!$A$2:$A$20,'DATA Census'!$C$2:$C$20),"") -> 0.13 | K6: =IF(OR(I6="",J6=""),"",I6*J6) -> 2.8759895 | L6: =IFERROR(_xlfn.XLOOKUP(A6,'DATA QCEW'!$A$2:$A$20,'DATA QCEW'!$F$2:$F$20),"") -> 570806 | M6: =IF(OR(L6="",H6=""),"",L6*H6) -> 165684.62 | N6: ='Projection Assumptions'!$C$9 -> 30 | O6: =IF(OR(M6="",N6=""),"",M6*N6*12/1000000000) -> 0.059646464 | P6: =IF(OR(M6="",J6=""),"",M6*J6) -> 21539.001 | Q6: =IF(OR(P6="",N6=""),"",P6*N6*12/1000000000) -> 0.0077540403
A7: 22 | B7: Utilities | C7: =IFERROR(_xlfn.XLOOKUP(A7,'DATA QCEW'!$A$2:$A$20,'DATA QCEW'!$C$2:$C$20)/1000000000,"") -> 85.024862 | D7: =SUMIF('DATA OEWS'!$A$2:$A$7806,A7,'DATA OEWS'!$G$2:$G$7806)/1000000000 -> 61.892073 | E7: =SUMIF('DATA OEWS'!$A$2:$A$7806,A7,'DATA OEWS'!$I$2:$I$7806)/1000000000 -> 61.630077 | F7: =SUMIF('DATA OEWS'!$A$2:$A$7806,A7,'DATA OEWS'!$J$2:$J$7806)/1000000000 -> 22.584317 | G7: =IF(D7=0,"",E7/D7) -> 0.99576689 | H7: =IF(E7=0,"",F7/E7) -> 0.3664496 | I7: =IF(OR(C7="",H7=""),"",C7*H7) -> 31.157326 | J7: =IFERROR(_xlfn.XLOOKUP(A7,'DATA Census'!$A$2:$A$20,'DATA Census'!$C$2:$C$20),"") -> 0.167 | K7: =IF(OR(I7="",J7=""),"",I7*J7) -> 5.2032735 | L7: =IFERROR(_xlfn.XLOOKUP(A7,'DATA QCEW'!$A$2:$A$20,'DATA QCEW'!$F$2:$F$20),"") -> 602080 | M7: =IF(OR(L7="",H7=""),"",L7*H7) -> 220631.97 | N7: ='Projection Assumptions'!$C$9 -> 30 | O7: =IF(OR(M7="",N7=""),"",M7*N7*12/1000000000) -> 0.07942751 | P7: =IF(OR(M7="",J7=""),"",M7*J7) -> 36845.54 | Q7: =IF(OR(P7="",N7=""),"",P7*N7*12/1000000000) -> 0.013264394
A8: 23 | B8: Construction | C8: =IFERROR(_xlfn.XLOOKUP(A8,'DATA QCEW'!$A$2:$A$20,'DATA QCEW'!$C$2:$C$20)/1000000000,"") -> 699.89625 | D8: =SUMIF('DATA OEWS'!$A$2:$A$7806,A8,'DATA OEWS'!$G$2:$G$7806)/1000000000 -> 598.12192 | E8: =SUMIF('DATA OEWS'!$A$2:$A$7806,A8,'DATA OEWS'!$I$2:$I$7806)/1000000000 -> 596.27577 | F8: =SUMIF('DATA OEWS'!$A$2:$A$7806,A8,'DATA OEWS'!$J$2:$J$7806)/1000000000 -> 158.59374 | G8: =IF(D8=0,"",E8/D8) -> 0.99691342 | H8: =IF(E8=0,"",F8/E8) -> 0.26597382 | I8: =IF(OR(C8="",H8=""),"",C8*H8) -> 186.15408 | J8: =IFERROR(_xlfn.XLOOKUP(A8,'DATA Census'!$A$2:$A$20,'DATA Census'!$C$2:$C$20),"") -> 0.172 | K8: =IF(OR(I8="",J8=""),"",I8*J8) -> 32.018501 | L8: =IFERROR(_xlfn.XLOOKUP(A8,'DATA QCEW'!$A$2:$A$20,'DATA QCEW'!$F$2:$F$20),"") -> 8251002 | M8: =IF(OR(L8="",H8=""),"",L8*H8) -> 2194550.5 | N8: ='Projection Assumptions'!$C$9 -> 30 | O8: =IF(OR(M8="",N8=""),"",M8*N8*12/1000000000) -> 0.79003818 | P8: =IF(OR(M8="",J8=""),"",M8*J8) -> 377462.69 | Q8: =IF(OR(P8="",N8=""),"",P8*N8*12/1000000000) -> 0.13588657
A9: 31-33 | B9: Manufacturing | C9: =IFERROR(_xlfn.XLOOKUP(A9,'DATA QCEW'!$A$2:$A$20,'DATA QCEW'!$C$2:$C$20)/1000000000,"") -> 1125.5427 | D9: =SUMIF('DATA OEWS'!$A$2:$A$7806,A9,'DATA OEWS'!$G$2:$G$7806)/1000000000 -> 874.49352 | E9: =SUMIF('DATA OEWS'!$A$2:$A$7806,A9,'DATA OEWS'!$I$2:$I$7806)/1000000000 -> 864.06661 | F9: =SUMIF('DATA OEWS'!$A$2:$A$7806,A9,'DATA OEWS'!$J$2:$J$7806)/1000000000 -> 286.93931 | G9: =IF(D9=0,"",E9/D9) -> 0.98807663 | H9: =IF(E9=0,"",F9/E9) -> 0.33208008 | I9: =IF(OR(C9="",H9=""),"",C9*H9) -> 373.7703 | J9: =IFERROR(_xlfn.XLOOKUP(A9,'DATA Census'!$A$2:$A$20,'DATA Census'!$C$2:$C$20),"") -> 0.208 | K9: =IF(OR(I9="",J9=""),"",I9*J9) -> 77.744222 | L9: =IFERROR(_xlfn.XLOOKUP(A9,'DATA QCEW'!$A$2:$A$20,'DATA QCEW'!$F$2:$F$20),"") -> 12579906 | M9: =IF(OR(L9="",H9=""),"",L9*H9) -> 4177536.1 | N9: ='Projection Assumptions'!$C$9 -> 30 | O9: =IF(OR(M9="",N9=""),"",M9*N9*12/1000000000) -> 1.503913 | P9: =IF(OR(M9="",J9=""),"",M9*J9) -> 868927.52 | Q9: =IF(OR(P9="",N9=""),"",P9*N9*12/1000000000) -> 0.31281391
A10: 42 | B10: Wholesale trade | C10: =IFERROR(_xlfn.XLOOKUP(A10,'DATA QCEW'!$A$2:$A$20,'DATA QCEW'!$C$2:$C$20)/1000000000,"") -> 638.87897 | D10: =SUMIF('DATA OEWS'!$A$2:$A$7806,A10,'DATA OEWS'!$G$2:$G$7806)/1000000000 -> 458.15484 | E10: =SUMIF('DATA OEWS'!$A$2:$A$7806,A10,'DATA OEWS'!$I$2:$I$7806)/1000000000 -> 455.37523 | F10: =SUMIF('DATA OEWS'!$A$2:$A$7806,A10,'DATA OEWS'!$J$2:$J$7806)/1000000000 -> 210.41317 | G10: =IF(D10=0,"",E10/D10) -> 0.99393303 | H10: =IF(E10=0,"",F10/E10) -> 0.46206547 | I10: =IF(OR(C10="",H10=""),"",C10*H10) -> 295.20392 | J10: =IFERROR(_xlfn.XLOOKUP(A10,'DATA Census'!$A$2:$A$20,'DATA Census'!$C$2:$C$20),"") -> 0.216 | K10: =IF(OR(I10="",J10=""),"",I10*J10) -> 63.764046 | L10: =IFERROR(_xlfn.XLOOKUP(A10,'DATA QCEW'!$A$2:$A$20,'DATA QCEW'!$F$2:$F$20),"") -> 6037213 | M10: =IF(OR(L10="",H10=""),"",L10*H10) -> 2789587.7 | N10: ='Projection Assumptions'!$C$9 -> 30 | O10: =IF(OR(M10="",N10=""),"",M10*N10*12/1000000000) -> 1.0042516 | P10: =IF(OR(M10="",J10=""),"",M10*J10) -> 602550.94 | Q10: =IF(OR(P10="",N10=""),"",P10*N10*12/1000000000) -> 0.21691834
A11: 44-45 | B11: Retail trade | C11: =IFERROR(_xlfn.XLOOKUP(A11,'DATA QCEW'!$A$2:$A$20,'DATA QCEW'!$C$2:$C$20)/1000000000,"") -> 668.86357 | D11: =SUMIF('DATA OEWS'!$A$2:$A$7806,A11,'DATA OEWS'!$G$2:$G$7806)/1000000000 -> 693.02976 | E11: =SUMIF('DATA OEWS'!$A$2:$A$7806,A11,'DATA OEWS'!$I$2:$I$7806)/1000000000 -> 689.44551 | F11: =SUMIF('DATA OEWS'!$A$2:$A$7806,A11,'DATA OEWS'!$J$2:$J$7806)/1000000000 -> 302.19336 | G11: =IF(D11=0,"",E11/D11) -> 0.99482815 | H11: =IF(E11=0,"",F11/E11) -> 0.43831363 | I11: =IF(OR(C11="",H11=""),"",C11*H11) -> 293.17202 | J11: =IFERROR(_xlfn.XLOOKUP(A11,'DATA Census'!$A$2:$A$20,'DATA Census'!$C$2:$C$20),"") -> 0.168 | K11: =IF(OR(I11="",J11=""),"",I11*J11) -> 49.252899 | L11: =IFERROR(_xlfn.XLOOKUP(A11,'DATA QCEW'!$A$2:$A$20,'DATA QCEW'!$F$2:$F$20),"") -> 15391082 | M11: =IF(OR(L11="",H11=""),"",L11*H11) -> 6746121 | N11: ='Projection Assumptions'!$C$9 -> 30 | O11: =IF(OR(M11="",N11=""),"",M11*N11*12/1000000000) -> 2.4286035 | P11: =IF(OR(M11="",J11=""),"",M11*J11) -> 1133348.3 | Q11: =IF(OR(P11="",N11=""),"",P11*N11*12/1000000000) -> 0.4080054
A12: 48-49 | B12: Transportation and warehousing | C12: =IFERROR(_xlfn.XLOOKUP(A12,'DATA QCEW'!$A$2:$A$20,'DATA QCEW'!$C$2:$C$20)/1000000000,"") -> 455.48394 | D12: =SUMIF('DATA OEWS'!$A$2:$A$7806,A12,'DATA OEWS'!$G$2:$G$7806)/1000000000 -> 478.82617 | E12: =SUMIF('DATA OEWS'!$A$2:$A$7806,A12,'DATA OEWS'!$I$2:$I$7806)/1000000000 -> 477.19288 | F12: =SUMIF('DATA OEWS'!$A$2:$A$7806,A12,'DATA OEWS'!$J$2:$J$7806)/1000000000 -> 157.08135 | G12: =IF(D12=0,"",E12/D12) -> 0.99658896 | H12: =IF(E12=0,"",F12/E12) -> 0.3291779 | I12: =IF(OR(C12="",H12=""),"",C12*H12) -> 149.93525 | J12: =IFERROR(_xlfn.XLOOKUP(A12,'DATA Census'!$A$2:$A$20,'DATA Census'!$C$2:$C$20),"") -> 0.105 | K12: =IF(OR(I12="",J12=""),"",I12*J12) -> 15.743201 | L12: =IFERROR(_xlfn.XLOOKUP(A12,'DATA QCEW'!$A$2:$A$20,'DATA QCEW'!$F$2:$F$20),"") -> 6618917 | M12: =IF(OR(L12="",H12=""),"",L12*H12) -> 2178801.2 | N12: ='Projection Assumptions'!$C$9 -> 30 | O12: =IF(OR(M12="",N12=""),"",M12*N12*12/1000000000) -> 0.78436842 | P12: =IF(OR(M12="",J12=""),"",M12*J12) -> 228774.12 | Q12: =IF(OR(P12="",N12=""),"",P12*N12*12/1000000000) -> 0.082358685
A13: 51 | B13: Information | C13: =IFERROR(_xlfn.XLOOKUP(A13,'DATA QCEW'!$A$2:$A$20,'DATA QCEW'!$C$2:$C$20)/1000000000,"") -> 544.46957 | D13: =SUMIF('DATA OEWS'!$A$2:$A$7806,A13,'DATA OEWS'!$G$2:$G$7806)/1000000000 -> 323.62617 | E13: =SUMIF('DATA OEWS'!$A$2:$A$7806,A13,'DATA OEWS'!$I$2:$I$7806)/1000000000 -> 321.61476 | F13: =SUMIF('DATA OEWS'!$A$2:$A$7806,A13,'DATA OEWS'!$J$2:$J$7806)/1000000000 -> 181.50197 | G13: =IF(D13=0,"",E13/D13) -> 0.99378476 | H13: =IF(E13=0,"",F13/E13) -> 0.5643459 | I13: =IF(OR(C13="",H13=""),"",C13*H13) -> 307.26917 | J13: =IFERROR(_xlfn.XLOOKUP(A13,'DATA Census'!$A$2:$A$20,'DATA Census'!$C$2:$C$20),"") -> 0.502 | K13: =IF(OR(I13="",J13=""),"",I13*J13) -> 154.24912 | L13: =IFERROR(_xlfn.XLOOKUP(A13,'DATA QCEW'!$A$2:$A$20,'DATA QCEW'!$F$2:$F$20),"") -> 2850904 | M13: =IF(OR(L13="",H13=""),"",L13*H13) -> 1608896 | N13: ='Projection Assumptions'!$C$9 -> 30 | O13: =IF(OR(M13="",N13=""),"",M13*N13*12/1000000000) -> 0.57920256 | P13: =IF(OR(M13="",J13=""),"",M13*J13) -> 807665.79 | Q13: =IF(OR(P13="",N13=""),"",P13*N13*12/1000000000) -> 0.29075968
A14: 52 | B14: Finance and insurance | C14: =IFERROR(_xlfn.XLOOKUP(A14,'DATA QCEW'!$A$2:$A$20,'DATA QCEW'!$C$2:$C$20)/1000000000,"") -> 966.66675 | D14: =SUMIF('DATA OEWS'!$A$2:$A$7806,A14,'DATA OEWS'!$G$2:$G$7806)/1000000000 -> 632.3122 | E14: =SUMIF('DATA OEWS'!$A$2:$A$7806,A14,'DATA OEWS'!$I$2:$I$7806)/1000000000 -> 628.98598 | F14: =SUMIF('DATA OEWS'!$A$2:$A$7806,A14,'DATA OEWS'!$J$2:$J$7806)/1000000000 -> 426.99129 | G14: =IF(D14=0,"",E14/D14) -> 0.99473959 | H14: =IF(E14=0,"",F14/E14) -> 0.67885661 | I14: =IF(OR(C14="",H14=""),"",C14*H14) -> 656.22812 | J14: =IFERROR(_xlfn.XLOOKUP(A14,'DATA Census'!$A$2:$A$20,'DATA Census'!$C$2:$C$20),"") -> 0.401 | K14: =IF(OR(I14="",J14=""),"",I14*J14) -> 263.14747 | L14: =IFERROR(_xlfn.XLOOKUP(A14,'DATA QCEW'!$A$2:$A$20,'DATA QCEW'!$F$2:$F$20),"") -> 6316381 | M14: =IF(OR(L14="",H14=""),"",L14*H14) -> 4287917 | N14: ='Projection Assumptions'!$C$9 -> 30 | O14: =IF(OR(M14="",N14=""),"",M14*N14*12/1000000000) -> 1.5436501 | P14: =IF(OR(M14="",J14=""),"",M14*J14) -> 1719454.7 | Q14: =IF(OR(P14="",N14=""),"",P14*N14*12/1000000000) -> 0.6190037
A15: 53 | B15: Real estate and rental and leasing | C15: =IFERROR(_xlfn.XLOOKUP(A15,'DATA QCEW'!$A$2:$A$20,'DATA QCEW'!$C$2:$C$20)/1000000000,"") -> 193.52918 | D15: =SUMIF('DATA OEWS'!$A$2:$A$7806,A15,'DATA OEWS'!$G$2:$G$7806)/1000000000 -> 157.85057 | E15: =SUMIF('DATA OEWS'!$A$2:$A$7806,A15,'DATA OEWS'!$I$2:$I$7806)/1000000000 -> 156.90478 | F15: =SUMIF('DATA OEWS'!$A$2:$A$7806,A15,'DATA OEWS'!$J$2:$J$7806)/1000000000 -> 73.211257 | G15: =IF(D15=0,"",E15/D15) -> 0.99400829 | H15: =IF(E15=0,"",F15/E15) -> 0.46659674 | I15: =IF(OR(C15="",H15=""),"",C15*H15) -> 90.300084 | J15: =IFERROR(_xlfn.XLOOKUP(A15,'DATA Census'!$A$2:$A$20,'DATA Census'!$C$2:$C$20),"") -> 0.308 | K15: =IF(OR(I15="",J15=""),"",I15*J15) -> 27.812426 | L15: =IFERROR(_xlfn.XLOOKUP(A15,'DATA QCEW'!$A$2:$A$20,'DATA QCEW'!$F$2:$F$20),"") -> 2411118 | M15: =IF(OR(L15="",H15=""),"",L15*H15) -> 1125019.8 | N15: ='Projection Assumptions'!$C$9 -> 30 | O15: =IF(OR(M15="",N15=""),"",M15*N15*12/1000000000) -> 0.40500713 | P15: =IF(OR(M15="",J15=""),"",M15*J15) -> 346506.1 | Q15: =IF(OR(P15="",N15=""),"",P15*N15*12/1000000000) -> 0.1247422
A16: 54 | B16: Professional, scientific, and technical services | C16: =IFERROR(_xlfn.XLOOKUP(A16,'DATA QCEW'!$A$2:$A$20,'DATA QCEW'!$C$2:$C$20)/1000000000,"") -> 1454.3907 | D16: =SUMIF('DATA OEWS'!$A$2:$A$7806,A16,'DATA OEWS'!$G$2:$G$7806)/1000000000 -> 1171.2565 | E16: =SUMIF('DATA OEWS'!$A$2:$A$7806,A16,'DATA OEWS'!$I$2:$I$7806)/1000000000 -> 1167.2182 | F16: =SUMIF('DATA OEWS'!$A$2:$A$7806,A16,'DATA OEWS'!$J$2:$J$7806)/1000000000 -> 647.40875 | G16: =IF(D16=0,"",E16/D16) -> 0.99655214 | H16: =IF(E16=0,"",F16/E16) -> 0.55465958 | I16: =IF(OR(C16="",H16=""),"",C16*H16) -> 806.69172 | J16: =IFERROR(_xlfn.XLOOKUP(A16,'DATA Census'!$A$2:$A$20,'DATA Census'!$C$2:$C$20),"") -> 0.427 | K16: =IF(OR(I16="",J16=""),"",I16*J16) -> 344.45736 | L16: =IFERROR(_xlfn.XLOOKUP(A16,'DATA QCEW'!$A$2:$A$20,'DATA QCEW'!$F$2:$F$20),"") -> 10750955 | M16: =IF(OR(L16="",H16=""),"",L16*H16) -> 5963120.2 | N16: ='Projection Assumptions'!$C$9 -> 30 | O16: =IF(OR(M16="",N16=""),"",M16*N16*12/1000000000) -> 2.1467233 | P16: =IF(OR(M16="",J16=""),"",M16*J16) -> 2546252.3 | Q16: =IF(OR(P16="",N16=""),"",P16*N16*12/1000000000) -> 0.91665083
... A23: 81 | B23: Other services (except public administration) | C23: =IFERROR(_xlfn.XLOOKUP(A23,'DATA QCEW'!$A$2:$A$20,'DATA QCEW'!$C$2:$C$20)/1000000000,"") -> 254.46891 | D23: =SUMIF('DATA OEWS'!$A$2:$A$7806,A23,'DATA OEWS'!$G$2:$G$7806)/1000000000 -> 254.71444 | E23: =SUMIF('DATA OEWS'!$A$2:$A$7806,A23,'DATA OEWS'!$I$2:$I$7806)/1000000000 -> 250.74309 | F23: =SUMIF('DATA OEWS'!$A$2:$A$7806,A23,'DATA OEWS'!$J$2:$J$7806)/1000000000 -> 90.672712 | G23: =IF(D23=0,"",E23/D23) -> 0.98440864 | H23: =IF(E23=0,"",F23/E23) -> 0.36161599 | I23: =IF(OR(C23="",H23=""),"",C23*H23) -> 92.02003 | J23: =IFERROR(_xlfn.XLOOKUP(A23,'DATA Census'!$A$2:$A$20,'DATA Census'!$C$2:$C$20),"") -> 0.127 | K23: =IF(OR(I23="",J23=""),"",I23*J23) -> 11.686544 | L23: =IFERROR(_xlfn.XLOOKUP(A23,'DATA QCEW'!$A$2:$A$20,'DATA QCEW'!$F$2:$F$20),"") -> 4675880 | M23: =IF(OR(L23="",H23=""),"",L23*H23) -> 1690873 | N23: ='Projection Assumptions'!$C$9 -> 30 | O23: =IF(OR(M23="",N23=""),"",M23*N23*12/1000000000) -> 0.60871428 | P23: =IF(OR(M23="",J23=""),"",M23*J23) -> 214740.87 | Q23: =IF(OR(P23="",N23=""),"",P23*N23*12/1000000000) -> 0.077306713
B25: TOTAL | 19 PRIVATE INDUSTRIES | C25: =SUM(C5:C23) -> 10515.646 | D25: =SUM(D5:D23) -> 9162.6479 | E25: =SUM(E5:E23) -> 9084.5354 | F25: =SUM(F5:F23) -> 3671.5561 | I25: =SUM(I5:I23) -> 4435.9142 | K25: =SUM(K5:K23) -> 1311.4477 | L25: =SUM(L5:L23) -> 132959111 | M25: =SUM(M5:M23) -> 50267365 | O25: =SUM(O5:O23) -> 18.096251 | P25: =SUM(P5:P23) -> 12633444 | Q25: =SUM(Q5:Q23) -> 4.5480399

Sheet Five-Year Projection
A1: FIVE-YEAR PROJECTION | 2025–2030
A2: BLS 2025–2035 employment projections + illustrative nominal wages + Wharton exposure + Census BTOS firm adoption.
A5: U.S. PRIVATE SECTORS ($bn) | B5: 2025 | C5: 2026 | D5: 2027 | E5: 2028 | F5: 2029 | G5: 2030
A6: Industry Annual Wages ($bn) | B6: =SUMIF($C$17:$C$130,B$5,$F$17:$F$130) -> 10515.646 | C6: =SUMIF($C$17:$C$130,C$5,$F$17:$F$130) -> 10877.917 | D6: =SUMIF($C$17:$C$130,D$5,$F$17:$F$130) -> 11252.782 | E6: =SUMIF($C$17:$C$130,E$5,$F$17:$F$130) -> 11640.684 | F6: =SUMIF($C$17:$C$130,F$5,$F$17:$F$130) -> 12042.078 | G6: =SUMIF($C$17:$C$130,G$5,$F$17:$F$130) -> 12457.439
A7: Gross AI-Exposed Wages ($bn) | B7: =SUMIF($C$17:$C$130,B$5,$J$17:$J$130) -> 4435.9142 | C7: =SUMIF($C$17:$C$130,C$5,$J$17:$J$130) -> 4588.4232 | D7: =SUMIF($C$17:$C$130,D$5,$J$17:$J$130) -> 4746.2206 | E7: =SUMIF($C$17:$C$130,E$5,$J$17:$J$130) -> 4909.4915 | F7: =SUMIF($C$17:$C$130,F$5,$J$17:$J$130) -> 5078.4273 | G7: =SUMIF($C$17:$C$130,G$5,$J$17:$J$130) -> 5253.2262
A8: Firm-Use Proxy ($bn) | B8: =IF(B$5=2025,"",SUMIF($C$17:$C$130,B$5,$K$17:$K$130)) | C8: =IF(C$5=2025,"",SUMIF($C$17:$C$130,C$5,$K$17:$K$130)) -> 1357.2013 | D8: =IF(D$5=2025,"",SUMIF($C$17:$C$130,D$5,$K$17:$K$130)) -> 1641.8751 | E8: =IF(E$5=2025,"",SUMIF($C$17:$C$130,E$5,$K$17:$K$130)) -> 1944.5421 | F8: =IF(F$5=2025,"",SUMIF($C$17:$C$130,F$5,$K$17:$K$130)) -> 2266.1112 | G8: =IF(G$5=2025,"",SUMIF($C$17:$C$130,G$5,$K$17:$K$130)) -> 2607.5329
A9: Firm-use proxy / Gross Exposure | B9: =IF(B$5=2025,"",IFERROR(B8/B7,"")) | C9: =IF(C$5=2025,"",IFERROR(C8/C7,"")) -> 0.29578817 | D9: =IF(D$5=2025,"",IFERROR(D8/D7,"")) -> 0.34593315 | E9: =IF(E$5=2025,"",IFERROR(E8/E7,"")) -> 0.3960781 | F9: =IF(F$5=2025,"",IFERROR(F8/F7,"")) -> 0.44622303 | G9: =IF(G$5=2025,"",IFERROR(G8/G7,"")) -> 0.49636791
A10: Private Employment (million) | B10: =SUMIF($C$17:$C$130,B$5,$L$17:$L$130)/1000000 -> 132.95911 | C10: =SUMIF($C$17:$C$130,C$5,$L$17:$L$130)/1000000 -> 133.49715 | D10: =SUMIF($C$17:$C$130,D$5,$L$17:$L$130)/1000000 -> 134.03877 | E10: =SUMIF($C$17:$C$130,E$5,$L$17:$L$130)/1000000 -> 134.58399 | F10: =SUMIF($C$17:$C$130,F$5,$L$17:$L$130)/1000000 -> 135.13284 | G10: =SUMIF($C$17:$C$130,G$5,$L$17:$L$130)/1000000 -> 135.68536
A11: Task-Exposed Seat Eq. (million) | B11: =SUMIF($C$17:$C$130,B$5,$M$17:$M$130)/1000000 -> 50.267365 | C11: =SUMIF($C$17:$C$130,C$5,$M$17:$M$130)/1000000 -> 50.461789 | D11: =SUMIF($C$17:$C$130,D$5,$M$17:$M$130)/1000000 -> 50.657486 | E11: =SUMIF($C$17:$C$130,E$5,$M$17:$M$130)/1000000 -> 50.854467 | F11: =SUMIF($C$17:$C$130,F$5,$M$17:$M$130)/1000000 -> 51.052739 | G11: =SUMIF($C$17:$C$130,G$5,$M$17:$M$130)/1000000 -> 51.252314
A12: Task-Equivalent AI Revenue ($bn) | B12: =SUMIF($C$17:$C$130,B$5,$O$17:$O$130) -> 18.096251 | C12: =SUMIF($C$17:$C$130,C$5,$O$17:$O$130) -> 18.166244 | D12: =SUMIF($C$17:$C$130,D$5,$O$17:$O$130) -> 18.236695 | E12: =SUMIF($C$17:$C$130,E$5,$O$17:$O$130) -> 18.307608 | F12: =SUMIF($C$17:$C$130,F$5,$O$17:$O$130) -> 18.378986 | G12: =SUMIF($C$17:$C$130,G$5,$O$17:$O$130) -> 18.450833
A13: BTOS-Adj. Seat Eq. (million) | B13: =IF(B$5=2025,"",SUMIF($C$17:$C$130,B$5,$P$17:$P$130)/1000000) | C13: =IF(C$5=2025,"",SUMIF($C$17:$C$130,C$5,$P$17:$P$130)/1000000) -> 12.689267 | D13: =IF(D$5=2025,"",SUMIF($C$17:$C$130,D$5,$P$17:$P$130)/1000000) -> 15.278347 | E13: =IF(E$5=2025,"",SUMIF($C$17:$C$130,E$5,$P$17:$P$130)/1000000) -> 17.887509 | F13: =IF(F$5=2025,"",SUMIF($C$17:$C$130,F$5,$P$17:$P$130)/1000000) -> 20.516952 | G13: =IF(G$5=2025,"",SUMIF($C$17:$C$130,G$5,$P$17:$P$130)/1000000) -> 23.166874
A14: BTOS-Adj. AI Revenue ($bn) | B14: =IF(B$5=2025,"",SUMIF($C$17:$C$130,B$5,$Q$17:$Q$130)) | C14: =IF(C$5=2025,"",SUMIF($C$17:$C$130,C$5,$Q$17:$Q$130)) -> 4.5681362 | D14: =IF(D$5=2025,"",SUMIF($C$17:$C$130,D$5,$Q$17:$Q$130)) -> 5.5002048 | E14: =IF(E$5=2025,"",SUMIF($C$17:$C$130,E$5,$Q$17:$Q$130)) -> 6.4395034 | F14: =IF(F$5=2025,"",SUMIF($C$17:$C$130,F$5,$Q$17:$Q$130)) -> 7.3861028 | G14: =IF(G$5=2025,"",SUMIF($C$17:$C$130,G$5,$Q$17:$Q$130)) -> 8.3400746
L15: ADD-ON: EMPLOYEES → TASK SEATS → IMPLIED AI SUBSCRIPTION REVENUE
A16: NAICS | B16: Industry | C16: Year | D16: BLS Employment CAGR | E16: Nominal Wage Growth | F16: Industry Wages ($bn) | G16: AI Adoption Change (pp) | H16: AI-Using Firms | I16: AI Task Exposure | J16: Gross Exposed Wages ($bn) | K16: Firm-Use Proxy ($bn) | L16: Projected Employees | M16: Task-Exposed Seat Eq. (Proxy) | N16: AI Price ($/month) | O16: Potential AI Revenue ($bn) | P16: BTOS-Adj. Seat Eq. (Proxy) | Q16: BTOS-Adj. AI Revenue ($bn)
A17: 11 | B17: Agriculture, forestry, fishing and hunting | C17: 2025 | D17: =IFERROR(_xlfn.XLOOKUP(A17,'DATA BLS Projections'!$A$2:$A$20,'DATA BLS Projections'!$E$2:$E$20),0) -> 0.001474046 | E17: =IFERROR(_xlfn.XLOOKUP(A17,'Projection Assumptions'!$A$13:$A$31,'Projection Assumptions'!$C$13:$C$31),0) -> 0.03 | F17: =IF(C17=2025,_xlfn.XLOOKUP(A17,'01 Industry Model'!$A$5:$A$23,'01 Industry Model'!$C$5:$C$23),F16*(1+D17)*(1+E17)) -> 60.088225 | G17: =IFERROR(_xlfn.XLOOKUP(A17,'Projection Assumptions'!$A$13:$A$31,'Projection Assumptions'!$D$13:$D$31),0) -> 0.05 | H17: =IF(C17=2025,"",IF(C17=2026,_xlfn.XLOOKUP(A17,'DATA Census'!$A$2:$A$20,'DATA Census'!$C$2:$C$20),MIN(1,H16+G17))) | I17: =MIN(1,MAX(0,_xlfn.XLOOKUP(A17,'01 Industry Model'!$A$5:$A$23,'01 Industry Model'!$H$5:$H$23)+(C17-2025)*_xlfn.XLOOKUP(A17,'Projection Assumptions'!$A$13:$A$31,'Projection Assumptions'!$E$13:$E$31))) -> 0.18131399 | J17: =IF(F17="","",F17*I17) -> 10.894836 | K17: =IF(H17="","",J17*H17) | L17: =IF(C17=2025,IFERROR(_xlfn.XLOOKUP(A17,'DATA QCEW'!$A$2:$A$20,'DATA QCEW'!$F$2:$F$20),""),L16*(1+D17)) -> 1231078 | M17: =IF(OR(L17="",I17=""),"",L17*I17) -> 223211.66 | N17: =IF(C17=2025,'Projection Assumptions'!$C$9,N16*(1+'Projection Assumptions'!$C$10)) -> 30 | O17: =IF(OR(M17="",N17=""),"",M17*N17*12/1000000000) -> 0.080356199 | P17: =IF(OR(M17="",H17=""),"",M17*H17) | Q17: =IF(OR(P17="",N17=""),"",P17*N17*12/1000000000)
A18: 11 | B18: Agriculture, forestry, fishing and hunting | C18: 2026 | D18: =IFERROR(_xlfn.XLOOKUP(A18,'DATA BLS Projections'!$A$2:$A$20,'DATA BLS Projections'!$E$2:$E$20),0) -> 0.001474046 | E18: =IFERROR(_xlfn.XLOOKUP(A18,'Projection Assumptions'!$A$13:$A$31,'Projection Assumptions'!$C$13:$C$31),0) -> 0.03 | F18: =IF(C18=2025,_xlfn.XLOOKUP(A18,'01 Industry Model'!$A$5:$A$23,'01 Industry Model'!$C$5:$C$23),F17*(1+D18)*(1+E18)) -> 61.982102 | G18: =IFERROR(_xlfn.XLOOKUP(A18,'Projection Assumptions'!$A$13:$A$31,'Projection Assumptions'!$D$13:$D$31),0) -> 0.05 | H18: =IF(C18=2025,"",IF(C18=2026,_xlfn.XLOOKUP(A18,'DATA Census'!$A$2:$A$20,'DATA Census'!$C$2:$C$20),MIN(1,H17+G18))) -> 0.095 | I18: =MIN(1,MAX(0,_xlfn.XLOOKUP(A18,'01 Industry Model'!$A$5:$A$23,'01 Industry Model'!$H$5:$H$23)+(C18-2025)*_xlfn.XLOOKUP(A18,'Projection Assumptions'!$A$13:$A$31,'Projection Assumptions'!$E$13:$E$31))) -> 0.18131399 | J18: =IF(F18="","",F18*I18) -> 11.238222 | K18: =IF(H18="","",J18*H18) -> 1.0676311 | L18: =IF(C18=2025,IFERROR(_xlfn.XLOOKUP(A18,'DATA QCEW'!$A$2:$A$20,'DATA QCEW'!$F$2:$F$20),""),L17*(1+D18)) -> 1232892.7 | M18: =IF(OR(L18="",I18=""),"",L18*I18) -> 223540.69 | N18: =IF(C18=2025,'Projection Assumptions'!$C$9,N17*(1+'Projection Assumptions'!$C$10)) -> 30 | O18: =IF(OR(M18="",N18=""),"",M18*N18*12/1000000000) -> 0.080474647 | P18: =IF(OR(M18="",H18=""),"",M18*H18) -> 21236.365 | Q18: =IF(OR(P18="",N18=""),"",P18*N18*12/1000000000) -> 0.0076450915
A19: 11 | B19: Agriculture, forestry, fishing and hunting | C19: 2027 | D19: =IFERROR(_xlfn.XLOOKUP(A19,'DATA BLS Projections'!$A$2:$A$20,'DATA BLS Projections'!$E$2:$E$20),0) -> 0.001474046 | E19: =IFERROR(_xlfn.XLOOKUP(A19,'Projection Assumptions'!$A$13:$A$31,'Projection Assumptions'!$C$13:$C$31),0) -> 0.03 | F19: =IF(C19=2025,_xlfn.XLOOKUP(A19,'01 Industry Model'!$A$5:$A$23,'01 Industry Model'!$C$5:$C$23),F18*(1+D19)*(1+E19)) -> 63.93567 | G19: =IFERROR(_xlfn.XLOOKUP(A19,'Projection Assumptions'!$A$13:$A$31,'Projection Assumptions'!$D$13:$D$31),0) -> 0.05 | H19: =IF(C19=2025,"",IF(C19=2026,_xlfn.XLOOKUP(A19,'DATA Census'!$A$2:$A$20,'DATA Census'!$C$2:$C$20),MIN(1,H18+G19))) -> 0.145 | I19: =MIN(1,MAX(0,_xlfn.XLOOKUP(A19,'01 Industry Model'!$A$5:$A$23,'01 Industry Model'!$H$5:$H$23)+(C19-2025)*_xlfn.XLOOKUP(A19,'Projection Assumptions'!$A$13:$A$31,'Projection Assumptions'!$E$13:$E$31))) -> 0.18131399 | J19: =IF(F19="","",F19*I19) -> 11.592431 | K19: =IF(H19="","",J19*H19) -> 1.6809026 | L19: =IF(C19=2025,IFERROR(_xlfn.XLOOKUP(A19,'DATA QCEW'!$A$2:$A$20,'DATA QCEW'!$F$2:$F$20),""),L18*(1+D19)) -> 1234710 | M19: =IF(OR(L19="",I19=""),"",L19*I19) -> 223870.2 | N19: =IF(C19=2025,'Projection Assumptions'!$C$9,N18*(1+'Projection Assumptions'!$C$10)) -> 30 | O19: =IF(OR(M19="",N19=""),"",M19*N19*12/1000000000) -> 0.080593271 | P19: =IF(OR(M19="",H19=""),"",M19*H19) -> 32461.179 | Q19: =IF(OR(P19="",N19=""),"",P19*N19*12/1000000000) -> 0.011686024
A20: 11 | B20: Agriculture, forestry, fishing and hunting | C20: 2028 | D20: =IFERROR(_xlfn.XLOOKUP(A20,'DATA BLS Projections'!$A$2:$A$20,'DATA BLS Projections'!$E$2:$E$20),0) -> 0.001474046 | E20: =IFERROR(_xlfn.XLOOKUP(A20,'Projection Assumptions'!$A$13:$A$31,'Projection Assumptions'!$C$13:$C$31),0) -> 0.03 | F20: =IF(C20=2025,_xlfn.XLOOKUP(A20,'01 Industry Model'!$A$5:$A$23,'01 Industry Model'!$C$5:$C$23),F19*(1+D20)*(1+E20)) -> 65.950812 | G20: =IFERROR(_xlfn.XLOOKUP(A20,'Projection Assumptions'!$A$13:$A$31,'Projection Assumptions'!$D$13:$D$31),0) -> 0.05 | H20: =IF(C20=2025,"",IF(C20=2026,_xlfn.XLOOKUP(A20,'DATA Census'!$A$2:$A$20,'DATA Census'!$C$2:$C$20),MIN(1,H19+G20))) -> 0.195 | I20: =MIN(1,MAX(0,_xlfn.XLOOKUP(A20,'01 Industry Model'!$A$5:$A$23,'01 Industry Model'!$H$5:$H$23)+(C20-2025)*_xlfn.XLOOKUP(A20,'Projection Assumptions'!$A$13:$A$31,'Projection Assumptions'!$E$13:$E$31))) -> 0.18131399 | J20: =IF(F20="","",F20*I20) -> 11.957805 | K20: =IF(H20="","",J20*H20) -> 2.3317719 | L20: =IF(C20=2025,IFERROR(_xlfn.XLOOKUP(A20,'DATA QCEW'!$A$2:$A$20,'DATA QCEW'!$F$2:$F$20),""),L19*(1+D20)) -> 1236530 | M20: =IF(OR(L20="",I20=""),"",L20*I20) -> 224200.19 | N20: =IF(C20=2025,'Projection Assumptions'!$C$9,N19*(1+'Projection Assumptions'!$C$10)) -> 30 | O20: =IF(OR(M20="",N20=""),"",M20*N20*12/1000000000) -> 0.080712069 | P20: =IF(OR(M20="",H20=""),"",M20*H20) -> 43719.037 | Q20: =IF(OR(P20="",N20=""),"",P20*N20*12/1000000000) -> 0.015738853
A21: 11 | B21: Agriculture, forestry, fishing and hunting | C21: 2029 | D21: =IFERROR(_xlfn.XLOOKUP(A21,'DATA BLS Projections'!$A$2:$A$20,'DATA BLS Projections'!$E$2:$E$20),0) -> 0.001474046 | E21: =IFERROR(_xlfn.XLOOKUP(A21,'Projection Assumptions'!$A$13:$A$31,'Projection Assumptions'!$C$13:$C$31),0) -> 0.03 | F21: =IF(C21=2025,_xlfn.XLOOKUP(A21,'01 Industry Model'!$A$5:$A$23,'01 Industry Model'!$C$5:$C$23),F20*(1+D21)*(1+E21)) -> 68.029467 | G21: =IFERROR(_xlfn.XLOOKUP(A21,'Projection Assumptions'!$A$13:$A$31,'Projection Assumptions'!$D$13:$D$31),0) -> 0.05 | H21: =IF(C21=2025,"",IF(C21=2026,_xlfn.XLOOKUP(A21,'DATA Census'!$A$2:$A$20,'DATA Census'!$C$2:$C$20),MIN(1,H20+G21))) -> 0.245 | I21: =MIN(1,MAX(0,_xlfn.XLOOKUP(A21,'01 Industry Model'!$A$5:$A$23,'01 Industry Model'!$H$5:$H$23)+(C21-2025)*_xlfn.XLOOKUP(A21,'Projection Assumptions'!$A$13:$A$31,'Projection Assumptions'!$E$13:$E$31))) -> 0.18131399 | J21: =IF(F21="","",F21*I21) -> 12.334694 | K21: =IF(H21="","",J21*H21) -> 3.022 | L21: =IF(C21=2025,IFERROR(_xlfn.XLOOKUP(A21,'DATA QCEW'!$A$2:$A$20,'DATA QCEW'!$F$2:$F$20),""),L20*(1+D21)) -> 1238352.7 | M21: =IF(OR(L21="",I21=""),"",L21*I21) -> 224530.67 | N21: =IF(C21=2025,'Projection Assumptions'!$C$9,N20*(1+'Projection Assumptions'!$C$10)) -> 30 | O21: =IF(OR(M21="",N21=""),"",M21*N21*12/1000000000) -> 0.080831042 | P21: =IF(OR(M21="",H21=""),"",M21*H21) -> 55010.015 | Q21: =IF(OR(P21="",N21=""),"",P21*N21*12/1000000000) -> 0.019803605
A22: 11 | B22: Agriculture, forestry, fishing and hunting | C22: 2030 | D22: =IFERROR(_xlfn.XLOOKUP(A22,'DATA BLS Projections'!$A$2:$A$20,'DATA BLS Projections'!$E$2:$E$20),0) -> 0.001474046 | E22: =IFERROR(_xlfn.XLOOKUP(A22,'Projection Assumptions'!$A$13:$A$31,'Projection Assumptions'!$C$13:$C$31),0) -> 0.03 | F22: =IF(C22=2025,_xlfn.XLOOKUP(A22,'01 Industry Model'!$A$5:$A$23,'01 Industry Model'!$C$5:$C$23),F21*(1+D22)*(1+E22)) -> 70.173638 | G22: =IFERROR(_xlfn.XLOOKUP(A22,'Projection Assumptions'!$A$13:$A$31,'Projection Assumptions'!$D$13:$D$31),0) -> 0.05 | H22: =IF(C22=2025,"",IF(C22=2026,_xlfn.XLOOKUP(A22,'DATA Census'!$A$2:$A$20,'DATA Census'!$C$2:$C$20),MIN(1,H21+G22))) -> 0.295 | I22: =MIN(1,MAX(0,_xlfn.XLOOKUP(A22,'01 Industry Model'!$A$5:$A$23,'01 Industry Model'!$H$5:$H$23)+(C22-2025)*_xlfn.XLOOKUP(A22,'Projection Assumptions'!$A$13:$A$31,'Projection Assumptions'!$E$13:$E$31))) -> 0.18131399 | J22: =IF(F22="","",F22*I22) -> 12.723462 | K22: =IF(H22="","",J22*H22) -> 3.7534214 | L22: =IF(C22=2025,IFERROR(_xlfn.XLOOKUP(A22,'DATA QCEW'!$A$2:$A$20,'DATA QCEW'!$F$2:$F$20),""),L21*(1+D22)) -> 1240178.1 | M22: =IF(OR(L22="",I22=""),"",L22*I22) -> 224861.64 | N22: =IF(C22=2025,'Projection Assumptions'!$C$9,N21*(1+'Projection Assumptions'!$C$10)) -> 30 | O22: =IF(OR(M22="",N22=""),"",M22*N22*12/1000000000) -> 0.080950191 | P22: =IF(OR(M22="",H22=""),"",M22*H22) -> 66334.184 | Q22: =IF(OR(P22="",N22=""),"",P22*N22*12/1000000000) -> 0.023880306
A23: 21 | B23: Mining, quarrying, and oil and gas extraction | C23: 2025 | D23: =IFERROR(_xlfn.XLOOKUP(A23,'DATA BLS Projections'!$A$2:$A$20,'DATA BLS Projections'!$E$2:$E$20),0) -> 0.00066063067 | E23: =IFERROR(_xlfn.XLOOKUP(A23,'Projection Assumptions'!$A$13:$A$31,'Projection Assumptions'!$C$13:$C$31),0) -> 0.03 | F23: =IF(C23=2025,_xlfn.XLOOKUP(A23,'01 Industry Model'!$A$5:$A$23,'01 Industry Model'!$C$5:$C$23),F22*(1+D23)*(1+E23)) -> 76.216722 | G23: =IFERROR(_xlfn.XLOOKUP(A23,'Projection Assumptions'!$A$13:$A$31,'Projection Assumptions'!$D$13:$D$31),0) -> 0.05 | H23: =IF(C23=2025,"",IF(C23=2026,_xlfn.XLOOKUP(A23,'DATA Census'!$A$2:$A$20,'DATA Census'!$C$2:$C$20),MIN(1,H22+G23))) | I23: =MIN(1,MAX(0,_xlfn.XLOOKUP(A23,'01 Industry Model'!$A$5:$A$23,'01 Industry Model'!$H$5:$H$23)+(C23-2025)*_xlfn.XLOOKUP(A23,'Projection Assumptions'!$A$13:$A$31,'Projection Assumptions'!$E$13:$E$31))) -> 0.29026433 | J23: =IF(F23="","",F23*I23) -> 22.122996 | K23: =IF(H23="","",J23*H23) | L23: =IF(C23=2025,IFERROR(_xlfn.XLOOKUP(A23,'DATA QCEW'!$A$2:$A$20,'DATA QCEW'!$F$2:$F$20),""),L22*(1+D23)) -> 570806 | M23: =IF(OR(L23="",I23=""),"",L23*I23) -> 165684.62 | N23: =IF(C23=2025,'Projection Assumptions'!$C$9,N22*(1+'Projection Assumptions'!$C$10)) -> 30 | O23: =IF(OR(M23="",N23=""),"",M23*N23*12/1000000000) -> 0.059646464 | P23: =IF(OR(M23="",H23=""),"",M23*H23) | Q23: =IF(OR(P23="",N23=""),"",P23*N23*12/1000000000)
A24: 21 | B24: Mining, quarrying, and oil and gas extraction | C24: 2026 | D24: =IFERROR(_xlfn.XLOOKUP(A24,'DATA BLS Projections'!$A$2:$A$20,'DATA BLS Projections'!$E$2:$E$20),0) -> 0.00066063067 | E24: =IFERROR(_xlfn.XLOOKUP(A24,'Projection Assumptions'!$A$13:$A$31,'Projection Assumptions'!$C$13:$C$31),0) -> 0.03 | F24: =IF(C24=2025,_xlfn.XLOOKUP(A24,'01 Industry Model'!$A$5:$A$23,'01 Industry Model'!$C$5:$C$23),F23*(1+D24)*(1+E24)) -> 78.555085 | G24: =IFERROR(_xlfn.XLOOKUP(A24,'Projection Assumptions'!$A$13:$A$31,'Projection Assumptions'!$D$13:$D$31),0) -> 0.05 | H24: =IF(C24=2025,"",IF(C24=2026,_xlfn.XLOOKUP(A24,'DATA Census'!$A$2:$A$20,'DATA Census'!$C$2:$C$20),MIN(1,H23+G24))) -> 0.13 | I24: =MIN(1,MAX(0,_xlfn.XLOOKUP(A24,'01 Industry Model'!$A$5:$A$23,'01 Industry Model'!$H$5:$H$23)+(C24-2025)*_xlfn.XLOOKUP(A24,'Projection Assumptions'!$A$13:$A$31,'Projection Assumptions'!$E$13:$E$31))) -> 0.29026433 | J24: =IF(F24="","",F24*I24) -> 22.801739 | K24: =IF(H24="","",J24*H24) -> 2.9642261 | L24: =IF(C24=2025,IFERROR(_xlfn.XLOOKUP(A24,'DATA QCEW'!$A$2:$A$20,'DATA QCEW'!$F$2:$F$20),""),L23*(1+D24)) -> 571183.09 | M24: =IF(OR(L24="",I24=""),"",L24*I24) -> 165794.08 | N24: =IF(C24=2025,'Projection Assumptions'!$C$9,N23*(1+'Projection Assumptions'!$C$10)) -> 30 | O24: =IF(OR(M24="",N24=""),"",M24*N24*12/1000000000) -> 0.059685868 | P24: =IF(OR(M24="",H24=""),"",M24*H24) -> 21553.23 | Q24: =IF(OR(P24="",N24=""),"",P24*N24*12/1000000000) -> 0.0077591629
A25: 21 | B25: Mining, quarrying, and oil and gas extraction | C25: 2027 | D25: =IFERROR(_xlfn.XLOOKUP(A25,'DATA BLS Projections'!$A$2:$A$20,'DATA BLS Projections'!$E$2:$E$20),0) -> 0.00066063067 | E25: =IFERROR(_xlfn.XLOOKUP(A25,'Projection Assumptions'!$A$13:$A$31,'Projection Assumptions'!$C$13:$C$31),0) -> 0.03 | F25: =IF(C25=2025,_xlfn.XLOOKUP(A25,'01 Industry Model'!$A$5:$A$23,'01 Industry Model'!$C$5:$C$23),F24*(1+D25)*(1+E25)) -> 80.965191 | G25: =IFERROR(_xlfn.XLOOKUP(A25,'Projection Assumptions'!$A$13:$A$31,'Projection Assumptions'!$D$13:$D$31),0) -> 0.05 | H25: =IF(C25=2025,"",IF(C25=2026,_xlfn.XLOOKUP(A25,'DATA Census'!$A$2:$A$20,'DATA Census'!$C$2:$C$20),MIN(1,H24+G25))) -> 0.18 | I25: =MIN(1,MAX(0,_xlfn.XLOOKUP(A25,'01 Industry Model'!$A$5:$A$23,'01 Industry Model'!$H$5:$H$23)+(C25-2025)*_xlfn.XLOOKUP(A25,'Projection Assumptions'!$A$13:$A$31,'Projection Assumptions'!$E$13:$E$31))) -> 0.29026433 | J25: =IF(F25="","",F25*I25) -> 23.501307 | K25: =IF(H25="","",J25*H25) -> 4.2302352 | L25: =IF(C25=2025,IFERROR(_xlfn.XLOOKUP(A25,'DATA QCEW'!$A$2:$A$20,'DATA QCEW'!$F$2:$F$20),""),L24*(1+D25)) -> 571560.43 | M25: =IF(OR(L25="",I25=""),"",L25*I25) -> 165903.61 | N25: =IF(C25=2025,'Projection Assumptions'!$C$9,N24*(1+'Projection Assumptions'!$C$10)) -> 30 | O25: =IF(OR(M25="",N25=""),"",M25*N25*12/1000000000) -> 0.059725298 | P25: =IF(OR(M25="",H25=""),"",M25*H25) -> 29862.649 | Q25: =IF(OR(P25="",N25=""),"",P25*N25*12/1000000000) -> 0.010750554
A26: 21 | B26: Mining, quarrying, and oil and gas extraction | C26: 2028 | D26: =IFERROR(_xlfn.XLOOKUP(A26,'DATA BLS Projections'!$A$2:$A$20,'DATA BLS Projections'!$E$2:$E$20),0) -> 0.00066063067 | E26: =IFERROR(_xlfn.XLOOKUP(A26,'Projection Assumptions'!$A$13:$A$31,'Projection Assumptions'!$C$13:$C$31),0) -> 0.03 | F26: =IF(C26=2025,_xlfn.XLOOKUP(A26,'01 Industry Model'!$A$5:$A$23,'01 Industry Model'!$C$5:$C$23),F25*(1+D26)*(1+E26)) -> 83.449239 | G26: =IFERROR(_xlfn.XLOOKUP(A26,'Projection Assumptions'!$A$13:$A$31,'Projection Assumptions'!$D$13:$D$31),0) -> 0.05 | H26: =IF(C26=2025,"",IF(C26=2026,_xlfn.XLOOKUP(A26,'DATA Census'!$A$2:$A$20,'DATA Census'!$C$2:$C$20),MIN(1,H25+G26))) -> 0.23 | I26: =MIN(1,MAX(0,_xlfn.XLOOKUP(A26,'01 Industry Model'!$A$5:$A$23,'01 Industry Model'!$H$5:$H$23)+(C26-2025)*_xlfn.XLOOKUP(A26,'Projection Assumptions'!$A$13:$A$31,'Projection Assumptions'!$E$13:$E$31))) -> 0.29026433 | J26: =IF(F26="","",F26*I26) -> 24.222338 | K26: =IF(H26="","",J26*H26) -> 5.5711376 | L26: =IF(C26=2025,IFERROR(_xlfn.XLOOKUP(A26,'DATA QCEW'!$A$2:$A$20,'DATA QCEW'!$F$2:$F$20),""),L25*(1+D26)) -> 571938.02 | M26: =IF(OR(L26="",I26=""),"",L26*I26) -> 166013.21 | N26: =IF(C26=2025,'Projection Assumptions'!$C$9,N25*(1+'Projection Assumptions'!$C$10)) -> 30 | O26: =IF(OR(M26="",N26=""),"",M26*N26*12/1000000000) -> 0.059764755 | P26: =IF(OR(M26="",H26=""),"",M26*H26) -> 38183.038 | Q26: =IF(OR(P26="",N26=""),"",P26*N26*12/1000000000) -> 0.013745894
A27: 21 | B27: Mining, quarrying, and oil and gas extraction | C27: 2029 | D27: =IFERROR(_xlfn.XLOOKUP(A27,'DATA BLS Projections'!$A$2:$A$20,'DATA BLS Projections'!$E$2:$E$20),0) -> 0.00066063067 | E27: =IFERROR(_xlfn.XLOOKUP(A27,'Projection Assumptions'!$A$13:$A$31,'Projection Assumptions'!$C$13:$C$31),0) -> 0.03 | F27: =IF(C27=2025,_xlfn.XLOOKUP(A27,'01 Industry Model'!$A$5:$A$23,'01 Industry Model'!$C$5:$C$23),F26*(1+D27)*(1+E27)) -> 86.009499 | G27: =IFERROR(_xlfn.XLOOKUP(A27,'Projection Assumptions'!$A$13:$A$31,'Projection Assumptions'!$D$13:$D$31),0) -> 0.05 | H27: =IF(C27=2025,"",IF(C27=2026,_xlfn.XLOOKUP(A27,'DATA Census'!$A$2:$A$20,'DATA Census'!$C$2:$C$20),MIN(1,H26+G27))) -> 0.28 | I27: =MIN(1,MAX(0,_xlfn.XLOOKUP(A27,'01 Industry Model'!$A$5:$A$23,'01 Industry Model'!$H$5:$H$23)+(C27-2025)*_xlfn.XLOOKUP(A27,'Projection Assumptions'!$A$13:$A$31,'Projection Assumptions'!$E$13:$E$31))) -> 0.29026433 | J27: =IF(F27="","",F27*I27) -> 24.96549 | K27: =IF(H27="","",J27*H27) -> 6.9903371 | L27: =IF(C27=2025,IFERROR(_xlfn.XLOOKUP(A27,'DATA QCEW'!$A$2:$A$20,'DATA QCEW'!$F$2:$F$20),""),L26*(1+D27)) -> 572315.86 | M27: =IF(OR(L27="",I27=""),"",L27*I27) -> 166122.88 | N27: =IF(C27=2025,'Projection Assumptions'!$C$9,N26*(1+'Projection Assumptions'!$C$10)) -> 30 | O27: =IF(OR(M27="",N27=""),"",M27*N27*12/1000000000) -> 0.059804237 | P27: =IF(OR(M27="",H27=""),"",M27*H27) -> 46514.407 | Q27: =IF(OR(P27="",N27=""),"",P27*N27*12/1000000000) -> 0.016745186
A28: 21 | B28: Mining, quarrying, and oil and gas extraction | C28: 2030 | D28: =IFERROR(_xlfn.XLOOKUP(A28,'DATA BLS Projections'!$A$2:$A$20,'DATA BLS Projections'!$E$2:$E$20),0) -> 0.00066063067 | E28: =IFERROR(_xlfn.XLOOKUP(A28,'Projection Assumptions'!$A$13:$A$31,'Projection Assumptions'!$C$13:$C$31),0) -> 0.03 | F28: =IF(C28=2025,_xlfn.XLOOKUP(A28,'01 Industry Model'!$A$5:$A$23,'01 Industry Model'!$C$5:$C$23),F27*(1+D28)*(1+E28)) -> 88.648309 | G28: =IFERROR(_xlfn.XLOOKUP(A28,'Projection Assumptions'!$A$13:$A$31,'Projection Assumptions'!$D$13:$D$31),0) -> 0.05 | H28: =IF(C28=2025,"",IF(C28=2026,_xlfn.XLOOKUP(A28,'DATA Census'!$A$2:$A$20,'DATA Census'!$C$2:$C$20),MIN(1,H27+G28))) -> 0.33 | I28: =MIN(1,MAX(0,_xlfn.XLOOKUP(A28,'01 Industry Model'!$A$5:$A$23,'01 Industry Model'!$H$5:$H$23)+(C28-2025)*_xlfn.XLOOKUP(A28,'Projection Assumptions'!$A$13:$A$31,'Projection Assumptions'!$E$13:$E$31))) -> 0.29026433 | J28: =IF(F28="","",F28*I28) -> 25.731442 | K28: =IF(H28="","",J28*H28) -> 8.4913759 | L28: =IF(C28=2025,IFERROR(_xlfn.XLOOKUP(A28,'DATA QCEW'!$A$2:$A$20,'DATA QCEW'!$F$2:$F$20),""),L27*(1+D28)) -> 572693.95 | M28: =IF(OR(L28="",I28=""),"",L28*I28) -> 166232.63 | N28: =IF(C28=2025,'Projection Assumptions'!$C$9,N27*(1+'Projection Assumptions'!$C$10)) -> 30 | O28: =IF(OR(M28="",N28=""),"",M28*N28*12/1000000000) -> 0.059843746 | P28: =IF(OR(M28="",H28=""),"",M28*H28) -> 54856.767 | Q28: =IF(OR(P28="",N28=""),"",P28*N28*12/1000000000) -> 0.019748436
... A130: 81 | B130: Other services (except public administration) | C130: 2030 | D130: =IFERROR(_xlfn.XLOOKUP(A130,'DATA BLS Projections'!$A$2:$A$20,'DATA BLS Projections'!$E$2:$E$20),0) -> 0.003692761 | E130: =IFERROR(_xlfn.XLOOKUP(A130,'Projection Assumptions'!$A$13:$A$31,'Projection Assumptions'!$C$13:$C$31),0) -> 0.03 | F130: =IF(C130=2025,_xlfn.XLOOKUP(A130,'01 Industry Model'!$A$5:$A$23,'01 Industry Model'!$C$5:$C$23),F129*(1+D130)*(1+E130)) -> 300.4864 | G130: =IFERROR(_xlfn.XLOOKUP(A130,'Projection Assumptions'!$A$13:$A$31,'Projection Assumptions'!$D$13:$D$31),0) -> 0.05 | H130: =IF(C130=2025,"",IF(C130=2026,_xlfn.XLOOKUP(A130,'DATA Census'!$A$2:$A$20,'DATA Census'!$C$2:$C$20),MIN(1,H129+G130))) -> 0.327 | I130: =MIN(1,MAX(0,_xlfn.XLOOKUP(A130,'01 Industry Model'!$A$5:$A$23,'01 Industry Model'!$H$5:$H$23)+(C130-2025)*_xlfn.XLOOKUP(A130,'Projection Assumptions'!$A$13:$A$31,'Projection Assumptions'!$E$13:$E$31))) -> 0.36161599 | J130: =IF(F130="","",F130*I130) -> 108.66069 | K130: =IF(H130="","",J130*H130) -> 35.532045 | L130: =IF(C130=2025,IFERROR(_xlfn.XLOOKUP(A130,'DATA QCEW'!$A$2:$A$20,'DATA QCEW'!$F$2:$F$20),""),L129*(1+D130)) -> 4762854.5 | M130: =IF(OR(L130="",I130=""),"",L130*I130) -> 1722324.4 | N130: =IF(C130=2025,'Projection Assumptions'!$C$9,N129*(1+'Projection Assumptions'!$C$10)) -> 30 | O130: =IF(OR(M130="",N130=""),"",M130*N130*12/1000000000) -> 0.62003678 | P130: =IF(OR(M130="",H130=""),"",M130*H130) -> 563200.07 | Q130: =IF(OR(P130="",N130=""),"",P130*N130*12/1000000000) -> 0.20275203

Sheet DATA QCEW
A1: NAICS (TEXT) | B1: Industry | C1: 2025 Private Annual Wages ($) | D1: Raw rows with this NAICS | E1: Data Check | F1: 2025 Private Avg Employment
A2: 11 | B2: Agriculture, forestry, fishing and hunting | C2: =IF(D2=1,_xlfn.XLOOKUP(A2,'DATA QCEW Raw'!$E$2:$E$3000,'DATA QCEW Raw'!$D$2:$D$3000),"") -> 60088224865 | D2: =COUNTIF('DATA QCEW Raw'!$E$2:$E$3000,A2) -> 1 | E2: =IF(D2=1,"OK",IF(D2=0,"MISSING","DUPLICATE")) -> OK | F2: =IF(D2=1,_xlfn.XLOOKUP(A2,'DATA QCEW Raw'!$E$2:$E$3000,'DATA QCEW Raw'!$C$2:$C$3000),"") -> 1231078
A3: 21 | B3: Mining, quarrying, and oil and gas extraction | C3: =IF(D3=1,_xlfn.XLOOKUP(A3,'DATA QCEW Raw'!$E$2:$E$3000,'DATA QCEW Raw'!$D$2:$D$3000),"") -> 76216722054 | D3: =COUNTIF('DATA QCEW Raw'!$E$2:$E$3000,A3) -> 1 | E3: =IF(D3=1,"OK",IF(D3=0,"MISSING","DUPLICATE")) -> OK | F3: =IF(D3=1,_xlfn.XLOOKUP(A3,'DATA QCEW Raw'!$E$2:$E$3000,'DATA QCEW Raw'!$C$2:$C$3000),"") -> 570806
A4: 22 | B4: Utilities | C4: =IF(D4=1,_xlfn.XLOOKUP(A4,'DATA QCEW Raw'!$E$2:$E$3000,'DATA QCEW Raw'!$D$2:$D$3000),"") -> 85024861666 | D4: =COUNTIF('DATA QCEW Raw'!$E$2:$E$3000,A4) -> 1 | E4: =IF(D4=1,"OK",IF(D4=0,"MISSING","DUPLICATE")) -> OK | F4: =IF(D4=1,_xlfn.XLOOKUP(A4,'DATA QCEW Raw'!$E$2:$E$3000,'DATA QCEW Raw'!$C$2:$C$3000),"") -> 602080
A5: 23 | B5: Construction | C5: =IF(D5=1,_xlfn.XLOOKUP(A5,'DATA QCEW Raw'!$E$2:$E$3000,'DATA QCEW Raw'!$D$2:$D$3000),"") -> 699896249139 | D5: =COUNTIF('DATA QCEW Raw'!$E$2:$E$3000,A5) -> 1 | E5: =IF(D5=1,"OK",IF(D5=0,"MISSING","DUPLICATE")) -> OK | F5: =IF(D5=1,_xlfn.XLOOKUP(A5,'DATA QCEW Raw'!$E$2:$E$3000,'DATA QCEW Raw'!$C$2:$C$3000),"") -> 8251002
A6: 31-33 | B6: Manufacturing | C6: =IF(D6=1,_xlfn.XLOOKUP(A6,'DATA QCEW Raw'!$E$2:$E$3000,'DATA QCEW Raw'!$D$2:$D$3000),"") -> 1125542676332 | D6: =COUNTIF('DATA QCEW Raw'!$E$2:$E$3000,A6) -> 1 | E6: =IF(D6=1,"OK",IF(D6=0,"MISSING","DUPLICATE")) -> OK | F6: =IF(D6=1,_xlfn.XLOOKUP(A6,'DATA QCEW Raw'!$E$2:$E$3000,'DATA QCEW Raw'!$C$2:$C$3000),"") -> 12579906
A7: 42 | B7: Wholesale trade | C7: =IF(D7=1,_xlfn.XLOOKUP(A7,'DATA QCEW Raw'!$E$2:$E$3000,'DATA QCEW Raw'!$D$2:$D$3000),"") -> 638878973832 | D7: =COUNTIF('DATA QCEW Raw'!$E$2:$E$3000,A7) -> 1 | E7: =IF(D7=1,"OK",IF(D7=0,"MISSING","DUPLICATE")) -> OK | F7: =IF(D7=1,_xlfn.XLOOKUP(A7,'DATA QCEW Raw'!$E$2:$E$3000,'DATA QCEW Raw'!$C$2:$C$3000),"") -> 6037213
A8: 44-45 | B8: Retail trade | C8: =IF(D8=1,_xlfn.XLOOKUP(A8,'DATA QCEW Raw'!$E$2:$E$3000,'DATA QCEW Raw'!$D$2:$D$3000),"") -> 668863568474 | D8: =COUNTIF('DATA QCEW Raw'!$E$2:$E$3000,A8) -> 1 | E8: =IF(D8=1,"OK",IF(D8=0,"MISSING","DUPLICATE")) -> OK | F8: =IF(D8=1,_xlfn.XLOOKUP(A8,'DATA QCEW Raw'!$E$2:$E$3000,'DATA QCEW Raw'!$C$2:$C$3000),"") -> 15391082
A9: 48-49 | B9: Transportation and warehousing | C9: =IF(D9=1,_xlfn.XLOOKUP(A9,'DATA QCEW Raw'!$E$2:$E$3000,'DATA QCEW Raw'!$D$2:$D$3000),"") -> 455483942924 | D9: =COUNTIF('DATA QCEW Raw'!$E$2:$E$3000,A9) -> 1 | E9: =IF(D9=1,"OK",IF(D9=0,"MISSING","DUPLICATE")) -> OK | F9: =IF(D9=1,_xlfn.XLOOKUP(A9,'DATA QCEW Raw'!$E$2:$E$3000,'DATA QCEW Raw'!$C$2:$C$3000),"") -> 6618917
A10: 51 | B10: Information | C10: =IF(D10=1,_xlfn.XLOOKUP(A10,'DATA QCEW Raw'!$E$2:$E$3000,'DATA QCEW Raw'!$D$2:$D$3000),"") -> 544469565204 | D10: =COUNTIF('DATA QCEW Raw'!$E$2:$E$3000,A10) -> 1 | E10: =IF(D10=1,"OK",IF(D10=0,"MISSING","DUPLICATE")) -> OK | F10: =IF(D10=1,_xlfn.XLOOKUP(A10,'DATA QCEW Raw'!$E$2:$E$3000,'DATA QCEW Raw'!$C$2:$C$3000),"") -> 2850904
A11: 52 | B11: Finance and insurance | C11: =IF(D11=1,_xlfn.XLOOKUP(A11,'DATA QCEW Raw'!$E$2:$E$3000,'DATA QCEW Raw'!$D$2:$D$3000),"") -> 966666752201 | D11: =COUNTIF('DATA QCEW Raw'!$E$2:$E$3000,A11) -> 1 | E11: =IF(D11=1,"OK",IF(D11=0,"MISSING","DUPLICATE")) -> OK | F11: =IF(D11=1,_xlfn.XLOOKUP(A11,'DATA QCEW Raw'!$E$2:$E$3000,'DATA QCEW Raw'!$C$2:$C$3000),"") -> 6316381
A12: 53 | B12: Real estate and rental and leasing | C12: =IF(D12=1,_xlfn.XLOOKUP(A12,'DATA QCEW Raw'!$E$2:$E$3000,'DATA QCEW Raw'!$D$2:$D$3000),"") -> 193529178704 | D12: =COUNTIF('DATA QCEW Raw'!$E$2:$E$3000,A12) -> 1 | E12: =IF(D12=1,"OK",IF(D12=0,"MISSING","DUPLICATE")) -> OK | F12: =IF(D12=1,_xlfn.XLOOKUP(A12,'DATA QCEW Raw'!$E$2:$E$3000,'DATA QCEW Raw'!$C$2:$C$3000),"") -> 2411118
A13: 54 | B13: Professional, scientific, and technical services | C13: =IF(D13=1,_xlfn.XLOOKUP(A13,'DATA QCEW Raw'!$E$2:$E$3000,'DATA QCEW Raw'!$D$2:$D$3000),"") -> 1454390668355 | D13: =COUNTIF('DATA QCEW Raw'!$E$2:$E$3000,A13) -> 1 | E13: =IF(D13=1,"OK",IF(D13=0,"MISSING","DUPLICATE")) -> OK | F13: =IF(D13=1,_xlfn.XLOOKUP(A13,'DATA QCEW Raw'!$E$2:$E$3000,'DATA QCEW Raw'!$C$2:$C$3000),"") -> 10750955
... A20: 81 | B20: Other services (except public administration) | C20: =IF(D20=1,_xlfn.XLOOKUP(A20,'DATA QCEW Raw'!$E$2:$E$3000,'DATA QCEW Raw'!$D$2:$D$3000),"") -> 254468914292 | D20: =COUNTIF('DATA QCEW Raw'!$E$2:$E$3000,A20) -> 1 | E20: =IF(D20=1,"OK",IF(D20=0,"MISSING","DUPLICATE")) -> OK | F20: =IF(D20=1,_xlfn.XLOOKUP(A20,'DATA QCEW Raw'!$E$2:$E$3000,'DATA QCEW Raw'!$C$2:$C$3000),"") -> 4675880
A23: TOTAL 19 INDUSTRIES | C23: =SUM(C2:C20) -> 10515645524505
A24: NAICS 99 UNCLASSIFIED | C24: =IFERROR(_xlfn.XLOOKUP("99",'DATA QCEW Raw'!$E$2:$E$3000,'DATA QCEW Raw'!$D$2:$D$3000),"") -> 16545877587
A25: US PRIVATE TOTAL | C25: 10532191402092
A26: RECONCILIATION GAP (SHOULD BE 0) | C26: =IF(C24="","",C23+C24-C25) -> 0

Sheet Projection Assumptions
A1: PROJECTION ASSUMPTIONS | BLUE = EDITABLE
A2: Nominal wage growth, BTOS firm adoption and task exposure expansion are illustrative assumptions, not official forecasts.
B5: Annual nominal wage growth per employee | C5: 0.03 | D5: Illustrative wage assumption (not BLS official forecast)
B6: Annual AI-using firm growth (percentage points) | C6: 0.05 | D6: Linear adoption increase after observed 2026, capped at 100%
B7: Annual task exposure increase (percentage points) | C7: 0 | D7: Keep Wharton task exposure unchanged by default
B9: Enterprise AI monthly spend / seat ($) | C9: 30 | D9: Illustrative price assumption; editable by user. Not BLS or Census data.
B10: Annual AI spend per seat growth | C10: 0 | D10: Illustrative nominal seat price inflation after 2025.
B11: Revenue interpretation | D11: Wharton is task exposure, NOT share of workers using AI. Revenue is a seat-equivalent scenario, not measured AI sales.
A12: NAICS (TEXT) | B12: Industry | C12: Wage Growth per Year | D12: AI Adoption Change (pp) | E12: AI Task Exposure Change (pp) | F12: Use / Override
A13: 11 | B13: Agriculture, forestry, fishing and hunting | C13: =$C$5 -> 0.03 | D13: =$C$6 -> 0.05 | E13: =$C$7 -> 0 | F13: Override C:E for sector-specific scenario
A14: 21 | B14: Mining, quarrying, and oil and gas extraction | C14: =$C$5 -> 0.03 | D14: =$C$6 -> 0.05 | E14: =$C$7 -> 0 | F14: Override C:E for sector-specific scenario
A15: 22 | B15: Utilities | C15: =$C$5 -> 0.03 | D15: =$C$6 -> 0.05 | E15: =$C$7 -> 0 | F15: Override C:E for sector-specific scenario
A16: 23 | B16: Construction | C16: =$C$5 -> 0.03 | D16: =$C$6 -> 0.05 | E16: =$C$7 -> 0 | F16: Override C:E for sector-specific scenario
A17: 31-33 | B17: Manufacturing | C17: =$C$5 -> 0.03 | D17: =$C$6 -> 0.05 | E17: =$C$7 -> 0 | F17: Override C:E for sector-specific scenario
A18: 42 | B18: Wholesale trade | C18: =$C$5 -> 0.03 | D18: =$C$6 -> 0.05 | E18: =$C$7 -> 0 | F18: Override C:E for sector-specific scenario
A19: 44-45 | B19: Retail trade | C19: =$C$5 -> 0.03 | D19: =$C$6 -> 0.05 | E19: =$C$7 -> 0 | F19: Override C:E for sector-specific scenario
A20: 48-49 | B20: Transportation and warehousing | C20: =$C$5 -> 0.03 | D20: =$C$6 -> 0.05 | E20: =$C$7 -> 0 | F20: Override C:E for sector-specific scenario
A21: 51 | B21: Information | C21: =$C$5 -> 0.03 | D21: =$C$6 -> 0.05 | E21: =$C$7 -> 0 | F21: Override C:E for sector-specific scenario
A22: 52 | B22: Finance and insurance | C22: =$C$5 -> 0.03 | D22: =$C$6 -> 0.05 | E22: =$C$7 -> 0 | F22: Override C:E for sector-specific scenario
A23: 53 | B23: Real estate and rental and leasing | C23: =$C$5 -> 0.03 | D23: =$C$6 -> 0.05 | E23: =$C$7 -> 0 | F23: Override C:E for sector-specific scenario
A24: 54 | B24: Professional, scientific, and technical services | C24: =$C$5 -> 0.03 | D24: =$C$6 -> 0.05 | E24: =$C$7 -> 0 | F24: Override C:E for sector-specific scenario
... A31: 81 | B31: Other services (except public administration) | C31: =$C$5 -> 0.03 | D31: =$C$6 -> 0.05 | E31: =$C$7 -> 0 | F31: Override C:E for sector-specific scenario

Sheet DATA BLS Projections
A1: NAICS (TEXT) | B1: Industry | C1: 2025 Employed (000s) | D1: 2035 Employed (000s) | E1: BLS Annual Employment CAGR [FORMULA] | F1: Sector mapping / notes
A2: 11 | B2: Agriculture, forestry, fishing and hunting | C2: 1462.4 | D2: 1484.1 | E2: =IF(OR(C2="",D2=""),"",(D2/C2)^(1/10)-1) -> 0.001474046 | F2: Corresponding private-sector NAICS major sector; rounded BLS 2025 & 2035 employment
A3: 21 | B3: Mining, quarrying, and oil and gas extraction | C3: 573.5 | D3: 577.3 | E3: =IF(OR(C3="",D3=""),"",(D3/C3)^(1/10)-1) -> 0.00066063067 | F3: Corresponding private-sector NAICS major sector; rounded BLS 2025 & 2035 employment
A4: 22 | B4: Utilities | C4: 601.3 | D4: 660.1 | E4: =IF(OR(C4="",D4=""),"",(D4/C4)^(1/10)-1) -> 0.0093733937 | F4: Corresponding private-sector NAICS major sector; rounded BLS 2025 & 2035 employment
A5: 23 | B5: Construction | C5: 8266.7 | D5: 8677.4 | E5: =IF(OR(C5="",D5=""),"",(D5/C5)^(1/10)-1) -> 0.0048604285 | F5: Corresponding private-sector NAICS major sector; rounded BLS 2025 & 2035 employment
A6: 31-33 | B6: Manufacturing | C6: 12633.7 | D6: 12705.8 | E6: =IF(OR(C6="",D6=""),"",(D6/C6)^(1/10)-1) -> 0.00056923549 | F6: Corresponding private-sector NAICS major sector; rounded BLS 2025 & 2035 employment
A7: 42 | B7: Wholesale trade | C7: 6059.5 | D7: 6184.7 | E7: =IF(OR(C7="",D7=""),"",(D7/C7)^(1/10)-1) -> 0.0020472139 | F7: Corresponding private-sector NAICS major sector; rounded BLS 2025 & 2035 employment
A8: 44-45 | B8: Retail trade | C8: 15440.9 | D8: 15413.4 | E8: =IF(OR(C8="",D8=""),"",(D8/C8)^(1/10)-1) -> -0.00017824132 | F8: Corresponding private-sector NAICS major sector; rounded BLS 2025 & 2035 employment
A9: 48-49 | B9: Transportation and warehousing | C9: 6639.5 | D9: 6846.8 | E9: =IF(OR(C9="",D9=""),"",(D9/C9)^(1/10)-1) -> 0.0030792041 | F9: BLS transportation excludes postal service; minor NAICS scope mismatch
A10: 51 | B10: Information | C10: 2861.9 | D10: 3012.9 | E10: =IF(OR(C10="",D10=""),"",(D10/C10)^(1/10)-1) -> 0.0051549744 | F10: Corresponding private-sector NAICS major sector; rounded BLS 2025 & 2035 employment
A11: 52 | B11: Finance and insurance | C11: 6739.3 | D11: 6893.6 | E11: =IF(OR(C11="",D11=""),"",(D11/C11)^(1/10)-1) -> 0.0022663025 | F11: Corresponding private-sector NAICS major sector; rounded BLS 2025 & 2035 employment
A12: 53 | B12: Real estate and rental and leasing | C12: 2456.7 | D12: 2539.7 | E12: =IF(OR(C12="",D12=""),"",(D12/C12)^(1/10)-1) -> 0.0033282241 | F12: Corresponding private-sector NAICS major sector; rounded BLS 2025 & 2035 employment
A13: 54 | B13: Professional, scientific, and technical services | C13: 10779.2 | D13: 11705.9 | E13: =IF(OR(C13="",D13=""),"",(D13/C13)^(1/10)-1) -> 0.0082815677 | F13: Corresponding private-sector NAICS major sector; rounded BLS 2025 & 2035 employment
... A20: 81 | B20: Other services (except public administration) | C20: 6575.7 | D20: 6822.6 | E20: =IF(OR(C20="",D20=""),"",(D20/C20)^(1/10)-1) -> 0.003692761 | F20: Corresponding private-sector NAICS major sector; rounded BLS 2025 & 2035 employment

Sheet DATA QCEW Raw
A1: Industry (paste BLS raw) | B1: Annual Establishments (optional) | C1: 2025 Private Avg Employment (BLS QCEW) | D1: Total Annual Wages ($) | E1: NAICS code [FORMULA] | F1: Industry title [FORMULA] | G1: Sector classification [FORMULA]
A2: NAICS 11 Agriculture, forestry, fishing and hunting | C2: 1231078 | D2: 60088224865 | E2: =IF(LEFT(TRIM(A2),6)="NAICS ",IFERROR(MID(TRIM(A2),7,FIND(" ",TRIM(A2)&" ",7)-7),""),"") -> 11 | F2: =IF(E2="","",TRIM(MID(TRIM(A2),FIND(" ",TRIM(A2)&" ",7)+1,255))) -> Agriculture, forestry, fishing and hunting | G2: =IF(E2="","",IF(COUNTIF('DATA QCEW'!$A$2:$A$20,E2)>0,"19-SECTOR","DETAIL / OTHER")) -> 19-SECTOR
A3: NAICS 21 Mining, quarrying, and oil and gas extraction | C3: 570806 | D3: 76216722054 | E3: =IF(LEFT(TRIM(A3),6)="NAICS ",IFERROR(MID(TRIM(A3),7,FIND(" ",TRIM(A3)&" ",7)-7),""),"") -> 21 | F3: =IF(E3="","",TRIM(MID(TRIM(A3),FIND(" ",TRIM(A3)&" ",7)+1,255))) -> Mining, quarrying, and oil and gas extraction | G3: =IF(E3="","",IF(COUNTIF('DATA QCEW'!$A$2:$A$20,E3)>0,"19-SECTOR","DETAIL / OTHER")) -> 19-SECTOR
A4: NAICS 22 Utilities | C4: 602080 | D4: 85024861666 | E4: =IF(LEFT(TRIM(A4),6)="NAICS ",IFERROR(MID(TRIM(A4),7,FIND(" ",TRIM(A4)&" ",7)-7),""),"") -> 22 | F4: =IF(E4="","",TRIM(MID(TRIM(A4),FIND(" ",TRIM(A4)&" ",7)+1,255))) -> Utilities | G4: =IF(E4="","",IF(COUNTIF('DATA QCEW'!$A$2:$A$20,E4)>0,"19-SECTOR","DETAIL / OTHER")) -> 19-SECTOR
A5: NAICS 23 Construction | C5: 8251002 | D5: 699896249139 | E5: =IF(LEFT(TRIM(A5),6)="NAICS ",IFERROR(MID(TRIM(A5),7,FIND(" ",TRIM(A5)&" ",7)-7),""),"") -> 23 | F5: =IF(E5="","",TRIM(MID(TRIM(A5),FIND(" ",TRIM(A5)&" ",7)+1,255))) -> Construction | G5: =IF(E5="","",IF(COUNTIF('DATA QCEW'!$A$2:$A$20,E5)>0,"19-SECTOR","DETAIL / OTHER")) -> 19-SECTOR
A6: NAICS 31-33 Manufacturing | C6: 12579906 | D6: 1125542676332 | E6: =IF(LEFT(TRIM(A6),6)="NAICS ",IFERROR(MID(TRIM(A6),7,FIND(" ",TRIM(A6)&" ",7)-7),""),"") -> 31-33 | F6: =IF(E6="","",TRIM(MID(TRIM(A6),FIND(" ",TRIM(A6)&" ",7)+1,255))) -> Manufacturing | G6: =IF(E6="","",IF(COUNTIF('DATA QCEW'!$A$2:$A$20,E6)>0,"19-SECTOR","DETAIL / OTHER")) -> 19-SECTOR
A7: NAICS 42 Wholesale trade | C7: 6037213 | D7: 638878973832 | E7: =IF(LEFT(TRIM(A7),6)="NAICS ",IFERROR(MID(TRIM(A7),7,FIND(" ",TRIM(A7)&" ",7)-7),""),"") -> 42 | F7: =IF(E7="","",TRIM(MID(TRIM(A7),FIND(" ",TRIM(A7)&" ",7)+1,255))) -> Wholesale trade | G7: =IF(E7="","",IF(COUNTIF('DATA QCEW'!$A$2:$A$20,E7)>0,"19-SECTOR","DETAIL / OTHER")) -> 19-SECTOR
A8: NAICS 44-45 Retail trade | C8: 15391082 | D8: 668863568474 | E8: =IF(LEFT(TRIM(A8),6)="NAICS ",IFERROR(MID(TRIM(A8),7,FIND(" ",TRIM(A8)&" ",7)-7),""),"") -> 44-45 | F8: =IF(E8="","",TRIM(MID(TRIM(A8),FIND(" ",TRIM(A8)&" ",7)+1,255))) -> Retail trade | G8: =IF(E8="","",IF(COUNTIF('DATA QCEW'!$A$2:$A$20,E8)>0,"19-SECTOR","DETAIL / OTHER")) -> 19-SECTOR
A9: NAICS 48-49 Transportation and warehousing | C9: 6618917 | D9: 455483942924 | E9: =IF(LEFT(TRIM(A9),6)="NAICS ",IFERROR(MID(TRIM(A9),7,FIND(" ",TRIM(A9)&" ",7)-7),""),"") -> 48-49 | F9: =IF(E9="","",TRIM(MID(TRIM(A9),FIND(" ",TRIM(A9)&" ",7)+1,255))) -> Transportation and warehousing | G9: =IF(E9="","",IF(COUNTIF('DATA QCEW'!$A$2:$A$20,E9)>0,"19-SECTOR","DETAIL / OTHER")) -> 19-SECTOR
A10: NAICS 51 Information | C10: 2850904 | D10: 544469565204 | E10: =IF(LEFT(TRIM(A10),6)="NAICS ",IFERROR(MID(TRIM(A10),7,FIND(" ",TRIM(A10)&" ",7)-7),""),"") -> 51 | F10: =IF(E10="","",TRIM(MID(TRIM(A10),FIND(" ",TRIM(A10)&" ",7)+1,255))) -> Information | G10: =IF(E10="","",IF(COUNTIF('DATA QCEW'!$A$2:$A$20,E10)>0,"19-SECTOR","DETAIL / OTHER")) -> 19-SECTOR
A11: NAICS 52 Finance and insurance | C11: 6316381 | D11: 966666752201 | E11: =IF(LEFT(TRIM(A11),6)="NAICS ",IFERROR(MID(TRIM(A11),7,FIND(" ",TRIM(A11)&" ",7)-7),""),"") -> 52 | F11: =IF(E11="","",TRIM(MID(TRIM(A11),FIND(" ",TRIM(A11)&" ",7)+1,255))) -> Finance and insurance | G11: =IF(E11="","",IF(COUNTIF('DATA QCEW'!$A$2:$A$20,E11)>0,"19-SECTOR","DETAIL / OTHER")) -> 19-SECTOR
A12: NAICS 53 Real estate and rental and leasing | C12: 2411118 | D12: 193529178704 | E12: =IF(LEFT(TRIM(A12),6)="NAICS ",IFERROR(MID(TRIM(A12),7,FIND(" ",TRIM(A12)&" ",7)-7),""),"") -> 53 | F12: =IF(E12="","",TRIM(MID(TRIM(A12),FIND(" ",TRIM(A12)&" ",7)+1,255))) -> Real estate and rental and leasing | G12: =IF(E12="","",IF(COUNTIF('DATA QCEW'!$A$2:$A$20,E12)>0,"19-SECTOR","DETAIL / OTHER")) -> 19-SECTOR
A13: NAICS 54 Professional, scientific, and technical services | C13: 10750955 | D13: 1454390668355 | E13: =IF(LEFT(TRIM(A13),6)="NAICS ",IFERROR(MID(TRIM(A13),7,FIND(" ",TRIM(A13)&" ",7)-7),""),"") -> 54 | F13: =IF(E13="","",TRIM(MID(TRIM(A13),FIND(" ",TRIM(A13)&" ",7)+1,255))) -> Professional, scientific, and technical services | G13: =IF(E13="","",IF(COUNTIF('DATA QCEW'!$A$2:$A$20,E13)>0,"19-SECTOR","DETAIL / OTHER")) -> 19-SECTOR
... A20: NAICS 81 Other services (except public administration) | C20: 4675880 | D20: 254468914292 | E20: =IF(LEFT(TRIM(A20),6)="NAICS ",IFERROR(MID(TRIM(A20),7,FIND(" ",TRIM(A20)&" ",7)-7),""),"") -> 81 | F20: =IF(E20="","",TRIM(MID(TRIM(A20),FIND(" ",TRIM(A20)&" ",7)+1,255))) -> Other services (except public administration) | G20: =IF(E20="","",IF(COUNTIF('DATA QCEW'!$A$2:$A$20,E20)>0,"19-SECTOR","DETAIL / OTHER")) -> 19-SECTOR
A21: NAICS 99 Unclassified | D21: 16545877587 | E21: =IF(LEFT(TRIM(A21),6)="NAICS ",IFERROR(MID(TRIM(A21),7,FIND(" ",TRIM(A21)&" ",7)-7),""),"") -> 99 | F21: =IF(E21="","",TRIM(MID(TRIM(A21),FIND(" ",TRIM(A21)&" ",7)+1,255))) -> Unclassified | G21: =IF(E21="","",IF(COUNTIF('DATA QCEW'!$A$2:$A$20,E21)>0,"19-SECTOR","DETAIL / OTHER")) -> DETAIL / OTHER
A22: 10 Total, all industries | C22: =SUM(C2:C20) -> 132959111 | D22: 10532191402092 | E22: =IF(LEFT(TRIM(A22),6)="NAICS ",IFERROR(MID(TRIM(A22),7,FIND(" ",TRIM(A22)&" ",7)-7),""),"") | F22: =IF(E22="","",TRIM(MID(TRIM(A22),FIND(" ",TRIM(A22)&" ",7)+1,255))) | G22: =IF(E22="","",IF(COUNTIF('DATA QCEW'!$A$2:$A$20,E22)>0,"19-SECTOR","DETAIL / OTHER"))
E23: =IF(LEFT(TRIM(A23),6)="NAICS ",IFERROR(MID(TRIM(A23),7,FIND(" ",TRIM(A23)&" ",7)-7),""),"") | F23: =IF(E23="","",TRIM(MID(TRIM(A23),FIND(" ",TRIM(A23)&" ",7)+1,255))) | G23: =IF(E23="","",IF(COUNTIF('DATA QCEW'!$A$2:$A$20,E23)>0,"19-SECTOR","DETAIL / OTHER"))
E24: =IF(LEFT(TRIM(A24),6)="NAICS ",IFERROR(MID(TRIM(A24),7,FIND(" ",TRIM(A24)&" ",7)-7),""),"") | F24: =IF(E24="","",TRIM(MID(TRIM(A24),FIND(" ",TRIM(A24)&" ",7)+1,255))) | G24: =IF(E24="","",IF(COUNTIF('DATA QCEW'!$A$2:$A$20,E24)>0,"19-SECTOR","DETAIL / OTHER"))
E25: =IF(LEFT(TRIM(A25),6)="NAICS ",IFERROR(MID(TRIM(A25),7,FIND(" ",TRIM(A25)&" ",7)-7),""),"") | F25: =IF(E25="","",TRIM(MID(TRIM(A25),FIND(" ",TRIM(A25)&" ",7)+1,255))) | G25: =IF(E25="","",IF(COUNTIF('DATA QCEW'!$A$2:$A$20,E25)>0,"19-SECTOR","DETAIL / OTHER"))
E26: =IF(LEFT(TRIM(A26),6)="NAICS ",IFERROR(MID(TRIM(A26),7,FIND(" ",TRIM(A26)&" ",7)-7),""),"") | F26: =IF(E26="","",TRIM(MID(TRIM(A26),FIND(" ",TRIM(A26)&" ",7)+1,255))) | G26: =IF(E26="","",IF(COUNTIF('DATA QCEW'!$A$2:$A$20,E26)>0,"19-SECTOR","DETAIL / OTHER"))
E27: =IF(LEFT(TRIM(A27),6)="NAICS ",IFERROR(MID(TRIM(A27),7,FIND(" ",TRIM(A27)&" ",7)-7),""),"") | F27: =IF(E27="","",TRIM(MID(TRIM(A27),FIND(" ",TRIM(A27)&" ",7)+1,255))) | G27: =IF(E27="","",IF(COUNTIF('DATA QCEW'!$A$2:$A$20,E27)>0,"19-SECTOR","DETAIL / OTHER"))
E28: =IF(LEFT(TRIM(A28),6)="NAICS ",IFERROR(MID(TRIM(A28),7,FIND(" ",TRIM(A28)&" ",7)-7),""),"") | F28: =IF(E28="","",TRIM(MID(TRIM(A28),FIND(" ",TRIM(A28)&" ",7)+1,255))) | G28: =IF(E28="","",IF(COUNTIF('DATA QCEW'!$A$2:$A$20,E28)>0,"19-SECTOR","DETAIL / OTHER"))
E29: =IF(LEFT(TRIM(A29),6)="NAICS ",IFERROR(MID(TRIM(A29),7,FIND(" ",TRIM(A29)&" ",7)-7),""),"") | F29: =IF(E29="","",TRIM(MID(TRIM(A29),FIND(" ",TRIM(A29)&" ",7)+1,255))) | G29: =IF(E29="","",IF(COUNTIF('DATA QCEW'!$A$2:$A$20,E29)>0,"19-SECTOR","DETAIL / OTHER"))
E30: =IF(LEFT(TRIM(A30),6)="NAICS ",IFERROR(MID(TRIM(A30),7,FIND(" ",TRIM(A30)&" ",7)-7),""),"") | F30: =IF(E30="","",TRIM(MID(TRIM(A30),FIND(" ",TRIM(A30)&" ",7)+1,255))) | G30: =IF(E30="","",IF(COUNTIF('DATA QCEW'!$A$2:$A$20,E30)>0,"19-SECTOR","DETAIL / OTHER"))
E31: =IF(LEFT(TRIM(A31),6)="NAICS ",IFERROR(MID(TRIM(A31),7,FIND(" ",TRIM(A31)&" ",7)-7),""),"") | F31: =IF(E31="","",TRIM(MID(TRIM(A31),FIND(" ",TRIM(A31)&" ",7)+1,255))) | G31: =IF(E31="","",IF(COUNTIF('DATA QCEW'!$A$2:$A$20,E31)>0,"19-SECTOR","DETAIL / OTHER"))
E32: =IF(LEFT(TRIM(A32),6)="NAICS ",IFERROR(MID(TRIM(A32),7,FIND(" ",TRIM(A32)&" ",7)-7),""),"") | F32: =IF(E32="","",TRIM(MID(TRIM(A32),FIND(" ",TRIM(A32)&" ",7)+1,255))) | G32: =IF(E32="","",IF(COUNTIF('DATA QCEW'!$A$2:$A$20,E32)>0,"19-SECTOR","DETAIL / OTHER"))
E33: =IF(LEFT(TRIM(A33),6)="NAICS ",IFERROR(MID(TRIM(A33),7,FIND(" ",TRIM(A33)&" ",7)-7),""),"") | F33: =IF(E33="","",TRIM(MID(TRIM(A33),FIND(" ",TRIM(A33)&" ",7)+1,255))) | G33: =IF(E33="","",IF(COUNTIF('DATA QCEW'!$A$2:$A$20,E33)>0,"19-SECTOR","DETAIL / OTHER"))
E34: =IF(LEFT(TRIM(A34),6)="NAICS ",IFERROR(MID(TRIM(A34),7,FIND(" ",TRIM(A34)&" ",7)-7),""),"") | F34: =IF(E34="","",TRIM(MID(TRIM(A34),FIND(" ",TRIM(A34)&" ",7)+1,255))) | G34: =IF(E34="","",IF(COUNTIF('DATA QCEW'!$A$2:$A$20,E34)>0,"19-SECTOR","DETAIL / OTHER"))
... E3000: =IF(LEFT(TRIM(A3000),6)="NAICS ",IFERROR(MID(TRIM(A3000),7,FIND(" ",TRIM(A3000)&" ",7)-7),""),"") | F3000: =IF(E3000="","",TRIM(MID(TRIM(A3000),FIND(" ",TRIM(A3000)&" ",7)+1,255))) | G3000: =IF(E3000="","",IF(COUNTIF('DATA QCEW'!$A$2:$A$20,E3000)>0,"19-SECTOR","DETAIL / OTHER"))

Sheet DATA OEWS
A1: NAICS (TEXT) | B1: Industry | C1: SOC code (TEXT) | D1: Occupation | E1: Employment | F1: Annual Mean Wage ($) | G1: Wage Bill [FORMULA] | H1: Wharton Exposure [VERIFIED INPUT] | I1: Matched Wage Bill [FORMULA] | J1: Exposed Wage Bill [FORMULA] | K1: Match Status [FORMULA]
A2: 11 | B2: Agriculture, Forestry, Fishing and Hunting | C2: 11-1011 | D2: Chief Executives | E2: 170 | F2: 277000 | G2: =IF(OR(E2="",F2=""),"",E2*F2) -> 47090000 | H2: 0.4775 | I2: =IF(G2="","",IF(ISNUMBER(H2),G2,"")) -> 47090000 | J2: =IF(I2="","",I2*H2) -> 22485475 | K2: =IF(G2="","MISSING OEWS",IF(ISNUMBER(H2),"MATCHED","MISSING WHARTON")) -> MATCHED
A3: 11 | B3: Agriculture, Forestry, Fishing and Hunting | C3: 11-1021 | D3: General and Operations Managers | E3: 5660 | F3: 99340 | G3: =IF(OR(E3="",F3=""),"",E3*F3) -> 562264400 | H3: 0.5382 | I3: =IF(G3="","",IF(ISNUMBER(H3),G3,"")) -> 562264400 | J3: =IF(I3="","",I3*H3) -> 3.026107e+08 | K3: =IF(G3="","MISSING OEWS",IF(ISNUMBER(H3),"MATCHED","MISSING WHARTON")) -> MATCHED
A4: 11 | B4: Agriculture, Forestry, Fishing and Hunting | C4: 11-2021 | D4: Marketing Managers | E4: 70 | F4: 129740 | G4: =IF(OR(E4="",F4=""),"",E4*F4) -> 9081800 | H4: 0.445 | I4: =IF(G4="","",IF(ISNUMBER(H4),G4,"")) -> 9081800 | J4: =IF(I4="","",I4*H4) -> 4041401 | K4: =IF(G4="","MISSING OEWS",IF(ISNUMBER(H4),"MATCHED","MISSING WHARTON")) -> MATCHED
A5: 11 | B5: Agriculture, Forestry, Fishing and Hunting | C5: 11-2022 | D5: Sales Managers | E5: 330 | F5: 162490 | G5: =IF(OR(E5="",F5=""),"",E5*F5) -> 53621700 | H5: 0.3735 | I5: =IF(G5="","",IF(ISNUMBER(H5),G5,"")) -> 53621700 | J5: =IF(I5="","",I5*H5) -> 20027705 | K5: =IF(G5="","MISSING OEWS",IF(ISNUMBER(H5),"MATCHED","MISSING WHARTON")) -> MATCHED
A6: 11 | B6: Agriculture, Forestry, Fishing and Hunting | C6: 11-3012 | D6: Administrative Services Managers | E6: 150 | F6: 124650 | G6: =IF(OR(E6="",F6=""),"",E6*F6) -> 18697500 | H6: 0.4444 | I6: =IF(G6="","",IF(ISNUMBER(H6),G6,"")) -> 18697500 | J6: =IF(I6="","",I6*H6) -> 8309169 | K6: =IF(G6="","MISSING OEWS",IF(ISNUMBER(H6),"MATCHED","MISSING WHARTON")) -> MATCHED
A7: 11 | B7: Agriculture, Forestry, Fishing and Hunting | C7: 11-3013 | D7: Facilities Managers | E7: 300 | F7: 115030 | G7: =IF(OR(E7="",F7=""),"",E7*F7) -> 34509000 | H7: 0.2907 | I7: =IF(G7="","",IF(ISNUMBER(H7),G7,"")) -> 34509000 | J7: =IF(I7="","",I7*H7) -> 10031766 | K7: =IF(G7="","MISSING OEWS",IF(ISNUMBER(H7),"MATCHED","MISSING WHARTON")) -> MATCHED
A8: 11 | B8: Agriculture, Forestry, Fishing and Hunting | C8: 11-3021 | D8: Computer and Information Systems Managers | E8: 140 | F8: 160470 | G8: =IF(OR(E8="",F8=""),"",E8*F8) -> 22465800 | H8: 0.5265 | I8: =IF(G8="","",IF(ISNUMBER(H8),G8,"")) -> 22465800 | J8: =IF(I8="","",I8*H8) -> 11828244 | K8: =IF(G8="","MISSING OEWS",IF(ISNUMBER(H8),"MATCHED","MISSING WHARTON")) -> MATCHED
A9: 11 | B9: Agriculture, Forestry, Fishing and Hunting | C9: 11-3031 | D9: Financial Managers | E9: 460 | F9: 156410 | G9: =IF(OR(E9="",F9=""),"",E9*F9) -> 71948600 | H9: 0.7221 | I9: =IF(G9="","",IF(ISNUMBER(H9),G9,"")) -> 71948600 | J9: =IF(I9="","",I9*H9) -> 51954084 | K9: =IF(G9="","MISSING OEWS",IF(ISNUMBER(H9),"MATCHED","MISSING WHARTON")) -> MATCHED
A10: 11 | B10: Agriculture, Forestry, Fishing and Hunting | C10: 11-3051 | D10: Industrial Production Managers | E10: 580 | F10: 108020 | G10: =IF(OR(E10="",F10=""),"",E10*F10) -> 62651600 | H10: 0.3636 | I10: =IF(G10="","",IF(ISNUMBER(H10),G10,"")) -> 62651600 | J10: =IF(I10="","",I10*H10) -> 22780122 | K10: =IF(G10="","MISSING OEWS",IF(ISNUMBER(H10),"MATCHED","MISSING WHARTON")) -> MATCHED
A11: 11 | B11: Agriculture, Forestry, Fishing and Hunting | C11: 11-3061 | D11: Purchasing Managers | E11: 50 | F11: 144980 | G11: =IF(OR(E11="",F11=""),"",E11*F11) -> 7249000 | H11: 0.6944 | I11: =IF(G11="","",IF(ISNUMBER(H11),G11,"")) -> 7249000 | J11: =IF(I11="","",I11*H11) -> 5033705.6 | K11: =IF(G11="","MISSING OEWS",IF(ISNUMBER(H11),"MATCHED","MISSING WHARTON")) -> MATCHED
A12: 11 | B12: Agriculture, Forestry, Fishing and Hunting | C12: 11-3071 | D12: Transportation, Storage, and Distribution Managers | E12: 320 | F12: 100610 | G12: =IF(OR(E12="",F12=""),"",E12*F12) -> 32195200 | H12: 0.5783 | I12: =IF(G12="","",IF(ISNUMBER(H12),G12,"")) -> 32195200 | J12: =IF(I12="","",I12*H12) -> 18618484 | K12: =IF(G12="","MISSING OEWS",IF(ISNUMBER(H12),"MATCHED","MISSING WHARTON")) -> MATCHED
A13: 11 | B13: Agriculture, Forestry, Fishing and Hunting | C13: 11-3121 | D13: Human Resources Managers | E13: 100 | F13: 141370 | G13: =IF(OR(E13="",F13=""),"",E13*F13) -> 14137000 | H13: 0.5962 | I13: =IF(G13="","",IF(ISNUMBER(H13),G13,"")) -> 14137000 | J13: =IF(I13="","",I13*H13) -> 8428479.4 | K13: =IF(G13="","MISSING OEWS",IF(ISNUMBER(H13),"MATCHED","MISSING WHARTON")) -> MATCHED
... A15: 11 | B15: Agriculture, Forestry, Fishing and Hunting | C15: 11-9121 | D15: Natural Sciences Managers | E15: 50 | F15: 120590 | G15: =IF(OR(E15="",F15=""),"",E15*F15) -> 6029500 | H15: 0.382 | I15: =IF(G15="","",IF(ISNUMBER(H15),G15,"")) -> 6029500 | J15: =IF(I15="","",I15*H15) -> 2303269 | K15: =IF(G15="","MISSING OEWS",IF(ISNUMBER(H15),"MATCHED","MISSING WHARTON")) -> MATCHED
A16: 11 | B16: Agriculture, Forestry, Fishing and Hunting | C16: 11-9199 | D16: Managers, All Other | E16: 470 | G16: =IF(OR(E16="",F16=""),"",E16*F16) | H16: 0.4896 | I16: =IF(G16="","",IF(ISNUMBER(H16),G16,"")) | J16: =IF(I16="","",I16*H16) | K16: =IF(G16="","MISSING OEWS",IF(ISNUMBER(H16),"MATCHED","MISSING WHARTON")) -> MISSING OEWS
A17: 11 | B17: Agriculture, Forestry, Fishing and Hunting | C17: 13-1020 | D17: Buyers and Purchasing Agents | E17: 520 | F17: 81950 | G17: =IF(OR(E17="",F17=""),"",E17*F17) -> 42614000 | H17: 0.5876 | I17: =IF(G17="","",IF(ISNUMBER(H17),G17,"")) -> 42614000 | J17: =IF(I17="","",I17*H17) -> 25039986 | K17: =IF(G17="","MISSING OEWS",IF(ISNUMBER(H17),"MATCHED","MISSING WHARTON")) -> MATCHED
A18: 11 | B18: Agriculture, Forestry, Fishing and Hunting | C18: 13-1041 | D18: Compliance Officers | E18: 60 | F18: 67290 | G18: =IF(OR(E18="",F18=""),"",E18*F18) -> 4037400 | H18: 0.4611 | I18: =IF(G18="","",IF(ISNUMBER(H18),G18,"")) -> 4037400 | J18: =IF(I18="","",I18*H18) -> 1861645.1 | K18: =IF(G18="","MISSING OEWS",IF(ISNUMBER(H18),"MATCHED","MISSING WHARTON")) -> MATCHED
A19: 11 | B19: Agriculture, Forestry, Fishing and Hunting | C19: 13-1071 | D19: Human Resources Specialists | E19: 700 | F19: 74400 | G19: =IF(OR(E19="",F19=""),"",E19*F19) -> 52080000 | H19: 0.7808 | I19: =IF(G19="","",IF(ISNUMBER(H19),G19,"")) -> 52080000 | J19: =IF(I19="","",I19*H19) -> 40664064 | K19: =IF(G19="","MISSING OEWS",IF(ISNUMBER(H19),"MATCHED","MISSING WHARTON")) -> MATCHED
A20: 11 | B20: Agriculture, Forestry, Fishing and Hunting | C20: 13-1074 | D20: Farm Labor Contractors | E20: 270 | F20: 62420 | G20: =IF(OR(E20="",F20=""),"",E20*F20) -> 16853400 | H20: 0.2375 | I20: =IF(G20="","",IF(ISNUMBER(H20),G20,"")) -> 16853400 | J20: =IF(I20="","",I20*H20) -> 4002682.5 | K20: =IF(G20="","MISSING OEWS",IF(ISNUMBER(H20),"MATCHED","MISSING WHARTON")) -> MATCHED
A21: 11 | B21: Agriculture, Forestry, Fishing and Hunting | C21: 13-1081 | D21: Logisticians | E21: 250 | F21: 75350 | G21: =IF(OR(E21="",F21=""),"",E21*F21) -> 18837500 | H21: 0.6943 | I21: =IF(G21="","",IF(ISNUMBER(H21),G21,"")) -> 18837500 | J21: =IF(I21="","",I21*H21) -> 13078876 | K21: =IF(G21="","MISSING OEWS",IF(ISNUMBER(H21),"MATCHED","MISSING WHARTON")) -> MATCHED
A22: 11 | B22: Agriculture, Forestry, Fishing and Hunting | C22: 13-1082 | D22: Project Management Specialists | E22: 130 | F22: 90840 | G22: =IF(OR(E22="",F22=""),"",E22*F22) -> 11809200 | H22: 0.6375 | I22: =IF(G22="","",IF(ISNUMBER(H22),G22,"")) -> 11809200 | J22: =IF(I22="","",I22*H22) -> 7528365 | K22: =IF(G22="","MISSING OEWS",IF(ISNUMBER(H22),"MATCHED","MISSING WHARTON")) -> MATCHED
A23: 11 | B23: Agriculture, Forestry, Fishing and Hunting | C23: 13-1111 | D23: Management Analysts | E23: 120 | G23: =IF(OR(E23="",F23=""),"",E23*F23) | H23: 0.5773 | I23: =IF(G23="","",IF(ISNUMBER(H23),G23,"")) | J23: =IF(I23="","",I23*H23) | K23: =IF(G23="","MISSING OEWS",IF(ISNUMBER(H23),"MATCHED","MISSING WHARTON")) -> MISSING OEWS
A24: 11 | B24: Agriculture, Forestry, Fishing and Hunting | C24: 13-1121 | D24: Meeting, Convention, and Event Planners | E24: 50 | F24: 48850 | G24: =IF(OR(E24="",F24=""),"",E24*F24) -> 2442500 | H24: 0.4476 | I24: =IF(G24="","",IF(ISNUMBER(H24),G24,"")) -> 2442500 | J24: =IF(I24="","",I24*H24) -> 1093263 | K24: =IF(G24="","MISSING OEWS",IF(ISNUMBER(H24),"MATCHED","MISSING WHARTON")) -> MATCHED
A25: 11 | B25: Agriculture, Forestry, Fishing and Hunting | C25: 13-1141 | D25: Compensation, Benefits, and Job Analysis Specialists | E25: 30 | G25: =IF(OR(E25="",F25=""),"",E25*F25) | H25: 0.6167 | I25: =IF(G25="","",IF(ISNUMBER(H25),G25,"")) | J25: =IF(I25="","",I25*H25) | K25: =IF(G25="","MISSING OEWS",IF(ISNUMBER(H25),"MATCHED","MISSING WHARTON")) -> MISSING OEWS
A26: 11 | B26: Agriculture, Forestry, Fishing and Hunting | C26: 13-1151 | D26: Training and Development Specialists | E26: 100 | G26: =IF(OR(E26="",F26=""),"",E26*F26) | H26: 0.565 | I26: =IF(G26="","",IF(ISNUMBER(H26),G26,"")) | J26: =IF(I26="","",I26*H26) | K26: =IF(G26="","MISSING OEWS",IF(ISNUMBER(H26),"MATCHED","MISSING WHARTON")) -> MISSING OEWS
A27: 11 | B27: Agriculture, Forestry, Fishing and Hunting | C27: 13-1161 | D27: Market Research Analysts and Marketing Specialists | E27: 210 | F27: 92250 | G27: =IF(OR(E27="",F27=""),"",E27*F27) -> 19372500 | H27: 0.7792 | I27: =IF(G27="","",IF(ISNUMBER(H27),G27,"")) -> 19372500 | J27: =IF(I27="","",I27*H27) -> 15095052 | K27: =IF(G27="","MISSING OEWS",IF(ISNUMBER(H27),"MATCHED","MISSING WHARTON")) -> MATCHED
A28: 11 | B28: Agriculture, Forestry, Fishing and Hunting | C28: 13-1199 | D28: Business Operations Specialists, All Other | E28: 660 | G28: =IF(OR(E28="",F28=""),"",E28*F28) | H28: 0.6599 | I28: =IF(G28="","",IF(ISNUMBER(H28),G28,"")) | J28: =IF(I28="","",I28*H28) | K28: =IF(G28="","MISSING OEWS",IF(ISNUMBER(H28),"MATCHED","MISSING WHARTON")) -> MISSING OEWS
A29: 11 | B29: Agriculture, Forestry, Fishing and Hunting | C29: 13-2011 | D29: Accountants and Auditors | E29: 1110 | F29: 83410 | G29: =IF(OR(E29="",F29=""),"",E29*F29) -> 92585100 | H29: 0.795 | I29: =IF(G29="","",IF(ISNUMBER(H29),G29,"")) -> 92585100 | J29: =IF(I29="","",I29*H29) -> 73605154 | K29: =IF(G29="","MISSING OEWS",IF(ISNUMBER(H29),"MATCHED","MISSING WHARTON")) -> MATCHED
A30: 11 | B30: Agriculture, Forestry, Fishing and Hunting | C30: 15-1211 | D30: Computer Systems Analysts | E30: 40 | F30: 107730 | G30: =IF(OR(E30="",F30=""),"",E30*F30) -> 4309200 | H30: 0.6388 | I30: =IF(G30="","",IF(ISNUMBER(H30),G30,"")) -> 4309200 | J30: =IF(I30="","",I30*H30) -> 2752717 | K30: =IF(G30="","MISSING OEWS",IF(ISNUMBER(H30),"MATCHED","MISSING WHARTON")) -> MATCHED
A31: 11 | B31: Agriculture, Forestry, Fishing and Hunting | C31: 15-1232 | D31: Computer User Support Specialists | E31: 230 | F31: 65730 | G31: =IF(OR(E31="",F31=""),"",E31*F31) -> 15117900 | H31: 0.6062 | I31: =IF(G31="","",IF(ISNUMBER(H31),G31,"")) -> 15117900 | J31: =IF(I31="","",I31*H31) -> 9164471 | K31: =IF(G31="","MISSING OEWS",IF(ISNUMBER(H31),"MATCHED","MISSING WHARTON")) -> MATCHED
A32: 11 | B32: Agriculture, Forestry, Fishing and Hunting | C32: 15-1244 | D32: Network and Computer Systems Administrators | E32: 80 | G32: =IF(OR(E32="",F32=""),"",E32*F32) | H32: 0.695 | I32: =IF(G32="","",IF(ISNUMBER(H32),G32,"")) | J32: =IF(I32="","",I32*H32) | K32: =IF(G32="","MISSING OEWS",IF(ISNUMBER(H32),"MATCHED","MISSING WHARTON")) -> MISSING OEWS
A33: 11 | B33: Agriculture, Forestry, Fishing and Hunting | C33: 15-1252 | D33: Software Developers | E33: 90 | G33: =IF(OR(E33="",F33=""),"",E33*F33) | H33: 0.5211 | I33: =IF(G33="","",IF(ISNUMBER(H33),G33,"")) | J33: =IF(I33="","",I33*H33) | K33: =IF(G33="","MISSING OEWS",IF(ISNUMBER(H33),"MATCHED","MISSING WHARTON")) -> MISSING OEWS
A34: 11 | B34: Agriculture, Forestry, Fishing and Hunting | C34: 15-1299 | D34: Computer Occupations, All Other | E34: 50 | F34: 101700 | G34: =IF(OR(E34="",F34=""),"",E34*F34) -> 5085000 | H34: 0.7425 | I34: =IF(G34="","",IF(ISNUMBER(H34),G34,"")) -> 5085000 | J34: =IF(I34="","",I34*H34) -> 3775612.5 | K34: =IF(G34="","MISSING OEWS",IF(ISNUMBER(H34),"MATCHED","MISSING WHARTON")) -> MATCHED
A35: 11 | B35: Agriculture, Forestry, Fishing and Hunting | C35: 17-2112 | D35: Industrial Engineers | E35: 100 | F35: 87540 | G35: =IF(OR(E35="",F35=""),"",E35*F35) -> 8754000 | H35: 0.4786 | I35: =IF(G35="","",IF(ISNUMBER(H35),G35,"")) -> 8754000 | J35: =IF(I35="","",I35*H35) -> 4189664.4 | K35: =IF(G35="","MISSING OEWS",IF(ISNUMBER(H35),"MATCHED","MISSING WHARTON")) -> MATCHED
A36: 11 | B36: Agriculture, Forestry, Fishing and Hunting | C36: 19-1011 | D36: Animal Scientists | E36: 220 | F36: 75660 | G36: =IF(OR(E36="",F36=""),"",E36*F36) -> 16645200 | H36: 0.2333 | I36: =IF(G36="","",IF(ISNUMBER(H36),G36,"")) -> 16645200 | J36: =IF(I36="","",I36*H36) -> 3883325.2 | K36: =IF(G36="","MISSING OEWS",IF(ISNUMBER(H36),"MATCHED","MISSING WHARTON")) -> MATCHED
A37: 11 | B37: Agriculture, Forestry, Fishing and Hunting | C37: 19-1012 | D37: Food Scientists and Technologists | E37: 230 | F37: 73850 | G37: =IF(OR(E37="",F37=""),"",E37*F37) -> 16985500 | H37: 0.1269 | I37: =IF(G37="","",IF(ISNUMBER(H37),G37,"")) -> 16985500 | J37: =IF(I37="","",I37*H37) -> 2155460 | K37: =IF(G37="","MISSING OEWS",IF(ISNUMBER(H37),"MATCHED","MISSING WHARTON")) -> MATCHED
A38: 11 | B38: Agriculture, Forestry, Fishing and Hunting | C38: 19-1013 | D38: Soil and Plant Scientists | E38: 770 | F38: 87270 | G38: =IF(OR(E38="",F38=""),"",E38*F38) -> 67197900 | H38: 0.0519 | I38: =IF(G38="","",IF(ISNUMBER(H38),G38,"")) -> 67197900 | J38: =IF(I38="","",I38*H38) -> 3487571 | K38: =IF(G38="","MISSING OEWS",IF(ISNUMBER(H38),"MATCHED","MISSING WHARTON")) -> MATCHED
A39: 11 | B39: Agriculture, Forestry, Fishing and Hunting | C39: 19-1029 | D39: Biological Scientists, All Other | E39: 210 | F39: 60360 | G39: =IF(OR(E39="",F39=""),"",E39*F39) -> 12675600 | H39: 0.4037 | I39: =IF(G39="","",IF(ISNUMBER(H39),G39,"")) -> 12675600 | J39: =IF(I39="","",I39*H39) -> 5117139.7 | K39: =IF(G39="","MISSING OEWS",IF(ISNUMBER(H39),"MATCHED","MISSING WHARTON")) -> MATCHED
A40: 11 | B40: Agriculture, Forestry, Fishing and Hunting | C40: 19-1032 | D40: Foresters | E40: 650 | F40: 81500 | G40: =IF(OR(E40="",F40=""),"",E40*F40) -> 52975000 | H40: 0.056 | I40: =IF(G40="","",IF(ISNUMBER(H40),G40,"")) -> 52975000 | J40: =IF(I40="","",I40*H40) -> 2966600 | K40: =IF(G40="","MISSING OEWS",IF(ISNUMBER(H40),"MATCHED","MISSING WHARTON")) -> MATCHED
A41: 11 | B41: Agriculture, Forestry, Fishing and Hunting | C41: 19-4012 | D41: Agricultural Technicians | E41: 1270 | F41: 52540 | G41: =IF(OR(E41="",F41=""),"",E41*F41) -> 66725800 | H41: 0.374 | I41: =IF(G41="","",IF(ISNUMBER(H41),G41,"")) -> 66725800 | J41: =IF(I41="","",I41*H41) -> 24955449 | K41: =IF(G41="","MISSING OEWS",IF(ISNUMBER(H41),"MATCHED","MISSING WHARTON")) -> MATCHED
A42: 11 | B42: Agriculture, Forestry, Fishing and Hunting | C42: 19-4013 | D42: Food Science Technicians | F42: 50010 | G42: =IF(OR(E42="",F42=""),"",E42*F42) | H42: 0.2969 | I42: =IF(G42="","",IF(ISNUMBER(H42),G42,"")) | J42: =IF(I42="","",I42*H42) | K42: =IF(G42="","MISSING OEWS",IF(ISNUMBER(H42),"MATCHED","MISSING WHARTON")) -> MISSING OEWS
A43: 11 | B43: Agriculture, Forestry, Fishing and Hunting | C43: 19-4021 | D43: Biological Technicians | E43: 50 | F43: 63050 | G43: =IF(OR(E43="",F43=""),"",E43*F43) -> 3152500 | H43: 0.2778 | I43: =IF(G43="","",IF(ISNUMBER(H43),G43,"")) -> 3152500 | J43: =IF(I43="","",I43*H43) -> 875764.5 | K43: =IF(G43="","MISSING OEWS",IF(ISNUMBER(H43),"MATCHED","MISSING WHARTON")) -> MATCHED
A44: 11 | B44: Agriculture, Forestry, Fishing and Hunting | C44: 19-5011 | D44: Occupational Health and Safety Specialists | E44: 330 | F44: 65690 | G44: =IF(OR(E44="",F44=""),"",E44*F44) -> 21677700 | H44: 0.2786 | I44: =IF(G44="","",IF(ISNUMBER(H44),G44,"")) -> 21677700 | J44: =IF(I44="","",I44*H44) -> 6039407.2 | K44: =IF(G44="","MISSING OEWS",IF(ISNUMBER(H44),"MATCHED","MISSING WHARTON")) -> MATCHED
A45: 11 | B45: Agriculture, Forestry, Fishing and Hunting | C45: 25-3021 | D45: Self-Enrichment Teachers | E45: 320 | F45: 41710 | G45: =IF(OR(E45="",F45=""),"",E45*F45) -> 13347200 | H45: 0.33 | I45: =IF(G45="","",IF(ISNUMBER(H45),G45,"")) -> 13347200 | J45: =IF(I45="","",I45*H45) -> 4404576 | K45: =IF(G45="","MISSING OEWS",IF(ISNUMBER(H45),"MATCHED","MISSING WHARTON")) -> MATCHED
A46: 11 | B46: Agriculture, Forestry, Fishing and Hunting | C46: 27-3031 | D46: Public Relations Specialists | E46: 60 | G46: =IF(OR(E46="",F46=""),"",E46*F46) | H46: 0.575 | I46: =IF(G46="","",IF(ISNUMBER(H46),G46,"")) | J46: =IF(I46="","",I46*H46) | K46: =IF(G46="","MISSING OEWS",IF(ISNUMBER(H46),"MATCHED","MISSING WHARTON")) -> MISSING OEWS
A47: 11 | B47: Agriculture, Forestry, Fishing and Hunting | C47: 29-1131 | D47: Veterinarians | E47: 150 | F47: 134040 | G47: =IF(OR(E47="",F47=""),"",E47*F47) -> 20106000 | H47: 0.163 | I47: =IF(G47="","",IF(ISNUMBER(H47),G47,"")) -> 20106000 | J47: =IF(I47="","",I47*H47) -> 3277278 | K47: =IF(G47="","MISSING OEWS",IF(ISNUMBER(H47),"MATCHED","MISSING WHARTON")) -> MATCHED
A48: 11 | B48: Agriculture, Forestry, Fishing and Hunting | C48: 29-2056 | D48: Veterinary Technologists and Technicians | E48: 210 | F48: 61840 | G48: =IF(OR(E48="",F48=""),"",E48*F48) -> 12986400 | H48: 0.2065 | I48: =IF(G48="","",IF(ISNUMBER(H48),G48,"")) -> 12986400 | J48: =IF(I48="","",I48*H48) -> 2681691.6 | K48: =IF(G48="","MISSING OEWS",IF(ISNUMBER(H48),"MATCHED","MISSING WHARTON")) -> MATCHED
A49: 11 | B49: Agriculture, Forestry, Fishing and Hunting | C49: 33-9032 | D49: Security Guards | E49: 480 | F49: 37550 | G49: =IF(OR(E49="",F49=""),"",E49*F49) -> 18024000 | H49: 0.1357 | I49: =IF(G49="","",IF(ISNUMBER(H49),G49,"")) -> 18024000 | J49: =IF(I49="","",I49*H49) -> 2445856.8 | K49: =IF(G49="","MISSING OEWS",IF(ISNUMBER(H49),"MATCHED","MISSING WHARTON")) -> MATCHED
A50: 11 | B50: Agriculture, Forestry, Fishing and Hunting | C50: 37-1011 | D50: First-Line Supervisors of Housekeeping and Janitorial Workers | E50: 80 | F50: 55650 | G50: =IF(OR(E50="",F50=""),"",E50*F50) -> 4452000 | H50: 0.2269 | I50: =IF(G50="","",IF(ISNUMBER(H50),G50,"")) -> 4452000 | J50: =IF(I50="","",I50*H50) -> 1010158.8 | K50: =IF(G50="","MISSING OEWS",IF(ISNUMBER(H50),"MATCHED","MISSING WHARTON")) -> MATCHED
A51: 11 | B51: Agriculture, Forestry, Fishing and Hunting | C51: 37-1012 | D51: First-Line Supervisors of Landscaping, Lawn Service, and Groundskeeping Workers | E51: 180 | F51: 65570 | G51: =IF(OR(E51="",F51=""),"",E51*F51) -> 11802600 | H51: 0.2357 | I51: =IF(G51="","",IF(ISNUMBER(H51),G51,"")) -> 11802600 | J51: =IF(I51="","",I51*H51) -> 2781872.8 | K51: =IF(G51="","MISSING OEWS",IF(ISNUMBER(H51),"MATCHED","MISSING WHARTON")) -> MATCHED
A52: 11 | B52: Agriculture, Forestry, Fishing and Hunting | C52: 37-2011 | D52: Janitors and Cleaners, Except Maids and Housekeeping Cleaners | E52: 2650 | F52: 37340 | G52: =IF(OR(E52="",F52=""),"",E52*F52) -> 98951000 | H52: 0 | I52: =IF(G52="","",IF(ISNUMBER(H52),G52,"")) -> 98951000 | J52: =IF(I52="","",I52*H52) -> 0 | K52: =IF(G52="","MISSING OEWS",IF(ISNUMBER(H52),"MATCHED","MISSING WHARTON")) -> MATCHED
A53: 11 | B53: Agriculture, Forestry, Fishing and Hunting | C53: 37-2012 | D53: Maids and Housekeeping Cleaners | E53: 140 | F53: 37400 | G53: =IF(OR(E53="",F53=""),"",E53*F53) -> 5236000 | H53: 0 | I53: =IF(G53="","",IF(ISNUMBER(H53),G53,"")) -> 5236000 | J53: =IF(I53="","",I53*H53) -> 0 | K53: =IF(G53="","MISSING OEWS",IF(ISNUMBER(H53),"MATCHED","MISSING WHARTON")) -> MATCHED
A54: 11 | B54: Agriculture, Forestry, Fishing and Hunting | C54: 37-2021 | D54: Pest Control Workers | E54: 70 | F54: 41940 | G54: =IF(OR(E54="",F54=""),"",E54*F54) -> 2935800 | H54: 0.1567 | I54: =IF(G54="","",IF(ISNUMBER(H54),G54,"")) -> 2935800 | J54: =IF(I54="","",I54*H54) -> 460039.86 | K54: =IF(G54="","MISSING OEWS",IF(ISNUMBER(H54),"MATCHED","MISSING WHARTON")) -> MATCHED
A55: 11 | B55: Agriculture, Forestry, Fishing and Hunting | C55: 37-3011 | D55: Landscaping and Groundskeeping Workers | E55: 1090 | F55: 42480 | G55: =IF(OR(E55="",F55=""),"",E55*F55) -> 46303200 | H55: 0 | I55: =IF(G55="","",IF(ISNUMBER(H55),G55,"")) -> 46303200 | J55: =IF(I55="","",I55*H55) -> 0 | K55: =IF(G55="","MISSING OEWS",IF(ISNUMBER(H55),"MATCHED","MISSING WHARTON")) -> MATCHED
A56: 11 | B56: Agriculture, Forestry, Fishing and Hunting | C56: 37-3012 | D56: Pesticide Handlers, Sprayers, and Applicators, Vegetation | E56: 2030 | F56: 43690 | G56: =IF(OR(E56="",F56=""),"",E56*F56) -> 88690700 | H56: 0 | I56: =IF(G56="","",IF(ISNUMBER(H56),G56,"")) -> 88690700 | J56: =IF(I56="","",I56*H56) -> 0 | K56: =IF(G56="","MISSING OEWS",IF(ISNUMBER(H56),"MATCHED","MISSING WHARTON")) -> MATCHED
A57: 11 | B57: Agriculture, Forestry, Fishing and Hunting | C57: 37-3013 | D57: Tree Trimmers and Pruners | F57: 50420 | G57: =IF(OR(E57="",F57=""),"",E57*F57) | H57: 0 | I57: =IF(G57="","",IF(ISNUMBER(H57),G57,"")) | J57: =IF(I57="","",I57*H57) | K57: =IF(G57="","MISSING OEWS",IF(ISNUMBER(H57),"MATCHED","MISSING WHARTON")) -> MISSING OEWS
A58: 11 | B58: Agriculture, Forestry, Fishing and Hunting | C58: 39-1014 | D58: First-Line Supervisors of Entertainment and Recreation Workers, Except Gambling Services | E58: 30 | F58: 49590 | G58: =IF(OR(E58="",F58=""),"",E58*F58) -> 1487700 | H58: 0.2974 | I58: =IF(G58="","",IF(ISNUMBER(H58),G58,"")) -> 1487700 | J58: =IF(I58="","",I58*H58) -> 442441.98 | K58: =IF(G58="","MISSING OEWS",IF(ISNUMBER(H58),"MATCHED","MISSING WHARTON")) -> MATCHED
A59: 11 | B59: Agriculture, Forestry, Fishing and Hunting | C59: 39-1022 | D59: First-Line Supervisors of Personal Service Workers | E59: 240 | F59: 52370 | G59: =IF(OR(E59="",F59=""),"",E59*F59) -> 12568800 | H59: 0.2765 | I59: =IF(G59="","",IF(ISNUMBER(H59),G59,"")) -> 12568800 | J59: =IF(I59="","",I59*H59) -> 3475273.2 | K59: =IF(G59="","MISSING OEWS",IF(ISNUMBER(H59),"MATCHED","MISSING WHARTON")) -> MATCHED
A60: 11 | B60: Agriculture, Forestry, Fishing and Hunting | C60: 39-2011 | D60: Animal Trainers | E60: 1430 | F60: 48390 | G60: =IF(OR(E60="",F60=""),"",E60*F60) -> 69197700 | H60: 0.05 | I60: =IF(G60="","",IF(ISNUMBER(H60),G60,"")) -> 69197700 | J60: =IF(I60="","",I60*H60) -> 3459885 | K60: =IF(G60="","MISSING OEWS",IF(ISNUMBER(H60),"MATCHED","MISSING WHARTON")) -> MATCHED
A61: 11 | B61: Agriculture, Forestry, Fishing and Hunting | C61: 39-2021 | D61: Animal Caretakers | E61: 5870 | F61: 38710 | G61: =IF(OR(E61="",F61=""),"",E61*F61) -> 227227700 | H61: 0.1614 | I61: =IF(G61="","",IF(ISNUMBER(H61),G61,"")) -> 227227700 | J61: =IF(I61="","",I61*H61) -> 36674551 | K61: =IF(G61="","MISSING OEWS",IF(ISNUMBER(H61),"MATCHED","MISSING WHARTON")) -> MATCHED
A62: 11 | B62: Agriculture, Forestry, Fishing and Hunting | C62: 41-1011 | D62: First-Line Supervisors of Retail Sales Workers | E62: 40 | G62: =IF(OR(E62="",F62=""),"",E62*F62) | H62: 0.4476 | I62: =IF(G62="","",IF(ISNUMBER(H62),G62,"")) | J62: =IF(I62="","",I62*H62) | K62: =IF(G62="","MISSING OEWS",IF(ISNUMBER(H62),"MATCHED","MISSING WHARTON")) -> MISSING OEWS
A63: 11 | B63: Agriculture, Forestry, Fishing and Hunting | C63: 41-1012 | D63: First-Line Supervisors of Non-Retail Sales Workers | E63: 50 | F63: 112040 | G63: =IF(OR(E63="",F63=""),"",E63*F63) -> 5602000 | H63: 0.4833 | I63: =IF(G63="","",IF(ISNUMBER(H63),G63,"")) -> 5602000 | J63: =IF(I63="","",I63*H63) -> 2707446.6 | K63: =IF(G63="","MISSING OEWS",IF(ISNUMBER(H63),"MATCHED","MISSING WHARTON")) -> MATCHED
A64: 11 | B64: Agriculture, Forestry, Fishing and Hunting | C64: 41-2031 | D64: Retail Salespersons | E64: 340 | F64: 43990 | G64: =IF(OR(E64="",F64=""),"",E64*F64) -> 14956600 | H64: 0.4938 | I64: =IF(G64="","",IF(ISNUMBER(H64),G64,"")) -> 14956600 | J64: =IF(I64="","",I64*H64) -> 7385569.1 | K64: =IF(G64="","MISSING OEWS",IF(ISNUMBER(H64),"MATCHED","MISSING WHARTON")) -> MATCHED
A65: 11 | B65: Agriculture, Forestry, Fishing and Hunting | C65: 41-3091 | D65: Sales Representatives of Services, Except Advertising, Insurance, Financial Services, and Travel | E65: 670 | F65: 81740 | G65: =IF(OR(E65="",F65=""),"",E65*F65) -> 54765800 | H65: 0.73 | I65: =IF(G65="","",IF(ISNUMBER(H65),G65,"")) -> 54765800 | J65: =IF(I65="","",I65*H65) -> 39979034 | K65: =IF(G65="","MISSING OEWS",IF(ISNUMBER(H65),"MATCHED","MISSING WHARTON")) -> MATCHED
A66: 11 | B66: Agriculture, Forestry, Fishing and Hunting | C66: 41-4012 | D66: Sales Representatives, Wholesale and Manufacturing, Except Technical and Scientific Products | E66: 1600 | F66: 76540 | G66: =IF(OR(E66="",F66=""),"",E66*F66) -> 122464000 | H66: 0.5105 | I66: =IF(G66="","",IF(ISNUMBER(H66),G66,"")) -> 122464000 | J66: =IF(I66="","",I66*H66) -> 62517872 | K66: =IF(G66="","MISSING OEWS",IF(ISNUMBER(H66),"MATCHED","MISSING WHARTON")) -> MATCHED
A67: 11 | B67: Agriculture, Forestry, Fishing and Hunting | C67: 41-9099 | D67: Sales and Related Workers, All Other | E67: 70 | F67: 66120 | G67: =IF(OR(E67="",F67=""),"",E67*F67) -> 4628400 | I67: =IF(G67="","",IF(ISNUMBER(H67),G67,"")) | J67: =IF(I67="","",I67*H67) | K67: =IF(G67="","MISSING OEWS",IF(ISNUMBER(H67),"MATCHED","MISSING WHARTON")) -> MISSING WHARTON
A68: 11 | B68: Agriculture, Forestry, Fishing and Hunting | C68: 43-1011 | D68: First-Line Supervisors of Office and Administrative Support Workers | E68: 1620 | F68: 70640 | G68: =IF(OR(E68="",F68=""),"",E68*F68) -> 114436800 | H68: 0.5034 | I68: =IF(G68="","",IF(ISNUMBER(H68),G68,"")) -> 114436800 | J68: =IF(I68="","",I68*H68) -> 57607485 | K68: =IF(G68="","MISSING OEWS",IF(ISNUMBER(H68),"MATCHED","MISSING WHARTON")) -> MATCHED
A69: 11 | B69: Agriculture, Forestry, Fishing and Hunting | C69: 43-3021 | D69: Billing and Posting Clerks | E69: 50 | F69: 50560 | G69: =IF(OR(E69="",F69=""),"",E69*F69) -> 2528000 | H69: 0.8617 | I69: =IF(G69="","",IF(ISNUMBER(H69),G69,"")) -> 2528000 | J69: =IF(I69="","",I69*H69) -> 2178377.6 | K69: =IF(G69="","MISSING OEWS",IF(ISNUMBER(H69),"MATCHED","MISSING WHARTON")) -> MATCHED
A70: 11 | B70: Agriculture, Forestry, Fishing and Hunting | C70: 43-3031 | D70: Bookkeeping, Accounting, and Auditing Clerks | E70: 4100 | F70: 51280 | G70: =IF(OR(E70="",F70=""),"",E70*F70) -> 210248000 | H70: 0.9517 | I70: =IF(G70="","",IF(ISNUMBER(H70),G70,"")) -> 210248000 | J70: =IF(I70="","",I70*H70) -> 2.0009302e+08 | K70: =IF(G70="","MISSING OEWS",IF(ISNUMBER(H70),"MATCHED","MISSING WHARTON")) -> MATCHED
A71: 11 | B71: Agriculture, Forestry, Fishing and Hunting | C71: 43-3051 | D71: Payroll and Timekeeping Clerks | E71: 1180 | F71: 50080 | G71: =IF(OR(E71="",F71=""),"",E71*F71) -> 59094400 | H71: 0.9409 | I71: =IF(G71="","",IF(ISNUMBER(H71),G71,"")) -> 59094400 | J71: =IF(I71="","",I71*H71) -> 55601921 | K71: =IF(G71="","MISSING OEWS",IF(ISNUMBER(H71),"MATCHED","MISSING WHARTON")) -> MATCHED
A72: 11 | B72: Agriculture, Forestry, Fishing and Hunting | C72: 43-3061 | D72: Procurement Clerks | E72: 60 | F72: 54540 | G72: =IF(OR(E72="",F72=""),"",E72*F72) -> 3272400 | H72: 0.8237 | I72: =IF(G72="","",IF(ISNUMBER(H72),G72,"")) -> 3272400 | J72: =IF(I72="","",I72*H72) -> 2695475.9 | K72: =IF(G72="","MISSING OEWS",IF(ISNUMBER(H72),"MATCHED","MISSING WHARTON")) -> MATCHED
A73: 11 | B73: Agriculture, Forestry, Fishing and Hunting | C73: 43-4051 | D73: Customer Service Representatives | E73: 510 | F73: 44350 | G73: =IF(OR(E73="",F73=""),"",E73*F73) -> 22618500 | H73: 0.82 | I73: =IF(G73="","",IF(ISNUMBER(H73),G73,"")) -> 22618500 | J73: =IF(I73="","",I73*H73) -> 18547170 | K73: =IF(G73="","MISSING OEWS",IF(ISNUMBER(H73),"MATCHED","MISSING WHARTON")) -> MATCHED
A74: 11 | B74: Agriculture, Forestry, Fishing and Hunting | C74: 43-4071 | D74: File Clerks | E74: 50 | F74: 36750 | G74: =IF(OR(E74="",F74=""),"",E74*F74) -> 1837500 | H74: 0.7526 | I74: =IF(G74="","",IF(ISNUMBER(H74),G74,"")) -> 1837500 | J74: =IF(I74="","",I74*H74) -> 1382902.5 | K74: =IF(G74="","MISSING OEWS",IF(ISNUMBER(H74),"MATCHED","MISSING WHARTON")) -> MATCHED
A75: 11 | B75: Agriculture, Forestry, Fishing and Hunting | C75: 43-4151 | D75: Order Clerks | E75: 40 | F75: 43250 | G75: =IF(OR(E75="",F75=""),"",E75*F75) -> 1730000 | H75: 0.9553 | I75: =IF(G75="","",IF(ISNUMBER(H75),G75,"")) -> 1730000 | J75: =IF(I75="","",I75*H75) -> 1652669 | K75: =IF(G75="","MISSING OEWS",IF(ISNUMBER(H75),"MATCHED","MISSING WHARTON")) -> MATCHED
A76: 11 | B76: Agriculture, Forestry, Fishing and Hunting | C76: 43-4161 | D76: Human Resources Assistants, Except Payroll and Timekeeping | E76: 320 | F76: 42230 | G76: =IF(OR(E76="",F76=""),"",E76*F76) -> 13513600 | H76: 0.8342 | I76: =IF(G76="","",IF(ISNUMBER(H76),G76,"")) -> 13513600 | J76: =IF(I76="","",I76*H76) -> 11273045 | K76: =IF(G76="","MISSING OEWS",IF(ISNUMBER(H76),"MATCHED","MISSING WHARTON")) -> MATCHED
A77: 11 | B77: Agriculture, Forestry, Fishing and Hunting | C77: 43-4171 | D77: Receptionists and Information Clerks | E77: 340 | F77: 40890 | G77: =IF(OR(E77="",F77=""),"",E77*F77) -> 13902600 | H77: 0.7368 | I77: =IF(G77="","",IF(ISNUMBER(H77),G77,"")) -> 13902600 | J77: =IF(I77="","",I77*H77) -> 10243436 | K77: =IF(G77="","MISSING OEWS",IF(ISNUMBER(H77),"MATCHED","MISSING WHARTON")) -> MATCHED
A78: 11 | B78: Agriculture, Forestry, Fishing and Hunting | C78: 43-5032 | D78: Dispatchers, Except Police, Fire, and Ambulance | E78: 190 | F78: 46970 | G78: =IF(OR(E78="",F78=""),"",E78*F78) -> 8924300 | H78: 0.8192 | I78: =IF(G78="","",IF(ISNUMBER(H78),G78,"")) -> 8924300 | J78: =IF(I78="","",I78*H78) -> 7310786.6 | K78: =IF(G78="","MISSING OEWS",IF(ISNUMBER(H78),"MATCHED","MISSING WHARTON")) -> MATCHED
A79: 11 | B79: Agriculture, Forestry, Fishing and Hunting | C79: 43-5061 | D79: Production, Planning, and Expediting Clerks | E79: 510 | F79: 52480 | G79: =IF(OR(E79="",F79=""),"",E79*F79) -> 26764800 | H79: 0.7794 | I79: =IF(G79="","",IF(ISNUMBER(H79),G79,"")) -> 26764800 | J79: =IF(I79="","",I79*H79) -> 20860485 | K79: =IF(G79="","MISSING OEWS",IF(ISNUMBER(H79),"MATCHED","MISSING WHARTON")) -> MATCHED
... A92: 11 | B92: Agriculture, Forestry, Fishing and Hunting | C92: 45-2093 | D92: Farmworkers, Farm, Ranch, and Aquacultural Animals | E92: 12770 | F92: 37490 | G92: =IF(OR(E92="",F92=""),"",E92*F92) -> 478747300 | H92: 0.0864 | I92: =IF(G92="","",IF(ISNUMBER(H92),G92,"")) -> 478747300 | J92: =IF(I92="","",I92*H92) -> 41363767 | K92: =IF(G92="","MISSING OEWS",IF(ISNUMBER(H92),"MATCHED","MISSING WHARTON")) -> MATCHED
A93: 11 | B93: Agriculture, Forestry, Fishing and Hunting | C93: 45-2099 | D93: Agricultural Workers, All Other | E93: 440 | F93: 43630 | G93: =IF(OR(E93="",F93=""),"",E93*F93) -> 19197200 | I93: =IF(G93="","",IF(ISNUMBER(H93),G93,"")) | J93: =IF(I93="","",I93*H93) | K93: =IF(G93="","MISSING OEWS",IF(ISNUMBER(H93),"MATCHED","MISSING WHARTON")) -> MISSING WHARTON
A94: 11 | B94: Agriculture, Forestry, Fishing and Hunting | C94: 45-4021 | D94: Fallers | E94: 2440 | F94: 57740 | G94: =IF(OR(E94="",F94=""),"",E94*F94) -> 140885600 | H94: 0 | I94: =IF(G94="","",IF(ISNUMBER(H94),G94,"")) -> 140885600 | J94: =IF(I94="","",I94*H94) -> 0 | K94: =IF(G94="","MISSING OEWS",IF(ISNUMBER(H94),"MATCHED","MISSING WHARTON")) -> MATCHED
A95: 11 | B95: Agriculture, Forestry, Fishing and Hunting | C95: 45-4022 | D95: Logging Equipment Operators | E95: 16680 | F95: 54350 | G95: =IF(OR(E95="",F95=""),"",E95*F95) -> 906558000 | H95: 0.2111 | I95: =IF(G95="","",IF(ISNUMBER(H95),G95,"")) -> 906558000 | J95: =IF(I95="","",I95*H95) -> 1.9137439e+08 | K95: =IF(G95="","MISSING OEWS",IF(ISNUMBER(H95),"MATCHED","MISSING WHARTON")) -> MATCHED
A96: 11 | B96: Agriculture, Forestry, Fishing and Hunting | C96: 45-4023 | D96: Log Graders and Scalers | E96: 120 | F96: 61790 | G96: =IF(OR(E96="",F96=""),"",E96*F96) -> 7414800 | H96: 0.1462 | I96: =IF(G96="","",IF(ISNUMBER(H96),G96,"")) -> 7414800 | J96: =IF(I96="","",I96*H96) -> 1084043.8 | K96: =IF(G96="","MISSING OEWS",IF(ISNUMBER(H96),"MATCHED","MISSING WHARTON")) -> MATCHED
A97: 11 | B97: Agriculture, Forestry, Fishing and Hunting | C97: 45-4029 | D97: Logging Workers, All Other | E97: 1420 | F97: 53780 | G97: =IF(OR(E97="",F97=""),"",E97*F97) -> 76367600 | I97: =IF(G97="","",IF(ISNUMBER(H97),G97,"")) | J97: =IF(I97="","",I97*H97) | K97: =IF(G97="","MISSING OEWS",IF(ISNUMBER(H97),"MATCHED","MISSING WHARTON")) -> MISSING WHARTON
A98: 11 | B98: Agriculture, Forestry, Fishing and Hunting | C98: 47-2031 | D98: Carpenters | E98: 100 | F98: 55940 | G98: =IF(OR(E98="",F98=""),"",E98*F98) -> 5594000 | H98: 0.081 | I98: =IF(G98="","",IF(ISNUMBER(H98),G98,"")) -> 5594000 | J98: =IF(I98="","",I98*H98) -> 453114 | K98: =IF(G98="","MISSING OEWS",IF(ISNUMBER(H98),"MATCHED","MISSING WHARTON")) -> MATCHED
A99: 11 | B99: Agriculture, Forestry, Fishing and Hunting | C99: 47-2073 | D99: Operating Engineers and Other Construction Equipment Operators | E99: 560 | F99: 63880 | G99: =IF(OR(E99="",F99=""),"",E99*F99) -> 35772800 | H99: 0.0589 | I99: =IF(G99="","",IF(ISNUMBER(H99),G99,"")) -> 35772800 | J99: =IF(I99="","",I99*H99) -> 2107017.9 | K99: =IF(G99="","MISSING OEWS",IF(ISNUMBER(H99),"MATCHED","MISSING WHARTON")) -> MATCHED
A100: 11 | B100: Agriculture, Forestry, Fishing and Hunting | C100: 47-2111 | D100: Electricians | E100: 100 | F100: 72210 | G100: =IF(OR(E100="",F100=""),"",E100*F100) -> 7221000 | H100: 0.0786 | I100: =IF(G100="","",IF(ISNUMBER(H100),G100,"")) -> 7221000 | J100: =IF(I100="","",I100*H100) -> 567570.6 | K100: =IF(G100="","MISSING OEWS",IF(ISNUMBER(H100),"MATCHED","MISSING WHARTON")) -> MATCHED
A101: 11 | B101: Agriculture, Forestry, Fishing and Hunting | C101: 49-1011 | D101: First-Line Supervisors of Mechanics, Installers, and Repairers | E101: 730 | F101: 77410 | G101: =IF(OR(E101="",F101=""),"",E101*F101) -> 56509300 | H101: 0.3523 | I101: =IF(G101="","",IF(ISNUMBER(H101),G101,"")) -> 56509300 | J101: =IF(I101="","",I101*H101) -> 19908226 | K101: =IF(G101="","MISSING OEWS",IF(ISNUMBER(H101),"MATCHED","MISSING WHARTON")) -> MATCHED
A102: 11 | B102: Agriculture, Forestry, Fishing and Hunting | C102: 49-3011 | D102: Aircraft Mechanics and Service Technicians | E102: 210 | F102: 55290 | G102: =IF(OR(E102="",F102=""),"",E102*F102) -> 11610900 | H102: 0.0434 | I102: =IF(G102="","",IF(ISNUMBER(H102),G102,"")) -> 11610900 | J102: =IF(I102="","",I102*H102) -> 503913.06 | K102: =IF(G102="","MISSING OEWS",IF(ISNUMBER(H102),"MATCHED","MISSING WHARTON")) -> MATCHED
A103: 11 | B103: Agriculture, Forestry, Fishing and Hunting | C103: 49-3031 | D103: Bus and Truck Mechanics and Diesel Engine Specialists | E103: 340 | F103: 55570 | G103: =IF(OR(E103="",F103=""),"",E103*F103) -> 18893800 | H103: 0 | I103: =IF(G103="","",IF(ISNUMBER(H103),G103,"")) -> 18893800 | J103: =IF(I103="","",I103*H103) -> 0 | K103: =IF(G103="","MISSING OEWS",IF(ISNUMBER(H103),"MATCHED","MISSING WHARTON")) -> MATCHED
A104: 11 | B104: Agriculture, Forestry, Fishing and Hunting | C104: 49-3041 | D104: Farm Equipment Mechanics and Service Technicians | E104: 3270 | F104: 47960 | G104: =IF(OR(E104="",F104=""),"",E104*F104) -> 156829200 | H104: 0.1357 | I104: =IF(G104="","",IF(ISNUMBER(H104),G104,"")) -> 156829200 | J104: =IF(I104="","",I104*H104) -> 21281722 | K104: =IF(G104="","MISSING OEWS",IF(ISNUMBER(H104),"MATCHED","MISSING WHARTON")) -> MATCHED
A105: 11 | B105: Agriculture, Forestry, Fishing and Hunting | C105: 49-3042 | D105: Mobile Heavy Equipment Mechanics, Except Engines | E105: 1300 | F105: 57410 | G105: =IF(OR(E105="",F105=""),"",E105*F105) -> 74633000 | H105: 0.1425 | I105: =IF(G105="","",IF(ISNUMBER(H105),G105,"")) -> 74633000 | J105: =IF(I105="","",I105*H105) -> 10635202 | K105: =IF(G105="","MISSING OEWS",IF(ISNUMBER(H105),"MATCHED","MISSING WHARTON")) -> MATCHED
A106: 11 | B106: Agriculture, Forestry, Fishing and Hunting | C106: 49-9021 | D106: Heating, Air Conditioning, and Refrigeration Mechanics and Installers | E106: 90 | F106: 62960 | G106: =IF(OR(E106="",F106=""),"",E106*F106) -> 5666400 | H106: 0.0867 | I106: =IF(G106="","",IF(ISNUMBER(H106),G106,"")) -> 5666400 | J106: =IF(I106="","",I106*H106) -> 491276.88 | K106: =IF(G106="","MISSING OEWS",IF(ISNUMBER(H106),"MATCHED","MISSING WHARTON")) -> MATCHED
A107: 11 | B107: Agriculture, Forestry, Fishing and Hunting | C107: 49-9041 | D107: Industrial Machinery Mechanics | E107: 1120 | F107: 56980 | G107: =IF(OR(E107="",F107=""),"",E107*F107) -> 63817600 | H107: 0.25 | I107: =IF(G107="","",IF(ISNUMBER(H107),G107,"")) -> 63817600 | J107: =IF(I107="","",I107*H107) -> 15954400 | K107: =IF(G107="","MISSING OEWS",IF(ISNUMBER(H107),"MATCHED","MISSING WHARTON")) -> MATCHED
A108: 11 | B108: Agriculture, Forestry, Fishing and Hunting | C108: 49-9043 | D108: Maintenance Workers, Machinery | E108: 250 | F108: 45340 | G108: =IF(OR(E108="",F108=""),"",E108*F108) -> 11335000 | H108: 0.0528 | I108: =IF(G108="","",IF(ISNUMBER(H108),G108,"")) -> 11335000 | J108: =IF(I108="","",I108*H108) -> 598488 | K108: =IF(G108="","MISSING OEWS",IF(ISNUMBER(H108),"MATCHED","MISSING WHARTON")) -> MATCHED
A109: 11 | B109: Agriculture, Forestry, Fishing and Hunting | C109: 49-9071 | D109: Maintenance and Repair Workers, General | E109: 3160 | F109: 47020 | G109: =IF(OR(E109="",F109=""),"",E109*F109) -> 148583200 | H109: 0.0867 | I109: =IF(G109="","",IF(ISNUMBER(H109),G109,"")) -> 148583200 | J109: =IF(I109="","",I109*H109) -> 12882163 | K109: =IF(G109="","MISSING OEWS",IF(ISNUMBER(H109),"MATCHED","MISSING WHARTON")) -> MATCHED
A110: 11 | B110: Agriculture, Forestry, Fishing and Hunting | C110: 49-9098 | D110: Helpers--Installation, Maintenance, and Repair Workers | E110: 220 | G110: =IF(OR(E110="",F110=""),"",E110*F110) | H110: 0.0594 | I110: =IF(G110="","",IF(ISNUMBER(H110),G110,"")) | J110: =IF(I110="","",I110*H110) | K110: =IF(G110="","MISSING OEWS",IF(ISNUMBER(H110),"MATCHED","MISSING WHARTON")) -> MISSING OEWS
A111: 11 | B111: Agriculture, Forestry, Fishing and Hunting | C111: 49-9099 | D111: Installation, Maintenance, and Repair Workers, All Other | E111: 60 | F111: 50350 | G111: =IF(OR(E111="",F111=""),"",E111*F111) -> 3021000 | H111: 0.1667 | I111: =IF(G111="","",IF(ISNUMBER(H111),G111,"")) -> 3021000 | J111: =IF(I111="","",I111*H111) -> 503600.7 | K111: =IF(G111="","MISSING OEWS",IF(ISNUMBER(H111),"MATCHED","MISSING WHARTON")) -> MATCHED
A112: 11 | B112: Agriculture, Forestry, Fishing and Hunting | C112: 51-1011 | D112: First-Line Supervisors of Production and Operating Workers | E112: 1500 | F112: 62390 | G112: =IF(OR(E112="",F112=""),"",E112*F112) -> 93585000 | H112: 0.3775 | I112: =IF(G112="","",IF(ISNUMBER(H112),G112,"")) -> 93585000 | J112: =IF(I112="","",I112*H112) -> 35328338 | K112: =IF(G112="","MISSING OEWS",IF(ISNUMBER(H112),"MATCHED","MISSING WHARTON")) -> MATCHED
A113: 11 | B113: Agriculture, Forestry, Fishing and Hunting | C113: 51-2090 | D113: Miscellaneous Assemblers and Fabricators | E113: 50 | F113: 37370 | G113: =IF(OR(E113="",F113=""),"",E113*F113) -> 1868500 | H113: 0.15 | I113: =IF(G113="","",IF(ISNUMBER(H113),G113,"")) -> 1868500 | J113: =IF(I113="","",I113*H113) -> 280275 | K113: =IF(G113="","MISSING OEWS",IF(ISNUMBER(H113),"MATCHED","MISSING WHARTON")) -> MATCHED
...

Sheet DATA Wharton
A1: SOC code (TEXT) | B1: Occupation title | C1: AI Task Exposure (0–1)
A2: 11-1011 | B2: Chief Executives | C2: 0.4775
A3: 11-1021 | B3: General and Operations Managers | C3: 0.5382
A4: 11-1031 | B4: Legislators | C4: 0.1967
A5: 11-2011 | B5: Advertising and Promotions Managers | C5: 0.5583
A6: 11-2021 | B6: Marketing Managers | C6: 0.445
A7: 11-2022 | B7: Sales Managers | C7: 0.3735
A8: 11-2032 | B8: Public Relations Managers | C8: 0.53
A9: 11-2033 | B9: Fundraising Managers | C9: 0.5594
A10: 11-3012 | B10: Administrative Services Managers | C10: 0.4444
A11: 11-3013 | B11: Facilities Managers | C11: 0.2907
A12: 11-3021 | B12: Computer and Information Systems Managers | C12: 0.5265
A13: 11-3031 | B13: Financial Managers | C13: 0.7221
... A785: 53-7121 | B785: Tank Car, Truck, and Ship Loaders | C785: 0.05

Sheet DATA Census
A1: NAICS (TEXT) | B1: Industry | C1: AI-using firms (%) | D1: Measurement / survey vintage
A2: 11 | B2: Agriculture, forestry, fishing and hunting | C2: 0.095 | D2: Census BTOS | 2026 | firms, not employees
A3: 21 | B3: Mining, quarrying, and oil and gas extraction | C3: 0.13 | D3: Census BTOS | 2026 | firms, not employees
A4: 22 | B4: Utilities | C4: 0.167 | D4: Census BTOS | 2026 | firms, not employees
A5: 23 | B5: Construction | C5: 0.172 | D5: Census BTOS | 2026 | firms, not employees
A6: 31-33 | B6: Manufacturing | C6: 0.208 | D6: Census BTOS | 2026 | firms, not employees
A7: 42 | B7: Wholesale trade | C7: 0.216 | D7: Census BTOS | 2026 | firms, not employees
A8: 44-45 | B8: Retail trade | C8: 0.168 | D8: Census BTOS | 2026 | firms, not employees
A9: 48-49 | B9: Transportation and warehousing | C9: 0.105 | D9: Census BTOS | 2026 | firms, not employees
A10: 51 | B10: Information | C10: 0.502 | D10: Census BTOS | 2026 | firms, not employees
A11: 52 | B11: Finance and insurance | C11: 0.401 | D11: Census BTOS | 2026 | firms, not employees
A12: 53 | B12: Real estate and rental and leasing | C12: 0.308 | D12: Census BTOS | 2026 | firms, not employees
A13: 54 | B13: Professional, scientific, and technical services | C13: 0.427 | D13: Census BTOS | 2026 | firms, not employees
... A20: 81 | B20: Other services (except public administration) | C20: 0.127 | D20: Census BTOS | 2026 | firms, not employees

Sheet 03 Sources and QA
A1: DATA SOURCES / MAPPING / QUALITY ASSURANCE
A2: No web hyperlinks are embedded: source names and local downloaded filenames only. Rebuild all formulas by dragging down.
A4: Source | B4: Dataset / Downloaded filename | C4: Required fields / filters | D4: Workbook destination | E4: Notes
A5: BLS QCEW (2025) | B5: Private, All Industry Aggregations, U.S. TOTAL; 2025 Annual | C5: Industry; Total Annual Wages; US000; private | D5: DATA QCEW Raw → DATA QCEW | E5: Gross annual wages; 19 sectors; 99 unclassified separate
A6: BLS OEWS (May 2025) | B6: natsector_M2025_dl.xlsx; nat3d_owner_M2025_dl.xlsx | C6: NAICS; OCC_CODE; O_GROUP=detailed; TOT_EMP; A_MEAN | D6: DATA OEWS | E6: Private adjustment for education / public hospitals; remaining mixed sector caveats
A7: Penn Wharton (2025) | B7: supp_exposure_by_occupation.csv | C7: Occupation Code; Exposure to AI Automation (% of tasks) | D7: DATA Wharton | E7: Use 0–1 fraction in Excel (47.75 → 0.4775)
A8: Census BTOS (2026) | B8: Sector (3).xlsx; cycle 202620 | C8: Industry; Question ID 7; Answer ID 1 | D8: DATA Census | E8: Firm-use share: NOT employee adoption
A9: BLS Emp Projections (2026 release) | B9: Employment by Major Industry Sector; 2025–2035 | C9: Employment in 2025/2035; private NAICS | D9: DATA BLS Projections | E9: Different statistical series from QCEW; use growth only
A10: CHECK: Private national total | B10: 2025 QCEW private total | C10: 10,532,191,402,092 dollars | D10: DATA QCEW C25 | E10: Total 19 + NAICS 99 must equal this
A11: CHECK: 19-sector wages | B11: 2025 QCEW private total less NAICS 99 | C11: 10,515,645,524,505 dollars | D11: 01 Industry Model C25 | E11: Should equal DATA QCEW C23 / 1e9
A12: CHECK: Wharton SOC coverage | B12: 784 unique SOC codes | C12: XLOOKUP by exact SOC | D12: DATA OEWS K column | E12: Unmatched rows not forced to zero exposure
A13: CHECK: OEWS duplication | B13: 7,805 unique Industry × SOC records | C13: Only detailed occupations, do not double count broad groups | D13: DATA OEWS A + C | E13: Old workbook had duplicate risk; new underlying detail has no duplicates
A14: MODEL SCOPE | B14: Potential wage exposure, not economic saving | C14: Gross Exposed = QCEW wages × wage-weighted task exposure | D14: 01 Industry Model I | E14: Do not interpret as dollars of layoffs / AI provider revenue
A15: PROJECTION SCOPE | B15: Illustrative growth, not company guidance | C15: Industry wages × (1+employment CAGR) × (1+wage growth) | D15: Five-Year Projection F | E15: 2026 BTOS survey anchors firm-use proxy, not wage-weighted adoption
